Workbook
Name _Toc536378868: 'Building Component'!$E$6
Name _Toc536378869: 'Building Component'!$F$6
Name _Toc536378870: 'Building Component'!$I$6
Name _Toc536378871: 'Building Component'!$L$6
Name _Toc536378872: 'Building Component'!$O$6
Name _Toc536378873: 'Building Component'!$R$6
Name _Toc536378874: 'Building Component'!$U$6
Name _Toc536378875: 'Building Component'!$F$7
Name _Toc536378876: 'Building Component'!$G$7
Name _Toc536378877: 'Building Component'!$H$7
Name _Toc536378878: 'Building Component'!$I$7
Name _Toc536378879: 'Building Component'!$J$7
Name _Toc536378880: 'Building Component'!$K$7
Name _Toc536378881: 'Building Component'!$L$7
Name _Toc536378882: 'Building Component'!$M$7
Name _Toc536378883: 'Building Component'!$N$7
Name _Toc536378884: 'Building Component'!$O$7
Name _Toc536378885: 'Building Component'!$P$7
Name _Toc536378886: 'Building Component'!$Q$7
Name _Toc536378887: 'Building Component'!$R$7
Name _Toc536378888: 'Building Component'!$S$7
Name _Toc536378889: 'Building Component'!$T$7
Name _Toc536378890: 'Building Component'!$U$7
Name _Toc536378891: 'Building Component'!$V$7
Name _Toc536378892: 'Building Component'!$W$7
Name _Toc536378893: 'Building Component'!$E$17
Name _Toc536378894: 'Building Component'!$F$17
Name _Toc536378895: 'Building Component'!$G$17
Name _Toc536378896: 'Building Component'!$H$17
Name _Toc536378897: 'Building Component'!$I$17
Name _Toc536378898: 'Building Component'!$J$17
Name _Toc536378899: 'Building Component'!$K$17
Name _Toc536378900: 'Building Component'!$L$17
Name _Toc536378901: 'Building Component'!$M$17
Name _Toc536378902: 'Building Component'!$N$17
Name _Toc536378903: 'Building Component'!$O$17
Name _Toc536378904: 'Building Component'!$P$17
Name _Toc536378905: 'Building Component'!$Q$17
Name _Toc536378906: 'Building Component'!$R$17
Name _Toc536378907: 'Building Component'!$S$17
Name _Toc536378908: 'Building Component'!$T$17
Name _Toc536378909: 'Building Component'!$U$17
Name _Toc536378910: 'Building Component'!$V$17
Name _Toc536378911: 'Building Component'!$W$17
Name _Toc536378912: 'Building Component'!$E$18
Name _Toc536378913: 'Building Component'!$F$18
Name _Toc536378914: 'Building Component'!$G$18
Name _Toc536378915: 'Building Component'!$H$18
Name _Toc536378916: 'Building Component'!$I$18
Name _Toc536378917: 'Building Component'!$J$18
Name _Toc536378918: 'Building Component'!$K$18
Name _Toc536378919: 'Building Component'!$L$18
Name _Toc536378920: 'Building Component'!$M$18
Name _Toc536378921: 'Building Component'!$N$18
Name _Toc536378922: 'Building Component'!$O$18
Name _Toc536378923: 'Building Component'!$P$18
Name _Toc536378924: 'Building Component'!$Q$18
Name _Toc536378925: 'Building Component'!$R$18
Name _Toc536378926: 'Building Component'!$S$18
Name _Toc536378927: 'Building Component'!$T$18

Sheet Location (2)
B1: Abirhajira
B2: A) Residential
B3: Plot Grade | C3: Up to 200 | D3: 201 - 400 | E3: 401-600 | F3: 601-800 | G3: 801-1,000 | H3: 1,001-1,500 | I3: 1,501-2,000 | J3: 2,001-3,000 | K3: 3001-5000 | L3: 5,001-10,000 | M3: ≥10,001
B4: 1st | C4: 1066 | D4: 800 | E4: 600 | F4: 450 | G4: 338 | H4: 252 | I4: 190 | J4: 142 | K4: 106 | L4: 80 | M4: 60
B5: 2nd | C5: 648 | D5: 486 | E5: 364 | F5: 274 | G5: 206 | H5: 154 | I5: 116 | J5: 86 | K5: 64 | L5: 48 | M5: 36
B6: 3rd | C6: 416 | D6: 312 | E6: 234 | F6: 176 | G6: 132 | H6: 98 | I6: 74 | J6: 56 | K6: 42 | L6: 32 | M6: 24
B7: 4th | C7: NOT APPLICABLE
B9: B) Commercial
B10: Plot Grade | C10: Up to 200 | D10: 201 - 400 | E10: 401-600 | F10: 601-800 | G10: 801-1,000 | H10: 1,001-1,500 | I10: 1,501-2,000 | J10: 2,001-3,000 | K10: 3001-5000 | L10: 5,001-10,000 | M10: ≥10,001
B11: 1st | C11: 1600 | D11: 1200 | E11: 900 | F11: 674 | G11: 506 | H11: 380 | I11: 284 | J11: 214 | K11: 160 | L11: 120 | M11: 90
B12: 2nd | C12: 972 | D12: 730 | E12: 546 | F12: 410 | G12: 308 | H12: 230 | I12: 172 | J12: 130 | K12: 98 | L12: 72 | M12: 54
B13: 3rd | C13: 624 | D13: 468 | E13: 352 | F13: 264 | G13: 198 | H13: 148 | I13: 112 | J13: 84 | K13: 62 | L13: 46 | M13: 36
B14: 4th | C14: NOT APPLICABLE
B16: Adama
B17: A) Residential
B18: Plot Grade | C18: Up to 200 | D18: 201 - 400 | E18: 401-600 | F18: 601-800 | G18: 801-1,000 | H18: 1,001-1,500 | I18: 1,501-2,000 | J18: 2,001-3,000 | K18: 3001-5000 | L18: 5,001-10,000 | M18: ≥10,001
B19: 1st | C19: 13750 | D19: 10312.5 | E19: 7735 | F19: 5800 | G19: 4350 | H19: 3262.5 | I19: 2447.5 | J19: 1835 | K19: 1377.5 | L19: 1032.5 | M19: 775
B20: 2nd | C20: 13000 | D20: 9750 | E20: 7312.5 | F20: 5485 | G20: 4112.5 | H20: 3085 | I20: 2312.5 | J20: 1735 | K20: 1302.5 | L20: 975 | M20: 732.5
B21: 3rd | C21: 12250 | D21: 9187.5 | E21: 6890 | F21: 5167.5 | G21: 3875 | H21: 2907.5 | I21: 2180 | J21: 1635 | K21: 1227.5 | L21: 920 | M21: 690
B22: 4th | C22: 11500 | D22: 8625 | E22: 6470 | F22: 4852.5 | G22: 3637.5 | H22: 2730 | I22: 2047.5 | J22: 1535 | K22: 1152.5 | L22: 862.5 | M22: 647.5
B24: B) Commercial
B25: Plot Grade | C25: Up to 200 | D25: 201 - 400 | E25: 401-600 | F25: 601-800 | G25: 801-1,000 | H25: 1,001-1,500 | I25: 1,501-2,000 | J25: 2,001-3,000 | K25: 3001-5000 | L25: 5,001-10,000 | M25: ≥10,001
B26: 1st | C26: 16250 | D26: 12187.5 | E26: 9140 | F26: 6855 | G26: 5142.5 | H26: 3855 | I26: 2892.5 | J26: 2170 | K26: 1627.5 | L26: 1220 | M26: 915
B27: 2nd | C27: 15375 | D27: 11532.5 | E27: 8647.5 | F27: 6487.5 | G27: 4865 | H27: 3647.5 | I27: 2737.5 | J27: 2052.5 | K27: 1540 | L27: 1155 | M27: 865
B28: 3rd | C28: 14500 | D28: 10875 | E28: 8157.5 | F28: 6117.5 | G28: 4587.5 | H28: 3440 | I28: 2580 | J28: 1935 | K28: 1452.5 | L28: 1087.5 | M28: 817.5
B29: 4th | C29: 13625 | D29: 10220 | E29: 7665 | F29: 5747.5 | G29: 4310 | H29: 3232.5 | I29: 2425 | J29: 1817.5 | K29: 1365 | L29: 1022.5 | M29: 767.5
B31: Addis Zemen
B32: A) Residential | P32: =4*200 -> 800
B33: Plot Grade | C33: Up to 200 | D33: 201 - 400 | E33: 401-600 | F33: 601-800 | G33: 801-1,000 | H33: 1,001-1,500 | I33: 1,501-2,000 | J33: 2,001-3,000 | K33: 3001-5000 | L33: 5,001-10,000 | M33: ≥10,001 | P33: =4500+P32 -> 5300
B34: 1st | C34: 3666 | D34: 2750 | E34: 2062 | F34: 1546 | G34: 1160 | H34: 870 | I34: 652 | J34: 490 | K34: 368 | L34: 276 | M34: 206
B35: 2nd | C35: 2460 | D35: 1846 | E35: 1384 | F35: 1038 | G35: 778 | H35: 584 | I35: 438 | J35: 328 | K35: 246 | L35: 184 | M35: 138
B36: 3rd | C36: 1652 | D36: 1238 | E36: 930 | F36: 696 | G36: 522 | H36: 392 | I36: 294 | J36: 220 | K36: 166 | L36: 124 | M36: 94 | O36: =14000 -> 14000 | P36: =1400*3 -> 4200
B37: 4th | C37: NOT APPLICABLE | O37: 12000 | P37: =P36+1400 -> 5600
O38: =O36+O37 -> 26000 | P38: =P37*2 -> 11200
B39: B) Commercial
B40: Plot Grade | C40: Up to 200 | D40: 201 - 400 | E40: 401-600 | F40: 601-800 | G40: 801-1,000 | H40: 1,001-1,500 | I40: 1,501-2,000 | J40: 2,001-3,000 | K40: 3001-5000 | L40: 5,001-10,000 | M40: ≥10,001 | O40: =196 -> 196 | P40: =180 -> 180 | Q40: =O40*P40 -> 35280
B41: 1st | C41: 5500 | D41: 4124 | E41: 3094 | F41: 2320 | G41: 1740 | H41: 1306 | I41: 978 | J41: 734 | K41: 550 | L41: 412 | M41: 310 | O41: 24 | P41: 190 | Q41: =O41*P41 -> 4560
B42: 2nd | C42: 3692 | D42: 2768 | E42: 2076 | F42: 1558 | G42: 1168 | H42: 876 | I42: 656 | J42: 492 | K42: 370 | L42: 278 | M42: 208 | Q42: =Q40+Q41 -> 39840
B43: 3rd | C43: 2478 | D43: 1858 | E43: 1394 | F43: 1046 | G43: 784 | H43: 588 | I43: 442 | J43: 330 | K43: 248 | L43: 186 | M43: 140 | Q43: =Q42/2 -> 19920 | R43: =17000+25000 -> 42000
B44: 4th | C44: NOT APPLICABLE | Q44: =17000+Q43 -> 36920
O45: =16*16*4 -> 1024
B46: Adi Shehu | O46: =16*14*4 -> 896
B47: A) Residential
B48: Plot Grade | C48: Up to 200 | D48: 201 - 400 | E48: 401-600 | F48: 601-800 | G48: 801-1,000 | H48: 1,001-1,500 | I48: 1,501-2,000 | J48: 2,001-3,000 | K48: 3001-5000 | L48: 5,001-10,000 | M48: ≥10,001
B49: 1st | C49: 2042 | D49: 1532 | E49: 1150 | F49: 862 | G49: 646 | H49: 484 | I49: 364 | J49: 272 | K49: 204 | L49: 154 | M49: 116
B50: 2nd | C50: NOT APPLICABLE
B51: 3rd | C51: NOT APPLICABLE
B52: 4th | C52: NOT APPLICABLE
B54: B) Commercial
B55: Plot Grade | C55: Up to 200 | D55: 201 - 400 | E55: 401-600 | F55: 601-800 | G55: 801-1,000 | H55: 1,001-1,500 | I55: 1,501-2,000 | J55: 2,001-3,000 | K55: 3001-5000 | L55: 5,001-10,000 | M55: ≥10,001
B56: 1st | C56: 2230 | D56: 1672 | E56: 1254 | F56: 940 | G56: 706 | H56: 528 | I56: 396 | J56: 298 | K56: 222 | L56: 168 | M56: 126
B57: 2nd | C57: NOT APPLICABLE
B58: 3rd | C58: NOT APPLICABLE
B59: 4th | C59: NOT APPLICABLE
B61: Adigrat
B62: A) Residential
B63: Plot Grade | C63: Up to 200 | D63: 201 - 400 | E63: 401-600 | F63: 601-800 | G63: 801-1,000 | H63: 1,001-1,500 | I63: 1,501-2,000 | J63: 2,001-3,000 | K63: 3001-5000 | L63: 5,001-10,000 | M63: ≥10,001
B64: 1st | C64: 5776 | D64: 4338 | E64: 3246 | F64: 2436 | G64: 1828 | H64: 1378 | I64: 1030 | J64: 768 | K64: 580 | L64: 294 | M64: 148
B65: 2nd | C65: NOT APPLICABLE
B66: 3rd | C66: NOT APPLICABLE
B67: 4th | C67: NOT APPLICABLE
B69: Adigudem
B70: A) Residential
B71: Plot Grade | C71: Up to 200 | D71: 201 - 400 | E71: 401-600 | F71: 601-800 | G71: 801-1,000 | H71: 1,001-1,500 | I71: 1,501-2,000 | J71: 2,001-3,000 | K71: 3001-5000 | L71: 5,001-10,000 | M71: ≥10,001
B72: 1st | C72: 2614 | D72: 1962 | E72: 1470 | F72: 1104 | G72: 828 | H72: 620 | I72: 466 | J72: 350 | K72: 262 | L72: 196 | M72: 146
B73: 2nd | C73: NOT APPLICABLE
B74: 3rd | C74: NOT APPLICABLE
B75: 4th | C75: NOT APPLICABLE
B77: B) Commercial
B78: Plot Grade | C78: Up to 200 | D78: 201 - 400 | E78: 401-600 | F78: 601-800 | G78: 801-1,000 | H78: 1,001-1,500 | I78: 1,501-2,000 | J78: 2,001-3,000 | K78: 3001-5000 | L78: 5,001-10,000 | M78: ≥10,001
B79: 1st | C79: 4232 | D79: 3174 | E79: 2380 | F79: 1786 | G79: 1340 | H79: 1004 | I79: 754 | J79: 564 | K79: 424 | L79: 318 | M79: 238
B80: 2nd | C80: NOT APPLICABLE
B81: 3rd | C81: NOT APPLICABLE
B82: 4th | C82: NOT APPLICABLE
B84: Agaro
B85: A) Residential
B86: Plot Grade | C86: Up to 200 | D86: 201 - 400 | E86: 401-600 | F86: 601-800 | G86: 801-1,000 | H86: 1,001-1,500 | I86: 1,501-2,000 | J86: 2,001-3,000 | K86: 3001-5000 | L86: 5,001-10,000 | M86: ≥10,001
B87: 1st | C87: 2440 | D87: 1806 | E87: 1336 | F87: 988 | G87: 732 | H87: 542 | I87: 400 | J87: 296 | K87: 220 | L87: 162 | M87: 120
B88: 2nd | C88: 1806 | D88: 1336 | E88: 988 | F88: 732 | G88: 542 | H88: 400 | I88: 296 | J88: 220 | K88: 162 | L88: 120 | M88: 100
B89: 3rd | C89: 1336 | D89: 988 | E89: 732 | F89: 542 | G89: 400 | H89: 296 | I89: 220 | J89: 162 | K89: 120 | L89: 100 | M89: 80
B90: 4th | C90: 988 | D90: 732 | E90: 542 | F90: 400 | G90: 296 | H90: 220 | I90: 162 | J90: 120 | K90: 100 | L90: 80 | M90: 60
B92: B) Commercial
B93: Plot Grade | C93: Up to 200 | D93: 201 - 400 | E93: 401-600 | F93: 601-800 | G93: 801-1,000 | H93: 1,001-1,500 | I93: 1,501-2,000 | J93: 2,001-3,000 | K93: 3001-5000 | L93: 5,001-10,000 | M93: ≥10,001
B94: 1st | C94: 3300 | D94: 2460 | E94: 1834 | F94: 1368 | G94: 1020 | H94: 760 | I94: 566 | J94: 422 | K94: 314 | L94: 234 | M94: 174
B95: 2nd | C95: 2640 | D95: 1834 | E95: 1368 | F95: 1020 | G95: 760 | H95: 566 | I95: 422 | J95: 314 | K95: 234 | L95: 174 | M95: 114
B96: 3rd | C96: 1832 | D96: 1368 | E96: 1020 | F96: 760 | G96: 566 | H96: 422 | I96: 314 | J96: 234 | K96: 174 | L96: 114 | M96: 54
B97: 4th | C97: 1368 | D97: 1020 | E97: 760 | F97: 566 | G97: 422 | H97: 314 | I97: 234 | J97: 174 | K97: 114 | L97: 54 | M97: 14
B99: Agula'e
B100: A) Residential
B101: Plot Grade | C101: Up to 200 | D101: 201 - 400 | E101: 401-600 | F101: 601-800 | G101: 801-1,000 | H101: 1,001-1,500 | I101: 1,501-2,000 | J101: 2,001-3,000 | K101: 3001-5000 | L101: 5,001-10,000 | M101: ≥10,001
B102: 1st | C102: 3226 | D102: 2420 | E102: 1814 | F102: 1360 | G102: 1020 | H102: 766 | I102: 574 | J102: 430 | K102: 322 | L102: 242 | M102: 182
B103: 2nd | C103: NOT APPLICABLE
B104: 3rd | C104: NOT APPLICABLE
B105: 4th | C105: NOT APPLICABLE
B107: B) Commercial
B108: Plot Grade | C108: Up to 200 | D108: 201 - 400 | E108: 401-600 | F108: 601-800 | G108: 801-1,000 | H108: 1,001-1,500 | I108: 1,501-2,000 | J108: 2,001-3,000 | K108: 3001-5000 | L108: 5,001-10,000 | M108: ≥10,001
B109: 1st | C109: 4718 | D109: 3538 | E109: 2654 | F109: 1990 | G109: 1492 | H109: 1120 | I109: 840 | J109: 630 | K109: 472 | L109: 354 | M109: 266
B110: 2nd | C110: NOT APPLICABLE
B111: 3rd | C111: NOT APPLICABLE
B112: 4th | C112: NOT APPLICABLE
...

Sheet Sheet1
A1: Ranges of Replacement cost rates for properties located in Addis Ababa
A2: Building Types | B2: Range of replacement cost rate | D2: Range used only for management purpose | F2: The diffrence
B3: Max | C3: Min | D3: Max | E3: Min | F3: Max | G3: Min | H3: Remark
A4: G+1 and G+2 | B4: ='G+ Buildings'!D166 -> 18745.139 | C4: ='G+ Buildings'!E166 -> 11081.785 | D4: 15582 | E4: 7588 | F4: =B4-D4 -> 3163.1388 | G4: =C4-E4 -> 3493.7846 | H4: Birr/m²
A5: G+3 and G+4 | B5: ='G+ Buildings'!I166 -> 16537.649 | C5: ='G+ Buildings'!J166 -> 11107.469 | D5: 16618 | E5: 9170 | F5: =B5-D5 -> -80.3506 | G5: =C5-E5 -> 1937.4688 | H5: Birr/m²
A6: G+5 and G+6 | B6: ='G+ Buildings'!N166 -> 16167.256 | C6: ='G+ Buildings'!O166 -> 11070.97 | D6: 17122 | E6: 8680 | F6: =B6-D6 -> -954.7438 | G6: =C6-E6 -> 2390.9702 | H6: Birr/m²
A7: G+7 and G+8 | B7: ='G+ Buildings'!S166 -> 19888.762 | C7: ='G+ Buildings'!T166 -> 11065.563 | D7: 16660 | E7: 12292 | F7: =B7-D7 -> 3228.7616 | G7: =C7-E7 -> -1226.437 | H7: Birr/m²
A8: G+9 and G+10 | B8: ='G+ Buildings'!X166 -> 13517.728 | C8: ='G+ Buildings'!Y166 -> 10670.837 | F8: =B8-D8 -> 13517.728 | G8: =C8-E8 -> 10670.837 | H8: Birr/m²
A9: G+11 to G+16 | B9: ='G+ Buildings'!AC166 -> 16584.962 | C9: ='G+ Buildings'!AD166 -> 10918.217 | F9: =B9-D9 -> 16584.962 | G9: =C9-E9 -> 10918.217 | H9: Birr/m²
A10: G+17 to G+22 | B10: ='G+ Buildings'!AH166 -> 16455.19 | C10: ='G+ Buildings'!AI166 -> 11022.305 | F10: =B10-D10 -> 16455.19 | G10: =C10-E10 -> 11022.305 | H10: Birr/m²
A11: G+23 and above | B11: ='G+ Buildings'!AM166 -> 16725.55 | C11: ='G+ Buildings'!AN166 -> 10946.605 | F11: =B11-D11 -> 16725.55 | G11: =C11-E11 -> 10946.605 | H11: Birr/m²
A12: Villa Higher | B12: ='Villa Higher'!D178 -> 25555.453 | C12: ='Villa Higher'!E178 -> 7776.2408 | D12: 16245 | E12: 3976 | F12: =B12-D12 -> 9310.4528 | G12: =C12-E12 -> 3800.2408 | H12: Birr/m²
A13: Lower Villa | B13: ='Villa Lower'!E62 -> 8862.0375 | C13: ='Villa Lower'!G62 -> 1510.004 | D13: 4032 | E13: 1694 | F13: =B13-D13 -> 4830.0375 | G13: =C13-E13 -> -183.996 | H13: Birr/m²
A14: Multipurpose Halls H<= 4m | B14: ='Multi-Purposed halls'!D151 -> 59422.793 | C14: ='Multi-Purposed halls'!E151 -> 11724.093 | D14: 9604 | E14: 1694 | F14: =B14-D14 -> 49818.793 | G14: =C14-E14 -> 10030.093 | H14: Birr/m²
A15: H=4.5 | B15: ='Multi-Purposed halls'!H151 -> 17215.99 | C15: ='Multi-Purposed halls'!I151 -> 3344.6534 | D15: 4732 | E15: 378 | F15: =B15-D15 -> 12483.99 | G15: =C15-E15 -> 2966.6534 | H15: Birr/m²
A16: H=5.5 | B16: ='Multi-Purposed halls'!L151 -> 1785.288 | C16: ='Multi-Purposed halls'!M151 -> 486.212 | D16: 1705 | E16: 196 | F16: =B16-D16 -> 80.288 | G16: =C16-E16 -> 290.212 | H16: Birr/m³
A17: H=6.5 | B17: ='Multi-Purposed halls'!P151 -> 1578.3152 | C17: ='Multi-Purposed halls'!Q151 -> 425.5908 | F17: =B17-D17 -> 1578.3152 | G17: =C17-E17 -> 425.5908 | H17: Birr/m³
A18: H=7.5 | B18: ='Multi-Purposed halls'!T151 -> 1364.851 | C18: ='Multi-Purposed halls'!U151 -> 359.7115 | D18: 1324 | E18: 154 | F18: =B18-D18 -> 40.851 | G18: =C18-E18 -> 205.7115 | H18: Birr/m³
A19: H=8.5 | B19: ='Multi-Purposed halls'!X151 -> 1297.5762 | C19: ='Multi-Purposed halls'!Y151 -> 331.9023 | F19: =B19-D19 -> 1297.5762 | G19: =C19-E19 -> 331.9023 | H19: Birr/m³
A20: H=10.5 | B20: ='Multi-Purposed halls'!AB151 -> 1178.378 | C20: ='Multi-Purposed halls'!AC151 -> 310.957 | D20: 1113 | E20: 154 | F20: =B20-D20 -> 65.378 | G20: =C20-E20 -> 156.957 | H20: Birr/m³
A21: H=11.5 | B21: ='Multi-Purposed halls'!AF151 -> 1127.794 | C21: ='Multi-Purposed halls'!AG151 -> 293.261 | F21: =B21-D21 -> 1127.794 | G21: =C21-E21 -> 293.261 | H21: Birr/m³

Sheet Villa Lower
A2: ITEM NO. | B2: Building components
A3: 1 | B3: Foundation | C3: Factors | E3: Max | G3: Min
B4: 1.1 Earth Work But no cart away | C4: 1 | E4: =MAX(C4:C7) -> 47.16 | F4: =MAX(D4:D7) -> 0 | G4: =MIN(C4:C7) -> 1 | I4: =$C4*H4/100 -> 0
B5: 1.2 Earth Work Foundation & cart away | C5: 4 | H5: 100 | I5: =$C5*H5/100 -> 4
B6: 1.3 Earth Work Foundation, hardcore, mass concrete, stone masonry | C6: 20.49 | I6: =$C6*H6/100 -> 0
B7: 1.4 Earth Work Foundation, hardcore, mass concrete, stone masonry BGL & AGL | C7: 47.16 | I7: =$C7*H7/100 -> 0
A8: 2 | B8: Structure | I8: =$C8*H8/100 -> 0
A9: 3 | B9: Block Work (Internal) | I9: =$C9*H9/100 -> 0
B10: 3.1 Chicka | C10: 2.16 | E10: =MAX(C10:C13) -> 10.63 | F10: =MAX(D10:D13) -> 0 | G10: =MIN(C10:C14) -> 1 | I10: =$C10*H10/100 -> 0
B11: 3.2 Poor Chika | C11: 1 | I11: =$C11*H11/100 -> 0
B12: 3.3 HCB but no R.C structure and plastering | C12: 10.63 | H12: 100 | I12: =$C12*H12/100 -> 10.63
B13: 3.4 Stone masonry with cement-chicka mortar mix | C13: 8.4 | I13: =$C13*H13/100 -> 0
B14: 3.5 CIS Wall | C14: 1.89 | I14: =$C14*H14/100 -> 0
A15: 4 | B15: Block Work (External) | I15: =$C15*H15/100 -> 0
B16: 4.1 Chicka | C16: 2.16 | E16: =MAX(C16:C20) -> 10.63 | F16: =MAX(D16:D20) -> 0 | G16: =MIN(C16:C20) -> 1 | I16: =$C16*H16/100 -> 0
B17: 4.2 Poor Chika | C17: 1 | I17: =$C17*H17/100 -> 0
B18: 4.3 HCB but no R.C structure and plastering | C18: 10.63 | H18: 100 | I18: =$C18*H18/100 -> 10.63
B19: 4.4 Stone masonry with cement-chicka mortar mix | C19: 8.4 | I19: =$C19*H19/100 -> 0
B20: 4.5 CIS Wall | C20: 1.89 | I20: =$C20*H20/100 -> 0
A21: 5 | B21: Roofing | I21: =$C21*H21/100 -> 0
B22: 5.1 CIS G-35 on wood | C22: 1 | E22: =MAX(C22:C24) -> 1.62 | F22: =MAX(D22:D24) -> 0 | G22: =MIN(C22:C24) -> 1 | H22: 100 | I22: =$C22*H22/100 -> 1
B23: 5.2 CIS G-32 on wood | C23: 1.37 | I23: =$C23*H23/100 -> 0
B24: 5.3 CIS G-30 on wood | C24: 1.62 | I24: =$C24*H24/100 -> 0
A25: 6 | B25: Joinery | I25: =$C25*H25/100 -> 0
B26: 6.1 Internal wooden door made of Low quality wood | C26: 1.67 | E26: =MAX(C26:C27) -> 1.67 | F26: =MAX(D26:D27) -> 0 | G26: =MIN(C26:C27) -> 1 | I26: =$C26*H26/100 -> 0
B27: 6.2 As item No.1 above but made of Poor Quality wood | C27: 1 | I27: =$C27*H27/100 -> 0
A28: 7 | B28: Metal Works | I28: =$C28*H28/100 -> 0
B29: 7.1 LTZ or RHS | C29: 1 | E29: =MAX(C29) -> 1 | F29: =MAX(D29) -> 0 | G29: =MIN(C29:C30) -> 1 | H29: 100 | I29: =$C29*H29/100 -> 1
A30: 8 | B30: Floor Finish | I30: =$C30*H30/100 -> 0
B31: 8.1 Cement Screed | C31: 1 | E31: =MAX(C31:C34) -> 6.49 | F31: =MAX(D31:D34) -> 0 | G31: =MIN(C31:C34) -> 1 | H31: 100 | I31: =$C31*H31/100 -> 1
B32: 8.2 Cement Tile | C32: 2.72 | I32: =$C32*H32/100 -> 0
B33: 8.3 Terrazzo | C33: 3.06 | I33: =$C33*H33/100 -> 0
B34: 8.4 Poor quality wooden | C34: 6.49 | I34: =$C34*H34/100 -> 0
A35: 9 | B35: Wall Finish (Internal) | I35: =$C35*H35/100 -> 0
B36: 9.1 Pointed HCB | C36: 1 | E36: =MAX(C36:C39) -> 4.04 | F36: =MAX(D36:D39) -> 0 | G36: =MIN(C36:C39) -> 1 | H36: 100 | I36: =$C36*H36/100 -> 1
B37: 9.2 Painted | C37: 1.08 | I37: =$C37*H37/100 -> 0
B38: 9.3 Plastered | C38: 2.96 | I38: =$C38*H38/100 -> 0
B39: 9.4 Plastering & Painting | C39: 4.04 | I39: =$C39*H39/100 -> 0
A40: 10 | B40: Wall Finish (External) | I40: =$C40*H40/100 -> 0
B41: 10.1 Pointed HCB | C41: 1 | E41: =MAX(C41:C48) -> 13.32 | F41: =MAX(D41:D48) -> 0 | G41: =MIN(C41:C48) -> 1 | H41: 100 | I41: =$C41*H41/100 -> 1
B42: 10.2 Painted | C42: 1.08 | I42: =$C42*H42/100 -> 0
B43: 10.3 Plastered | C43: 2.96 | I43: =$C43*H43/100 -> 0
B44: 10.4 Rendered | C44: 2.96 | I44: =$C44*H44/100 -> 0
B45: 10.5 Rendered & Painted | C45: 4.04 | I45: =$C45*H45/100 -> 0
B46: 10.6 Ambo stone clad over ‘chicka’ wall | C46: 12.12 | I46: =$C46*H46/100 -> 0
B47: 10.7 Brick clad over ‘chicka’ wall | C47: 10.55 | I47: =$C47*H47/100 -> 0
B48: 10.8 Pointed Stone | C48: 13.32 | I48: =$C48*H48/100 -> 0
A49: 11 | B49: Ceiling Finish | I49: =$C49*H49/100 -> 0
B50: 11.1 Hardboard not painted | C50: 1.48 | E50: =MAX(C50:C54) -> 1.48 | F50: =MAX(D50:D54) -> 0 | G50: =MIN(C50:C54) -> 0.2 | I50: =$C50*H50/100 -> 0
B51: 11.2 Abujedi not Painted | C51: 1 | I51: =$C51*H51/100 -> 0
B52: 11.3 Painting | C52: 0.2 | I52: =$C52*H52/100 -> 0
B53: 11.4 Plywood not painted | C53: 1.19 | I53: =$C53*H53/100 -> 0
B54: 11.5 Chip wood not painted | C54: 1.24 | I54: =$C54*H54/100 -> 0
A55: 12 | B55: Electrical | I55: =$C55*H55/100 -> 0
B56: 12.1 Class A | C56: 4.21 | E56: =MAX(C56:C60) -> 4.21 | F56: =MAX(D56:D60) -> 0 | G56: =MIN(C56:C60) -> 1 | I56: =$C56*H56/100 -> 0
B57: 12.2 Class B | C57: 3.55 | I57: =$C57*H57/100 -> 0
B58: 12.3 Class C | C58: 2.31 | I58: =$C58*H58/100 -> 0
B59: 12.4 Class D | C59: 1.66 | I59: =$C59*H59/100 -> 0
B60: 12.5 Class E | C60: 1 | H60: 100 | I60: =$C60*H60/100 -> 1
B61: Factor sum | C61: =SUM(C4:C60) -> 216.69 | D61: =SUM(D4:D60) -> 0 | E61: =SUM(E4:E60) -> 102.25 | F61: =SUM(F4:F60) -> 0 | G61: =SUM(G4:G60) -> 10.2 | I61: =ROUND(SUM(I4:I60),2) -> 31.26
B62: Plinth Area/ Volumetric Rate (Ra=79.87flv+695.33) | D62: =IF(D61>0,(79.87*D61+695.33),0) -> 0 | E62: =IF(E61>0,(79.87*E61+695.33),0) -> 8862.0375 | F62: =IF(F61>0,(79.87*F61+695.33),0) -> 0 | G62: =IF(G61>0,(79.87*G61+695.33),0) -> 1510.004 | I62: =IF(I61>0,(79.87*I61+695.33),0) -> 3192.0662
B63: Depreciation %
B64: Plinth Area/ Volumetric Rate (Ra=79.87flv+695.33) | I64: =(1-H63%)*I62 -> 3192.0662
B65: Plinth Area/ Volumetric | I65: =#REF!+#REF!+#REF! -> #REF!
B66: Total | I66: =I64*I65 -> #REF!

Sheet Villa Higher
A2: ITEM NO. | B2: Building components
A3: 1 | B3: Foundation | C3: Factors | D3: Max | E3: Min
B4: 1.1 Foundation Work in: Earthwortk,Hard-core,Mass concrete floor with C-15,Stone masnory AGL and BGL | C4: 1.31 | D4: =MAX(C4:C8) -> 8.3 | E4: =MIN(C4:C8) -> 1.31 | G4: =$C4*F4/100 -> 0
B5: 1.2 Foundation work as Item No.1 above but with mass concrete of higher class (c-20) | C5: 1.48 | G5: =$C5*F5/100 -> 0
B6: 1.3 Foundation work as Item No.2 above but with R.C. grade beam | C6: 2.85 | G6: =$C6*F6/100 -> 0
B7: 1.4 Foundation work as Item No.1 above but with R.C. floor slab and R.C grade beam | C7: 5.53 | G7: =$C7*F7/100 -> 0
B8: 1.4 Foundation work as Item No.4 above but with R.C. foundation column and R.C Footing | C8: 8.3 | F8: 100 | G8: =$C8*F8/100 -> 8.3
A9: 2 | B9: Structure | G9: =$C9*F9/100 -> 0
B10: 2.1 Structure for mud and CIS-on- wooden walls | D10: =MAX(C10:C12) -> 9.19 | E10: =MIN(C10:C12) -> 4.2 | G10: =$C10*F10/100 -> 0
B11: 2.2 .R.C structure (Elevation colums and tie beam) | C11: 4.2 | F11: 100 | G11: =$C11*F11/100 -> 4.2
B12: 2.3 As item no.2 above but for R.C roof slab | C12: 9.19 | G12: =$C12*F12/100 -> 0
A13: 3 | B13: Block Work | G13: =$C13*F13/100 -> 0
B14: 3.1 Internal | G14: =$C14*F14/100 -> 0
B15: 3.1.1 Chicka | C15: 0.48 | D15: =MAX(C15:C26) -> 6.92 | E15: =MIN(C15:C38) -> 0.48 | G15: =$C15*F15/100 -> 0
B16: 3.1.2 CIS G-32 | C16: 0.75 | G16: =$C16*F16/100 -> 0
B17: 3.1.3 CIS G-30 | C17: 0.71 | G17: =$C17*F17/100 -> 0
B18: 3.1.4 CIS G-28 | C18: 0.96 | G18: =$C18*F18/100 -> 0
B19: 3.1.5 HCB 15 cm thick | C19: 0.69 | F19: 100 | G19: =$C19*F19/100 -> 0.69
B20: 3.1.6 Brick 12cm thick | C20: 2.2 | G20: =$C20*F20/100 -> 0
B21: 3.1.7 stone 40cm thick | C21: 1.21 | G21: =$C21*F21/100 -> 0
B22: 3.1.8 Chip wood-double | C22: 1.03 | G22: =$C22*F22/100 -> 0
B23: 3.1.9 Alumimium | C23: 6.92 | G23: =$C23*F23/100 -> 0
B24: 3.1.10 HCB 10 cm thick | C24: 0.55 | G24: =$C24*F24/100 -> 0
B25: 3.1.11 Hard board fixed to zigba frame (one face) | C25: 0.65 | G25: =$C25*F25/100 -> 0
B26: 3.1.12 Ditto as above but both side coverd | C26: 1.12 | G26: =$C26*F26/100 -> 0
B27: 3.2 External | G27: =$C27*F27/100 -> 0
B28: 3.2.1 Chicka | C28: 0.93 | D28: =MAX(C28:C38) -> 18.59 | E28: =MIN(C28:C38) -> 0.93 | G28: =$C28*F28/100 -> 0
B29: 3.2.2 CIS G-32 | C29: 1.44 | G29: =$C29*F29/100 -> 0
B30: 3.2.3 CIS G-30 | C30: 1.37 | G30: =$C30*F30/100 -> 0
B31: 3.2.4 CIS G-28 | C31: 1.86 | G31: =$C31*F31/100 -> 0
B32: 3.2.5 EGA on steel | C32: 2.33 | G32: =$C32*F32/100 -> 0
B33: 3.2.6 HCB 20 cm thick | C33: 1.35 | F33: 100 | G33: =$C33*F33/100 -> 1.35
B34: 3.2.7 Brick 25cm thick | C34: 8.71 | G34: =$C34*F34/100 -> 0
B35: 3.2.8 stone 40cm thick | C35: 2.34 | G35: =$C35*F35/100 -> 0
B36: 3.2.9 stone 50cm thick | C36: 2.93 | G36: =$C36*F36/100 -> 0
B37: 3.2.10 Alumimium | C37: 13.8 | G37: =$C37*F37/100 -> 0
B38: 3.2.11 Curtin wall made with special frame & 4mm cored polycarbonate treated against UV rail | C38: 18.59 | G38: =$C38*F38/100 -> 0
A39: 4 | B39: Roofing | G39: =$C39*F39/100 -> 0
B40: 4.1 CIS G-32 on wood | C40: 1.6 | D40: =MAX(C40:C54) -> 4.98 | E40: =MIN(C40:C54) -> 1.6 | G40: =$C40*F40/100 -> 0
B41: 4.2 CIS G-30 on wood | C41: 1.61 | G41: =$C41*F41/100 -> 0
B42: 4.3 CIS G-28 on wood | C42: 1.97 | F42: 100 | G42: =$C42*F42/100 -> 1.97
B43: 4.4 EGA on steel | C43: 3.24 | G43: =$C43*F43/100 -> 0
B44: 4.5 EGA on wood | C44: 2.16 | G44: =$C44*F44/100 -> 0
B45: 4.6 CIS G-28 on steel | C45: 2.95 | G45: =$C45*F45/100 -> 0
B46: 4.7 Cement roof tile | C46: 2.46 | G46: =$C46*F46/100 -> 0
B47: 4.8 R.C without water-proof material (Accessible) | C47: 3.73 | G47: =$C47*F47/100 -> 0
B48: 4.9 R.C without water-proof material (in Accessible) | C48: 2.99 | G48: =$C48*F48/100 -> 0
B49: 4.10 R.C with water-proof material (Accessible) | C49: 4.98 | G49: =$C49*F49/100 -> 0
B50: 4.11 R.C with water-proof material (in Accessible) | C50: 3.48 | G50: =$C50*F50/100 -> 0
B51: 4.11 Metal sheet roofing with sand coating on wood (Imported) | C51: 3.28 | G51: =$C51*F51/100 -> 0
B52: 4.12 Metal sheet roofing with sand coating on wood (local) | C52: 2.04 | G52: =$C52*F52/100 -> 0
B53: 4.13Metal sheet roofing with sand coating on steel (Imported) | C53: 4.92 | G53: =$C53*F53/100 -> 0
B54: 4.14 Metal sheet roofing with sand coating on steel (local) | C54: 3.06 | G54: =$C54*F54/100 -> 0
A55: 5 | B55: Joinery | G55: =$C55*F55/100 -> 0
B56: 5.1 Internal wooden door made of Low quality wood | C56: 1.07 | D56: =MAX(C56:C62) -> 4.58 | E56: =MIN(C56:C62) -> 1.07 | G56: =$C56*F56/100 -> 0
B57: 5.2 As item No.1 above but made of medium Quality wood | C57: 1.3 | F57: 100 | G57: =$C57*F57/100 -> 1.3
B58: 5.3 As item No.2 above but with built-in cup board | C58: 2.35 | G58: =$C58*F58/100 -> 0
B59: 5.4 As item No.1 above but made of Quality wood | C59: 2.72 | G59: =$C59*F59/100 -> 0
B60: 5.5 As item No.4 above but with built-in cup board | C60: 2.86 | G60: =$C60*F60/100 -> 0
B61: 5.6 As item No.1 above but made of best Quality wood | C61: 4.35 | G61: =$C61*F61/100 -> 0
B62: 5.7 As item No.6 above but with built-in cup board | C62: 4.58 | G62: =$C62*F62/100 -> 0
A63: 6 | B63: Metal Works | G63: =$C63*F63/100 -> 0
B64: 6.1 LTZ or RHS profile for external openings with clear glass | C64: 2.55 | D64: =MAX(C64:C76) -> 4.13 | E64: =MIN(C64:C76) -> 1.92 | G64: =$C64*F64/100 -> 0
B65: 6.2 LTZ with 4mm- frosted glass | C65: 2.65 | G65: =$C65*F65/100 -> 0
B66: 6.3 Ditto but with 4mm-tinted glass | C66: 2.64 | F66: 100 | G66: =$C66*F66/100 -> 2.64
B67: 6.4 Ditto but with 6mm-tinted glass | C67: 3 | G67: =$C67*F67/100 -> 0
B68: 6.5 Secco profile for external openings with clear glass | C68: 1.92 | G68: =$C68*F68/100 -> 0
B69: 6.6 Secco with 4mm-frosted glass | C69: 1.98 | G69: =$C69*F69/100 -> 0
B70: 6.7 Ditto but with 4mm-tinted glass | C70: 2.01 | G70: =$C70*F70/100 -> 0
B71: 6.8 Ditto but with 6mm-tinted glass | C71: 2.36 | G71: =$C71*F71/100 -> 0
B72: 6.9 Imitation with clear glass | C72: 3.04 | G72: =$C72*F72/100 -> 0
B73: 6.10 Imitation with 4mm frosted glass | C73: 3.08 | G73: =$C73*F73/100 -> 0
B74: 6.11 Imitation with 4mm tinted glass | C74: 3.08 | G74: =$C74*F74/100 -> 0
B75: 6.12 Imitation with 6mm tinted glass | C75: 3.24 | G75: =$C75*F75/100 -> 0
B76: 6.13 Aluminium profile for external opening | C76: 4.13 | G76: =$C76*F76/100 -> 0
A77: 7 | B77: Floor Finish | G77: =$C77*F77/100 -> 0
B78: 7.1 Cement Screed | C78: 0.68 | D78: =MAX(C78:C95) -> 10.42 | E78: =MIN(C78:C95) -> 0.68 | F78: 80 | G78: =$C78*F78/100 -> 0.544
B79: 7.2 Cement Tile | C79: 1.43 | G79: =$C79*F79/100 -> 0
B80: 7.3 Terrazzo Tile | C80: 2.03 | G80: =$C80*F80/100 -> 0
B81: 7.4 PVC tile | C81: 2.38 | G81: =$C81*F81/100 -> 0
B82: 7.5 Ceramic medium quality Porcelain | C82: 3.37 | F82: 20 | G82: =$C82*F82/100 -> 0.674
B83: 7.6 Ceramic best quality | C83: 4.21 | G83: =$C83*F83/100 -> 0
B84: 7.7 Porcelain | C84: 3.54 | G84: =$C84*F84/100 -> 0
B85: 7.8 Marble chip lower quality | C85: 4.44 | G85: =$C85*F85/100 -> 0
B86: 7.9 Marble chip best quality | C86: 5.33 | G86: =$C86*F86/100 -> 0
B87: 7.10 Harar marble | C87: 6.2 | G87: =$C87*F87/100 -> 0
B88: 7.11 Mankush marble | C88: 8.77 | G88: =$C88*F88/100 -> 0
B89: 7.12 Parquet lower quality on screed | C89: 4.52 | G89: =$C89*F89/100 -> 0
B90: 7.13 Parquet best quality on screed | C90: 10.42 | G90: =$C90*F90/100 -> 0
B91: 7.14 Parquet quality on screed | C91: 7.07 | G91: =$C91*F91/100 -> 0
B92: 7.15 Parquet medium quality on screed | C92: 5.66 | G92: =$C92*F92/100 -> 0
B93: 7.16 Parquet poor quality on wooden frame | C93: 3.84 | G93: =$C93*F93/100 -> 0
B94: 7.17 Granite | C94: 6.58 | G94: =$C94*F94/100 -> 0
B95: 7.18 Mosaic | C95: 5.12 | G95: =$C95*F95/100 -> 0
A96: 8 | B96: Wall Finish | G96: =$C96*F96/100 -> 0
B97: 8.1 Internal | G97: =$C97*F97/100 -> 0
B98: 8.1.1 plasterd | C98: 1.05 | D98: =MAX(C98:C115) -> 9.97 | E98: =MIN(C98:C115) -> 0.46 | G98: =$C98*F98/100 -> 0
B99: 8.1.2 Plasterd and painted | C99: 1.41 | F99: 100 | G99: =$C99*F99/100 -> 1.41
B100: 8.1.3 Pointed HCB | C100: 0.46 | G100: =$C100*F100/100 -> 0
B101: 8.1.4 Pointed dressed stone | C101: 0.6 | G101: =$C101*F101/100 -> 0
...

Sheet G+ Buildings
A2: ITEM NO. | B2: Building components
A3: 1 | B3: Foundation | C3: Factors | H3: Factors | M3: Factors | R3: Factors | W3: Factors | AB3: Factors | AG3: Factors | AL3: Factors
C4: G+1 & G+2 | H4: G+3 & G+4 | M4: G+5 & G+6 | R4: G+7 & G+8 | W4: G+9 & G+10 | AB4: G+11 to G+16 | AG4: G+17 to G+22 | AL4: G+23 & Above
D5: Max | E5: Min | I5: Max | J5: Min | N5: Max | O5: Min | S5: Max | T5: Min | X5: Max | Y5: Min | AC5: Max | AD5: Min | AH5: Max | AI5: Min | AM5: Max | AN5: Min
B6: 1.1 Foundation | C6: 4.99 | D6: =MAX(C6) -> 4.99 | E6: =MIN(C6) -> 4.99 | F6: 100 | G6: =$C6*F6/100 -> 4.99 | H6: 4.53 | I6: =MAX(H6) -> 4.53 | J6: =MIN(H6) -> 4.53 | L6: =$H6*K6/100 -> 0 | M6: 5.78 | N6: =MAX(M6) -> 5.78 | O6: =MIN(M6) -> 5.78 | Q6: =$M6*P6/100 -> 0 | R6: 3.29 | S6: =MAX(R6) -> 3.29 | T6: =MIN(R6) -> 3.29 | V6: =$R6*U6/100 -> 0 | W6: 4.61 | X6: =MAX(W6) -> 4.61 | Y6: =MIN(W6) -> 4.61 | AA6: =$W6*Z6/100 -> 0 | AB6: 3.72 | AC6: =MAX(AB6) -> 3.72 | AD6: =MIN(AB6) -> 3.72 | AF6: =$AB6*AE6/100 -> 0 | AG6: 4.9 | AH6: =MAX(AG6) -> 4.9 | AI6: =MIN(AG6) -> 4.9 | AK6: =$AG6*AJ6/100 -> 0 | AL6: 4.03 | AM6: =MAX(AL6) -> 4.03 | AN6: =MIN(AL6) -> 4.03 | AP6: =$AL6*AO6/100 -> 0
A7: 2 | B7: Structure | G7: =$C7*F7/100 -> 0 | L7: =$H7*K7/100 -> 0 | Q7: =$M7*P7/100 -> 0 | V7: =$R7*U7/100 -> 0 | AA7: =$W7*Z7/100 -> 0 | AF7: =$AB7*AE7/100 -> 0 | AK7: =$AG7*AJ7/100 -> 0 | AP7: =$AL7*AO7/100 -> 0
B8: 2.1 .R.C structure (Elevation colums and suspended beam) | C8: 4.94 | D8: =MAX(C8) -> 4.94 | E8: =MIN(C8) -> 4.94 | F8: 100 | G8: =$C8*F8/100 -> 4.94 | H8: 6.96 | I8: =MAX(H8) -> 6.96 | J8: =MIN(H8) -> 6.96 | L8: =$H8*K8/100 -> 0 | M8: 5.54 | N8: =MAX(M8) -> 5.54 | O8: =MIN(M8) -> 5.54 | Q8: =$M8*P8/100 -> 0 | R8: 5.75 | S8: =MAX(R8) -> 5.75 | T8: =MIN(R8) -> 5.75 | V8: =$R8*U8/100 -> 0 | W8: 4.01 | X8: =MAX(W8) -> 4.01 | Y8: =MIN(W8) -> 4.01 | AA8: =$W8*Z8/100 -> 0 | AB8: 6.85 | AC8: =MAX(AB8) -> 6.85 | AD8: =MIN(AB8) -> 6.85 | AF8: =$AB8*AE8/100 -> 0 | AG8: 7.16 | AH8: =MAX(AG8) -> 7.16 | AI8: =MIN(AG8) -> 7.16 | AK8: =$AG8*AJ8/100 -> 0 | AL8: 8.6 | AM8: =MAX(AL8) -> 8.6 | AN8: =MIN(AL8) -> 8.6 | AP8: =$AL8*AO8/100 -> 0
A9: 3 | B9: Block Work | G9: =$C9*F9/100 -> 0 | L9: =$H9*K9/100 -> 0 | Q9: =$M9*P9/100 -> 0 | V9: =$R9*U9/100 -> 0 | AA9: =$W9*Z9/100 -> 0 | AF9: =$AB9*AE9/100 -> 0 | AK9: =$AG9*AJ9/100 -> 0 | AP9: =$AL9*AO9/100 -> 0
B10: 3.1 Internal | G10: =$C10*F10/100 -> 0 | L10: =$H10*K10/100 -> 0 | Q10: =$M10*P10/100 -> 0 | V10: =$R10*U10/100 -> 0 | AA10: =$W10*Z10/100 -> 0 | AF10: =$AB10*AE10/100 -> 0 | AK10: =$AG10*AJ10/100 -> 0 | AP10: =$AL10*AO10/100 -> 0
B11: 3.1.1 HCB 15 cm thick | C11: 0.53 | D11: =MAX(C11:C17) -> 5.26 | E11: =MIN(C11:C17) -> 0.42 | F11: 100 | G11: =$C11*F11/100 -> 0.53 | H11: 0.43 | I11: =MAX(H11:H17) -> 4.31 | J11: =MIN(H11:H17) -> 0.34 | L11: =$H11*K11/100 -> 0 | M11: 0.29 | N11: =MAX(M11:M17) -> 2.95 | O11: =MIN(M11:M17) -> 0.23 | Q11: =$M11*P11/100 -> 0 | R11: 2.69 | S11: =MAX(R11:R17) -> 26.92 | T11: =MIN(R11:R17) -> 2.14 | V11: =$R11*U11/100 -> 0 | W11: 0.38 | X11: =MAX(W11:W17) -> 3.78 | Y11: =MIN(W11:W17) -> 0.3 | AA11: =$W11*Z11/100 -> 0 | AB11: 0.06 | AC11: =MAX(AB11:AB17) -> 0.61 | AD11: =MIN(AB11:AB17) -> 0.05 | AF11: =$AB11*AE11/100 -> 0 | AG11: 0.37 | AH11: =MAX(AG11:AG17) -> 3.72 | AI11: =MIN(AG11:AG17) -> 0.3 | AK11: =$AG11*AJ11/100 -> 0 | AL11: 0.24 | AM11: =MAX(AL11:AL17) -> 2.39 | AN11: =MIN(AL11:AL17) -> 0.19 | AP11: =$AL11*AO11/100 -> 0
B12: 3.1.2 Brick 12cm thick | C12: 1.68 | G12: =$C12*F12/100 -> 0 | H12: 1.37 | L12: =$H12*K12/100 -> 0 | M12: 0.94 | Q12: =$M12*P12/100 -> 0 | R12: 8.57 | V12: =$R12*U12/100 -> 0 | W12: 1.2 | AA12: =$W12*Z12/100 -> 0 | AB12: 0.2 | AF12: =$AB12*AE12/100 -> 0 | AG12: 1.19 | AK12: =$AG12*AJ12/100 -> 0 | AL12: 0.76 | AP12: =$AL12*AO12/100 -> 0
B13: 3.1.3 stone 40cm thick | C13: 0.92 | G13: =$C13*F13/100 -> 0 | H13: 0.75 | L13: =$H13*K13/100 -> 0 | M13: 0.52 | Q13: =$M13*P13/100 -> 0 | R13: 4.71 | V13: =$R13*U13/100 -> 0 | W13: 0.66 | AA13: =$W13*Z13/100 -> 0 | AB13: 0.11 | AF13: =$AB13*AE13/100 -> 0 | AG13: 0.65 | AK13: =$AG13*AJ13/100 -> 0 | AL13: 0.42 | AP13: =$AL13*AO13/100 -> 0
B14: 3.1.4 Chip wood-double | C14: 0.78 | G14: =$C14*F14/100 -> 0 | H14: 0.64 | L14: =$H14*K14/100 -> 0 | M14: 0.44 | Q14: =$M14*P14/100 -> 0 | R14: 4 | V14: =$R14*U14/100 -> 0 | W14: 0.56 | AA14: =$W14*Z14/100 -> 0 | AB14: 0.09 | AF14: =$AB14*AE14/100 -> 0 | AG14: 0.55 | AK14: =$AG14*AJ14/100 -> 0 | AL14: 0.36 | AP14: =$AL14*AO14/100 -> 0
B15: 3.1.5 Alumimium | C15: 5.26 | G15: =$C15*F15/100 -> 0 | H15: 4.31 | L15: =$H15*K15/100 -> 0 | M15: 2.95 | Q15: =$M15*P15/100 -> 0 | R15: 26.92 | V15: =$R15*U15/100 -> 0 | W15: 3.78 | AA15: =$W15*Z15/100 -> 0 | AB15: 0.61 | AF15: =$AB15*AE15/100 -> 0 | AG15: 3.72 | AK15: =$AG15*AJ15/100 -> 0 | AL15: 2.39 | AP15: =$AL15*AO15/100 -> 0
B16: 3.1.6 HCB 10 cm thick | C16: 0.42 | G16: =$C16*F16/100 -> 0 | H16: 0.34 | L16: =$H16*K16/100 -> 0 | M16: 0.23 | Q16: =$M16*P16/100 -> 0 | R16: 2.14 | V16: =$R16*U16/100 -> 0 | W16: 0.3 | AA16: =$W16*Z16/100 -> 0 | AB16: 0.05 | AF16: =$AB16*AE16/100 -> 0 | AG16: 0.3 | AK16: =$AG16*AJ16/100 -> 0 | AL16: 0.19 | AP16: =$AL16*AO16/100 -> 0
B17: 3.1.7 Magnesium/Gypsum Board | C17: 0.85 | G17: =$C17*F17/100 -> 0 | H17: 0.7 | L17: =$H17*K17/100 -> 0 | M17: 0.48 | Q17: =$M17*P17/100 -> 0 | R17: 4.36 | V17: =$R17*U17/100 -> 0 | W17: 0.61 | AA17: =$W17*Z17/100 -> 0 | AB17: 0.1 | AF17: =$AB17*AE17/100 -> 0 | AG17: 0.6 | AK17: =$AG17*AJ17/100 -> 0 | AL17: 0.39 | AP17: =$AL17*AO17/100 -> 0
B18: 3.2 External | G18: =$C18*F18/100 -> 0 | L18: =$H18*K18/100 -> 0 | Q18: =$M18*P18/100 -> 0 | V18: =$R18*U18/100 -> 0 | AA18: =$W18*Z18/100 -> 0 | AF18: =$AB18*AE18/100 -> 0 | AK18: =$AG18*AJ18/100 -> 0 | AP18: =$AL18*AO18/100 -> 0
B19: 3.2.1 HCB 20 cm thick | C19: 1.03 | D19: =MAX(C19:C25) -> 14.24 | E19: =MIN(C19:C25) -> 1.03 | F19: 100 | G19: =$C19*F19/100 -> 1.03 | H19: 0.58 | I19: =MAX(H19:H25) -> 8 | J19: =MIN(H19:H25) -> 0.58 | L19: =$H19*K19/100 -> 0 | M19: 0.29 | N19: =MAX(M19:M25) -> 4.05 | O19: =MIN(M19:M25) -> 0.29 | Q19: =$M19*P19/100 -> 0 | R19: 1.02 | S19: =MAX(R19:R25) -> 14.06 | T19: =MIN(R19:R25) -> 1.02 | V19: =$R19*U19/100 -> 0 | W19: 0.26 | X19: =MAX(W19:W25) -> 3.54 | Y19: =MIN(W19:W25) -> 0.26 | AA19: =$W19*Z19/100 -> 0 | AB19: 0.17 | AC19: =MAX(AB19:AB25) -> 2.34 | AD19: =MIN(AB19:AB25) -> 0.17 | AF19: =$AB19*AE19/100 -> 0 | AG19: 0.21 | AH19: =MAX(AG19:AG25) -> 2.82 | AI19: =MIN(AG19:AG25) -> 0.21 | AK19: =$AG19*AJ19/100 -> 0 | AL19: 0.91 | AM19: =MAX(AL19:AL25) -> 12.57 | AN19: =MIN(AL19:AL25) -> 0.91 | AP19: =$AL19*AO19/100 -> 0
B20: 3.2.2 Brick 25cm thick | C20: 6.67 | G20: =$C20*F20/100 -> 0 | H20: 3.75 | L20: =$H20*K20/100 -> 0 | M20: 1.9 | Q20: =$M20*P20/100 -> 0 | R20: 6.59 | V20: =$R20*U20/100 -> 0 | W20: 1.66 | AA20: =$W20*Z20/100 -> 0 | AB20: 1.1 | AF20: =$AB20*AE20/100 -> 0 | AG20: 1.32 | AK20: =$AG20*AJ20/100 -> 0 | AL20: 5.89 | AP20: =$AL20*AO20/100 -> 0
B21: 3.2.3 stone 40cm thick | C21: 1.8 | G21: =$C21*F21/100 -> 0 | H21: 1.01 | L21: =$H21*K21/100 -> 0 | M21: 0.51 | Q21: =$M21*P21/100 -> 0 | R21: 1.77 | V21: =$R21*U21/100 -> 0 | W21: 0.45 | AA21: =$W21*Z21/100 -> 0 | AB21: 0.3 | AF21: =$AB21*AE21/100 -> 0 | AG21: 0.36 | AK21: =$AG21*AJ21/100 -> 0 | AL21: 1.59 | AP21: =$AL21*AO21/100 -> 0
B22: 3.2.4 stone 50cm thick | C22: 2.24 | G22: =$C22*F22/100 -> 0 | H22: 1.26 | L22: =$H22*K22/100 -> 0 | M22: 0.64 | Q22: =$M22*P22/100 -> 0 | R22: 2.22 | V22: =$R22*U22/100 -> 0 | W22: 0.56 | AA22: =$W22*Z22/100 -> 0 | AB22: 0.37 | AF22: =$AB22*AE22/100 -> 0 | AG22: 0.45 | AK22: =$AG22*AJ22/100 -> 0 | AL22: 1.98 | AP22: =$AL22*AO22/100 -> 0
B23: 3.2.5 Alumimium | C23: 10.25 | G23: =$C23*F23/100 -> 0 | H23: 5.76 | L23: =$H23*K23/100 -> 0 | M23: 2.92 | Q23: =$M23*P23/100 -> 0 | R23: 10.13 | V23: =$R23*U23/100 -> 0 | W23: 2.55 | AA23: =$W23*Z23/100 -> 0 | AB23: 1.69 | AF23: =$AB23*AE23/100 -> 0 | AG23: 2.03 | AK23: =$AG23*AJ23/100 -> 0 | AL23: 9.05 | AP23: =$AL23*AO23/100 -> 0
B24: 3.2.6 Magnesium/Gypsum Board | C24: 1.66 | G24: =$C24*F24/100 -> 0 | H24: 0.93 | L24: =$H24*K24/100 -> 0 | M24: 0.47 | Q24: =$M24*P24/100 -> 0 | R24: 1.64 | V24: =$R24*U24/100 -> 0 | W24: 0.41 | AA24: =$W24*Z24/100 -> 0 | AB24: 0.27 | AF24: =$AB24*AE24/100 -> 0 | AG24: 0.33 | AK24: =$AG24*AJ24/100 -> 0 | AL24: 1.47 | AP24: =$AL24*AO24/100 -> 0
B25: 3.2.7 Curtin wall made with special frame & 4mm cored polycarbonate treated against UV rail | C25: 14.24 | G25: =$C25*F25/100 -> 0 | H25: 8 | L25: =$H25*K25/100 -> 0 | M25: 4.05 | Q25: =$M25*P25/100 -> 0 | R25: 14.06 | V25: =$R25*U25/100 -> 0 | W25: 3.54 | AA25: =$W25*Z25/100 -> 0 | AB25: 2.34 | AF25: =$AB25*AE25/100 -> 0 | AG25: 2.82 | AK25: =$AG25*AJ25/100 -> 0 | AL25: 12.57 | AP25: =$AL25*AO25/100 -> 0
A26: 4 | B26: Roofing | G26: =$C26*F26/100 -> 0 | L26: =$H26*K26/100 -> 0 | Q26: =$M26*P26/100 -> 0 | V26: =$R26*U26/100 -> 0 | AA26: =$W26*Z26/100 -> 0 | AF26: =$AB26*AE26/100 -> 0 | AK26: =$AG26*AJ26/100 -> 0 | AP26: =$AL26*AO26/100 -> 0
B27: 4.1 CIS G-32 on wood | C27: 1.8 | D27: =MAX(C27:C41) -> 6.5 | E27: =MIN(C27:C41) -> 1.32 | G27: =$C27*F27/100 -> 0 | H27: 0.7 | I27: =MAX(H27:H41) -> 4.13 | J27: =MIN(H27:H41) -> 0.56 | L27: =$H27*K27/100 -> 0 | M27: 0.4 | N27: =MAX(M27:M41) -> 4.59 | O27: =MIN(M27:M41) -> 0.3 | Q27: =$M27*P27/100 -> 0 | R27: 0.39 | S27: =MAX(R27:R41) -> 5.63 | T27: =MIN(R27:R41) -> 0.27 | V27: =$R27*U27/100 -> 0 | W27: 0.24 | X27: =MAX(W27:W41) -> 4.38 | Y27: =MIN(W27:W41) -> 0.17 | AA27: =$W27*Z27/100 -> 0 | AB27: 0.23 | AC27: =MAX(AB27:AB41) -> 24.05 | AD27: =MIN(AB27:AB41) -> 0.14 | AF27: =$AB27*AE27/100 -> 0 | AG27: 0.16 | AH27: =MAX(AG27:AG41) -> 9.57 | AI27: =MIN(AG27:AG41) -> 0.14 | AK27: =$AG27*AJ27/100 -> 0 | AL27: 0.08 | AM27: =MAX(AL27:AL41) -> 8.57 | AN27: =MIN(AL27:AL41) -> 0.06 | AP27: =$AL27*AO27/100 -> 0
B28: 4.2 CIS G-30 on wood | C28: 1.81 | G28: =$C28*F28/100 -> 0 | H28: 0.7 | L28: =$H28*K28/100 -> 0 | M28: 0.4 | Q28: =$M28*P28/100 -> 0 | R28: 0.39 | V28: =$R28*U28/100 -> 0 | W28: 0.24 | AA28: =$W28*Z28/100 -> 0 | AB28: 0.23 | AF28: =$AB28*AE28/100 -> 0 | AG28: 0.16 | AK28: =$AG28*AJ28/100 -> 0 | AL28: 0.08 | AP28: =$AL28*AO28/100 -> 0
B29: 4.3 CIS G-28 on wood | C29: 2.04 | F29: 100 | G29: =$C29*F29/100 -> 2.04 | H29: 0.76 | L29: =$H29*K29/100 -> 0 | M29: 0.45 | Q29: =$M29*P29/100 -> 0 | R29: 0.45 | V29: =$R29*U29/100 -> 0 | W29: 0.27 | AA29: =$W29*Z29/100 -> 0 | AB29: 0.27 | AF29: =$AB29*AE29/100 -> 0 | AG29: 0.17 | AK29: =$AG29*AJ29/100 -> 0 | AL29: 0.1 | AP29: =$AL29*AO29/100 -> 0
B30: 4.4 EGA on steel | C30: 2.64 | G30: =$C30*F30/100 -> 0 | H30: 0.67 | L30: =$H30*K30/100 -> 0 | M30: 0.38 | Q30: =$M30*P30/100 -> 0 | R30: 0.37 | V30: =$R30*U30/100 -> 0 | W30: 0.23 | AA30: =$W30*Z30/100 -> 0 | AB30: 0.21 | AF30: =$AB30*AE30/100 -> 0 | AG30: 0.16 | AK30: =$AG30*AJ30/100 -> 0 | AL30: 0.08 | AP30: =$AL30*AO30/100 -> 0
B31: 4.5 EGA on wood | C31: 1.72 | G31: =$C31*F31/100 -> 0 | H31: 0.67 | L31: =$H31*K31/100 -> 0 | M31: 0.38 | Q31: =$M31*P31/100 -> 0 | R31: 0.37 | V31: =$R31*U31/100 -> 0 | W31: 0.23 | AA31: =$W31*Z31/100 -> 0 | AB31: 0.21 | AF31: =$AB31*AE31/100 -> 0 | AG31: 0.16 | AK31: =$AG31*AJ31/100 -> 0 | AL31: 0.08 | AP31: =$AL31*AO31/100 -> 0
B32: 4.6 CIS G-28 on steel | C32: 2.76 | G32: =$C32*F32/100 -> 0 | H32: 0.67 | L32: =$H32*K32/100 -> 0 | M32: 0.38 | Q32: =$M32*P32/100 -> 0 | R32: 0.37 | V32: =$R32*U32/100 -> 0 | W32: 0.23 | AA32: =$W32*Z32/100 -> 0 | AB32: 0.21 | AF32: =$AB32*AE32/100 -> 0 | AG32: 0.16 | AK32: =$AG32*AJ32/100 -> 0 | AL32: 0.08 | AP32: =$AL32*AO32/100 -> 0
B33: 4.7 Cement roof tile | C33: 1.32 | G33: =$C33*F33/100 -> 0 | H33: 0.56 | L33: =$H33*K33/100 -> 0 | M33: 0.3 | Q33: =$M33*P33/100 -> 0 | R33: 0.27 | V33: =$R33*U33/100 -> 0 | W33: 0.18 | AA33: =$W33*Z33/100 -> 0 | AB33: 0.14 | AF33: =$AB33*AE33/100 -> 0 | AG33: 0.14 | AK33: =$AG33*AJ33/100 -> 0 | AL33: 0.06 | AP33: =$AL33*AO33/100 -> 0
B34: 4.8 R.C without water-proof material (Accessible) | C34: 4.97 | G34: =$C34*F34/100 -> 0 | H34: 2.93 | L34: =$H34*K34/100 -> 0 | M34: 1.04 | Q34: =$M34*P34/100 -> 0 | R34: 0.94 | V34: =$R34*U34/100 -> 0 | W34: 0.77 | AA34: =$W34*Z34/100 -> 0 | AB34: 0.77 | AF34: =$AB34*AE34/100 -> 0 | AG34: 0.77 | AK34: =$AG34*AJ34/100 -> 0 | AL34: 0.77 | AP34: =$AL34*AO34/100 -> 0
B35: 4.9 R.C without water-proof material (in Accessible) | C35: 4.72 | G35: =$C35*F35/100 -> 0 | H35: 2.86 | L35: =$H35*K35/100 -> 0 | M35: 1.02 | Q35: =$M35*P35/100 -> 0 | R35: 0.92 | V35: =$R35*U35/100 -> 0 | W35: 0.75 | AA35: =$W35*Z35/100 -> 0 | AB35: 0.75 | AF35: =$AB35*AE35/100 -> 0 | AG35: 0.75 | AK35: =$AG35*AJ35/100 -> 0 | AL35: 0.75 | AP35: =$AL35*AO35/100 -> 0
B36: 4.10 R.C with water-proof material (Accessible) | C36: 6.5 | G36: =$C36*F36/100 -> 0 | H36: 2.39 | L36: =$H36*K36/100 -> 0 | M36: 2.72 | Q36: =$M36*P36/100 -> 0 | R36: 1.48 | V36: =$R36*U36/100 -> 0 | W36: 0.25 | AA36: =$W36*Z36/100 -> 0 | AB36: 0.43 | AF36: =$AB36*AE36/100 -> 0 | AG36: 0.65 | AK36: =$AG36*AJ36/100 -> 0 | AL36: 0.36 | AP36: =$AL36*AO36/100 -> 0
B37: 4.11 R.C with water-proof material (in Accessible) | C37: 5.52 | G37: =$C37*F37/100 -> 0 | H37: 2.27 | L37: =$H37*K37/100 -> 0 | M37: 2.21 | Q37: =$M37*P37/100 -> 0 | R37: 1.44 | V37: =$R37*U37/100 -> 0 | W37: 0.17 | AA37: =$W37*Z37/100 -> 0 | AB37: 0.27 | AF37: =$AB37*AE37/100 -> 0 | AG37: 0.34 | AK37: =$AG37*AJ37/100 -> 0 | AL37: 0.36 | AP37: =$AL37*AO37/100 -> 0
B38: 4.12 Metal sheet roofing with sand coating on wood (Imported) | C38: 3.55 | G38: =$C38*F38/100 -> 0 | H38: 4.13 | L38: =$H38*K38/100 -> 0 | M38: 4.59 | Q38: =$M38*P38/100 -> 0 | R38: 5.63 | V38: =$R38*U38/100 -> 0 | W38: 4.38 | AA38: =$W38*Z38/100 -> 0 | AB38: 24.05 | AF38: =$AB38*AE38/100 -> 0 | AG38: 9.57 | AK38: =$AG38*AJ38/100 -> 0 | AL38: 8.57 | AP38: =$AL38*AO38/100 -> 0
B39: 4.13 Metal sheet roofing with sand coating on wood (local) | C39: 2.21 | G39: =$C39*F39/100 -> 0 | H39: 3.24 | L39: =$H39*K39/100 -> 0 | M39: 3.59 | Q39: =$M39*P39/100 -> 0 | R39: 4.4 | V39: =$R39*U39/100 -> 0 | W39: 3.43 | AA39: =$W39*Z39/100 -> 0 | AB39: 18.83 | AF39: =$AB39*AE39/100 -> 0 | AG39: 7.49 | AK39: =$AG39*AJ39/100 -> 0 | AL39: 6.71 | AP39: =$AL39*AO39/100 -> 0
B40: 4.14 Metal sheet roofing with sand coating on steel (Imported) | C40: 4.79 | G40: =$C40*F40/100 -> 0 | H40: 2.69 | L40: =$H40*K40/100 -> 0 | M40: 2.98 | Q40: =$M40*P40/100 -> 0 | R40: 3.66 | V40: =$R40*U40/100 -> 0 | W40: 2.85 | AA40: =$W40*Z40/100 -> 0 | AB40: 15.65 | AF40: =$AB40*AE40/100 -> 0 | AG40: 6.23 | AK40: =$AG40*AJ40/100 -> 0 | AL40: 5.57 | AP40: =$AL40*AO40/100 -> 0
B41: 4.15 Metal sheet roofing with sand coating on steel (local) | C41: 2.98 | G41: =$C41*F41/100 -> 0 | H41: 2.1 | L41: =$H41*K41/100 -> 0 | M41: 2.34 | Q41: =$M41*P41/100 -> 0 | R41: 2.86 | V41: =$R41*U41/100 -> 0 | W41: 2.23 | AA41: =$W41*Z41/100 -> 0 | AB41: 12.25 | AF41: =$AB41*AE41/100 -> 0 | AG41: 4.87 | AK41: =$AG41*AJ41/100 -> 0 | AL41: 4.36 | AP41: =$AL41*AO41/100 -> 0
A42: 5 | B42: Joinery | G42: =$C42*F42/100 -> 0 | L42: =$H42*K42/100 -> 0 | Q42: =$M42*P42/100 -> 0 | V42: =$R42*U42/100 -> 0 | AA42: =$W42*Z42/100 -> 0 | AF42: =$AB42*AE42/100 -> 0 | AK42: =$AG42*AJ42/100 -> 0 | AP42: =$AL42*AO42/100 -> 0
B43: 5.1 Internal wooden door made of Low quality wood | C43: 0.51 | D43: =MAX(C43:C49) -> 3.98 | E43: =MIN(C43:C49) -> 0.51 | G43: =$C43*F43/100 -> 0 | H43: 0.81 | I43: =MAX(H43:H49) -> 5.19 | J43: =MIN(H43:H49) -> 0.81 | L43: =$H43*K43/100 -> 0 | M43: 0.89 | N43: =MAX(M43:M49) -> 5.04 | O43: =MIN(M43:M49) -> 0.89 | Q43: =$M43*P43/100 -> 0 | R43: 0.74 | S43: =MAX(R43:R49) -> 3.29 | T43: =MIN(R43:R49) -> 0.74 | V43: =$R43*U43/100 -> 0 | W43: 0.07 | X43: =MAX(W43:W49) -> 0.44 | Y43: =MIN(W43:W49) -> 0.07 | AA43: =$W43*Z43/100 -> 0 | AB43: 0.61 | AC43: =MAX(AB43:AB49) -> 3.89 | AD43: =MIN(AB43:AB49) -> 0.61 | AF43: =$AB43*AE43/100 -> 0 | AG43: 1.47 | AH43: =MAX(AG43:AG49) -> 9.43 | AI43: =MIN(AG43:AG49) -> 1.47 | AK43: =$AG43*AJ43/100 -> 0 | AL43: 0.04 | AM43: =MAX(AL43:AL49) -> 0.23 | AN43: =MIN(AL43:AL49) -> 0.04 | AP43: =$AL43*AO43/100 -> 0
B44: 5.2 As item No.1 above but made of medium Quality wood | C44: 0.73 | G44: =$C44*F44/100 -> 0 | H44: 0.95 | L44: =$H44*K44/100 -> 0 | M44: 1.02 | Q44: =$M44*P44/100 -> 0 | R44: 0.82 | V44: =$R44*U44/100 -> 0 | W44: 0.08 | AA44: =$W44*Z44/100 -> 0 | AB44: 0.71 | AF44: =$AB44*AE44/100 -> 0 | AG44: 1.72 | AK44: =$AG44*AJ44/100 -> 0 | AL44: 0.04 | AP44: =$AL44*AO44/100 -> 0
B45: 5.3 As item No.2 above but with built-in cup board | C45: 2.2 | G45: =$C45*F45/100 -> 0 | H45: 1.04 | L45: =$H45*K45/100 -> 0 | M45: 1.1 | Q45: =$M45*P45/100 -> 0 | R45: 0.88 | V45: =$R45*U45/100 -> 0 | W45: 0.09 | AA45: =$W45*Z45/100 -> 0 | AB45: 0.78 | AF45: =$AB45*AE45/100 -> 0 | AG45: 1.88 | AK45: =$AG45*AJ45/100 -> 0 | AL45: 0.05 | AP45: =$AL45*AO45/100 -> 0
B46: 5.4 As item No.1 above but made of Quality wood | C46: 1.36 | F46: 100 | G46: =$C46*F46/100 -> 1.36 | H46: 1.78 | L46: =$H46*K46/100 -> 0 | M46: 1.8 | Q46: =$M46*P46/100 -> 0 | R46: 1.31 | V46: =$R46*U46/100 -> 0 | W46: 0.15 | AA46: =$W46*Z46/100 -> 0 | AB46: 1.33 | AF46: =$AB46*AE46/100 -> 0 | AG46: 3.23 | AK46: =$AG46*AJ46/100 -> 0 | AL46: 0.08 | AP46: =$AL46*AO46/100 -> 0
B47: 5.5 As item No.4 above but with built-in cup board | C47: 3.08 | G47: =$C47*F47/100 -> 0 | H47: 4.02 | L47: =$H47*K47/100 -> 0 | M47: 3.93 | Q47: =$M47*P47/100 -> 0 | R47: 2.61 | V47: =$R47*U47/100 -> 0 | W47: 0.34 | AA47: =$W47*Z47/100 -> 0 | AB47: 3.01 | AF47: =$AB47*AE47/100 -> 0 | AG47: 7.31 | AK47: =$AG47*AJ47/100 -> 0 | AL47: 0.18 | AP47: =$AL47*AO47/100 -> 0
B48: 5.6 As item No.1 above but made of best Quality wood | C48: 2.26 | G48: =$C48*F48/100 -> 0 | H48: 2.94 | L48: =$H48*K48/100 -> 0 | M48: 2.91 | Q48: =$M48*P48/100 -> 0 | R48: 1.99 | V48: =$R48*U48/100 -> 0 | W48: 0.25 | AA48: =$W48*Z48/100 -> 0 | AB48: 2.21 | AF48: =$AB48*AE48/100 -> 0 | AG48: 5.35 | AK48: =$AG48*AJ48/100 -> 0 | AL48: 0.13 | AP48: =$AL48*AO48/100 -> 0
B49: 5.7 As item No.6 above but with built-in cup board | C49: 3.98 | G49: =$C49*F49/100 -> 0 | H49: 5.19 | L49: =$H49*K49/100 -> 0 | M49: 5.04 | Q49: =$M49*P49/100 -> 0 | R49: 3.29 | V49: =$R49*U49/100 -> 0 | W49: 0.44 | AA49: =$W49*Z49/100 -> 0 | AB49: 3.89 | AF49: =$AB49*AE49/100 -> 0 | AG49: 9.43 | AK49: =$AG49*AJ49/100 -> 0 | AL49: 0.23 | AP49: =$AL49*AO49/100 -> 0
A50: 6 | B50: Metal Works | G50: =$C50*F50/100 -> 0 | L50: =$H50*K50/100 -> 0 | Q50: =$M50*P50/100 -> 0 | V50: =$R50*U50/100 -> 0 | AA50: =$W50*Z50/100 -> 0 | AF50: =$AB50*AE50/100 -> 0 | AK50: =$AG50*AJ50/100 -> 0 | AP50: =$AL50*AO50/100 -> 0
B51: 6.1 LTZ or RHS profile for external openings with clear glass | C51: 2.02 | D51: =MAX(C51:C63) -> 2.9 | E51: =MIN(C51:C63) -> 1.66 | G51: =$C51*F51/100 -> 0 | H51: 1.62 | I51: =MAX(H51:H63) -> 2.29 | J51: =MIN(H51:H63) -> 1.35 | L51: =$H51*K51/100 -> 0 | M51: 1.2 | N51: =MAX(M51:M63) -> 1.63 | O51: =MIN(M51:M63) -> 1.03 | Q51: =$M51*P51/100 -> 0 | R51: 2.03 | S51: =MAX(R51:R63) -> 3.02 | T51: =MIN(R51:R63) -> 1.63 | V51: =$R51*U51/100 -> 0 | W51: 0.66 | X51: =MAX(W51:W63) -> 0.96 | Y51: =MIN(W51:W63) -> 0.54 | AA51: =$W51*Z51/100 -> 0 | AB51: 0.73 | AC51: =MAX(AB51:AB63) -> 1.18 | AD51: =MIN(AB51:AB63) -> 0.55 | AF51: =$AB51*AE51/100 -> 0 | AG51: 0.58 | AH51: =MAX(AG51:AG63) -> 0.88 | AI51: =MIN(AG51:AG63) -> 0.47 | AK51: =$AG51*AJ51/100 -> 0 | AL51: 0.61 | AM51: =MAX(AL51:AL63) -> 0.99 | AN51: =MIN(AL51:AL63) -> 0.46 | AP51: =$AL51*AO51/100 -> 0
B52: 6.2 LTZ with 4mm- frosted glass | C52: 2.07 | G52: =$C52*F52/100 -> 0 | H52: 1.66 | L52: =$H52*K52/100 -> 0 | M52: 1.23 | Q52: =$M52*P52/100 -> 0 | R52: 2.09 | V52: =$R52*U52/100 -> 0 | W52: 0.68 | AA52: =$W52*Z52/100 -> 0 | AB52: 0.76 | AF52: =$AB52*AE52/100 -> 0 | AG52: 0.6 | AK52: =$AG52*AJ52/100 -> 0 | AL52: 0.63 | AP52: =$AL52*AO52/100 -> 0
B53: 6.3 Ditto but with 4mm-tinted glass | C53: 2.07 | G53: =$C53*F53/100 -> 0 | H53: 1.66 | L53: =$H53*K53/100 -> 0 | M53: 1.22 | Q53: =$M53*P53/100 -> 0 | R53: 2.08 | V53: =$R53*U53/100 -> 0 | W53: 0.68 | AA53: =$W53*Z53/100 -> 0 | AB53: 0.76 | AF53: =$AB53*AE53/100 -> 0 | AG53: 0.6 | AK53: =$AG53*AJ53/100 -> 0 | AL53: 0.63 | AP53: =$AL53*AO53/100 -> 0
B54: 6.4 Ditto but with 6mm-tinted glass | C54: 2.27 | G54: =$C54*F54/100 -> 0 | H54: 1.81 | L54: =$H54*K54/100 -> 0 | M54: 1.32 | Q54: =$M54*P54/100 -> 0 | R54: 2.31 | V54: =$R54*U54/100 -> 0 | W54: 0.75 | AA54: =$W54*Z54/100 -> 0 | AB54: 0.86 | AF54: =$AB54*AE54/100 -> 0 | AG54: 0.67 | AK54: =$AG54*AJ54/100 -> 0 | AL54: 0.72 | AP54: =$AL54*AO54/100 -> 0
B55: 6.5 Secco profile for external openings with clear glass | C55: 1.66 | G55: =$C55*F55/100 -> 0 | H55: 1.35 | L55: =$H55*K55/100 -> 0 | M55: 1.03 | Q55: =$M55*P55/100 -> 0 | R55: 1.63 | V55: =$R55*U55/100 -> 0 | W55: 0.54 | AA55: =$W55*Z55/100 -> 0 | AB55: 0.55 | AF55: =$AB55*AE55/100 -> 0 | AG55: 0.47 | AK55: =$AG55*AJ55/100 -> 0 | AL55: 0.46 | AP55: =$AL55*AO55/100 -> 0
B56: 6.6 Secco with 4mm-frosted glass | C56: 1.7 | G56: =$C56*F56/100 -> 0 | H56: 1.37 | L56: =$H56*K56/100 -> 0 | M56: 1.04 | Q56: =$M56*P56/100 -> 0 | R56: 1.66 | V56: =$R56*U56/100 -> 0 | W56: 0.56 | AA56: =$W56*Z56/100 -> 0 | AB56: 0.57 | AF56: =$AB56*AE56/100 -> 0 | AG56: 0.48 | AK56: =$AG56*AJ56/100 -> 0 | AL56: 0.47 | AP56: =$AL56*AO56/100 -> 0
B57: 6.7 Ditto but with 4mm-tinted glass | C57: 1.71 | G57: =$C57*F57/100 -> 0 | H57: 1.38 | L57: =$H57*K57/100 -> 0 | M57: 1.05 | Q57: =$M57*P57/100 -> 0 | R57: 1.68 | V57: =$R57*U57/100 -> 0 | W57: 0.56 | AA57: =$W57*Z57/100 -> 0 | AB57: 0.58 | AF57: =$AB57*AE57/100 -> 0 | AG57: 0.48 | AK57: =$AG57*AJ57/100 -> 0 | AL57: 0.48 | AP57: =$AL57*AO57/100 -> 0
B58: 6.8 Ditto but with 6mm-tinted glass | C58: 1.91 | G58: =$C58*F58/100 -> 0 | H58: 1.54 | L58: =$H58*K58/100 -> 0 | M58: 1.15 | Q58: =$M58*P58/100 -> 0 | R58: 1.9 | V58: =$R58*U58/100 -> 0 | W58: 0.63 | AA58: =$W58*Z58/100 -> 0 | AB58: 0.68 | AF58: =$AB58*AE58/100 -> 0 | AG58: 0.55 | AK58: =$AG58*AJ58/100 -> 0 | AL58: 0.56 | AP58: =$AL58*AO58/100 -> 0
B59: 6.9 Imitation with clear glass | C59: 2.39 | G59: =$C59*F59/100 -> 0 | H59: 1.88 | L59: =$H59*K59/100 -> 0 | M59: 1.33 | Q59: =$M59*P59/100 -> 0 | R59: 2.33 | V59: =$R59*U59/100 -> 0 | W59: 0.76 | AA59: =$W59*Z59/100 -> 0 | AB59: 0.87 | AF59: =$AB59*AE59/100 -> 0 | AG59: 0.67 | AK59: =$AG59*AJ59/100 -> 0 | AL59: 0.72 | AP59: =$AL59*AO59/100 -> 0
B60: 6.10 Imitation with 4mm frosted glass | C60: 2.41 | G60: =$C60*F60/100 -> 0 | H60: 1.9 | L60: =$H60*K60/100 -> 0 | M60: 1.34 | Q60: =$M60*P60/100 -> 0 | R60: 2.36 | V60: =$R60*U60/100 -> 0 | W60: 0.76 | AA60: =$W60*Z60/100 -> 0 | AB60: 0.88 | AF60: =$AB60*AE60/100 -> 0 | AG60: 0.68 | AK60: =$AG60*AJ60/100 -> 0 | AL60: 0.74 | AP60: =$AL60*AO60/100 -> 0
B61: 6.11 Imitation with 4mm tinted glass | C61: 2.41 | G61: =$C61*F61/100 -> 0 | H61: 1.9 | L61: =$H61*K61/100 -> 0 | M61: 1.34 | Q61: =$M61*P61/100 -> 0 | R61: 2.36 | V61: =$R61*U61/100 -> 0 | W61: 0.76 | AA61: =$W61*Z61/100 -> 0 | AB61: 0.88 | AF61: =$AB61*AE61/100 -> 0 | AG61: 0.68 | AK61: =$AG61*AJ61/100 -> 0 | AL61: 0.73 | AP61: =$AL61*AO61/100 -> 0
B62: 6.12 Imitation with 6mm tinted glass | C62: 2.5 | G62: =$C62*F62/100 -> 0 | H62: 1.97 | L62: =$H62*K62/100 -> 0 | M62: 1.38 | Q62: =$M62*P62/100 -> 0 | R62: 2.46 | V62: =$R62*U62/100 -> 0 | W62: 0.79 | AA62: =$W62*Z62/100 -> 0 | AB62: 0.93 | AF62: =$AB62*AE62/100 -> 0 | AG62: 0.71 | AK62: =$AG62*AJ62/100 -> 0 | AL62: 0.77 | AP62: =$AL62*AO62/100 -> 0
B63: 6.13 Aluminium profile for external opening | C63: 2.9 | F63: 100 | G63: =$C63*F63/100 -> 2.9 | H63: 2.29 | L63: =$H63*K63/100 -> 0 | M63: 1.63 | Q63: =$M63*P63/100 -> 0 | R63: 3.02 | V63: =$R63*U63/100 -> 0 | W63: 0.96 | AA63: =$W63*Z63/100 -> 0 | AB63: 1.18 | AF63: =$AB63*AE63/100 -> 0 | AG63: 0.88 | AK63: =$AG63*AJ63/100 -> 0 | AL63: 0.99 | AP63: =$AL63*AO63/100 -> 0
A64: 7 | B64: Floor Finish | G64: =$C64*F64/100 -> 0 | L64: =$H64*K64/100 -> 0 | Q64: =$M64*P64/100 -> 0 | V64: =$R64*U64/100 -> 0 | AA64: =$W64*Z64/100 -> 0 | AF64: =$AB64*AE64/100 -> 0 | AK64: =$AG64*AJ64/100 -> 0 | AP64: =$AL64*AO64/100 -> 0
B65: 7.1 Cement Screed | C65: 0.37 | D65: =MAX(C65:C82) -> 4.49 | E65: =MIN(C65:C82) -> 0.37 | G65: =$C65*F65/100 -> 0 | H65: 0.4 | I65: =MAX(H65:H82) -> 5.07 | J65: =MIN(H65:H82) -> 0.4 | L65: =$H65*K65/100 -> 0 | M65: 0.55 | N65: =MAX(M65:M82) -> 5.07 | O65: =MIN(M65:M82) -> 0.55 | Q65: =$M65*P65/100 -> 0 | R65: 0.34 | S65: =MAX(R65:R82) -> 5.19 | T65: =MIN(R65:R82) -> 0.34 | V65: =$R65*U65/100 -> 0 | W65: 0.18 | X65: =MAX(W65:W82) -> 1.53 | Y65: =MIN(W65:W82) -> 0.18 | AA65: =$W65*Z65/100 -> 0 | AB65: 0.43 | AC65: =MAX(AB65:AB82) -> 3.7 | AD65: =MIN(AB65:AB82) -> 0.43 | AF65: =$AB65*AE65/100 -> 0 | AG65: 0.39 | AH65: =MAX(AG65:AG82) -> 3.55 | AI65: =MIN(AG65:AG82) -> 0.39 | AK65: =$AG65*AJ65/100 -> 0 | AL65: 0.3 | AM65: =MAX(AL65:AL82) -> 3.63 | AN65: =MIN(AL65:AL82) -> 0.3 | AP65: =$AL65*AO65/100 -> 0
B66: 7.2 Cement Tile | C66: 0.68 | G66: =$C66*F66/100 -> 0 | H66: 0.76 | L66: =$H66*K66/100 -> 0 | M66: 0.89 | Q66: =$M66*P66/100 -> 0 | R66: 0.71 | V66: =$R66*U66/100 -> 0 | W66: 0.28 | AA66: =$W66*Z66/100 -> 0 | AB66: 0.68 | AF66: =$AB66*AE66/100 -> 0 | AG66: 0.64 | AK66: =$AG66*AJ66/100 -> 0 | AL66: 0.55 | AP66: =$AL66*AO66/100 -> 0
B67: 7.3 Terrazzo Tile | C67: 0.94 | G67: =$C67*F67/100 -> 0 | H67: 1.05 | L67: =$H67*K67/100 -> 0 | M67: 1.18 | Q67: =$M67*P67/100 -> 0 | R67: 1.01 | V67: =$R67*U67/100 -> 0 | W67: 0.36 | AA67: =$W67*Z67/100 -> 0 | AB67: 0.88 | AF67: =$AB67*AE67/100 -> 0 | AG67: 0.83 | AK67: =$AG67*AJ67/100 -> 0 | AL67: 0.76 | AP67: =$AL67*AO67/100 -> 0
B68: 7.4 PVC tile | C68: 1.09 | G68: =$C68*F68/100 -> 0 | H68: 1.22 | L68: =$H68*K68/100 -> 0 | M68: 1.34 | Q68: =$M68*P68/100 -> 0 | R68: 1.19 | V68: =$R68*U68/100 -> 0 | W68: 0.41 | AA68: =$W68*Z68/100 -> 0 | AB68: 1 | AF68: =$AB68*AE68/100 -> 0 | AG68: 0.94 | AK68: =$AG68*AJ68/100 -> 0 | AL68: 0.88 | AP68: =$AL68*AO68/100 -> 0
B69: 7.5 Ceramic medium quality Porcelain | C69: 1.22 | G69: =$C69*F69/100 -> 0 | H69: 1.37 | L69: =$H69*K69/100 -> 0 | M69: 1.48 | Q69: =$M69*P69/100 -> 0 | R69: 1.34 | V69: =$R69*U69/100 -> 0 | W69: 0.46 | AA69: =$W69*Z69/100 -> 0 | AB69: 1.11 | AF69: =$AB69*AE69/100 -> 0 | AG69: 1.05 | AK69: =$AG69*AJ69/100 -> 0 | AL69: 0.99 | AP69: =$AL69*AO69/100 -> 0
B70: 7.6 Ceramic best quality | C70: 1.86 | F70: 100 | G70: =$C70*F70/100 -> 1.86 | H70: 2.09 | L70: =$H70*K70/100 -> 0 | M70: 2.18 | Q70: =$M70*P70/100 -> 0 | R70: 2.1 | V70: =$R70*U70/100 -> 0 | W70: 0.67 | AA70: =$W70*Z70/100 -> 0 | AB70: 1.61 | AF70: =$AB70*AE70/100 -> 0 | AG70: 1.54 | AK70: =$AG70*AJ70/100 -> 0 | AL70: 1.51 | AP70: =$AL70*AO70/100 -> 0
B71: 7.7 Porcelain | C71: 1.64 | G71: =$C71*F71/100 -> 0 | H71: 1.83 | L71: =$H71*K71/100 -> 0 | M71: 1.87 | Q71: =$M71*P71/100 -> 0 | R71: 1.76 | V71: =$R71*U71/100 -> 0 | W71: 0.57 | AA71: =$W71*Z71/100 -> 0 | AB71: 1.39 | AF71: =$AB71*AE71/100 -> 0 | AG71: 1.32 | AK71: =$AG71*AJ71/100 -> 0 | AL71: 1.27 | AP71: =$AL71*AO71/100 -> 0
B72: 7.8 Mosaic | C72: 2.25 | G72: =$C72*F72/100 -> 0 | H72: 2.53 | L72: =$H72*K72/100 -> 0 | M72: 2.61 | Q72: =$M72*P72/100 -> 0 | R72: 2.55 | V72: =$R72*U72/100 -> 0 | W72: 0.8 | AA72: =$W72*Z72/100 -> 0 | AB72: 1.92 | AF72: =$AB72*AE72/100 -> 0 | AG72: 1.83 | AK72: =$AG72*AJ72/100 -> 0 | AL72: 1.82 | AP72: =$AL72*AO72/100 -> 0
B73: 7.9 Marble chip lower quality | C73: 1.96 | G73: =$C73*F73/100 -> 0 | H73: 2.2 | L73: =$H73*K73/100 -> 0 | M73: 2.29 | Q73: =$M73*P73/100 -> 0 | R73: 2.21 | V73: =$R73*U73/100 -> 0 | W73: 0.7 | AA73: =$W73*Z73/100 -> 0 | AB73: 1.69 | AF73: =$AB73*AE73/100 -> 0 | AG73: 1.61 | AK73: =$AG73*AJ73/100 -> 0 | AL73: 1.58 | AP73: =$AL73*AO73/100 -> 0
B74: 7.10 Marble chip best quality | C74: 2.33 | G74: =$C74*F74/100 -> 0 | H74: 2.63 | L74: =$H74*K74/100 -> 0 | M74: 2.7 | Q74: =$M74*P74/100 -> 0 | R74: 2.65 | V74: =$R74*U74/100 -> 0 | W74: 0.82 | AA74: =$W74*Z74/100 -> 0 | AB74: 1.99 | AF74: =$AB74*AE74/100 -> 0 | AG74: 1.9 | AK74: =$AG74*AJ74/100 -> 0 | AL74: 1.89 | AP74: =$AL74*AO74/100 -> 0
B75: 7.11 Harar marble | C75: 2.7 | G75: =$C75*F75/100 -> 0 | H75: 3.05 | L75: =$H75*K75/100 -> 0 | M75: 3.11 | Q75: =$M75*P75/100 -> 0 | R75: 3.09 | V75: =$R75*U75/100 -> 0 | W75: 0.95 | AA75: =$W75*Z75/100 -> 0 | AB75: 2.28 | AF75: =$AB75*AE75/100 -> 0 | AG75: 2.18 | AK75: =$AG75*AJ75/100 -> 0 | AL75: 2.19 | AP75: =$AL75*AO75/100 -> 0
B76: 7.12 Mankush marble | C76: 3.79 | G76: =$C76*F76/100 -> 0 | H76: 4.28 | L76: =$H76*K76/100 -> 0 | M76: 4.3 | Q76: =$M76*P76/100 -> 0 | R76: 4.37 | V76: =$R76*U76/100 -> 0 | W76: 1.3 | AA76: =$W76*Z76/100 -> 0 | AB76: 3.14 | AF76: =$AB76*AE76/100 -> 0 | AG76: 3.01 | AK76: =$AG76*AJ76/100 -> 0 | AL76: 3.07 | AP76: =$AL76*AO76/100 -> 0
B77: 7.13 Parquet lower quality on screed | C77: 1.99 | G77: =$C77*F77/100 -> 0 | H77: 2.24 | L77: =$H77*K77/100 -> 0 | M77: 2.33 | Q77: =$M77*P77/100 -> 0 | R77: 2.25 | V77: =$R77*U77/100 -> 0 | W77: 0.71 | AA77: =$W77*Z77/100 -> 0 | AB77: 1.72 | AF77: =$AB77*AE77/100 -> 0 | AG77: 1.64 | AK77: =$AG77*AJ77/100 -> 0 | AL77: 1.61 | AP77: =$AL77*AO77/100 -> 0
B78: 7.14 Parquet best quality on screed | C78: 4.49 | G78: =$C78*F78/100 -> 0 | H78: 5.07 | L78: =$H78*K78/100 -> 0 | M78: 5.07 | Q78: =$M78*P78/100 -> 0 | R78: 5.19 | V78: =$R78*U78/100 -> 0 | W78: 1.53 | AA78: =$W78*Z78/100 -> 0 | AB78: 3.7 | AF78: =$AB78*AE78/100 -> 0 | AG78: 3.55 | AK78: =$AG78*AJ78/100 -> 0 | AL78: 3.63 | AP78: =$AL78*AO78/100 -> 0
B79: 7.15 Parquet quality on screed | C79: 3.07 | G79: =$C79*F79/100 -> 0 | H79: 3.46 | L79: =$H79*K79/100 -> 0 | M79: 3.51 | Q79: =$M79*P79/100 -> 0 | R79: 3.52 | V79: =$R79*U79/100 -> 0 | W79: 1.07 | AA79: =$W79*Z79/100 -> 0 | AB79: 2.58 | AF79: =$AB79*AE79/100 -> 0 | AG79: 2.46 | AK79: =$AG79*AJ79/100 -> 0 | AL79: 2.49 | AP79: =$AL79*AO79/100 -> 0
B80: 7.16 Parquet medium quality on screed | C80: 1.99 | G80: =$C80*F80/100 -> 0 | H80: 2.25 | L80: =$H80*K80/100 -> 0 | M80: 2.33 | Q80: =$M80*P80/100 -> 0 | R80: 2.25 | V80: =$R80*U80/100 -> 0 | W80: 0.71 | AA80: =$W80*Z80/100 -> 0 | AB80: 1.72 | AF80: =$AB80*AE80/100 -> 0 | AG80: 1.64 | AK80: =$AG80*AJ80/100 -> 0 | AL80: 1.61 | AP80: =$AL80*AO80/100 -> 0
B81: 7.17 Parquet poor quality on wooden frame | C81: 1.7 | G81: =$C81*F81/100 -> 0 | H81: 1.91 | L81: =$H81*K81/100 -> 0 | M81: 2.01 | Q81: =$M81*P81/100 -> 0 | R81: 1.91 | V81: =$R81*U81/100 -> 0 | W81: 0.62 | AA81: =$W81*Z81/100 -> 0 | AB81: 1.49 | AF81: =$AB81*AE81/100 -> 0 | AG81: 1.41 | AK81: =$AG81*AJ81/100 -> 0 | AL81: 1.38 | AP81: =$AL81*AO81/100 -> 0
B82: 7.18 Granite | C82: 2.86 | G82: =$C82*F82/100 -> 0 | H82: 3.23 | L82: =$H82*K82/100 -> 0 | M82: 3.28 | Q82: =$M82*P82/100 -> 0 | R82: 3.28 | V82: =$R82*U82/100 -> 0 | W82: 1 | AA82: =$W82*Z82/100 -> 0 | AB82: 2.41 | AF82: =$AB82*AE82/100 -> 0 | AG82: 2.3 | AK82: =$AG82*AJ82/100 -> 0 | AL82: 2.32 | AP82: =$AL82*AO82/100 -> 0
A83: 8 | B83: Wall Finish | G83: =$C83*F83/100 -> 0 | L83: =$H83*K83/100 -> 0 | Q83: =$M83*P83/100 -> 0 | V83: =$R83*U83/100 -> 0 | AA83: =$W83*Z83/100 -> 0 | AF83: =$AB83*AE83/100 -> 0 | AK83: =$AG83*AJ83/100 -> 0 | AP83: =$AL83*AO83/100 -> 0
B84: 8.1 Internal | G84: =$C84*F84/100 -> 0 | L84: =$H84*K84/100 -> 0 | Q84: =$M84*P84/100 -> 0 | V84: =$R84*U84/100 -> 0 | AA84: =$W84*Z84/100 -> 0 | AF84: =$AB84*AE84/100 -> 0 | AK84: =$AG84*AJ84/100 -> 0 | AP84: =$AL84*AO84/100 -> 0
B85: 8.1.1 plasterd | C85: 1.18 | D85: =MAX(C85:C101) -> 11.23 | E85: =MIN(C85:C101) -> 0.52 | G85: =$C85*F85/100 -> 0 | H85: 0.9 | I85: =MAX(H85:H101) -> 8.56 | J85: =MIN(H85:H101) -> 0.4 | L85: =$H85*K85/100 -> 0 | M85: 0.98 | N85: =MAX(M85:M101) -> 9.31 | O85: =MIN(M85:M101) -> 0.43 | Q85: =$M85*P85/100 -> 0 | R85: 0.7 | S85: =MAX(R85:R101) -> 6.64 | T85: =MIN(R85:R101) -> 0.31 | V85: =$R85*U85/100 -> 0 | W85: 0.33 | X85: =MAX(W85:W101) -> 3.12 | Y85: =MIN(W85:W101) -> 0.15 | AA85: =$W85*Z85/100 -> 0 | AB85: 0.65 | AC85: =MAX(AB85:AB101) -> 3.1 | AD85: =MIN(AB85:AB101) -> 0.49 | AF85: =$AB85*AE85/100 -> 0 | AG85: 0.8 | AH85: =MAX(AG85:AG101) -> 7.64 | AI85: =MIN(AG85:AG101) -> 0.36 | AK85: =$AG85*AJ85/100 -> 0 | AL85: 1.25 | AM85: =MAX(AL85:AL101) -> 11.87 | AN85: =MIN(AL85:AL101) -> 0.55 | AP85: =$AL85*AO85/100 -> 0
B86: 8.1.2 Plasterd and painted | C86: 1.59 | F86: 100 | G86: =$C86*F86/100 -> 1.59 | H86: 1.21 | L86: =$H86*K86/100 -> 0 | M86: 1.32 | Q86: =$M86*P86/100 -> 0 | R86: 0.94 | V86: =$R86*U86/100 -> 0 | W86: 0.44 | AA86: =$W86*Z86/100 -> 0 | AB86: 0.75 | AF86: =$AB86*AE86/100 -> 0 | AG86: 1.08 | AK86: =$AG86*AJ86/100 -> 0 | AL86: 1.68 | AP86: =$AL86*AO86/100 -> 0
B87: 8.1.3 Pointed HCB | C87: 0.52 | G87: =$C87*F87/100 -> 0 | H87: 0.4 | L87: =$H87*K87/100 -> 0 | M87: 0.43 | Q87: =$M87*P87/100 -> 0 | R87: 0.31 | V87: =$R87*U87/100 -> 0 | W87: 0.15 | AA87: =$W87*Z87/100 -> 0 | AB87: 0.49 | AF87: =$AB87*AE87/100 -> 0 | AG87: 0.36 | AK87: =$AG87*AJ87/100 -> 0 | AL87: 0.55 | AP87: =$AL87*AO87/100 -> 0
B88: 8.1.4 Pointed dressed stone | C88: 0.67 | G88: =$C88*F88/100 -> 0 | H88: 0.51 | L88: =$H88*K88/100 -> 0 | M88: 0.56 | Q88: =$M88*P88/100 -> 0 | R88: 0.4 | V88: =$R88*U88/100 -> 0 | W88: 0.19 | AA88: =$W88*Z88/100 -> 0 | AB88: 0.52 | AF88: =$AB88*AE88/100 -> 0 | AG88: 0.46 | AK88: =$AG88*AJ88/100 -> 0 | AL88: 0.71 | AP88: =$AL88*AO88/100 -> 0
B89: 8.1.5 Pointed brick | C89: 0.84 | G89: =$C89*F89/100 -> 0 | H89: 0.64 | L89: =$H89*K89/100 -> 0 | M89: 0.7 | Q89: =$M89*P89/100 -> 0 | R89: 0.5 | V89: =$R89*U89/100 -> 0 | W89: 0.23 | AA89: =$W89*Z89/100 -> 0 | AB89: 0.56 | AF89: =$AB89*AE89/100 -> 0 | AG89: 0.57 | AK89: =$AG89*AJ89/100 -> 0 | AL89: 0.89 | AP89: =$AL89*AO89/100 -> 0
B90: 8.1.6 Plasterd and Addis I wall paper | C90: 4.07 | G90: =$C90*F90/100 -> 0 | H90: 3.1 | L90: =$H90*K90/100 -> 0 | M90: 3.38 | Q90: =$M90*P90/100 -> 0 | R90: 2.41 | V90: =$R90*U90/100 -> 0 | W90: 1.13 | AA90: =$W90*Z90/100 -> 0 | AB90: 1.35 | AF90: =$AB90*AE90/100 -> 0 | AG90: 2.77 | AK90: =$AG90*AJ90/100 -> 0 | AL90: 4.31 | AP90: =$AL90*AO90/100 -> 0
B91: 8.1.7 Mosaic | C91: 7.73 | G91: =$C91*F91/100 -> 0 | H91: 5.89 | L91: =$H91*K91/100 -> 0 | M91: 6.41 | Q91: =$M91*P91/100 -> 0 | R91: 4.57 | V91: =$R91*U91/100 -> 0 | W91: 2.15 | AA91: =$W91*Z91/100 -> 0 | AB91: 2.24 | AF91: =$AB91*AE91/100 -> 0 | AG91: 5.26 | AK91: =$AG91*AJ91/100 -> 0 | AL91: 8.17 | AP91: =$AL91*AO91/100 -> 0
B92: 8.1.8a Imported, high quality ceramic | C92: 6.35 | G92: =$C92*F92/100 -> 0 | H92: 4.84 | L92: =$H92*K92/100 -> 0 | M92: 5.26 | Q92: =$M92*P92/100 -> 0 | R92: 3.75 | V92: =$R92*U92/100 -> 0 | W92: 1.77 | AA92: =$W92*Z92/100 -> 0 | AB92: 1.91 | AF92: =$AB92*AE92/100 -> 0 | AG92: 4.32 | AK92: =$AG92*AJ92/100 -> 0 | AL92: 6.71 | AP92: =$AL92*AO92/100 -> 0
B93: 8.1.8b Imported, quality ceramic | C93: 4 | G93: =$C93*F93/100 -> 0 | H93: 3.05 | L93: =$H93*K93/100 -> 0 | M93: 3.32 | Q93: =$M93*P93/100 -> 0 | R93: 2.37 | V93: =$R93*U93/100 -> 0 | W93: 1.11 | AA93: =$W93*Z93/100 -> 0 | AB93: 1.33 | AF93: =$AB93*AE93/100 -> 0 | AG93: 2.72 | AK93: =$AG93*AJ93/100 -> 0 | AL93: 4.23 | AP93: =$AL93*AO93/100 -> 0
B94: 8.1.8c Imported, medium quality ceramic | C94: 2.95 | G94: =$C94*F94/100 -> 0 | H94: 2.25 | L94: =$H94*K94/100 -> 0 | M94: 2.45 | Q94: =$M94*P94/100 -> 0 | R94: 1.75 | V94: =$R94*U94/100 -> 0 | W94: 0.82 | AA94: =$W94*Z94/100 -> 0 | AB94: 1.08 | AF94: =$AB94*AE94/100 -> 0 | AG94: 2.01 | AK94: =$AG94*AJ94/100 -> 0 | AL94: 3.12 | AP94: =$AL94*AO94/100 -> 0
B95: 8.1.8d Lower quality ceramic | C95: 2.91 | G95: =$C95*F95/100 -> 0 | H95: 2.22 | L95: =$H95*K95/100 -> 0 | M95: 2.41 | Q95: =$M95*P95/100 -> 0 | R95: 1.72 | V95: =$R95*U95/100 -> 0 | W95: 0.81 | AA95: =$W95*Z95/100 -> 0 | AB95: 1.07 | AF95: =$AB95*AE95/100 -> 0 | AG95: 1.98 | AK95: =$AG95*AJ95/100 -> 0 | AL95: 3.08 | AP95: =$AL95*AO95/100 -> 0
B96: 8.1.9 Pointed and painted HCB | C96: 0.94 | G96: =$C96*F96/100 -> 0 | H96: 0.71 | L96: =$H96*K96/100 -> 0 | M96: 0.78 | Q96: =$M96*P96/100 -> 0 | R96: 0.55 | V96: =$R96*U96/100 -> 0 | W96: 0.26 | AA96: =$W96*Z96/100 -> 0 | AB96: 0.59 | AF96: =$AB96*AE96/100 -> 0 | AG96: 0.64 | AK96: =$AG96*AJ96/100 -> 0 | AL96: 0.99 | AP96: =$AL96*AO96/100 -> 0
B97: 8.1.10 Pointed and painted Brick | C97: 1.25 | G97: =$C97*F97/100 -> 0 | H97: 0.96 | L97: =$H97*K97/100 -> 0 | M97: 1.04 | Q97: =$M97*P97/100 -> 0 | R97: 0.74 | V97: =$R97*U97/100 -> 0 | W97: 0.35 | AA97: =$W97*Z97/100 -> 0 | AB97: 0.66 | AF97: =$AB97*AE97/100 -> 0 | AG97: 0.85 | AK97: =$AG97*AJ97/100 -> 0 | AL97: 1.32 | AP97: =$AL97*AO97/100 -> 0
B98: 8.1.11 Harar marble | C98: 7.09 | G98: =$C98*F98/100 -> 0 | H98: 5.4 | L98: =$H98*K98/100 -> 0 | M98: 5.87 | Q98: =$M98*P98/100 -> 0 | R98: 4.19 | V98: =$R98*U98/100 -> 0 | W98: 1.97 | AA98: =$W98*Z98/100 -> 0 | AB98: 2.09 | AF98: =$AB98*AE98/100 -> 0 | AG98: 4.82 | AK98: =$AG98*AJ98/100 -> 0 | AL98: 7.49 | AP98: =$AL98*AO98/100 -> 0
... B101: 8.1.15 Granite | C101: 10.51 | G101: =$C101*F101/100 -> 0 | H101: 8.01 | L101: =$H101*K101/100 -> 0 | M101: 8.71 | Q101: =$M101*P101/100 -> 0 | R101: 6.22 | V101: =$R101*U101/100 -> 0 | W101: 2.92 | AA101: =$W101*Z101/100 -> 0 | AB101: 2.92 | AF101: =$AB101*AE101/100 -> 0 | AG101: 7.15 | AK101: =$AG101*AJ101/100 -> 0 | AL101: 11.11 | AP101: =$AL101*AO101/100 -> 0
B102: 8.2 External | G102: =$C102*F102/100 -> 0 | L102: =$H102*K102/100 -> 0 | Q102: =$M102*P102/100 -> 0 | V102: =$R102*U102/100 -> 0 | AA102: =$W102*Z102/100 -> 0 | AF102: =$AB102*AE102/100 -> 0 | AK102: =$AG102*AJ102/100 -> 0 | AP102: =$AL102*AO102/100 -> 0
B103: 8.2.1 Plastering | C103: 0.55 | D103: =MAX(C103:C127) -> 5.2 | E103: =MIN(C103:C127) -> 0.24 | G103: =$C103*F103/100 -> 0 | H103: 0.23 | I103: =MAX(H103:H127) -> 2.24 | J103: =MIN(H103:H127) -> 0.1 | L103: =$H103*K103/100 -> 0 | M103: 0.24 | N103: =MAX(M103:M127) -> 2.25 | O103: =MIN(M103:M127) -> 0.11 | Q103: =$M103*P103/100 -> 0 | R103: 0.2 | S103: =MAX(R103:R127) -> 1.87 | T103: =MIN(R103:R127) -> 0.09 | V103: =$R103*U103/100 -> 0 | W103: 0.1 | X103: =MAX(W103:W127) -> 0.97 | Y103: =MIN(W103:W127) -> 0.05 | AA103: =$W103*Z103/100 -> 0 | AB103: 0.16 | AC103: =MAX(AB103:AB127) -> 1.14 | AD103: =MIN(AB103:AB127) -> 0.09 | AF103: =$AB103*AE103/100 -> 0 | AG103: 0.12 | AH103: =MAX(AG103:AG127) -> 0.87 | AI103: =MIN(AG103:AG127) -> 0.08 | AK103: =$AG103*AJ103/100 -> 0 | AL103: 0.11 | AM103: =MAX(AL103:AL127) -> 1.04 | AN103: =MIN(AL103:AL127) -> 0.05 | AP103: =$AL103*AO103/100 -> 0
...

Sheet Multi-Purposed halls
A2: ITEM NO. | B2: Building components
C3: H | F3: <= | G3: 4 | H3: = | K3: 4.5 | L3: = | O3: 5.5 | P3: = | S3: 6.5 | V3: = | W3: 7.5 | Z3: = | AA3: 8.5 | AD3: = | AE3: 10.5 | AH3: = | AI3: 11.5
A4: 1 | B4: Foundation | C4: Factors | D4: Max | E4: Min | H4: Max | I4: Min | L4: Max | M4: Min | P4: Max | Q4: Min | T4: Max | U4: Min | X4: Max | Y4: Min | AB4: Max | AC4: Min | AF4: Max | AG4: Min
B5: 1.1 Foundation only earthwork | C5: 0.22 | D5: =MAX(C5:C16) -> 4.2 | E5: =MIN(C5:C16) -> 0.22 | G5: =$C5*F5/100 -> 0 | H5: =MAX(C5:C16) -> 4.2 | I5: =MIN(C5:C16) -> 0.22 | K5: =$C5*H5/100 -> 0.00924 | L5: 4.2 | M5: 0.22 | O5: =C5*N5/100 -> 0 | P5: 4.2 | Q5: 0.22 | S5: =$C5*P5/100 -> 0.00924 | T5: 4.2 | U5: 0.22 | W5: =$C5*V5/100 -> 0 | X5: 4.2 | Y5: 0.22 | AA5: =$C5*Z5/100 -> 0 | AB5: 4.2 | AC5: 0.22 | AE5: =$C5*AD5/100 -> 0 | AF5: =MAX(C5:C16) -> 4.2 | AG5: =MIN(C5:C16) -> 0.22 | AI5: =$C5*AH5/100 -> 0
B6: 1.2 a. Earthwortk and masnory | C6: 0.69 | G6: =$C6*F6/100 -> 0 | K6: =$C6*H6/100 -> 0 | O6: =$C6*N6/100 -> 0 | S6: =$C6*P6/100 -> 0 | W6: =$C6*V6/100 -> 0 | AA6: =$C6*Z6/100 -> 0 | AE6: =$C6*AD6/100 -> 0 | AI6: =$C6*AH6/100 -> 0
B7: 1.2 b. AGL and BGL
B8: 1.3 Foundation work in | C8: 2 | G8: =$C8*F8/100 -> 0 | K8: =$C8*H8/100 -> 0 | O8: =$C8*N8/100 -> 0 | S8: =$C8*P8/100 -> 0 | W8: =$C8*V8/100 -> 0 | AA8: =$C8*Z8/100 -> 0 | AE8: =$C8*AD8/100 -> 0 | AI8: =$C8*AH8/100 -> 0
B9: 1.3a. Earthwork
B10: 1.3b. Hard rock
B11: 1.3c. Mass concrete floor slab
B12: 1.3d. R.C grade beam
B13: 1.3e. Masnory BGL and AGL
B14: 1.4 As item No.3 above but with R.C floor slab | C14: 2.87 | G14: =$C14*F14/100 -> 0 | K14: =$C14*H14/100 -> 0 | O14: =$C14*N14/100 -> 0 | S14: =$C14*P14/100 -> 0 | W14: =$C14*V14/100 -> 0 | AA14: =$C14*Z14/100 -> 0 | AE14: =$C14*AD14/100 -> 0 | AI14: =$C14*AH14/100 -> 0
B15: 1.5 As item no 4 above but with R.C footing and foundation column | C15: 3.43 | G15: =$C15*F15/100 -> 0 | K15: =$C15*H15/100 -> 0 | N15: 100 | O15: =$C15*N15/100 -> 3.43 | S15: =$C15*P15/100 -> 0 | W15: =$C15*V15/100 -> 0 | AA15: =$C15*Z15/100 -> 0 | AE15: =$C15*AD15/100 -> 0 | AI15: =$C15*AH15/100 -> 0
B16: 1.6 As item no 5 above but for R.C roof slab | C16: 4.2 | O16: =$C16*N16/100 -> 0
A17: 2 | B17: Structure | G17: =$C17*F17/100 -> 0 | K17: =$C17*H17/100 -> 0 | O17: =$C17*N17/100 -> 0 | S17: =$C17*P17/100 -> 0 | W17: =$C17*V17/100 -> 0 | AA17: =$C17*Z17/100 -> 0 | AE17: =$C17*AD17/100 -> 0 | AI17: =$C17*AH17/100 -> 0
B18: 2.1 .R.C structure (Elevation colums and tie beam) | C18: 1.38 | D18: =MAX(C18:C20) -> 10.76 | E18: =MIN(C18:C20) -> 1.38 | G18: =$C18*F18/100 -> 0 | H18: =MAX(C18:C20) -> 10.76 | I18: =MIN(C18:C20) -> 1.38 | K18: =$C18*H18/100 -> 0.148488 | L18: 10.76 | M18: 1.38 | N18: 100 | O18: =$C18*N18/100 -> 1.38 | P18: 10.76 | Q18: 1.38 | S18: =$C18*P18/100 -> 0.148488 | T18: 10.76 | U18: 1.38 | W18: =$C18*V18/100 -> 0 | X18: 10.76 | Y18: 1.38 | AA18: =$C18*Z18/100 -> 0 | AB18: 10.76 | AC18: 1.38 | AE18: =$C18*AD18/100 -> 0 | AF18: =MAX(C18:C20) -> 10.76 | AG18: =MIN(C18:C20) -> 1.38 | AI18: =$C18*AH18/100 -> 0
B19: 2.2 As item no.2 above but for R.C roof slab | C19: 2.37 | G19: =$C19*F19/100 -> 0 | K19: =$C19*H19/100 -> 0 | O19: =$C19*N19/100 -> 0 | S19: =$C19*P19/100 -> 0 | W19: =$C19*V19/100 -> 0 | AA19: =$C19*Z19/100 -> 0 | AE19: =$C19*AD19/100 -> 0 | AI19: =$C19*AH19/100 -> 0
B20: 2.3 Steel structure (R.H.S) | C20: 10.76 | G20: =$C20*F20/100 -> 0 | K20: =$C20*H20/100 -> 0 | O20: =$C20*N20/100 -> 0 | S20: =$C20*P20/100 -> 0 | W20: =$C20*V20/100 -> 0 | AA20: =$C20*Z20/100 -> 0 | AE20: =$C20*AD20/100 -> 0 | AI20: =$C20*AH20/100 -> 0
A21: 3 | B21: Block Work | G21: =$C21*F21/100 -> 0 | K21: =$C21*H21/100 -> 0 | O21: =$C21*N21/100 -> 0 | S21: =$C21*P21/100 -> 0 | W21: =$C21*V21/100 -> 0 | AA21: =$C21*Z21/100 -> 0 | AE21: =$C21*AD21/100 -> 0 | AI21: =$C21*AH21/100 -> 0
B22: 3.1 Internal | G22: =$C22*F22/100 -> 0 | K22: =$C22*H22/100 -> 0 | O22: =$C22*N22/100 -> 0 | S22: =$C22*P22/100 -> 0 | W22: =$C22*V22/100 -> 0 | AA22: =$C22*Z22/100 -> 0 | AE22: =$C22*AD22/100 -> 0 | AI22: =$C22*AH22/100 -> 0
B23: 3.1. see the methodology disscused on page 15 | G23: =$C23*F23/100 -> 0 | K23: =$C23*H23/100 -> 0 | O23: =$C23*N23/100 -> 0 | S23: =$C23*P23/100 -> 0 | W23: =$C23*V23/100 -> 0 | AA23: =$C23*Z23/100 -> 0 | AE23: =$C23*AD23/100 -> 0 | AI23: =$C23*AH23/100 -> 0
B24: 3.2 External | G24: =$C24*F24/100 -> 0 | K24: =$C24*H24/100 -> 0 | O24: =$C24*N24/100 -> 0 | S24: =$C24*P24/100 -> 0 | W24: =$C24*V24/100 -> 0 | AA24: =$C24*Z24/100 -> 0 | AE24: =$C24*AD24/100 -> 0 | AI24: =$C24*AH24/100 -> 0
B25: 3.2.1 Mud | C25: 0.26 | D25: =MAX(C25:C33) -> 2.42 | E25: =MIN(C25:C33) -> 0.26 | G25: =$C25*F25/100 -> 0 | H25: =MAX(C25:C33) -> 2.42 | I25: =MIN(C25:C33) -> 0.26 | K25: =$C25*H25/100 -> 0.006292 | L25: 2.42 | M25: 0.26 | O25: =$C25*N25/100 -> 0 | P25: 2.42 | Q25: 0.26 | S25: =$C25*P25/100 -> 0.006292 | T25: 2.42 | U25: 0.26 | W25: =$C25*V25/100 -> 0 | X25: 2.42 | Y25: 0.26 | AA25: =$C25*Z25/100 -> 0 | AB25: 2.42 | AC25: 0.26 | AE25: =$C25*AD25/100 -> 0 | AF25: =MAX(C25:C33) -> 2.42 | AG25: =MIN(C25:C33) -> 0.26 | AI25: =$C25*AH25/100 -> 0
B26: 3.2.2 CIS G-28 | C26: 0.52 | G26: =$C26*F26/100 -> 0 | K26: =$C26*H26/100 -> 0 | O26: =$C26*N26/100 -> 0 | S26: =$C26*P26/100 -> 0 | W26: =$C26*V26/100 -> 0 | AA26: =$C26*Z26/100 -> 0 | AE26: =$C26*AD26/100 -> 0 | AI26: =$C26*AH26/100 -> 0
B27: 3.2.3 CIS G-30 | C27: 0.38 | G27: =$C27*F27/100 -> 0 | K27: =$C27*H27/100 -> 0 | O27: =$C27*N27/100 -> 0 | S27: =$C27*P27/100 -> 0 | W27: =$C27*V27/100 -> 0 | AA27: =$C27*Z27/100 -> 0 | AE27: =$C27*AD27/100 -> 0 | AI27: =$C27*AH27/100 -> 0
B28: 3.2.4 CIS G-32 | C28: 0.4 | G28: =$C28*F28/100 -> 0 | K28: =$C28*H28/100 -> 0 | O28: =$C28*N28/100 -> 0 | S28: =$C28*P28/100 -> 0 | W28: =$C28*V28/100 -> 0 | AA28: =$C28*Z28/100 -> 0 | AE28: =$C28*AD28/100 -> 0 | AI28: =$C28*AH28/100 -> 0
B29: 3.2.5 EGA on steel | C29: 0.99 | G29: =$C29*F29/100 -> 0 | K29: =$C29*H29/100 -> 0 | O29: =$C29*N29/100 -> 0 | S29: =$C29*P29/100 -> 0 | W29: =$C29*V29/100 -> 0 | AA29: =$C29*Z29/100 -> 0 | AE29: =$C29*AD29/100 -> 0 | AI29: =$C29*AH29/100 -> 0
B30: 3.2.6 HCB 20 cm thick | C30: 0.38 | G30: =$C30*F30/100 -> 0 | K30: =$C30*H30/100 -> 0 | N30: 100 | O30: =$C30*N30/100 -> 0.38 | S30: =$C30*P30/100 -> 0 | W30: =$C30*V30/100 -> 0 | AA30: =$C30*Z30/100 -> 0 | AE30: =$C30*AD30/100 -> 0 | AI30: =$C30*AH30/100 -> 0
B31: 3.2.7 Brick 25cm thick | C31: 2.42 | G31: =$C31*F31/100 -> 0 | K31: =$C31*H31/100 -> 0 | O31: =$C31*N31/100 -> 0 | S31: =$C31*P31/100 -> 0 | W31: =$C31*V31/100 -> 0 | AA31: =$C31*Z31/100 -> 0 | AE31: =$C31*AD31/100 -> 0 | AI31: =$C31*AH31/100 -> 0
B32: 3.2.8 stone 40cm thick | C32: 1.63 | G32: =$C32*F32/100 -> 0 | K32: =$C32*H32/100 -> 0 | O32: =$C32*N32/100 -> 0 | S32: =$C32*P32/100 -> 0 | W32: =$C32*V32/100 -> 0 | AA32: =$C32*Z32/100 -> 0 | AE32: =$C32*AD32/100 -> 0 | AI32: =$C32*AH32/100 -> 0
B33: 3.2.9 stone 50cm thick | C33: 2.19 | G33: =$C33*F33/100 -> 0 | K33: =$C33*H33/100 -> 0 | O33: =$C33*N33/100 -> 0 | S33: =$C33*P33/100 -> 0 | W33: =$C33*V33/100 -> 0 | AA33: =$C33*Z33/100 -> 0 | AE33: =$C33*AD33/100 -> 0 | AI33: =$C33*AH33/100 -> 0
B34: 3.2.10 Alumimium | C34: 0 | G34: =$C34*F34/100 -> 0 | K34: =$C34*H34/100 -> 0 | O34: =$C34*N34/100 -> 0 | S34: =$C34*P34/100 -> 0 | W34: =$C34*V34/100 -> 0 | AA34: =$C34*Z34/100 -> 0 | AE34: =$C34*AD34/100 -> 0 | AI34: =$C34*AH34/100 -> 0
A35: 4 | B35: Roofing | G35: =$C35*F35/100 -> 0 | K35: =$C35*H35/100 -> 0 | O35: =$C35*N35/100 -> 0 | S35: =$C35*P35/100 -> 0 | W35: =$C35*V35/100 -> 0 | AA35: =$C35*Z35/100 -> 0 | AE35: =$C35*AD35/100 -> 0 | AI35: =$C35*AH35/100 -> 0
B36: 4.1 CIS G-32 on wood | C36: 4.29 | D36: =MAX(C36:C44) -> 16.22 | E36: =MIN(C36:C44) -> 4.14 | G36: =$C36*F36/100 -> 0 | H36: =MAX(C36:C44) -> 16.22 | I36: =MIN(C36:C44) -> 4.14 | K36: =$C36*H36/100 -> 0.695838 | L36: 16.22 | M36: 4.14 | O36: =$C36*N36/100 -> 0 | P36: 16.22 | Q36: 4.14 | S36: =$C36*P36/100 -> 0.695838 | T36: 16.22 | U36: 4.14 | W36: =$C36*V36/100 -> 0 | X36: 16.22 | Y36: 4.14 | AA36: =$C36*Z36/100 -> 0 | AB36: 16.22 | AC36: 4.14 | AE36: =$C36*AD36/100 -> 0 | AF36: =MAX(C36:C44) -> 16.22 | AG36: =MIN(C36:C44) -> 4.14 | AI36: =$C36*AH36/100 -> 0
B37: 4.2 CIS G-30 on wood | C37: 4.41 | G37: =$C37*F37/100 -> 0 | K37: =$C37*H37/100 -> 0 | O37: =$C37*N37/100 -> 0 | S37: =$C37*P37/100 -> 0 | W37: =$C37*V37/100 -> 0 | AA37: =$C37*Z37/100 -> 0 | AE37: =$C37*AD37/100 -> 0 | AI37: =$C37*AH37/100 -> 0
B38: 4.3 CIS G-28 on wood | C38: 4.71 | G38: =$C38*F38/100 -> 0 | K38: =$C38*H38/100 -> 0 | O38: =$C38*N38/100 -> 0 | S38: =$C38*P38/100 -> 0 | W38: =$C38*V38/100 -> 0 | AA38: =$C38*Z38/100 -> 0 | AE38: =$C38*AD38/100 -> 0 | AI38: =$C38*AH38/100 -> 0
B39: 4.4 EGA on steel | C39: 15.25 | G39: =$C39*F39/100 -> 0 | K39: =$C39*H39/100 -> 0 | O39: =$C39*N39/100 -> 0 | S39: =$C39*P39/100 -> 0 | W39: =$C39*V39/100 -> 0 | AA39: =$C39*Z39/100 -> 0 | AE39: =$C39*AD39/100 -> 0 | AI39: =$C39*AH39/100 -> 0
B40: 4.5 EGA on wood | C40: 9.98 | G40: =$C40*F40/100 -> 0 | K40: =$C40*H40/100 -> 0 | O40: =$C40*N40/100 -> 0 | S40: =$C40*P40/100 -> 0 | W40: =$C40*V40/100 -> 0 | AA40: =$C40*Z40/100 -> 0 | AE40: =$C40*AD40/100 -> 0 | AI40: =$C40*AH40/100 -> 0
B41: 4.6 CIS G-28 on steel | C41: 16.22 | G41: =$C41*F41/100 -> 0 | K41: =$C41*H41/100 -> 0 | N41: 100 | O41: =$C41*N41/100 -> 16.22 | S41: =$C41*P41/100 -> 0 | W41: =$C41*V41/100 -> 0 | AA41: =$C41*Z41/100 -> 0 | AE41: =$C41*AD41/100 -> 0 | AI41: =$C41*AH41/100 -> 0
B42: 4.7 Cement roof tile | C42: 4.14 | G42: =$C42*F42/100 -> 0 | K42: =$C42*H42/100 -> 0 | O42: =$C42*N42/100 -> 0 | S42: =$C42*P42/100 -> 0 | W42: =$C42*V42/100 -> 0 | AA42: =$C42*Z42/100 -> 0 | AE42: =$C42*AD42/100 -> 0 | AI42: =$C42*AH42/100 -> 0
B43: 4.8 R.C without water-proof material | C43: 6.91 | G43: =$C43*F43/100 -> 0 | K43: =$C43*H43/100 -> 0 | O43: =$C43*N43/100 -> 0 | S43: =$C43*P43/100 -> 0 | W43: =$C43*V43/100 -> 0 | AA43: =$C43*Z43/100 -> 0 | AE43: =$C43*AD43/100 -> 0 | AI43: =$C43*AH43/100 -> 0
B44: 4.9 R.C with water-proof material | C44: 8.02 | G44: =$C44*F44/100 -> 0 | K44: =$C44*H44/100 -> 0 | O44: =$C44*N44/100 -> 0 | S44: =$C44*P44/100 -> 0 | W44: =$C44*V44/100 -> 0 | AA44: =$C44*Z44/100 -> 0 | AE44: =$C44*AD44/100 -> 0 | AI44: =$C44*AH44/100 -> 0
A45: 5 | B45: Joinery | G45: =$C45*F45/100 -> 0 | K45: =$C45*H45/100 -> 0 | O45: =$C45*N45/100 -> 0 | S45: =$C45*P45/100 -> 0 | W45: =$C45*V45/100 -> 0 | AA45: =$C45*Z45/100 -> 0 | AE45: =$C45*AD45/100 -> 0 | AI45: =$C45*AH45/100 -> 0
B46: 5.1 Low quality wood External | C46: 0.8 | D46: =MAX(C46:C49) -> 1.32 | E46: =MIN(C46:C49) -> 0.3 | G46: =$C46*F46/100 -> 0 | H46: =MAX(C46:C49) -> 1.32 | I46: =MIN(C46:C49) -> 0.3 | K46: =$C46*H46/100 -> 0.01056 | L46: 1.32 | M46: 0.3 | O46: =$C46*N46/100 -> 0 | P46: 1.32 | Q46: 0.3 | S46: =$C46*P46/100 -> 0.01056 | T46: 1.32 | U46: 0.3 | W46: =$C46*V46/100 -> 0 | X46: 1.32 | Y46: 0.3 | AA46: =$C46*Z46/100 -> 0 | AB46: 1.32 | AC46: 0.3 | AE46: =$C46*AD46/100 -> 0 | AF46: =MAX(C46:C49) -> 1.32 | AG46: =MIN(C46:C49) -> 0.3 | AI46: =$C46*AH46/100 -> 0
B47: 5.2 medium Quality wood ,External | C47: 0.3 | G47: =$C47*F47/100 -> 0 | K47: =$C47*H47/100 -> 0 | O47: =$C47*N47/100 -> 0 | S47: =$C47*P47/100 -> 0 | W47: =$C47*V47/100 -> 0 | AA47: =$C47*Z47/100 -> 0 | AE47: =$C47*AD47/100 -> 0 | AI47: =$C47*AH47/100 -> 0
B48: 5.3 Quality external | C48: 0.76 | G48: =$C48*F48/100 -> 0 | K48: =$C48*H48/100 -> 0 | O48: =$C48*N48/100 -> 0 | S48: =$C48*P48/100 -> 0 | W48: =$C48*V48/100 -> 0 | AA48: =$C48*Z48/100 -> 0 | AE48: =$C48*AD48/100 -> 0 | AI48: =$C48*AH48/100 -> 0
B49: 5.4 Best quality wood external | C49: 1.32 | G49: =$C49*F49/100 -> 0 | K49: =$C49*H49/100 -> 0 | O49: =$C49*N49/100 -> 0 | S49: =$C49*P49/100 -> 0 | W49: =$C49*V49/100 -> 0 | AA49: =$C49*Z49/100 -> 0 | AE49: =$C49*AD49/100 -> 0 | AI49: =$C49*AH49/100 -> 0
A50: 6 | B50: Metal Works | G50: =$C50*F50/100 -> 0 | K50: =$C50*H50/100 -> 0 | O50: =$C50*N50/100 -> 0 | S50: =$C50*P50/100 -> 0 | W50: =$C50*V50/100 -> 0 | AA50: =$C50*Z50/100 -> 0 | AE50: =$C50*AD50/100 -> 0 | AI50: =$C50*AH50/100 -> 0
B51: 6.1 LTZ or RHS profile for external openings with clear glass | C51: 0.67 | D51: =MAX(C51:C59) -> 1.08 | E51: =MIN(C51:C59) -> 0.5 | G51: =$C51*F51/100 -> 0 | H51: =MAX(C51:C59) -> 1.08 | I51: =MIN(C51:C59) -> 0.5 | K51: =$C51*H51/100 -> 0.007236 | L51: 1.08 | M51: 0.5 | N51: 100 | O51: =$C51*N51/100 -> 0.67 | P51: 1.08 | Q51: 0.5 | S51: =$C51*P51/100 -> 0.007236 | T51: 1.08 | U51: 0.5 | W51: =$C51*V51/100 -> 0 | X51: 1.08 | Y51: 0.5 | AA51: =$C51*Z51/100 -> 0 | AB51: 1.08 | AC51: 0.5 | AE51: =$C51*AD51/100 -> 0 | AF51: =MAX(C51:C59) -> 1.08 | AG51: =MIN(C51:C59) -> 0.5 | AI51: =$C51*AH51/100 -> 0
B52: 6.2 Ditto above but with 4mm- frosted glass | C52: 0.69 | G52: =$C52*F52/100 -> 0 | K52: =$C52*H52/100 -> 0 | O52: =$C52*N52/100 -> 0 | S52: =$C52*P52/100 -> 0 | W52: =$C52*V52/100 -> 0 | AA52: =$C52*Z52/100 -> 0 | AE52: =$C52*AD52/100 -> 0 | AI52: =$C52*AH52/100 -> 0
B53: 6.3 Ditto but with 4mm-tinted glass | C53: 0.69 | G53: =$C53*F53/100 -> 0 | K53: =$C53*H53/100 -> 0 | O53: =$C53*N53/100 -> 0 | S53: =$C53*P53/100 -> 0 | W53: =$C53*V53/100 -> 0 | AA53: =$C53*Z53/100 -> 0 | AE53: =$C53*AD53/100 -> 0 | AI53: =$C53*AH53/100 -> 0
B54: 6.4 Ditto but with 6mm-tinted glass | C54: 0.78 | G54: =$C54*F54/100 -> 0 | K54: =$C54*H54/100 -> 0 | O54: =$C54*N54/100 -> 0 | S54: =$C54*P54/100 -> 0 | W54: =$C54*V54/100 -> 0 | AA54: =$C54*Z54/100 -> 0 | AE54: =$C54*AD54/100 -> 0 | AI54: =$C54*AH54/100 -> 0
B55: 6.3 Ditto but with 4mm-clear glass | C55: 0.5 | O55: =$C55*N55/100 -> 0
B56: 6.5 Secco with 4mm-frosted glass | C56: 0.52 | G56: =$C56*F56/100 -> 0 | K56: =$C56*H56/100 -> 0 | O56: =$C56*N56/100 -> 0 | S56: =$C56*P56/100 -> 0 | W56: =$C56*V56/100 -> 0 | AA56: =$C56*Z56/100 -> 0 | AE56: =$C56*AD56/100 -> 0 | AI56: =$C56*AH56/100 -> 0
B57: 6.6 Ditto but with 4mm-tinted glass | C57: 0.52 | G57: =$C57*F57/100 -> 0 | K57: =$C57*H57/100 -> 0 | O57: =$C57*N57/100 -> 0 | S57: =$C57*P57/100 -> 0 | W57: =$C57*V57/100 -> 0 | AA57: =$C57*Z57/100 -> 0 | AE57: =$C57*AD57/100 -> 0 | AI57: =$C57*AH57/100 -> 0
B58: 6.7 Ditto but with 6mm-tinted glass | C58: 0.62 | G58: =$C58*F58/100 -> 0 | K58: =$C58*H58/100 -> 0 | O58: =$C58*N58/100 -> 0 | S58: =$C58*P58/100 -> 0 | W58: =$C58*V58/100 -> 0 | AA58: =$C58*Z58/100 -> 0 | AE58: =$C58*AD58/100 -> 0 | AI58: =$C58*AH58/100 -> 0
B59: 6.8 Ditto as above but aluminium | C59: 1.08 | G59: =$C59*F59/100 -> 0 | K59: =$C59*H59/100 -> 0 | O59: =$C59*N59/100 -> 0 | S59: =$C59*P59/100 -> 0 | W59: =$C59*V59/100 -> 0 | AA59: =$C59*Z59/100 -> 0 | AE59: =$C59*AD59/100 -> 0 | AI59: =$C59*AH59/100 -> 0
A60: 7 | B60: Floor Finish | G60: =$C60*F60/100 -> 0 | K60: =$C60*H60/100 -> 0 | O60: =$C60*N60/100 -> 0 | S60: =$C60*P60/100 -> 0 | W60: =$C60*V60/100 -> 0 | AA60: =$C60*Z60/100 -> 0 | AE60: =$C60*AD60/100 -> 0 | AI60: =$C60*AH60/100 -> 0
B61: 7.1 Cement Screed | C61: 0.27 | D61: =MAX(C61:C75) -> 4.18 | E61: =MIN(C61:C75) -> 0.27 | G61: =$C61*F61/100 -> 0 | H61: =MAX(C61:C75) -> 4.18 | I61: =MIN(C61:C75) -> 0.27 | K61: =$C61*H61/100 -> 0.011286 | L61: 4.18 | M61: 0.27 | N61: 100 | O61: =$C61*N61/100 -> 0.27 | P61: 4.18 | Q61: 0.27 | S61: =$C61*P61/100 -> 0.011286 | T61: 4.18 | U61: 0.27 | W61: =$C61*V61/100 -> 0 | X61: 4.18 | Y61: 0.27 | AA61: =$C61*Z61/100 -> 0 | AB61: 4.18 | AC61: 0.27 | AE61: =$C61*AD61/100 -> 0 | AF61: =MAX(C61:C75) -> 4.18 | AG61: =MIN(C61:C75) -> 0.27 | AI61: =$C61*AH61/100 -> 0
B62: 7.2 Cement Tile | C62: 0.57 | G62: =$C62*F62/100 -> 0 | K62: =$C62*H62/100 -> 0 | O62: =$C62*N62/100 -> 0 | S62: =$C62*P62/100 -> 0 | W62: =$C62*V62/100 -> 0 | AA62: =$C62*Z62/100 -> 0 | AE62: =$C62*AD62/100 -> 0 | AI62: =$C62*AH62/100 -> 0
B63: 7.3 Terrazzo Tile | C63: 0.81 | G63: =$C63*F63/100 -> 0 | K63: =$C63*H63/100 -> 0 | O63: =$C63*N63/100 -> 0 | S63: =$C63*P63/100 -> 0 | W63: =$C63*V63/100 -> 0 | AA63: =$C63*Z63/100 -> 0 | AE63: =$C63*AD63/100 -> 0 | AI63: =$C63*AH63/100 -> 0
B64: 7.4 PVC tile | C64: 0.95 | G64: =$C64*F64/100 -> 0 | K64: =$C64*H64/100 -> 0 | O64: =$C64*N64/100 -> 0 | S64: =$C64*P64/100 -> 0 | W64: =$C64*V64/100 -> 0 | AA64: =$C64*Z64/100 -> 0 | AE64: =$C64*AD64/100 -> 0 | AI64: =$C64*AH64/100 -> 0
B65: 7.5 Ceramic medium quality Porcelain | C65: 1.08 | G65: =$C65*F65/100 -> 0 | K65: =$C65*H65/100 -> 0 | O65: =$C65*N65/100 -> 0 | S65: =$C65*P65/100 -> 0 | W65: =$C65*V65/100 -> 0 | AA65: =$C65*Z65/100 -> 0 | AE65: =$C65*AD65/100 -> 0 | AI65: =$C65*AH65/100 -> 0
B66: 7.6 Ceramic best quality | C66: 1.69 | G66: =$C66*F66/100 -> 0 | K66: =$C66*H66/100 -> 0 | O66: =$C66*N66/100 -> 0 | S66: =$C66*P66/100 -> 0 | W66: =$C66*V66/100 -> 0 | AA66: =$C66*Z66/100 -> 0 | AE66: =$C66*AD66/100 -> 0 | AI66: =$C66*AH66/100 -> 0
B67: 7.7 Marble chip lower quality | C67: 1.78 | G67: =$C67*F67/100 -> 0 | K67: =$C67*H67/100 -> 0 | O67: =$C67*N67/100 -> 0 | S67: =$C67*P67/100 -> 0 | W67: =$C67*V67/100 -> 0 | AA67: =$C67*Z67/100 -> 0 | AE67: =$C67*AD67/100 -> 0 | AI67: =$C67*AH67/100 -> 0
B68: 7.8 Marble chip best quality | C68: 2.14 | G68: =$C68*F68/100 -> 0 | K68: =$C68*H68/100 -> 0 | O68: =$C68*N68/100 -> 0 | S68: =$C68*P68/100 -> 0 | W68: =$C68*V68/100 -> 0 | AA68: =$C68*Z68/100 -> 0 | AE68: =$C68*AD68/100 -> 0 | AI68: =$C68*AH68/100 -> 0
B69: 7.9 Harar marble | C69: 2.49 | G69: =$C69*F69/100 -> 0 | K69: =$C69*H69/100 -> 0 | O69: =$C69*N69/100 -> 0 | S69: =$C69*P69/100 -> 0 | W69: =$C69*V69/100 -> 0 | AA69: =$C69*Z69/100 -> 0 | AE69: =$C69*AD69/100 -> 0 | AI69: =$C69*AH69/100 -> 0
B70: 7.10 Mankush marble | C70: 3.52 | G70: =$C70*F70/100 -> 0 | K70: =$C70*H70/100 -> 0 | O70: =$C70*N70/100 -> 0 | S70: =$C70*P70/100 -> 0 | W70: =$C70*V70/100 -> 0 | AA70: =$C70*Z70/100 -> 0 | AE70: =$C70*AD70/100 -> 0 | AI70: =$C70*AH70/100 -> 0
B71: 7.11 Parquet best quality on screed | C71: 4.18 | G71: =$C71*F71/100 -> 0 | K71: =$C71*H71/100 -> 0 | O71: =$C71*N71/100 -> 0 | S71: =$C71*P71/100 -> 0 | W71: =$C71*V71/100 -> 0 | AA71: =$C71*Z71/100 -> 0 | AE71: =$C71*AD71/100 -> 0 | AI71: =$C71*AH71/100 -> 0
B72: 7.12 Parquet quality on screed | C72: 2.84 | G72: =$C72*F72/100 -> 0 | K72: =$C72*H72/100 -> 0 | O72: =$C72*N72/100 -> 0 | S72: =$C72*P72/100 -> 0 | W72: =$C72*V72/100 -> 0 | AA72: =$C72*Z72/100 -> 0 | AE72: =$C72*AD72/100 -> 0 | AI72: =$C72*AH72/100 -> 0
B73: 7.13 Parquet medium quality on screed | C73: 2.84 | G73: =$C73*F73/100 -> 0 | K73: =$C73*H73/100 -> 0 | O73: =$C73*N73/100 -> 0 | S73: =$C73*P73/100 -> 0 | W73: =$C73*V73/100 -> 0 | AA73: =$C73*Z73/100 -> 0 | AE73: =$C73*AD73/100 -> 0 | AI73: =$C73*AH73/100 -> 0
... B75: 7.15 Granite | C75: 2.64 | G75: =$C75*F75/100 -> 0 | K75: =$C75*H75/100 -> 0 | O75: =$C75*N75/100 -> 0 | S75: =$C75*P75/100 -> 0 | W75: =$C75*V75/100 -> 0 | AA75: =$C75*Z75/100 -> 0 | AE75: =$C75*AD75/100 -> 0 | AI75: =$C75*AH75/100 -> 0
A76: 8 | B76: Wall Finish | G76: =$C76*F76/100 -> 0 | K76: =$C76*H76/100 -> 0 | O76: =$C76*N76/100 -> 0 | S76: =$C76*P76/100 -> 0 | W76: =$C76*V76/100 -> 0 | AA76: =$C76*Z76/100 -> 0 | AE76: =$C76*AD76/100 -> 0 | AI76: =$C76*AH76/100 -> 0
B77: 8.1 Internal | G77: =$C77*F77/100 -> 0 | K77: =$C77*H77/100 -> 0 | O77: =$C77*N77/100 -> 0 | S77: =$C77*P77/100 -> 0 | W77: =$C77*V77/100 -> 0 | AA77: =$C77*Z77/100 -> 0 | AE77: =$C77*AD77/100 -> 0 | AI77: =$C77*AH77/100 -> 0
B78: 8.1.1 plasterd | C78: 0.21 | D78: =MAX(C78:C95) -> 2 | E78: =MIN(C78:C119) -> 0.09 | G78: =$C78*F78/100 -> 0 | H78: =MAX(C78:C95) -> 2 | I78: =MIN(C78:C119) -> 0.09 | K78: =$C78*H78/100 -> 0.0042 | L78: 2 | M78: 0.09 | N78: 100 | O78: =$C78*N78/100 -> 0.21 | P78: 2 | Q78: 0.09 | S78: =$C78*P78/100 -> 0.0042 | T78: 2 | U78: 0.09 | W78: =$C78*V78/100 -> 0 | X78: 2 | Y78: 0.09 | AA78: =$C78*Z78/100 -> 0 | AB78: 2 | AC78: 0.09 | AE78: =$C78*AD78/100 -> 0 | AF78: =MAX(C78:C95) -> 2 | AG78: =MIN(C78:C119) -> 0.09 | AI78: =$C78*AH78/100 -> 0
B79: 8.1.2 Plasterd and painted | C79: 0.28 | G79: =$C79*F79/100 -> 0 | K79: =$C79*H79/100 -> 0 | O79: =$C79*N79/100 -> 0 | S79: =$C79*P79/100 -> 0 | W79: =$C79*V79/100 -> 0 | AA79: =$C79*Z79/100 -> 0 | AE79: =$C79*AD79/100 -> 0 | AI79: =$C79*AH79/100 -> 0
B80: 8.1.3 Pointed HCB | C80: 0.09 | G80: =$C80*F80/100 -> 0 | K80: =$C80*H80/100 -> 0 | O80: =$C80*N80/100 -> 0 | S80: =$C80*P80/100 -> 0 | W80: =$C80*V80/100 -> 0 | AA80: =$C80*Z80/100 -> 0 | AE80: =$C80*AD80/100 -> 0 | AI80: =$C80*AH80/100 -> 0
B81: 8.1.4 Pointed dressed stone | C81: 0.12 | G81: =$C81*F81/100 -> 0 | K81: =$C81*H81/100 -> 0 | O81: =$C81*N81/100 -> 0 | S81: =$C81*P81/100 -> 0 | W81: =$C81*V81/100 -> 0 | AA81: =$C81*Z81/100 -> 0 | AE81: =$C81*AD81/100 -> 0 | AI81: =$C81*AH81/100 -> 0
B82: 8.1.5 Pointed brick | C82: 0.15 | G82: =$C82*F82/100 -> 0 | K82: =$C82*H82/100 -> 0 | O82: =$C82*N82/100 -> 0 | S82: =$C82*P82/100 -> 0 | W82: =$C82*V82/100 -> 0 | AA82: =$C82*Z82/100 -> 0 | AE82: =$C82*AD82/100 -> 0 | AI82: =$C82*AH82/100 -> 0
B83: 8.1.6 Plasterd and Addis I wall paper | C83: 0.73 | G83: =$C83*F83/100 -> 0 | K83: =$C83*H83/100 -> 0 | O83: =$C83*N83/100 -> 0 | S83: =$C83*P83/100 -> 0 | W83: =$C83*V83/100 -> 0 | AA83: =$C83*Z83/100 -> 0 | AE83: =$C83*AD83/100 -> 0 | AI83: =$C83*AH83/100 -> 0
B84: 8.1.7 Mosaic | C84: 1.38 | G84: =$C84*F84/100 -> 0 | K84: =$C84*H84/100 -> 0 | O84: =$C84*N84/100 -> 0 | S84: =$C84*P84/100 -> 0 | W84: =$C84*V84/100 -> 0 | AA84: =$C84*Z84/100 -> 0 | AE84: =$C84*AD84/100 -> 0 | AI84: =$C84*AH84/100 -> 0
B85: 8.1.8a Imported, high quality ceramic | C85: 1.13 | G85: =$C85*F85/100 -> 0 | K85: =$C85*H85/100 -> 0 | O85: =$C85*N85/100 -> 0 | S85: =$C85*P85/100 -> 0 | W85: =$C85*V85/100 -> 0 | AA85: =$C85*Z85/100 -> 0 | AE85: =$C85*AD85/100 -> 0 | AI85: =$C85*AH85/100 -> 0
B86: 8.1.8b Imported, quality ceramic | C86: 0.71 | G86: =$C86*F86/100 -> 0 | K86: =$C86*H86/100 -> 0 | O86: =$C86*N86/100 -> 0 | S86: =$C86*P86/100 -> 0 | W86: =$C86*V86/100 -> 0 | AA86: =$C86*Z86/100 -> 0 | AE86: =$C86*AD86/100 -> 0 | AI86: =$C86*AH86/100 -> 0
B87: 8.1.8c Imported, medium quality ceramic | C87: 0.53 | G87: =$C87*F87/100 -> 0 | K87: =$C87*H87/100 -> 0 | O87: =$C87*N87/100 -> 0 | S87: =$C87*P87/100 -> 0 | W87: =$C87*V87/100 -> 0 | AA87: =$C87*Z87/100 -> 0 | AE87: =$C87*AD87/100 -> 0 | AI87: =$C87*AH87/100 -> 0
B88: 8.1.8d Lower quality ceramic | C88: 0.52 | G88: =$C88*F88/100 -> 0 | K88: =$C88*H88/100 -> 0 | O88: =$C88*N88/100 -> 0 | S88: =$C88*P88/100 -> 0 | W88: =$C88*V88/100 -> 0 | AA88: =$C88*Z88/100 -> 0 | AE88: =$C88*AD88/100 -> 0 | AI88: =$C88*AH88/100 -> 0
B89: 8.1.9 Pointed and painted HCB | C89: 0.17 | G89: =$C89*F89/100 -> 0 | K89: =$C89*H89/100 -> 0 | O89: =$C89*N89/100 -> 0 | S89: =$C89*P89/100 -> 0 | W89: =$C89*V89/100 -> 0 | AA89: =$C89*Z89/100 -> 0 | AE89: =$C89*AD89/100 -> 0 | AI89: =$C89*AH89/100 -> 0
B90: 8.1.10 Pointed and painted Brick | C90: 0.22 | G90: =$C90*F90/100 -> 0 | K90: =$C90*H90/100 -> 0 | O90: =$C90*N90/100 -> 0 | S90: =$C90*P90/100 -> 0 | W90: =$C90*V90/100 -> 0 | AA90: =$C90*Z90/100 -> 0 | AE90: =$C90*AD90/100 -> 0 | AI90: =$C90*AH90/100 -> 0
... B95: 8.1.15 Boka marble | C95: 1.87 | G95: =$C95*F95/100 -> 0 | K95: =$C95*H95/100 -> 0 | O95: =$C95*N95/100 -> 0 | S95: =$C95*P95/100 -> 0 | W95: =$C95*V95/100 -> 0 | AA95: =$C95*Z95/100 -> 0 | AE95: =$C95*AD95/100 -> 0 | AI95: =$C95*AH95/100 -> 0
B96: 8.2 External | G96: =$C96*F96/100 -> 0 | K96: =$C96*H96/100 -> 0 | O96: =$C96*N96/100 -> 0 | S96: =$C96*P96/100 -> 0 | W96: =$C96*V96/100 -> 0 | AA96: =$C96*Z96/100 -> 0 | AE96: =$C96*AD96/100 -> 0 | AI96: =$C96*AH96/100 -> 0
B97: 8.2.1 Plastering | C97: 0.26 | D97: =MAX(C97:C119) -> 2.49 | E97: =MIN(C97:C119) -> 0.12 | G97: =$C97*F97/100 -> 0 | H97: =MAX(C97:C119) -> 2.49 | I97: =MIN(C97:C119) -> 0.12 | K97: =$C97*H97/100 -> 0.006474 | L97: 2.49 | M97: 0.12 | O97: =$C97*N97/100 -> 0 | P97: 2.49 | Q97: 0.12 | S97: =$C97*P97/100 -> 0.006474 | T97: 2.49 | U97: 0.12 | W97: =$C97*V97/100 -> 0 | X97: 2.49 | Y97: 0.12 | AA97: =$C97*Z97/100 -> 0 | AB97: 2.49 | AC97: 0.12 | AE97: =$C97*AD97/100 -> 0 | AF97: =MAX(C97:C119) -> 2.49 | AG97: =MIN(C97:C119) -> 0.12 | AI97: =$C97*AH97/100 -> 0
B98: 8.2.2 Plastering and painting | C98: 0.35 | G98: =$C98*F98/100 -> 0 | K98: =$C98*H98/100 -> 0 | N98: 100 | O98: =$C98*N98/100 -> 0.35 | S98: =$C98*P98/100 -> 0 | W98: =$C98*V98/100 -> 0 | AA98: =$C98*Z98/100 -> 0 | AE98: =$C98*AD98/100 -> 0 | AI98: =$C98*AH98/100 -> 0
B99: 8.2.3 Pointed HCB | C99: 0.12 | G99: =$C99*F99/100 -> 0 | K99: =$C99*H99/100 -> 0 | O99: =$C99*N99/100 -> 0 | S99: =$C99*P99/100 -> 0 | W99: =$C99*V99/100 -> 0 | AA99: =$C99*Z99/100 -> 0 | AE99: =$C99*AD99/100 -> 0 | AI99: =$C99*AH99/100 -> 0
B100: 8.2.4 Pointed stone | C100: 0.15 | G100: =$C100*F100/100 -> 0 | K100: =$C100*H100/100 -> 0 | O100: =$C100*N100/100 -> 0 | S100: =$C100*P100/100 -> 0 | W100: =$C100*V100/100 -> 0 | AA100: =$C100*Z100/100 -> 0 | AE100: =$C100*AD100/100 -> 0 | AI100: =$C100*AH100/100 -> 0
B101: 8.2.5 pointed ambo cladding | C101: 1.82 | G101: =$C101*F101/100 -> 0 | K101: =$C101*H101/100 -> 0 | O101: =$C101*N101/100 -> 0 | S101: =$C101*P101/100 -> 0 | W101: =$C101*V101/100 -> 0 | AA101: =$C101*Z101/100 -> 0 | AE101: =$C101*AD101/100 -> 0 | AI101: =$C101*AH101/100 -> 0
B102: 8.2.6 Not pointed ambo cladding | C102: 1.67 | G102: =$C102*F102/100 -> 0 | K102: =$C102*H102/100 -> 0 | O102: =$C102*N102/100 -> 0 | S102: =$C102*P102/100 -> 0 | W102: =$C102*V102/100 -> 0 | AA102: =$C102*Z102/100 -> 0 | AE102: =$C102*AD102/100 -> 0 | AI102: =$C102*AH102/100 -> 0
B103: 8.2.7 Dressed stone cladding | C103: 1.67 | G103: =$C103*F103/100 -> 0 | K103: =$C103*H103/100 -> 0 | O103: =$C103*N103/100 -> 0 | S103: =$C103*P103/100 -> 0 | W103: =$C103*V103/100 -> 0 | AA103: =$C103*Z103/100 -> 0 | AE103: =$C103*AD103/100 -> 0 | AI103: =$C103*AH103/100 -> 0
B104: 8.2.8 pointing brick | C104: 0.19 | G104: =$C104*F104/100 -> 0 | K104: =$C104*H104/100 -> 0 | O104: =$C104*N104/100 -> 0 | S104: =$C104*P104/100 -> 0 | W104: =$C104*V104/100 -> 0 | AA104: =$C104*Z104/100 -> 0 | AE104: =$C104*AD104/100 -> 0 | AI104: =$C104*AH104/100 -> 0
B105: 8.2.9 Rendred | C105: 0.26 | G105: =$C105*F105/100 -> 0 | K105: =$C105*H105/100 -> 0 | O105: =$C105*N105/100 -> 0 | S105: =$C105*P105/100 -> 0 | W105: =$C105*V105/100 -> 0 | AA105: =$C105*Z105/100 -> 0 | AE105: =$C105*AD105/100 -> 0 | AI105: =$C105*AH105/100 -> 0
B106: 8.2.10 Rendred and painted | C106: 0.35 | G106: =$C106*F106/100 -> 0 | K106: =$C106*H106/100 -> 0 | O106: =$C106*N106/100 -> 0 | S106: =$C106*P106/100 -> 0 | W106: =$C106*V106/100 -> 0 | AA106: =$C106*Z106/100 -> 0 | AE106: =$C106*AD106/100 -> 0 | AI106: =$C106*AH106/100 -> 0
...

Sheet Plot grade
B1: No | D1: Plot grade
B2: 1 | D2: 1-1b
B3: 2 | D3: 1-1a
B4: 3 | D4: 1-1
B5: 4 | D5: 1-2
B6: 5 | D6: 2-1
B7: 6 | D7: 1-3
B8: 7 | D8: 2-2
B9: 8 | D9: 3-1
B10: 9 | D10: 2-3
B11: 10 | D11: 3-2
B12: 11 | D12: 4-1
B13: 12 | D13: 3-3
B14: 13 | D14: 4-2
B15: 14 | D15: 4-3 | G15: 1000097015264
B16: 15 | D16: 4-4 | G16: 1000059902702 | H16: hawine mulugeta
D18: 1-1b | F18: 1-1a | H18: 1-1 | J18: 1-2 | L18: 2-1 | N18: 1-3 | P18: 2-2 | R18: 3-1 | T18: 2-3 | V18: 3-2 | X18: 4-1 | Z18: 3-3 | AB18: 4-2 | AD18: 4-3 | AF18: 4-4
D19: 1 | F19: 2 | H19: 3 | J19: 4 | L19: 5 | N19: 6 | P19: 7 | R19: 8 | T19: 9 | V19: 10 | X19: 11 | Z19: 12 | AB19: 13 | AD19: 14 | AF19: 15
B20: 0-100 | C20: 100 | D20: 67844 | E20: =$C$20*D20 -> 6784400 | F20: 44355 | G20: =$C$20*F20 -> 4435500 | H20: 35523 | I20: =$C$20*H20 -> 3552300 | J20: 30912 | K20: =$C$20*J20 -> 3091200 | L20: 26368 | M20: =$C$20*L20 -> 2636800 | N20: 23599 | O20: =$C$20*N20 -> 2359900 | P20: 21576 | Q20: =$C$20*P20 -> 2157600 | R20: 20351 | S20: =$C$20*R20 -> 2035100 | T20: 17283 | U20: =$C$20*T20 -> 1728300 | V20: 16267 | W20: =$C$20*V20 -> 1626700 | X20: 15202 | Y20: =$C$20*X20 -> 1520200 | Z20: 14559 | AA20: =$C$20*Z20 -> 1455900 | AB20: 14168 | AC20: =$C$20*AB20 -> 1416800 | AD20: 13275 | AE20: =$C$20*AD20 -> 1327500 | AF20: 126888
B21: 101-200 | C21: 200 | D21: 62975 | E21: =E20+((C21-C20)*D21) -> 13081900 | F21: 43454 | G21: =G20+((C21-C20)*F21) -> 8780900 | H21: 345992 | I21: =I20+((C21-C20)*H21) -> 38151500 | J21: 30521 | K21: =K20+((C21-C20)*J21) -> 6143300 | L21: 26031 | M21: =M20+((C21-C20)*L21) -> 5239900 | N21: 23069 | O21: =O20+((C21-C20)*N21) -> 4666800 | P21: 20104 | Q21: =Q20+((C21-C20)*P21) -> 4168000 | R21: 18420 | S21: =S20+((C21-C20)*R21) -> 3877100 | T21: 17082 | U21: =U20+((C21-C20)*T21) -> 3436500 | V21: 15588 | W21: =W20+((C21-C20)*V21) -> 3185500 | X21: 14625 | Y21: =Y20+((C21-C20)*X21) -> 2982700 | Z21: 14104 | AA21: =AA20+((C21-C20)*Z21) -> 2866300 | AB21: 13800 | AC21: =AC20+((C21-C20)*AB21) -> 2796800 | AD21: 12537 | AE21: =AE20+((C21-C20)*AD21) -> 2581200 | AF21: 11933
B22: 201-300 | C22: 300 | D22: 58106 | E22: =E21+((C22-C21)*D22) -> 18892500 | F22: 42553 | G22: =G21+((C22-C21)*F22) -> 13036200 | H22: 34261 | I22: =I21+((C22-C21)*H22) -> 41577600 | J22: 30130 | K22: =K21+((C22-C21)*J22) -> 9156300 | L22: 25694 | M22: =M21+((C22-C21)*L22) -> 7809300 | N22: 22539 | O22: =O21+((C22-C21)*N22) -> 6920700 | P22: 19022 | Q22: =Q21+((C22-C21)*P22) -> 6070200 | R22: 17315 | S22: =S21+((C22-C21)*R22) -> 5608600 | T22: 16898 | U22: =U21+((C22-C21)*T22) -> 5126300 | V22: 14991 | W22: =W21+((C22-C21)*V22) -> 4684600 | X22: 14128 | Y22: =Y21+((C22-C21)*X22) -> 4395500 | Z22: 13518 | AA22: =AA21+((C22-C21)*Z22) -> 4218100 | AB22: 13622 | AC22: =AC21+((C22-C21)*AB22) -> 4159000 | AD22: 11799 | AE22: =AE21+((C22-C21)*AD22) -> 3761100 | AF22: 11318
B23: 301-400 | C23: 400 | D23: 54919 | E23: =E22+((C23-C22)*D23) -> 24384400 | F23: 41705 | G23: =G22+((C23-C22)*F23) -> 17206700 | H23: 33805 | I23: =I22+((C23-C22)*H23) -> 44958100 | J23: 29745 | K23: =K22+((C23-C22)*J23) -> 12130800 | L23: 25445 | M23: =M22+((C23-C22)*L23) -> 10353800 | N23: 22284 | O23: =O22+((C23-C22)*N23) -> 9149100 | P23: 18829 | Q23: =Q22+((C23-C22)*P23) -> 7953100 | R23: 17146 | S23: =S22+((C23-C22)*R23) -> 7323200 | T23: 16726 | U23: =U22+((C23-C22)*T23) -> 6798900 | V23: 14541 | W23: =W22+((C23-C22)*V23) -> 6138700 | X23: 13986 | Y23: =Y22+((C23-C22)*X23) -> 5794100 | Z23: 13385 | AA23: =AA22+((C23-C22)*Z23) -> 5556600 | AB23: 13487 | AC23: =AC22+((C23-C22)*AB23) -> 5507700 | AD23: 11644 | AE23: =AE22+((C23-C22)*AD23) -> 4925500 | AF23: 11197
B24: 401-500 | C24: 500 | D24: 54358 | E24: =E23+((C24-C23)*D24) -> 29820200 | F24: 41283 | G24: =G23+((C24-C23)*F24) -> 21335000 | H24: 33463 | I24: =I23+((C24-C23)*H24) -> 48304400 | J24: 29444 | K24: =K23+((C24-C23)*J24) -> 15075200 | L24: 25195 | M24: =M23+((C24-C23)*L24) -> 12873300 | N24: 22048 | O24: =O23+((C24-C23)*N24) -> 11353900 | P24: 18636 | Q24: =Q23+((C24-C23)*P24) -> 9816700 | R24: 16977 | S24: =S23+((C24-C23)*R24) -> 9020900 | T24: 16554 | U24: =U23+((C24-C23)*T24) -> 8454300 | V24: 14691 | W24: =W23+((C24-C23)*V24) -> 7607800 | X24: 13844 | Y24: =Y23+((C24-C23)*X24) -> 7178500 | Z24: 13252 | AA24: =AA23+((C24-C23)*Z24) -> 6881800 | AB24: 13352 | AC24: =AC23+((C24-C23)*AB24) -> 6842900 | AD24: 11513 | AE24: =AE23+((C24-C23)*AD24) -> 6076800 | AF24: 11076
B25: 501-600 | C25: 600 | D25: 20732 | E25: =E24+((C25-C24)*D25) -> 31893400 | F25: 18639 | G25: =G24+((C25-C24)*F25) -> 23198900 | H25: 17813 | I25: =I24+((C25-C24)*H25) -> 50085700 | J25: 18643 | K25: =K24+((C25-C24)*J25) -> 16939500 | L25: 16694 | M25: =M24+((C25-C24)*L25) -> 14542700 | N25: 14505 | O25: =O24+((C25-C24)*N25) -> 12804400 | P25: 14141 | Q25: =Q24+((C25-C24)*P25) -> 11230800 | R25: 12909 | S25: =S24+((C25-C24)*R25) -> 10311800 | T25: 11677 | U25: =U24+((C25-C24)*T25) -> 9622000 | V25: 11071 | W25: =W24+((C25-C24)*V25) -> 8714900 | X25: 10703 | Y25: =Y24+((C25-C24)*X25) -> 8248800 | Z25: 9812 | AA25: =AA24+((C25-C24)*Z25) -> 7863000 | AB25: 7311 | AC25: =AC24+((C25-C24)*AB25) -> 7574000 | AD25: 7239 | AE25: =AE24+((C25-C24)*AD25) -> 6800700 | AF25: 6212
B26: 601-700 | C26: 700 | D26: 20477 | E26: =E25+((C26-C25)*D26) -> 33941100 | F26: 18351 | G26: =G25+((C26-C25)*F26) -> 25034000 | H26: 17591 | I26: =I25+((C26-C25)*H26) -> 51844800 | J26: 16832 | K26: =K25+((C26-C25)*J26) -> 18622700 | L26: 16408 | M26: =M25+((C26-C25)*L26) -> 16183500 | N26: 14318 | O26: =O25+((C26-C25)*N26) -> 14236200 | P26: 13946 | Q26: =Q25+((C26-C25)*P26) -> 12625400 | R26: 12612 | S26: =S25+((C26-C25)*R26) -> 11573000 | T26: 11545 | U26: =U25+((C26-C25)*T26) -> 10776500 | V26: 11006 | W26: =W25+((C26-C25)*V26) -> 9815500 | X26: 10551 | Y26: =Y25+((C26-C25)*X26) -> 9303900 | Z26: 9731 | AA26: =AA25+((C26-C25)*Z26) -> 8836100 | AB26: 7221 | AC26: =AC25+((C26-C25)*AB26) -> 8296100 | AD26: 7215 | AE26: =AE25+((C26-C25)*AD26) -> 7522200 | AF26: 6167
B27: 701-800 | C27: 800 | D27: 20213 | E27: =E26+((C27-C26)*D27) -> 35962400 | F27: 18501 | G27: =G26+((C27-C26)*F27) -> 26884100 | H27: 18739 | I27: =I26+((C27-C26)*H27) -> 53718700 | J27: 18220 | K27: =K26+((C27-C26)*J27) -> 20444700 | L27: 16394 | M27: =M26+((C27-C26)*L27) -> 17822900 | N27: 14154 | O27: =O26+((C27-C26)*N27) -> 15651600 | P27: 13967 | Q27: =Q26+((C27-C26)*P27) -> 14022100 | R27: 13388 | S27: =S26+((C27-C26)*R27) -> 12911800 | T27: 12804 | U27: =U26+((C27-C26)*T27) -> 12056900 | V27: 12348 | W27: =W26+((C27-C26)*V27) -> 11050300 | X27: 11897 | Y27: =Y26+((C27-C26)*X27) -> 10493600 | Z27: 10044 | AA27: =AA26+((C27-C26)*Z27) -> 9840500 | AB27: 8936 | AC27: =AC26+((C27-C26)*AB27) -> 9189700 | AD27: 7184 | AE27: =AE26+((C27-C26)*AD27) -> 8240600 | AF27: 6118
B28: 801-900 | C28: 900 | D28: 25258 | E28: =E27+((C28-C27)*D28) -> 38488200 | F28: 23415 | G28: =G27+((C28-C27)*F28) -> 29225600 | H28: 23415 | I28: =I27+((C28-C27)*H28) -> 56060200 | J28: 22656 | K28: =K27+((C28-C27)*J28) -> 22710300 | L28: 21508 | M28: =M27+((C28-C27)*L28) -> 19973700 | N28: 20158 | O28: =O27+((C28-C27)*N28) -> 17667400 | P28: 20107 | Q28: =Q27+((C28-C27)*P28) -> 16032800 | R28: 19988 | S28: =S27+((C28-C27)*R28) -> 14910600 | T28: 19861 | U28: =U27+((C28-C27)*T28) -> 14043000 | V28: 19614 | W28: =W27+((C28-C27)*V28) -> 13011700 | X28: 19382 | Y28: =Y27+((C28-C27)*X28) -> 12431800 | Z28: 16111 | AA28: =AA27+((C28-C27)*Z28) -> 11451600 | AB28: 14026 | AC28: =AC27+((C28-C27)*AB28) -> 10592300 | AD28: 7158 | AE28: =AE27+((C28-C27)*AD28) -> 8956400 | AF28: 6062
B29: 901-1000 | C29: 1000 | D29: 25001 | E29: =E28+((C29-C28)*D29) -> 40988300 | F29: 23190 | G29: =G28+((C29-C28)*F29) -> 31544600 | H29: 23190 | I29: =I28+((C29-C28)*H29) -> 58379200 | J29: 23332 | K29: =K28+((C29-C28)*J29) -> 25043500 | L29: 21968 | M29: =M28+((C29-C28)*L29) -> 22170500 | N29: 21622 | O29: =O28+((C29-C28)*N29) -> 19829600 | P29: 20783 | Q29: =Q28+((C29-C28)*P29) -> 18111100 | R29: 20366 | S29: =S28+((C29-C28)*R29) -> 16947200 | T29: 19943 | U29: =U28+((C29-C28)*T29) -> 16037300 | V29: 19871 | W29: =W28+((C29-C28)*V29) -> 14998800 | X29: 19249 | Y29: =Y28+((C29-C28)*X29) -> 14356700 | Z29: 18181 | AA29: =AA28+((C29-C28)*Z29) -> 13269700 | AB29: 16066 | AC29: =AC28+((C29-C28)*AB29) -> 12198900 | AD29: 7130 | AE29: =AE28+((C29-C28)*AD29) -> 9669400 | AF29: 6011
B30: 1001-1100 | C30: 1100 | D30: 24751 | E30: =E29+((C30-C29)*D30) -> 43463400 | F30: 22575 | G30: =G29+((C30-C29)*F30) -> 33802100 | H30: 21758 | I30: =I29+((C30-C29)*H30) -> 60555000 | J30: 21064 | K30: =K29+((C30-C29)*J30) -> 27149900 | L30: 20168 | M30: =M29+((C30-C29)*L30) -> 24187300 | N30: 19825 | O30: =O29+((C30-C29)*N30) -> 21812100 | P30: 18009 | Q30: =Q29+((C30-C29)*P30) -> 19912000 | R30: 17165 | S30: =S29+((C30-C29)*R30) -> 18663700 | T30: 16316 | U30: =U29+((C30-C29)*T30) -> 17668900 | V30: 7699 | W30: =W29+((C30-C29)*V30) -> 15768700 | X30: 7486 | Y30: =Y29+((C30-C29)*X30) -> 15105300 | Z30: 7412 | AA30: =AA29+((C30-C29)*Z30) -> 14010900 | AB30: 7340 | AC30: =AC29+((C30-C29)*AB30) -> 12932900 | AD30: 6600 | AE30: =AE29+((C30-C29)*AD30) -> 10329400 | AF30: 5966
B31: 1101-1200 | C31: 1200 | D31: 26991 | E31: =E30+((C31-C30)*D31) -> 46162500 | F31: 25943 | G31: =G30+((C31-C30)*F31) -> 36396400 | H31: 21050 | I31: =I30+((C31-C30)*H31) -> 62660000 | J31: 20390 | K31: =K30+((C31-C30)*J31) -> 29188900 | L31: 19852 | M31: =M30+((C31-C30)*L31) -> 26172500 | N31: 19488 | O31: =O30+((C31-C30)*N31) -> 23760900 | P31: 17803 | Q31: =Q30+((C31-C30)*P31) -> 21692300 | R31: 16905 | S31: =S30+((C31-C30)*R31) -> 20354200 | T31: 15843 | U31: =U30+((C31-C30)*T31) -> 19253200 | V31: 7623 | W31: =W30+((C31-C30)*V31) -> 16531000 | X31: 7335 | Y31: =Y30+((C31-C30)*X31) -> 15838800 | Z31: 7276 | AA31: =AA30+((C31-C30)*Z31) -> 14738500 | AB31: 7249 | AC31: =AC30+((C31-C30)*AB31) -> 13657800 | AD31: 6545 | AE31: =AE30+((C31-C30)*AD31) -> 10983900 | AF31: 5916
B32: 1201-1300 | C32: 1300 | D32: 26638 | E32: =E31+((C32-C31)*D32) -> 48826300 | F32: 25605 | G32: =G31+((C32-C31)*F32) -> 38956900 | H32: 17908 | I32: =I31+((C32-C31)*H32) -> 64450800 | J32: 17269 | K32: =K31+((C32-C31)*J32) -> 30915800 | L32: 16881 | M32: =M31+((C32-C31)*L32) -> 27860600 | N32: 16517 | O32: =O31+((C32-C31)*N32) -> 25412600 | P32: 15951 | Q32: =Q31+((C32-C31)*P32) -> 23287400 | R32: 16558 | S32: =S31+((C32-C31)*R32) -> 22010000 | T32: 15382 | U32: =U31+((C32-C31)*T32) -> 20791400 | V32: 7699 | W32: =W31+((C32-C31)*V32) -> 17300900 | X32: 7184 | Y32: =Y31+((C32-C31)*X32) -> 16557200 | Z32: 7148 | AA32: =AA31+((C32-C31)*Z32) -> 15453300 | AB32: 7099 | AC32: =AC31+((C32-C31)*AB32) -> 14367700 | AD32: 5361 | AE32: =AE31+((C32-C31)*AD32) -> 11520000 | AF32: 5875
... B44: 40001-70000 | C44: 70000 | D44: 4540 | E44: =E43+((C44-C43)*D44) -> 574677400 | F44: 4134 | G44: =G43+((C44-C43)*F44) -> 511702900 | H44: 4034 | I44: =I43+((C44-C43)*H44) -> 453592000 | J44: 3673 | K44: =K43+((C44-C43)*J44) -> 397844300 | L44: 3166 | M44: =M43+((C44-C43)*L44) -> 990523500 | N44: 2597 | O44: =O43+((C44-C43)*N44) -> 307058300 | P44: 2477 | Q44: =Q43+((C44-C43)*P44) -> 281272400 | R44: 2237 | S44: =S43+((C44-C43)*R44) -> 230181800 | T44: 1936 | U44: =U43+((C44-C43)*T44) -> 210368600 | V44: 1640 | W44: =W43+((C44-C43)*V44) -> 190544300 | X44: 1328 | Y44: =Y43+((C44-C43)*X44) -> 173690500 | Z44: 850 | AA44: =AA43+((C44-C43)*Z44) -> 151894500 | AB44: 715 | AC44: =AC43+((C44-C43)*AB44) -> 141740600 | AD44: 520 | AE44: =AE43+((C44-C43)*AD44) -> 87844900 | AF44: 547
B45: >70000 | D45: 2012 | E45: =E44+((C45-C44)*D45) -> 433837400 | F45: 1874 | G45: =G44+((C45-C44)*F45) -> 380522900 | H45: 1848 | I45: =I44+((C45-C44)*H45) -> 324232000 | J45: 1738 | K45: =K44+((C45-C44)*J45) -> 276184300 | L45: 1488 | M45: =M44+((C45-C44)*L45) -> 886363500 | N45: 1218 | O45: =O44+((C45-C44)*N45) -> 221798300 | P45: 1079 | Q45: =Q44+((C45-C44)*P45) -> 205742400 | R45: 1089 | S45: =S44+((C45-C44)*R45) -> 153951800 | T45: 707 | U45: =U44+((C45-C44)*T45) -> 160878600 | V45: 677 | W45: =W44+((C45-C44)*V45) -> 143154300 | X45: 641 | Y45: =Y44+((C45-C44)*X45) -> 128820500 | Z45: 401 | AA45: =AA44+((C45-C44)*Z45) -> 123824500 | AB45: 364 | AC45: =AC44+((C45-C44)*AB45) -> 116260600 | AD45: 361 | AE45: =AE44+((C45-C44)*AD45) -> 62574900 | AF45: 295
B48: Architectural
B49: Structural
B50: Electrical
B51: Sanitary
B52: Specification and Bill of quantity
B54: Water Supply & Drain Line
B55: Septic tank
B56: Intake line & man holes
B57: Compound lighting

Sheet Location
A6: Location value | I6: =31.5*16 -> 504
A7: Property location
A8: City | B8: A.A
A9: Sub city | B9: Nifas Silk
A10: Worda | B10: 2 | H10: 2720 | I10: 200 | J10: 200 | K10: =H10*J10 -> 544000
A11: Plot Area | B11: 220.9 | H11: 2040 | I11: 97.29 | J11: 131.7 | K11: =H11*J11 -> 268668
A12: Plot Grade | B12: 2-1 | I12: 200 | K12: =H12*J12 -> 0
A13: Location Value | B13: =IF(B12="1-1b",D48,IF(B12="1-1a",F48,IF(B12="1-1",H48,IF(B12="1-2",K48,IF(B12="2-1",M48,IF(B12="1-3",O48,IF(B12="2-2",Q48,IF(B12="3-1",S48,IF(B12="2-3",U48,IF(B12="3-2",W48,IF(B12="4-1",Y48,IF(B12="3-3",AA48,IF(B12="4-2",AC48,IF(B12="4-3",AE48,IF(B12="4-4",AG48))))))))))))))) -> 5776904.6 | I13: 200 | K13: =H13*J13 -> 0 | M13: =100*(K13+K14+K15+K16+K17) -> 0
A14: Total lease amount | I14: 200 | K14: =H14*J14 -> 0
A15: Paid up Lease amount | B15: 0 | I15: 500 | K15: =H15*J15 -> 0
A16: Remaining lease amount | B16: =IF(B14>1,B14-B15,"0") -> 0 | H16: =226*2.5 -> 565 | I16: 500 | K16: =H16*J16 -> 0
A17: Location Value | H17: =177*2.5 -> 442.5 | I17: 1000 | K17: =H17*J17 -> 0
A18: Location value in previous Estimation | I18: =SUM(I10:I17) -> 2897.29 | J18: =SUM(J10:J17) -> 331.7 | K18: =SUM(K10:K17) -> 812668 | L18: =SUM(L13:L17) -> 0 | R18: =B13-R19 -> 168304.6
A19: Location value Considered | B19: =K18 -> 812668 | R19: =(100*R22)+(100*R23)+(100*R24) -> 5608600 | AF19: =100*AF22+100*AF23 -> 2462100
C20: 1-1b | E20: 1-1a | G20: 1-1 | I20: 1-2 | L20: 2-1 | N20: 1-3 | P20: 2-2 | R20: 3-1 | T20: 2-3 | V20: 3-2 | X20: 4-1 | Z20: 3-3 | AB20: 4-2 | AD20: 4-3 | AF20: 4-4
C21: 1 | E21: 2 | G21: 3 | I21: 4 | L21: 5 | N21: 6 | P21: 7 | R21: 8 | T21: 9 | V21: 10 | X21: 11 | Z21: 12 | AB21: 13 | AD21: 14 | AF21: 15
A22: 0-100 | B22: 100 | C22: 67844 | D22: =$B$22*C22 -> 6784400 | E22: 44355 | F22: =$B$22*E22 -> 4435500 | G22: 35523 | H22: =$B$22*G22 -> 3552300 | I22: 30912 | K22: =$B$22*I22 -> 3091200 | L22: 26368 | M22: =$B$22*L22 -> 2636800 | N22: 23599 | O22: =$B$22*N22 -> 2359900 | P22: 21576 | Q22: =$B$22*P22 -> 2157600 | R22: 20351 | S22: =$B$22*R22 -> 2035100 | T22: 17283 | U22: =$B$22*T22 -> 1728300 | V22: 16267 | W22: =$B$22*V22 -> 1626700 | X22: 15202 | Y22: =$B$22*X22 -> 1520200 | Z22: 14559 | AA22: =$B$22*Z22 -> 1455900 | AB22: 14168 | AC22: =$B$22*AB22 -> 1416800 | AD22: 13275 | AE22: =$B$22*AD22 -> 1327500 | AF22: 12688 | AG22: =$B$22*AF22 -> 1268800
A23: 101-200 | B23: 200 | C23: 62975 | D23: =D22+((B23-B22)*C23) -> 13081900 | E23: 43454 | F23: =F22+((B23-B22)*E23) -> 8780900 | G23: 34892 | H23: =H22+((B23-B22)*G23) -> 7041500 | I23: 30521 | K23: =K22+((B23-B22)*I23) -> 6143300 | L23: 26031 | M23: =M22+((B23-B22)*L23) -> 5239900 | N23: 23069 | O23: =O22+((B23-B22)*N23) -> 4666800 | P23: 20104 | Q23: =Q22+((B23-B22)*P23) -> 4168000 | R23: 18420 | S23: =S22+((B23-B22)*R23) -> 3877100 | T23: 17082 | U23: =U22+((B23-B22)*T23) -> 3436500 | V23: 15588 | W23: =W22+((B23-B22)*V23) -> 3185500 | X23: 14625 | Y23: =Y22+((B23-B22)*X23) -> 2982700 | Z23: 14104 | AA23: =AA22+((B23-B22)*Z23) -> 2866300 | AB23: 13800 | AC23: =AC22+((B23-B22)*AB23) -> 2796800 | AD23: 12537 | AE23: =AE22+((B23-B22)*AD23) -> 2581200 | AF23: 11933 | AG23: =AG22+((B23-B22)*AF23) -> 2462100
A24: 201-300 | B24: 300 | C24: 58106 | D24: =D23+((B24-B23)*C24) -> 18892500 | E24: 42553 | F24: =F23+((B24-B23)*E24) -> 13036200 | G24: 34261 | H24: =H23+((B24-B23)*G24) -> 10467600 | I24: 30130 | K24: =K23+((B24-B23)*I24) -> 9156300 | L24: 25694 | M24: =M23+((B24-B23)*L24) -> 7809300 | N24: 22539 | O24: =O23+((B24-B23)*N24) -> 6920700 | P24: 19022 | Q24: =Q23+((B24-B23)*P24) -> 6070200 | R24: 17315 | S24: =S23+((B24-B23)*R24) -> 5608600 | T24: 16898 | U24: =U23+((B24-B23)*T24) -> 5126300 | V24: 14991 | W24: =W23+((B24-B23)*V24) -> 4684600 | X24: 14128 | Y24: =Y23+((B24-B23)*X24) -> 4395500 | Z24: 13518 | AA24: =AA23+((B24-B23)*Z24) -> 4218100 | AB24: 13622 | AC24: =AC23+((B24-B23)*AB24) -> 4159000 | AD24: 11799 | AE24: =AE23+((B24-B23)*AD24) -> 3761100 | AF24: 11318 | AG24: =AG23+((B24-B23)*AF24) -> 3593900
A25: 301-400 | B25: 400 | C25: 54919 | D25: =D24+((B25-B24)*C25) -> 24384400 | E25: 41705 | F25: =F24+((B25-B24)*E25) -> 17206700 | G25: 33805 | H25: =H24+((B25-B24)*G25) -> 13848100 | I25: 29745 | K25: =K24+((B25-B24)*I25) -> 12130800 | L25: 25445 | M25: =M24+((B25-B24)*L25) -> 10353800 | N25: 22284 | O25: =O24+((B25-B24)*N25) -> 9149100 | P25: 18829 | Q25: =Q24+((B25-B24)*P25) -> 7953100 | R25: 17146 | S25: =S24+((B25-B24)*R25) -> 7323200 | T25: 16726 | U25: =U24+((B25-B24)*T25) -> 6798900 | V25: 14541 | W25: =W24+((B25-B24)*V25) -> 6138700 | X25: 13986 | Y25: =Y24+((B25-B24)*X25) -> 5794100 | Z25: 13385 | AA25: =AA24+((B25-B24)*Z25) -> 5556600 | AB25: 13487 | AC25: =AC24+((B25-B24)*AB25) -> 5507700 | AD25: 11644 | AE25: =AE24+((B25-B24)*AD25) -> 4925500 | AF25: 11197 | AG25: =AG24+((B25-B24)*AF25) -> 4713600
A26: 401-500 | B26: 500 | C26: 54358 | D26: =D25+((B26-B25)*C26) -> 29820200 | E26: 41283 | F26: =F25+((B26-B25)*E26) -> 21335000 | G26: 33463 | H26: =H25+((B26-B25)*G26) -> 17194400 | I26: 29444 | K26: =K25+((B26-B25)*I26) -> 15075200 | L26: 25195 | M26: =M25+((B26-B25)*L26) -> 12873300 | N26: 22048 | O26: =O25+((B26-B25)*N26) -> 11353900 | P26: 18636 | Q26: =Q25+((B26-B25)*P26) -> 9816700 | R26: 16977 | S26: =S25+((B26-B25)*R26) -> 9020900 | T26: 16554 | U26: =U25+((B26-B25)*T26) -> 8454300 | V26: 14691 | W26: =W25+((B26-B25)*V26) -> 7607800 | X26: 13844 | Y26: =Y25+((B26-B25)*X26) -> 7178500 | Z26: 13252 | AA26: =AA25+((B26-B25)*Z26) -> 6881800 | AB26: 13352 | AC26: =AC25+((B26-B25)*AB26) -> 6842900 | AD26: 11513 | AE26: =AE25+((B26-B25)*AD26) -> 6076800 | AF26: 11076 | AG26: =AG25+((B26-B25)*AF26) -> 5821200
A27: 501-600 | B27: 600 | C27: 20732 | D27: =D26+((B27-B26)*C27) -> 31893400 | E27: 18639 | F27: =F26+((B27-B26)*E27) -> 23198900 | G27: 17813 | H27: =H26+((B27-B26)*G27) -> 18975700 | I27: 18643 | K27: =K26+((B27-B26)*I27) -> 16939500 | L27: 16694 | M27: =M26+((B27-B26)*L27) -> 14542700 | N27: 14505 | O27: =O26+((B27-B26)*N27) -> 12804400 | P27: 14141 | Q27: =Q26+((B27-B26)*P27) -> 11230800 | R27: 12909 | S27: =S26+((B27-B26)*R27) -> 10311800 | T27: 11677 | U27: =U26+((B27-B26)*T27) -> 9622000 | V27: 11071 | W27: =W26+((B27-B26)*V27) -> 8714900 | X27: 10703 | Y27: =Y26+((B27-B26)*X27) -> 8248800 | Z27: 9812 | AA27: =AA26+((B27-B26)*Z27) -> 7863000 | AB27: 7311 | AC27: =AC26+((B27-B26)*AB27) -> 7574000 | AD27: 7239 | AE27: =AE26+((B27-B26)*AD27) -> 6800700 | AF27: 6212 | AG27: =AG26+((B27-B26)*AF27) -> 6442400
A28: 601-700 | B28: 700 | C28: 20477 | D28: =D27+((B28-B27)*C28) -> 33941100 | E28: 18351 | F28: =F27+((B28-B27)*E28) -> 25034000 | G28: 17591 | H28: =H27+((B28-B27)*G28) -> 20734800 | I28: 16832 | K28: =K27+((B28-B27)*I28) -> 18622700 | L28: 16408 | M28: =M27+((B28-B27)*L28) -> 16183500 | N28: 14318 | O28: =O27+((B28-B27)*N28) -> 14236200 | P28: 13946 | Q28: =Q27+((B28-B27)*P28) -> 12625400 | R28: 12612 | S28: =S27+((B28-B27)*R28) -> 11573000 | T28: 11545 | U28: =U27+((B28-B27)*T28) -> 10776500 | V28: 11006 | W28: =W27+((B28-B27)*V28) -> 9815500 | X28: 10551 | Y28: =Y27+((B28-B27)*X28) -> 9303900 | Z28: 9731 | AA28: =AA27+((B28-B27)*Z28) -> 8836100 | AB28: 7221 | AC28: =AC27+((B28-B27)*AB28) -> 8296100 | AD28: 7215 | AE28: =AE27+((B28-B27)*AD28) -> 7522200 | AF28: 6167 | AG28: =AG27+((B28-B27)*AF28) -> 7059100
A29: 701-800 | B29: 800 | C29: 20213 | D29: =D28+((B29-B28)*C29) -> 35962400 | E29: 18501 | F29: =F28+((B29-B28)*E29) -> 26884100 | G29: 18739 | H29: =H28+((B29-B28)*G29) -> 22608700 | I29: 18220 | K29: =K28+((B29-B28)*I29) -> 20444700 | L29: 16394 | M29: =M28+((B29-B28)*L29) -> 17822900 | N29: 14154 | O29: =O28+((B29-B28)*N29) -> 15651600 | P29: 13967 | Q29: =Q28+((B29-B28)*P29) -> 14022100 | R29: 13388 | S29: =S28+((B29-B28)*R29) -> 12911800 | T29: 12804 | U29: =U28+((B29-B28)*T29) -> 12056900 | V29: 12348 | W29: =W28+((B29-B28)*V29) -> 11050300 | X29: 11897 | Y29: =Y28+((B29-B28)*X29) -> 10493600 | Z29: 10044 | AA29: =AA28+((B29-B28)*Z29) -> 9840500 | AB29: 8936 | AC29: =AC28+((B29-B28)*AB29) -> 9189700 | AD29: 7184 | AE29: =AE28+((B29-B28)*AD29) -> 8240600 | AF29: 6118 | AG29: =AG28+((B29-B28)*AF29) -> 7670900
A30: 801-900 | B30: 900 | C30: 25258 | D30: =D29+((B30-B29)*C30) -> 38488200 | E30: 23415 | F30: =F29+((B30-B29)*E30) -> 29225600 | G30: 23415 | H30: =H29+((B30-B29)*G30) -> 24950200 | I30: 22656 | K30: =K29+((B30-B29)*I30) -> 22710300 | L30: 21508 | M30: =M29+((B30-B29)*L30) -> 19973700 | N30: 20158 | O30: =O29+((B30-B29)*N30) -> 17667400 | P30: 20107 | Q30: =Q29+((B30-B29)*P30) -> 16032800 | R30: 19988 | S30: =S29+((B30-B29)*R30) -> 14910600 | T30: 19861 | U30: =U29+((B30-B29)*T30) -> 14043000 | V30: 19614 | W30: =W29+((B30-B29)*V30) -> 13011700 | X30: 19382 | Y30: =Y29+((B30-B29)*X30) -> 12431800 | Z30: 16111 | AA30: =AA29+((B30-B29)*Z30) -> 11451600 | AB30: 14026 | AC30: =AC29+((B30-B29)*AB30) -> 10592300 | AD30: 7158 | AE30: =AE29+((B30-B29)*AD30) -> 8956400 | AF30: 6062 | AG30: =AG29+((B30-B29)*AF30) -> 8277100
A31: 901-1000 | B31: 1000 | C31: 25001 | D31: =D30+((B31-B30)*C31) -> 40988300 | E31: 23190 | F31: =F30+((B31-B30)*E31) -> 31544600 | G31: 23190 | H31: =H30+((B31-B30)*G31) -> 27269200 | I31: 23332 | K31: =K30+((B31-B30)*I31) -> 25043500 | L31: 21968 | M31: =M30+((B31-B30)*L31) -> 22170500 | N31: 21622 | O31: =O30+((B31-B30)*N31) -> 19829600 | P31: 20783 | Q31: =Q30+((B31-B30)*P31) -> 18111100 | R31: 20366 | S31: =S30+((B31-B30)*R31) -> 16947200 | T31: 19943 | U31: =U30+((B31-B30)*T31) -> 16037300 | V31: 19871 | W31: =W30+((B31-B30)*V31) -> 14998800 | X31: 19249 | Y31: =Y30+((B31-B30)*X31) -> 14356700 | Z31: 18181 | AA31: =AA30+((B31-B30)*Z31) -> 13269700 | AB31: 16066 | AC31: =AC30+((B31-B30)*AB31) -> 12198900 | AD31: 7130 | AE31: =AE30+((B31-B30)*AD31) -> 9669400 | AF31: 6011 | AG31: =AG30+((B31-B30)*AF31) -> 8878200
A32: 1001-1100 | B32: 1100 | C32: 24751 | D32: =D31+((B32-B31)*C32) -> 43463400 | E32: 22575 | F32: =F31+((B32-B31)*E32) -> 33802100 | G32: 21758 | H32: =H31+((B32-B31)*G32) -> 29445000 | I32: 21064 | K32: =K31+((B32-B31)*I32) -> 27149900 | L32: 20168 | M32: =M31+((B32-B31)*L32) -> 24187300 | N32: 19825 | O32: =O31+((B32-B31)*N32) -> 21812100 | P32: 18009 | Q32: =Q31+((B32-B31)*P32) -> 19912000 | R32: 17165 | S32: =S31+((B32-B31)*R32) -> 18663700 | T32: 16316 | U32: =U31+((B32-B31)*T32) -> 17668900 | V32: 7699 | W32: =W31+((B32-B31)*V32) -> 15768700 | X32: 7486 | Y32: =Y31+((B32-B31)*X32) -> 15105300 | Z32: 7412 | AA32: =AA31+((B32-B31)*Z32) -> 14010900 | AB32: 7340 | AC32: =AC31+((B32-B31)*AB32) -> 12932900 | AD32: 6600 | AE32: =AE31+((B32-B31)*AD32) -> 10329400 | AF32: 5966 | AG32: =AG31+((B32-B31)*AF32) -> 9474800
A33: 1101-1200 | B33: 1200 | C33: 26991 | D33: =D32+((B33-B32)*C33) -> 46162500 | E33: 25943 | F33: =F32+((B33-B32)*E33) -> 36396400 | G33: 21050 | H33: =H32+((B33-B32)*G33) -> 31550000 | I33: 20390 | K33: =K32+((B33-B32)*I33) -> 29188900 | L33: 19852 | M33: =M32+((B33-B32)*L33) -> 26172500 | N33: 19488 | O33: =O32+((B33-B32)*N33) -> 23760900 | P33: 17803 | Q33: =Q32+((B33-B32)*P33) -> 21692300 | R33: 16905 | S33: =S32+((B33-B32)*R33) -> 20354200 | T33: 15843 | U33: =U32+((B33-B32)*T33) -> 19253200 | V33: 7623 | W33: =W32+((B33-B32)*V33) -> 16531000 | X33: 7335 | Y33: =Y32+((B33-B32)*X33) -> 15838800 | Z33: 7276 | AA33: =AA32+((B33-B32)*Z33) -> 14738500 | AB33: 7249 | AC33: =AC32+((B33-B32)*AB33) -> 13657800 | AD33: 6545 | AE33: =AE32+((B33-B32)*AD33) -> 10983900 | AF33: 5916 | AG33: =AG32+((B33-B32)*AF33) -> 10066400
A34: 1201-1300 | B34: 1300 | C34: 26638 | D34: =D33+((B34-B33)*C34) -> 48826300 | E34: 25605 | F34: =F33+((B34-B33)*E34) -> 38956900 | G34: 17908 | H34: =H33+((B34-B33)*G34) -> 33340800 | I34: 17269 | K34: =K33+((B34-B33)*I34) -> 30915800 | L34: 16881 | M34: =M33+((B34-B33)*L34) -> 27860600 | N34: 16517 | O34: =O33+((B34-B33)*N34) -> 25412600 | P34: 15951 | Q34: =Q33+((B34-B33)*P34) -> 23287400 | R34: 16558 | S34: =S33+((B34-B33)*R34) -> 22010000 | T34: 15382 | U34: =U33+((B34-B33)*T34) -> 20791400 | V34: 7699 | W34: =W33+((B34-B33)*V34) -> 17300900 | X34: 7184 | Y34: =Y33+((B34-B33)*X34) -> 16557200 | Z34: 7148 | AA34: =AA33+((B34-B33)*Z34) -> 15453300 | AB34: 7099 | AC34: =AC33+((B34-B33)*AB34) -> 14367700 | AD34: 5361 | AE34: =AE33+((B34-B33)*AD34) -> 11520000 | AF34: 5875 | AG34: =AG33+((B34-B33)*AF34) -> 10653900
... A46: 40001-70000 | B46: 70000 | C46: 4540 | D46: =D45+((B46-B45)*C46) -> 574677400 | E46: 4134 | F46: =F45+((B46-B45)*E46) -> 511702900 | G46: 4034 | H46: =H45+((B46-B45)*G46) -> 422482000 | I46: 3673 | K46: =K45+((B46-B45)*I46) -> 397844300 | L46: 3166 | M46: =M45+((B46-B45)*L46) -> 990523500 | N46: 2597 | O46: =O45+((B46-B45)*N46) -> 307058300 | P46: 2477 | Q46: =Q45+((B46-B45)*P46) -> 281272400 | R46: 2237 | S46: =S45+((B46-B45)*R46) -> 230181800 | T46: 1936 | U46: =U45+((B46-B45)*T46) -> 210368600 | V46: 1640 | W46: =W45+((B46-B45)*V46) -> 190544300 | X46: 1328 | Y46: =Y45+((B46-B45)*X46) -> 173690500 | Z46: 850 | AA46: =AA45+((B46-B45)*Z46) -> 151894500 | AB46: 715 | AC46: =AC45+((B46-B45)*AB46) -> 141740600 | AD46: 520 | AE46: =AE45+((B46-B45)*AD46) -> 87844900 | AF46: 547 | AG46: =AG45+((B46-B45)*AF46) -> 80552100
A47: >70000 | C47: 2012 | D47: =D46+((B47-B46)*C47) -> 433837400 | E47: 1874 | F47: =F46+((B47-B46)*E47) -> 380522900 | G47: 1848 | H47: =H46+((B47-B46)*G47) -> 293122000 | I47: 1738 | K47: =K46+((B47-B46)*I47) -> 276184300 | L47: 1488 | M47: =M46+((B47-B46)*L47) -> 886363500 | N47: 1218 | O47: =O46+((B47-B46)*N47) -> 221798300 | P47: 1079 | Q47: =Q46+((B47-B46)*P47) -> 205742400 | R47: 1089 | S47: =S46+((B47-B46)*R47) -> 153951800 | T47: 707 | U47: =U46+((B47-B46)*T47) -> 160878600 | V47: 677 | W47: =W46+((B47-B46)*V47) -> 143154300 | X47: 641 | Y47: =Y46+((B47-B46)*X47) -> 128820500 | Z47: 401 | AA47: =AA46+((B47-B46)*Z47) -> 123824500 | AB47: 364 | AC47: =AC46+((B47-B46)*AB47) -> 116260600 | AD47: 361 | AE47: =AE46+((B47-B46)*AD47) -> 62574900 | AF47: 295 | AG47: =AG46+((B47-B46)*AF47) -> 59902100
D48: =IF(B11<100,B11*C22,(IF($B$11<=2500,(LOOKUP($B$11,$B$22:$B$47,D$22:D$47))+(($B$11-LOOKUP($B$11,$B$22:$B$47))*LOOKUP(($B$11+100),$B$22:$B$47,C$22:C$47)),IF((2500<$B$11)*AND($B$11<=10000),(LOOKUP($B$11,$B$22:$B$47,D$22:D$47))+(($B$11-LOOKUP($B$11,$B$22:$B$47))*LOOKUP(($B$11+7500),$B$22:$B$47,C$22:C$47)),IF((10000<$B$11)*AND($B$11<=20000),(LOOKUP($B$11,$B$22:$B$47,D$22:D$47))+(($B$11-LOOKUP($B$11,$B$22:$B$47))*LOOKUP(($B$11+10000),$B$22:$B$47,C$22:C$47)),IF((20000<$B$11)*AND($B$11<=40000),(LOOKUP($B$11,$B$22:$B$47,D$22:D$47))+(($B$11-LOOKUP($B$11,$B$22:$B$47))*LOOKUP(($B$11+20000),$B$22:$B$47,C$22:C$47)),IF((40000<$B$11)*AND($B$11<=70000),(LOOKUP($B$11,$B$22:$B$47,D$22:D$47))+(($B$11-LOOKUP($B$11,$B$22:$B$47))*LOOKUP(($B$11+30000),$B$22:$B$47,C$22:C$47)),(LOOKUP($B$11,$B$22:$B$47,D$22:D$47))+(($B$11-LOOKUP($B$11,$B$22:$B$47))*C$47)))))))) -> 14296315 | F48: =IF(B11<100,B11*E22,(IF($B$11<=2500,(LOOKUP($B$11,$B$22:$B$47,F$22:F$47))+(($B$11-LOOKUP($B$11,$B$22:$B$47))*LOOKUP(($B$11+100),$B$22:$B$47,E$22:E$47)),IF((2500<$B$11)*AND($B$11<=10000),(LOOKUP($B$11,$B$22:$B$47,F$22:F$47))+(($B$11-LOOKUP($B$11,$B$22:$B$47))*LOOKUP(($B$11+7500),$B$22:$B$47,E$22:E$47)),IF((10000<$B$11)*AND($B$11<=20000),(LOOKUP($B$11,$B$22:$B$47,F$22:F$47))+(($B$11-LOOKUP($B$11,$B$22:$B$47))*LOOKUP(($B$11+10000),$B$22:$B$47,E$22:E$47)),IF((20000<$B$11)*AND($B$11<=40000),(LOOKUP($B$11,$B$22:$B$47,F$22:F$47))+(($B$11-LOOKUP($B$11,$B$22:$B$47))*LOOKUP(($B$11+20000),$B$22:$B$47,E$22:E$47)),IF((40000<$B$11)*AND($B$11<=70000),(LOOKUP($B$11,$B$22:$B$47,F$22:F$47))+(($B$11-LOOKUP($B$11,$B$22:$B$47))*LOOKUP(($B$11+30000),$B$22:$B$47,E$22:E$47)),(LOOKUP($B$11,$B$22:$B$47,F$22:F$47))+(($B$11-LOOKUP($B$11,$B$22:$B$47))*E$47)))))))) -> 9670257.7 | H48: =IF(B11<100,B11*G22,(IF($B$11<=2500,(LOOKUP($B$11,$B$22:$B$47,H$22:H$47))+(($B$11-LOOKUP($B$11,$B$22:$B$47))*LOOKUP(($B$11+100),$B$22:$B$47,G$22:G$47)),IF((2500<$B$11)*AND($B$11<=10000),(LOOKUP($B$11,$B$22:$B$47,H$22:H$47))+(($B$11-LOOKUP($B$11,$B$22:$B$47))*LOOKUP(($B$11+7500),$B$22:$B$47,G$22:G$47)),IF((10000<$B$11)*AND($B$11<=20000),(LOOKUP($B$11,$B$22:$B$47,H$22:H$47))+(($B$11-LOOKUP($B$11,$B$22:$B$47))*LOOKUP(($B$11+10000),$B$22:$B$47,G$22:G$47)),IF((20000<$B$11)*AND($B$11<=40000),(LOOKUP($B$11,$B$22:$B$47,H$22:H$47))+(($B$11-LOOKUP($B$11,$B$22:$B$47))*LOOKUP(($B$11+20000),$B$22:$B$47,G$22:G$47)),IF((40000<$B$11)*AND($B$11<=70000),(LOOKUP($B$11,$B$22:$B$47,H$22:H$47))+(($B$11-LOOKUP($B$11,$B$22:$B$47))*LOOKUP(($B$11+30000),$B$22:$B$47,G$22:G$47)),(LOOKUP($B$11,$B$22:$B$47,H$22:H$47))+(($B$11-LOOKUP($B$11,$B$22:$B$47))*G$47)))))))) -> 7757554.9 | K48: =IF(B11<100,B11*I22,(IF($B$11<=2500,(LOOKUP($B$11,$B$22:$B$47,K$22:K$47))+(($B$11-LOOKUP($B$11,$B$22:$B$47))*LOOKUP(($B$11+100),$B$22:$B$47,I$22:I$47)),IF((2500<$B$11)*AND($B$11<=10000),(LOOKUP($B$11,$B$22:$B$47,K$22:K$47))+(($B$11-LOOKUP($B$11,$B$22:$B$47))*LOOKUP(($B$11+7500),$B$22:$B$47,I$22:I$47)),IF((10000<$B$11)*AND($B$11<=20000),(LOOKUP($B$11,$B$22:$B$47,K$22:K$47))+(($B$11-LOOKUP($B$11,$B$22:$B$47))*LOOKUP(($B$11+10000),$B$22:$B$47,I$22:I$47)),IF((20000<$B$11)*AND($B$11<=40000),(LOOKUP($B$11,$B$22:$B$47,K$22:K$47))+(($B$11-LOOKUP($B$11,$B$22:$B$47))*LOOKUP(($B$11+20000),$B$22:$B$47,I$22:I$47)),IF((40000<$B$11)*AND($B$11<=70000),(LOOKUP($B$11,$B$22:$B$47,K$22:K$47))+(($B$11-LOOKUP($B$11,$B$22:$B$47))*LOOKUP(($B$11+30000),$B$22:$B$47,I$22:I$47)),(LOOKUP($B$11,$B$22:$B$47,K$22:K$47))+(($B$11-LOOKUP($B$11,$B$22:$B$47))*I$47)))))))) -> 6773017 | M48: =IF(B11<100,B11*L22,(IF($B$11<=2500,(LOOKUP($B$11,$B$22:$B$47,M$22:M$47))+(($B$11-LOOKUP($B$11,$B$22:$B$47))*LOOKUP(($B$11+100),$B$22:$B$47,L$22:L$47)),IF((2500<$B$11)*AND($B$11<=10000),(LOOKUP($B$11,$B$22:$B$47,M$22:M$47))+(($B$11-LOOKUP($B$11,$B$22:$B$47))*LOOKUP(($B$11+7500),$B$22:$B$47,L$22:L$47)),IF((10000<$B$11)*AND($B$11<=20000),(LOOKUP($B$11,$B$22:$B$47,M$22:M$47))+(($B$11-LOOKUP($B$11,$B$22:$B$47))*LOOKUP(($B$11+10000),$B$22:$B$47,L$22:L$47)),IF((20000<$B$11)*AND($B$11<=40000),(LOOKUP($B$11,$B$22:$B$47,M$22:M$47))+(($B$11-LOOKUP($B$11,$B$22:$B$47))*LOOKUP(($B$11+20000),$B$22:$B$47,L$22:L$47)),IF((40000<$B$11)*AND($B$11<=70000),(LOOKUP($B$11,$B$22:$B$47,M$22:M$47))+(($B$11-LOOKUP($B$11,$B$22:$B$47))*LOOKUP(($B$11+30000),$B$22:$B$47,L$22:L$47)),(LOOKUP($B$11,$B$22:$B$47,M$22:M$47))+(($B$11-LOOKUP($B$11,$B$22:$B$47))*L$47)))))))) -> 5776904.6 | O48: =IF(B11<100,B11*N22,(IF($B$11<=2500,(LOOKUP($B$11,$B$22:$B$47,O$22:O$47))+(($B$11-LOOKUP($B$11,$B$22:$B$47))*LOOKUP(($B$11+100),$B$22:$B$47,N$22:N$47)),IF((2500<$B$11)*AND($B$11<=10000),(LOOKUP($B$11,$B$22:$B$47,O$22:O$47))+(($B$11-LOOKUP($B$11,$B$22:$B$47))*LOOKUP(($B$11+7500),$B$22:$B$47,N$22:N$47)),IF((10000<$B$11)*AND($B$11<=20000),(LOOKUP($B$11,$B$22:$B$47,O$22:O$47))+(($B$11-LOOKUP($B$11,$B$22:$B$47))*LOOKUP(($B$11+10000),$B$22:$B$47,N$22:N$47)),IF((20000<$B$11)*AND($B$11<=40000),(LOOKUP($B$11,$B$22:$B$47,O$22:O$47))+(($B$11-LOOKUP($B$11,$B$22:$B$47))*LOOKUP(($B$11+20000),$B$22:$B$47,N$22:N$47)),IF((40000<$B$11)*AND($B$11<=70000),(LOOKUP($B$11,$B$22:$B$47,O$22:O$47))+(($B$11-LOOKUP($B$11,$B$22:$B$47))*LOOKUP(($B$11+30000),$B$22:$B$47,N$22:N$47)),(LOOKUP($B$11,$B$22:$B$47,O$22:O$47))+(($B$11-LOOKUP($B$11,$B$22:$B$47))*N$47)))))))) -> 5137865.1 | Q48: =IF(B11<100,B11*P22,(IF($B$11<=2500,(LOOKUP($B$11,$B$22:$B$47,Q$22:Q$47))+(($B$11-LOOKUP($B$11,$B$22:$B$47))*LOOKUP(($B$11+100),$B$22:$B$47,P$22:P$47)),IF((2500<$B$11)*AND($B$11<=10000),(LOOKUP($B$11,$B$22:$B$47,Q$22:Q$47))+(($B$11-LOOKUP($B$11,$B$22:$B$47))*LOOKUP(($B$11+7500),$B$22:$B$47,P$22:P$47)),IF((10000<$B$11)*AND($B$11<=20000),(LOOKUP($B$11,$B$22:$B$47,Q$22:Q$47))+(($B$11-LOOKUP($B$11,$B$22:$B$47))*LOOKUP(($B$11+10000),$B$22:$B$47,P$22:P$47)),IF((20000<$B$11)*AND($B$11<=40000),(LOOKUP($B$11,$B$22:$B$47,Q$22:Q$47))+(($B$11-LOOKUP($B$11,$B$22:$B$47))*LOOKUP(($B$11+20000),$B$22:$B$47,P$22:P$47)),IF((40000<$B$11)*AND($B$11<=70000),(LOOKUP($B$11,$B$22:$B$47,Q$22:Q$47))+(($B$11-LOOKUP($B$11,$B$22:$B$47))*LOOKUP(($B$11+30000),$B$22:$B$47,P$22:P$47)),(LOOKUP($B$11,$B$22:$B$47,Q$22:Q$47))+(($B$11-LOOKUP($B$11,$B$22:$B$47))*P$47)))))))) -> 4565559.8 | S48: =IF(B11<100,B11*R22,(IF($B$11<=2500,(LOOKUP($B$11,$B$22:$B$47,S$22:S$47))+(($B$11-LOOKUP($B$11,$B$22:$B$47))*LOOKUP(($B$11+100),$B$22:$B$47,R$22:R$47)),IF((2500<$B$11)*AND($B$11<=10000),(LOOKUP($B$11,$B$22:$B$47,S$22:S$47))+(($B$11-LOOKUP($B$11,$B$22:$B$47))*LOOKUP(($B$11+7500),$B$22:$B$47,R$22:R$47)),IF((10000<$B$11)*AND($B$11<=20000),(LOOKUP($B$11,$B$22:$B$47,S$22:S$47))+(($B$11-LOOKUP($B$11,$B$22:$B$47))*LOOKUP(($B$11+10000),$B$22:$B$47,R$22:R$47)),IF((20000<$B$11)*AND($B$11<=40000),(LOOKUP($B$11,$B$22:$B$47,S$22:S$47))+(($B$11-LOOKUP($B$11,$B$22:$B$47))*LOOKUP(($B$11+20000),$B$22:$B$47,R$22:R$47)),IF((40000<$B$11)*AND($B$11<=70000),(LOOKUP($B$11,$B$22:$B$47,S$22:S$47))+(($B$11-LOOKUP($B$11,$B$22:$B$47))*LOOKUP(($B$11+30000),$B$22:$B$47,R$22:R$47)),(LOOKUP($B$11,$B$22:$B$47,S$22:S$47))+(($B$11-LOOKUP($B$11,$B$22:$B$47))*R$47)))))))) -> 4238983.5 | U48: =IF(B11<100,B11*T22,(IF($B$11<=2500,(LOOKUP($B$11,$B$22:$B$47,U$22:U$47))+(($B$11-LOOKUP($B$11,$B$22:$B$47))*LOOKUP(($B$11+100),$B$22:$B$47,T$22:T$47)),IF((2500<$B$11)*AND($B$11<=10000),(LOOKUP($B$11,$B$22:$B$47,U$22:U$47))+(($B$11-LOOKUP($B$11,$B$22:$B$47))*LOOKUP(($B$11+7500),$B$22:$B$47,T$22:T$47)),IF((10000<$B$11)*AND($B$11<=20000),(LOOKUP($B$11,$B$22:$B$47,U$22:U$47))+(($B$11-LOOKUP($B$11,$B$22:$B$47))*LOOKUP(($B$11+10000),$B$22:$B$47,T$22:T$47)),IF((20000<$B$11)*AND($B$11<=40000),(LOOKUP($B$11,$B$22:$B$47,U$22:U$47))+(($B$11-LOOKUP($B$11,$B$22:$B$47))*LOOKUP(($B$11+20000),$B$22:$B$47,T$22:T$47)),IF((40000<$B$11)*AND($B$11<=70000),(LOOKUP($B$11,$B$22:$B$47,U$22:U$47))+(($B$11-LOOKUP($B$11,$B$22:$B$47))*LOOKUP(($B$11+30000),$B$22:$B$47,T$22:T$47)),(LOOKUP($B$11,$B$22:$B$47,U$22:U$47))+(($B$11-LOOKUP($B$11,$B$22:$B$47))*T$47)))))))) -> 3789668.2 | W48: =IF(B11<100,B11*V22,(IF($B$11<=2500,(LOOKUP($B$11,$B$22:$B$47,W$22:W$47))+(($B$11-LOOKUP($B$11,$B$22:$B$47))*LOOKUP(($B$11+100),$B$22:$B$47,V$22:V$47)),IF((2500<$B$11)*AND($B$11<=10000),(LOOKUP($B$11,$B$22:$B$47,W$22:W$47))+(($B$11-LOOKUP($B$11,$B$22:$B$47))*LOOKUP(($B$11+7500),$B$22:$B$47,V$22:V$47)),IF((10000<$B$11)*AND($B$11<=20000),(LOOKUP($B$11,$B$22:$B$47,W$22:W$47))+(($B$11-LOOKUP($B$11,$B$22:$B$47))*LOOKUP(($B$11+10000),$B$22:$B$47,V$22:V$47)),IF((20000<$B$11)*AND($B$11<=40000),(LOOKUP($B$11,$B$22:$B$47,W$22:W$47))+(($B$11-LOOKUP($B$11,$B$22:$B$47))*LOOKUP(($B$11+20000),$B$22:$B$47,V$22:V$47)),IF((40000<$B$11)*AND($B$11<=70000),(LOOKUP($B$11,$B$22:$B$47,W$22:W$47))+(($B$11-LOOKUP($B$11,$B$22:$B$47))*LOOKUP(($B$11+30000),$B$22:$B$47,V$22:V$47)),(LOOKUP($B$11,$B$22:$B$47,W$22:W$47))+(($B$11-LOOKUP($B$11,$B$22:$B$47))*V$47)))))))) -> 3498811.9 | Y48: =IF(B11<100,B11*X22,(IF($B$11<=2500,(LOOKUP($B$11,$B$22:$B$47,Y$22:Y$47))+(($B$11-LOOKUP($B$11,$B$22:$B$47))*LOOKUP(($B$11+100),$B$22:$B$47,X$22:X$47)),IF((2500<$B$11)*AND($B$11<=10000),(LOOKUP($B$11,$B$22:$B$47,Y$22:Y$47))+(($B$11-LOOKUP($B$11,$B$22:$B$47))*LOOKUP(($B$11+7500),$B$22:$B$47,X$22:X$47)),IF((10000<$B$11)*AND($B$11<=20000),(LOOKUP($B$11,$B$22:$B$47,Y$22:Y$47))+(($B$11-LOOKUP($B$11,$B$22:$B$47))*LOOKUP(($B$11+10000),$B$22:$B$47,X$22:X$47)),IF((20000<$B$11)*AND($B$11<=40000),(LOOKUP($B$11,$B$22:$B$47,Y$22:Y$47))+(($B$11-LOOKUP($B$11,$B$22:$B$47))*LOOKUP(($B$11+20000),$B$22:$B$47,X$22:X$47)),IF((40000<$B$11)*AND($B$11<=70000),(LOOKUP($B$11,$B$22:$B$47,Y$22:Y$47))+(($B$11-LOOKUP($B$11,$B$22:$B$47))*LOOKUP(($B$11+30000),$B$22:$B$47,X$22:X$47)),(LOOKUP($B$11,$B$22:$B$47,Y$22:Y$47))+(($B$11-LOOKUP($B$11,$B$22:$B$47))*X$47)))))))) -> 3277975.2 | AA48: =IF(B11<100,B11*Z22,(IF($B$11<=2500,(LOOKUP($B$11,$B$22:$B$47,AA$22:AA$47))+(($B$11-LOOKUP($B$11,$B$22:$B$47))*LOOKUP(($B$11+100),$B$22:$B$47,Z$22:Z$47)),IF((2500<$B$11)*AND($B$11<=10000),(LOOKUP($B$11,$B$22:$B$47,AA$22:AA$47))+(($B$11-LOOKUP($B$11,$B$22:$B$47))*LOOKUP(($B$11+7500),$B$22:$B$47,Z$22:Z$47)),IF((10000<$B$11)*AND($B$11<=20000),(LOOKUP($B$11,$B$22:$B$47,AA$22:AA$47))+(($B$11-LOOKUP($B$11,$B$22:$B$47))*LOOKUP(($B$11+10000),$B$22:$B$47,Z$22:Z$47)),IF((20000<$B$11)*AND($B$11<=40000),(LOOKUP($B$11,$B$22:$B$47,AA$22:AA$47))+(($B$11-LOOKUP($B$11,$B$22:$B$47))*LOOKUP(($B$11+20000),$B$22:$B$47,Z$22:Z$47)),IF((40000<$B$11)*AND($B$11<=70000),(LOOKUP($B$11,$B$22:$B$47,AA$22:AA$47))+(($B$11-LOOKUP($B$11,$B$22:$B$47))*LOOKUP(($B$11+30000),$B$22:$B$47,Z$22:Z$47)),(LOOKUP($B$11,$B$22:$B$47,AA$22:AA$47))+(($B$11-LOOKUP($B$11,$B$22:$B$47))*Z$47)))))))) -> 3148826.2 | AC48: =IF(B11<100,B11*AB22,(IF($B$11<=2500,(LOOKUP($B$11,$B$22:$B$47,AC$22:AC$47))+(($B$11-LOOKUP($B$11,$B$22:$B$47))*LOOKUP(($B$11+100),$B$22:$B$47,AB$22:AB$47)),IF((2500<$B$11)*AND($B$11<=10000),(LOOKUP($B$11,$B$22:$B$47,AC$22:AC$47))+(($B$11-LOOKUP($B$11,$B$22:$B$47))*LOOKUP(($B$11+7500),$B$22:$B$47,AB$22:AB$47)),IF((10000<$B$11)*AND($B$11<=20000),(LOOKUP($B$11,$B$22:$B$47,AC$22:AC$47))+(($B$11-LOOKUP($B$11,$B$22:$B$47))*LOOKUP(($B$11+10000),$B$22:$B$47,AB$22:AB$47)),IF((20000<$B$11)*AND($B$11<=40000),(LOOKUP($B$11,$B$22:$B$47,AC$22:AC$47))+(($B$11-LOOKUP($B$11,$B$22:$B$47))*LOOKUP(($B$11+20000),$B$22:$B$47,AB$22:AB$47)),IF((40000<$B$11)*AND($B$11<=70000),(LOOKUP($B$11,$B$22:$B$47,AC$22:AC$47))+(($B$11-LOOKUP($B$11,$B$22:$B$47))*LOOKUP(($B$11+30000),$B$22:$B$47,AB$22:AB$47)),(LOOKUP($B$11,$B$22:$B$47,AC$22:AC$47))+(($B$11-LOOKUP($B$11,$B$22:$B$47))*AB$47)))))))) -> 3081499.8 | AE48: =IF(B11<100,B11*AD22,(IF($B$11<=2500,(LOOKUP($B$11,$B$22:$B$47,AE$22:AE$47))+(($B$11-LOOKUP($B$11,$B$22:$B$47))*LOOKUP(($B$11+100),$B$22:$B$47,AD$22:AD$47)),IF((2500<$B$11)*AND($B$11<=10000),(LOOKUP($B$11,$B$22:$B$47,AE$22:AE$47))+(($B$11-LOOKUP($B$11,$B$22:$B$47))*LOOKUP(($B$11+7500),$B$22:$B$47,AD$22:AD$47)),IF((10000<$B$11)*AND($B$11<=20000),(LOOKUP($B$11,$B$22:$B$47,AE$22:AE$47))+(($B$11-LOOKUP($B$11,$B$22:$B$47))*LOOKUP(($B$11+10000),$B$22:$B$47,AD$22:AD$47)),IF((20000<$B$11)*AND($B$11<=40000),(LOOKUP($B$11,$B$22:$B$47,AE$22:AE$47))+(($B$11-LOOKUP($B$11,$B$22:$B$47))*LOOKUP(($B$11+20000),$B$22:$B$47,AD$22:AD$47)),IF((40000<$B$11)*AND($B$11<=70000),(LOOKUP($B$11,$B$22:$B$47,AE$22:AE$47))+(($B$11-LOOKUP($B$11,$B$22:$B$47))*LOOKUP(($B$11+30000),$B$22:$B$47,AD$22:AD$47)),(LOOKUP($B$11,$B$22:$B$47,AE$22:AE$47))+(($B$11-LOOKUP($B$11,$B$22:$B$47))*AD$47)))))))) -> 2827799.1 | AG48: =IF(B11<100,B11*AF22,(IF($B$11<=2500,(LOOKUP($B$11,$B$22:$B$47,AG$22:AG$47))+(($B$11-LOOKUP($B$11,$B$22:$B$47))*LOOKUP(($B$11+100),$B$22:$B$47,AF$22:AF$47)),IF((2500<$B$11)*AND($B$11<=10000),(LOOKUP($B$11,$B$22:$B$47,AG$22:AG$47))+(($B$11-LOOKUP($B$11,$B$22:$B$47))*LOOKUP(($B$11+7500),$B$22:$B$47,AF$22:AF$47)),IF((10000<$B$11)*AND($B$11<=20000),(LOOKUP($B$11,$B$22:$B$47,AG$22:AG$47))+(($B$11-LOOKUP($B$11,$B$22:$B$47))*LOOKUP(($B$11+10000),$B$22:$B$47,AF$22:AF$47)),IF((20000<$B$11)*AND($B$11<=40000),(LOOKUP($B$11,$B$22:$B$47,AG$22:AG$47))+(($B$11-LOOKUP($B$11,$B$22:$B$47))*LOOKUP(($B$11+20000),$B$22:$B$47,AF$22:AF$47)),IF((40000<$B$11)*AND($B$11<=70000),(LOOKUP($B$11,$B$22:$B$47,AG$22:AG$47))+(($B$11-LOOKUP($B$11,$B$22:$B$47))*LOOKUP(($B$11+30000),$B$22:$B$47,AF$22:AF$47)),(LOOKUP($B$11,$B$22:$B$47,AG$22:AG$47))+(($B$11-LOOKUP($B$11,$B$22:$B$47))*AD$47)))))))) -> 2698646.2
A49: Internal structure | B49: ='Fence and Compund'!G207 -> 0 | H49: =20+15.1 -> 35.1 | I49: =H49/2 -> 17.55 | J49: =18.9*I49 -> 331.695
A50: External sanitary work | B50: For A = | D50: =area!C2 -> 61.364
A51: Water Supply & Drain Line | D51: =IF(D50=0,0,IF(D50<=200,4.37-D50*0.014,IF(D50<=2000,2.34-D50/1103,IF(D50<=2800,1.2-D50/3025,IF(2800<D50,0.2))))) -> 3.510904 | E51: % X | F51: =area!E2 -> 1853192.8 | G51: Birr
A52: Septic tank | D52: =IF(A51="Water Supply & Drain Line",D51*(F51+B49)/100,0) -> 65063.82 | E52: Birr
A53: Septic tank | B53: 1 | C53: Capacity = | D53: =IF(AND(A53="Septic tank",F51<>0),IF(D50<=200,10,IF(D50<1000,ROUND(((D50-200)/80+10),2),IF(D50=1000,20,IF(D50<2000,ROUND(((D50-1000)/100+20),2),IF(D50=2000,30,IF(D50<3000,ROUND(((D50-2000)*0.03+30),2),IF(D50>=3000,60))))))),0) -> 10 | E53: m3 | F53: =ROUND((B53*D53),2) -> 10
B54: y=3064X+23793 => | D54: =IF(D53=0,0,3064*F53+23793) -> 54433 | E54: Birr
A55: Capacity Factor =
A56: Total External sanitary work | D56: =D54+D52 -> 119496.82
A57: External Electric work
B58: Floor area (M2) | C58: Intake line & man holes | E58: Compound lighting
B59: =D50 -> 61.364 | C59: =IF(C58="Intake line & man holes",(IF(B59<=200,0.35,IF(B59<=1000,0.35+(0.59-0.35)/(1000-200)*(B59-200),IF(B59<=2000,(0.89-0.59)*(B59-1000)/(2000-1000)+0.59,IF(B59<3000,(1.01-0.89)/(3000-200)*(B59-2000)+0.89,IF(B59>=3000,1.01)))))),0) -> 0.35 | E59: =IF(E58="Compound lighting",(IF(B59<=200,0.26,IF(B59<=1000,0.26+(0.45-0.26)/(1000-200)*(B59-200),IF(B59<=2000,(0.69-0.45)/(2000-1000)*(B59-1000)+0.45,IF(B59<3000,(0.36-0.69)/(3000-2000)*(B59-2000)+0.69,IF(B59>=3000,0.36)))))),0) -> 0.26
B60: Total Percentage | C60: =C59+E59 -> 0.61
C62: =C60 -> 0.61 | D62: =F51 -> 1853192.8 | F62: Birr
C63: =IF(OR(C60=0,F51=0),0,MAX(C62*D62/100,7500)) -> 11304.476 | E63: Birr
A64: Water Tank & stand | B64: = | C64: ='Fence and Compund'!G145 -> 0 | E64: Birr
A65: External Electric and sanitary work | B65: = | C65: =C64+C63+D56 -> 130801.3 | E65: Birr
A66: Consultancy fee | B66: Project Cost | C66: =D75+D76+D77+D78 -> 1983994.1
A67: Including Design & Supervision
A68: Architectural | B68: =IF(A68="Architectural",(IF(C66<=500000,45%*4.25%*C66*(C68/100),IF(C66<=1000000,45%*3.75%*C66*(C68/100),IF(C66<=2500000,45%*3.25%*C66*(C68/100),IF(C66<=5000000,45%*2.75%*C66*(C68/100),IF(C66<=10000000,45%*2.25%*C66*(C68/100),IF(C66>10000000,45%*1.75%*C66*(C68/100)))))))),0) -> 29015.914 | C68: 100 | K68: 200 | L68: 4818 | M68: =L68*2 -> 9636 | N68: =K68*M68 -> 1927200
A69: Structural | B69: =IF(A69="Structural",(IF(C66<=500000,30%*4.25%*C66*(C69/100),IF(C66<=1000000,30%*3.75%*C66*(C69/100),IF(C66<=2500000,30%*3.25%*C66*(C69/100),IF(C66<=5000000,30%*2.75%*C66*(C69/100),IF(C66<=10000000,30%*2.25%*C66*(C69/100),IF(C66>10000000,30%*1.75%*C66*(C69/100)))))))),0) -> 0 | C69: 0 | K69: 200 | L69: 3818 | M69: =L69*2 -> 7636 | N69: =K69*M69 -> 1527200
A70: Electrical | B70: =IF(A70="Electrical",(IF(C66<=500000,10%*4.25%*C66*(C70/100),IF(C66<=1000000,10%*3.75%*C66*(C70/100),IF(C66<=2500000,10%*3.25%*C66*(C70/100),IF(C66<=5000000,10%*2.75%*C66*(C70/100),IF(C66<=10000000,10%*2.25%*C66*(C70/100),IF(C66>10000000,10%*1.75%*C66*(C70/100)))))))),0) -> 0 | K70: 200 | L70: 2818 | M70: =L70*2 -> 5636 | N70: =K70*M70 -> 1127200
A71: Sanitary | B71: =IF(A71="Sanitary",(IF(C66<=500000,2.75%*4.25%*C66*(C71/100),IF(C66<=1000000,2.75%*3.75%*C66*(C71/100),IF(C66<=2500000,2.75%*3.25%*C66*(C71/100),IF(C66<=5000000,2.75%*2.75%*C66*(C71/100),IF(C66<=10000000,2.75%*2.25%*C66*(C71/100),IF(C66>10000000,2.75%*1.75%*C66*(C71/100)))))))),0) -> 0 | K71: 500 | L71: 2418 | M71: =L71*2 -> 4836 | N71: =K71*M71 -> 2418000
A72: Specification and Bill of quantity | B72: =IF(A72="Specification and bill of quantity",(IF(C66<=500000,2.25%*4.25%*C66*(C72/100),IF(C66<=1000000,2.25%*3.75%*C66*(C72/100),IF(C66<=2500000,2.25%*3.25%*C66*(C72/100),IF(C66<=5000000,2.25%*2.75%*C66*(C72/100),IF(C66<=10000000,2.25%*2.25%*C66*(C72/100),IF(C66>10000000,2.25%*1.75%*C66*(C72/100)))))))),0) -> 0 | K72: 500 | L72: 2218 | M72: =L72*2 -> 4436 | N72: =K72*M72 -> 2218000
A73: Total Consultancy Fee | B73: =SUM(B68:B72) -> 29015.914 | H73: =D75+D78 -> 1853192.8 | K73: 1000 | L73: 1718 | M73: =L73*2 -> 3436 | N73: =K73*M73 -> 3436000
K74: 2000 | L74: 1218 | M74: =L74*2 -> 2436 | N74: =K74*M74 -> 4872000
B75: Building Cost | D75: =F51 -> 1853192.8 | K75: 6.4 | L75: 718 | M75: =L75*2 -> 1436 | N75: =K75*M75 -> 9190.4
B76: Internal Structure | D76: =B49 -> 0 | K76: =K66+K67+K68+K69+K70+K71+K72+K73+K74 -> 4600 | N76: =N66+N67+N68+N69+N70+N71+N72+N73+N74+N75 -> 17534790
B77: External Elecrical & Sanitary Works | D77: =C65 -> 130801.3 | H77: =D75+D77+D78 -> 1983994.1
B78: Fence & compound = | D78: ='Fence and Compund'!G78 -> 0 | H78: =H77*3 -> 5951982.3 | I78: =1789.2*60 -> 107352
B79: Consultancy Service | D79: =B73 -> 29015.914 | H79: =D80*3 -> 2438004
B80: Location Value | D80: =B19 -> 812668 | H80: =B13/B11 -> 26151.673
B81: Total Estimate = | D81: =SUM(D75:D80) -> 2825678
H88: =11.5+12.5 -> 24 | I88: =H88/2 -> 12
I89: =I88*20 -> 240

Sheet Fence and Compund
B2: Fence Work
A3: Item | B3: Description | C3: Unit | D3: Quantity | E3: new | F3: New Rate | G3: Amount | I3: =IF(SUM(G4:G55)=0,"-",1) -> -
A4: 1 | B4: Stone masonry fence, semi-dressed | I4: =IF(SUM(G5:G12)=0,"-",1) -> -
A5: 1.1 | B5: Left for finishing | C5: m3 | E5: =2.75*F5 -> 4414.7675 | F5: 1605.37 | G5: =D5*E5 -> 0 | I5: =IF(G5=0,"-",1) -> -
A6: 1.2 | B6: One side pointed | C6: m3 | E6: =2.75*F6 -> 4616.865 | F6: 1678.86 | G6: =D6*E6 -> 0 | I6: =IF(G6=0,"-",1) -> -
A7: 1.3 | B7: Two sides pointed | C7: m3 | E7: =2.75*F7 -> 4819.0175 | F7: 1752.37 | G7: =D7*E7 -> 0 | I7: =IF(G7=0,"-",1) -> -
A8: 1.4 | B8: One sides plastered | C8: m3 | E8: =2.75*F8 -> 4984.0725 | F8: 1812.39 | G8: =D8*E8 -> 0 | I8: =IF(G8=0,"-",1) -> -
A9: 1.5 | B9: Two side plastered | C9: m3 | E9: =2.75*F9 -> 4829.0275 | F9: 1756.01 | G9: =D9*E9 -> 0 | I9: =IF(G9=0,"-",1) -> -
A10: 1.6 | B10: One side rendered | C10: m3 | E10: =2.75*F10 -> 4333.9725 | F10: 1575.99 | G10: =D10*E10 -> 0 | I10: =IF(G10=0,"-",1) -> -
A11: 1.7 | B11: Two sides rendered | C11: m3 | E11: =2.75*F11 -> 4829.0275 | F11: 1756.01 | G11: =D11*E11 -> 0 | I11: =IF(G11=0,"-",1) -> -
A12: 1.8 | B12: Painting (add to the above fence work if there is any) | C12: m2 | E12: =2.75*F12 -> 172.81 | F12: 62.84 | G12: =D12*E12 -> 0 | I12: =IF(G12=0,"-",1) -> -
A13: 2 | B13: Stone masonry fence well dressed | E13: =2.75*F13 -> 0 | F13: 0 | G13: =D13*E13 -> 0 | I13: =IF(SUM(G14:G17)=0,"-",1) -> -
A14: 2.1 | B14: Left for finishing | C14: m3 | E14: =2.75*F14 -> 4619.4775 | F14: 1679.81 | G14: =D14*E14 -> 0 | I14: =IF(G14=0,"-",1) -> -
A15: 2.2 | B15: One side pointed | C15: m3 | E15: =2.75*F15 -> 4795.23 | F15: 1743.72 | G15: =D15*E15 -> 0 | I15: =IF(G15=0,"-",1) -> -
A16: 2.4 | B16: Two sides pointed | C16: m3 | E16: =2.75*F16 -> 4971.01 | F16: 1807.64 | G16: =D16*E16 -> 0 | I16: =IF(G16=0,"-",1) -> -
A17: 2.5 | B17: Foundation (Add on the above fence work) | C17: ml | E17: =2.75*F17 -> 2722.3625 | F17: 989.95 | G17: =D17*E17 -> 0 | I17: =IF(G17=0,"-",1) -> -
A18: 3 | B18: HCB fence | E18: =2.75*F18 -> 0 | G18: =D18*E18 -> 0 | I18: =IF(SUM(G19:G26)=0,"-",1) -> -
A19: 3.1 | B19: Left for finishing | C19: m2 | E19: =2.75*F19 -> 1221.5775 | F19: 444.21 | G19: =D19*E19 -> 0 | I19: =IF(G19=0,"-",1) -> -
A20: 3.2 | B20: One side pointed | C20: m2 | E20: =2.75*F20 -> 1464.1 | F20: 532.4 | G20: =D20*E20 -> 0 | I20: =IF(G20=0,"-",1) -> -
A21: 3.3 | B21: Two sides pointed | C21: m2 | E21: =2.75*F21 -> 1706.6775 | F21: 620.61 | G21: =D21*E21 -> 0 | I21: =IF(G21=0,"-",1) -> -
A22: 3.4 | B22: One side plastered | C22: m2 | E22: =2.75*F22 -> 1904.7325 | F22: 692.63 | G22: =D22*E22 -> 0 | I22: =IF(G22=0,"-",1) -> -
A23: 3.5 | B23: Two side plastered | C23: m2 | D23: =area!C21 -> 0 | E23: =2.75*F23 -> 2062.83 | F23: 750.12 | G23: =D23*E23 -> 0 | I23: =IF(G23=0,"-",1) -> -
A24: 3.6 | B24: One side rendered | C24: m2 | E24: =2.75*F24 -> 1904.7325 | F24: 692.63 | G24: =D24*E24 -> 0 | I24: =IF(G24=0,"-",1) -> -
A25: 3.7 | B25: Two sides rendered | C25: m2 | E25: =2.75*F25 -> 2062.83 | F25: 750.12 | G25: =D25*E25 -> 0 | I25: =IF(G25=0,"-",1) -> -
A26: 3.8 | B26: Painting (Add the unit price on the above finishing if there are any) | C26: m2 | D26: =D23*2 -> 0 | E26: =2.75*F26 -> 172.81 | F26: 62.84 | G26: =D26*E26 -> 0 | I26: =IF(G26=0,"-",1) -> -
A27: 4 | B27: Brick fence (25cm thick) | E27: =2.75*F27 -> 0 | G27: =D27*E27 -> 0 | I27: =IF(SUM(G28:G35)=0,"-",1) -> -
A28: 4.1 | B28: Left for finishing | C28: m2 | E28: =2.75*F28 -> 4563.295 | F28: 1659.38 | G28: =D28*E28 -> 0 | I28: =IF(G28=0,"-",1) -> -
A29: 4.2 | B29: One side pointed | C29: m2 | E29: =2.75*F29 -> 4703.9025 | F29: 1710.51 | G29: =D29*E29 -> 0 | I29: =IF(G29=0,"-",1) -> -
A30: 4.3 | B30: Two sides pointed | C30: m2 | E30: =2.75*F30 -> 4844.5375 | F30: 1761.65 | G30: =D30*E30 -> 0 | I30: =IF(G30=0,"-",1) -> -
A31: 4.4 | B31: One side plastered | C31: m2 | E31: =2.75*F31 -> 4959.35 | F31: 1803.4 | G31: =D31*E31 -> 0 | I31: =IF(G31=0,"-",1) -> -
A32: 4.5 | B32: Two sides plastered | C32: m2 | E32: =2.75*F32 -> 5355.405 | F32: 1947.42 | G32: =D32*E32 -> 0 | I32: =IF(G32=0,"-",1) -> -
A33: 4.6 | B33: One side rendered | C33: m2 | E33: =2.75*F33 -> 4563.295 | F33: 1659.38 | G33: =D33*E33 -> 0 | I33: =IF(G33=0,"-",1) -> -
A34: 4.7 | B34: Two sides rendered | C34: m2 | E34: =2.75*F34 -> 4959.35 | F34: 1803.4 | G34: =D34*E34 -> 0 | I34: =IF(G34=0,"-",1) -> -
A35: 4.8 | B35: Painting (Add the unit price on the above finishing if there are any) | C35: m2 | E35: =2.75*F35 -> 172.81 | F35: 62.84 | G35: =D35*E35 -> 0 | I35: =IF(G35=0,"-",1) -> -
A36: 5 | B36: Brick fence (12cm) | E36: =2.75*F36 -> 0 | G36: =D36*E36 -> 0 | I36: =IF(SUM(G37:G44)=0,"-",1) -> -
A37: 5.1 | B37: Left for finishing | C37: m2 | E37: =2.75*F37 -> 2792.46 | F37: 1015.44 | G37: =D37*E37 -> 0 | I37: =IF(G37=0,"-",1) -> -
A38: 5.2 | B38: One side pointed | C38: m2 | E38: =2.75*F38 -> 3146.1925 | F38: 1144.07 | G38: =D38*E38 -> 0 | I38: =IF(G38=0,"-",1) -> -
A39: 5.3 | B39: Two sides pointed | C39: m2 | E39: =2.75*F39 -> 3499.925 | F39: 1272.7 | G39: =D39*E39 -> 0 | I39: =IF(G39=0,"-",1) -> -
A40: 5.4 | B40: One side plastered | C40: m2 | E40: =2.75*F40 -> 3287.515 | F40: 1195.46 | G40: =D40*E40 -> 0 | I40: =IF(G40=0,"-",1) -> -
A41: 5.5 | B41: Two sides plastered | C41: m2 | E41: =2.75*F41 -> 3782.57 | F41: 1375.48 | G41: =D41*E41 -> 0 | I41: =IF(G41=0,"-",1) -> -
A42: 5.6 | B42: One side rendered | C42: m2 | E42: =2.75*F42 -> 3287.515 | F42: 1195.46 | G42: =D42*E42 -> 0 | I42: =IF(G42=0,"-",1) -> -
A43: 5.7 | B43: Two sides rendered | C43: m2 | E43: =2.75*F43 -> 3782.57 | F43: 1375.48 | G43: =D43*E43 -> 0 | I43: =IF(G43=0,"-",1) -> -
A44: 5.8 | B44: Painting (add to the above fence work) | C44: m2 | E44: =2.75*F44 -> 172.81 | F44: 62.84 | G44: =D44*E44 -> 0 | I44: =IF(G44=0,"-",1) -> -
A45: 6 | B45: Hydra foam Fence (12cm) | E45: =2.75*F45 -> 0 | G45: =D45*E45 -> 0 | I45: =IF(SUM(G46:G53)=0,"-",1) -> -
A46: 6.1 | B46: Left for finishing | C46: m2 | E46: =2.75*F46 -> 887.8375 | F46: 322.85 | G46: =D46*E46 -> 0 | I46: =IF(G46=0,"-",1) -> -
A47: 7 | B47: Hydra foam Fence (14cm) | E47: =2.75*F47 -> 0 | G47: =D47*E47 -> 0 | I47: =IF(SUM(G48:G55)=0,"-",1) -> -
A48: 7.1 | B48: Left for finishing | C48: m2 | E48: =2.75*F48 -> 1203.895 | F48: 437.78 | G48: =D48*E48 -> 0 | I48: =IF(G48=0,"-",1) -> -
A49: 8 | B49: Metal grill | C49: m2 | E49: =2.75*F49 -> 5830 | F49: 2120 | G49: =D49*E49 -> 0 | I49: =IF(G49=0,"-",1) -> -
A50: 9 | B50: RHS metal grill fence | C50: ml | E50: =2.75*F50 -> 2333.1 | F50: 848.4 | G50: =D50*E50 -> 0 | I50: =IF(G50=0,"-",1) -> -
A51: 10 | B51: Main gate with metal sheet | C51: m2 | E51: =2.75*F51 -> 5362.5 | F51: 1950 | G51: =D51*E51 -> 0 | I51: =IF(G51=0,"-",1) -> -
A52: 11 | B52: Main gate with RHS grill structure | C52: m2 | E52: =2.75*F52 -> 7700 | F52: 2800 | G52: =D52*E52 -> 0 | I52: =IF(G52=0,"-",1) -> -
A53: 12 | B53: Decorated gates with RHS grill structure and metal sheet | C53: m2 | E53: =2.75*F53 -> 12512.5 | F53: 4550 | G53: =D53*E53 -> 0 | I53: =IF(G53=0,"-",1) -> -
A54: 13 | B54: Securty Wire | C54: ml | E54: =2.75*F54 -> 1213.3 | F54: 441.2 | G54: =D54*E54 -> 0 | I54: =IF(G54=0,"-",1) -> -
B55: Total Fence Work | F55: 0 | G55: =SUM(G6:G54) -> 0 | I55: =IF(G55=0,"-",1) -> -
F56: 0 | I56: =IF(D56=0,"-",1) -> -
B57: Compound Work | F57: 0 | I57: =IF(SUM(G58:G65)=0,"-",1) -> -
A58: Item | B58: Description | C58: Unit | D58: Quantity | E58: new | F58: Rate | G58: Amount | I58: =IF(SUM(G59:G66)=0,"-",1) -> -
A59: 1 | B59: 7cm-thick red ash pavement | C59: m2 | E59: =2.75*F59 -> 250.8825 | F59: 91.23 | G59: =D59*E59 -> 0 | I59: =IF(G59=0,"-",1) -> -
A60: 2 | B60: 5cm-thick gravel pavement | C60: m2 | E60: =2.75*F60 -> 453.75 | F60: 165 | G60: =D60*E60 -> 0 | I60: =IF(G60=0,"-",1) -> -
A61: 3 | B61: Roughly dressed stone pavement | C61: m2 | E61: =2.75*F61 -> 1366.6125 | F61: 496.95 | G61: =D61*E61 -> 0 | I61: =IF(G61=0,"-",1) -> -
A62: 4 | B62: Asphalt | C62: m2 | E62: =2.75*F62 -> 3142.865 | F62: 1142.86 | G62: =D62*E62 -> 0 | I62: =IF(G62=0,"-",1) -> -
A63: 5 | B63: 10cm thick C-15 concrete pavement | C63: m2 | D63: =area!A23 -> 0 | E63: =2.75*F63 -> 1922.8825 | F63: 699.23 | G63: =D63*E63 -> 0 | I63: =IF(G63=0,"-",1) -> - | K63: =400*2.75 -> 1100
A64: 6 | B64: Ditto but RC pavement | C64: m2 | E64: =2.75*F64 -> 2470.16 | F64: 898.24 | G64: =D64*E64 -> 0 | I64: =IF(G64=0,"-",1) -> -
A65: 7 | B65: Checkered tile with 15cm thick RC slab | C65: m2 | E65: =2.75*F65 -> 3374.36 | F65: 1227.04 | G65: =D65*E65 -> 0 | I65: =IF(G65=0,"-",1) -> -
A66: 8 | B66: Checkered tile with mass concrete | C66: m2 | E66: =2.75*F66 -> 2337.005 | F66: 849.82 | G66: =D66*E66 -> 0 | I66: =IF(G66=0,"-",1) -> -
A67: 9 | B67: Best Quality marble chips with RC concrete | C67: m2 | E67: =2.75*F67 -> 3103.375 | F67: 1128.5 | G67: =D67*E67 -> 0 | I67: =IF(G67=0,"-",1) -> -
A68: 10 | B68: Harar marble chips with RC concrete | C68: m2 | E68: =2.75*F68 -> 4158.77 | F68: 1512.28 | G68: =D68*E68 -> 0 | I68: =IF(G68=0,"-",1) -> -
A69: 11 | B69: Terrazzo tile with RC concrete | C69: m2 | E69: =2.75*F69 -> 3757.71 | F69: 1366.44 | G69: =D69*E69 -> 0 | I69: =IF(G69=0,"-",1) -> -
A70: 12 | B70: Ditto but with mass concrete | C70: m2 | E70: =2.75*F70 -> 2720.355 | F70: 989.22 | G70: =D70*E70 -> 0 | I70: =IF(G70=0,"-",1) -> -
A71: 13 | B71: Ceramic tile with RC concrete | C71: m2 | E71: =2.75*F71 -> 5184.1625 | F71: 1885.15 | G71: =D71*E71 -> 0 | I71: =IF(G71=0,"-",1) -> -
A72: 14 | B72: Ditto but with mass concrete. | C72: m2 | E72: =2.75*F72 -> 4146.835 | F72: 1507.94 | G72: =D72*E72 -> 0 | I72: =IF(G72=0,"-",1) -> -
A73: 15 | B73: Cement tile with RC concrete | C73: m2 | E73: =2.75*F73 -> 3374.36 | F73: 1227.04 | G73: =D73*E73 -> 0 | I73: =IF(G73=0,"-",1) -> -
A74: 16 | B74: Ditto but with mass concrete. | C74: m2 | E74: =2.75*F74 -> 2312.0075 | F74: 840.73 | G74: =D74*E74 -> 0 | I74: =IF(G74=0,"-",1) -> -
A75: 17 | B75: Concrete Curb Stone | C75: ml | E75: =2.75*F75 -> 1100.605 | F75: 400.22 | G75: =D75*E75 -> 0 | I75: =IF(G75=0,"-",1) -> -
B76: Total Compound Work | G76: =SUM(G59:G75) -> 0 | I76: =IF(G76=0,"-",1) -> -
I77: =IF(G77=0,"-",1) -> -
B78: Total Fence & Compound Work | G78: =G76+G55 -> 0 | I78: =IF(G78=0,"-",1) -> -
A79: WATER TANKS AND SUPPORTS | I79: =IF(SUM(G80:G87)=0,"-",1) -> -
A80: 1.0 Water tanks | I80: =IF(SUM(G81:G88)=0,"-",1) -> -
A81: 1.1 Plastic Water Tanks | F81: 0 | I81: =IF(SUM(G82:G89)=0,"-",1) -> -
A82: Item No. | B82: Capacity ( litters) | C82: unit | D82: Quantity | E82: new | F82: Rate | G82: Amount | I82: =IF(SUM(G83:G90)=0,"-",1) -> -
A83: 1 | B83: 250 | C83: pcs | E83: =2.75*F83 -> 4455 | F83: 1620 | G83: =D83*E83 -> 0 | I83: =IF(G83=0,"-",1) -> -
A84: 2 | B84: 500 | C84: pcs | E84: =2.75*F84 -> 7631.25 | F84: 2775 | G84: =D84*E84 -> 0 | I84: =IF(G84=0,"-",1) -> -
A85: 3 | B85: 1000 | C85: pcs | E85: =2.75*F85 -> 13818.75 | F85: 5025 | G85: =D85*E85 -> 0 | I85: =IF(G85=0,"-",1) -> -
A86: 4 | B86: 1500 | C86: pcs | E86: =2.75*F86 -> 15675 | F86: 5700 | G86: =D86*E86 -> 0 | I86: =IF(G86=0,"-",1) -> -
A87: 5 | B87: 2000 | C87: pcs | E87: =2.75*F87 -> 21862.5 | F87: 7950 | G87: =D87*E87 -> 0 | I87: =IF(G87=0,"-",1) -> -
A88: 7 | B88: 3000 | C88: pcs | E88: =2.75*F88 -> 33825 | F88: 12300 | G88: =D88*E88 -> 0 | I88: =IF(G88=0,"-",1) -> -
A89: 8 | B89: 4000 | C89: pcs | E89: =2.75*F89 -> 46612.5 | F89: 16950 | G89: =D89*E89 -> 0 | I89: =IF(G89=0,"-",1) -> -
A90: 9 | B90: 5000 | C90: pcs | E90: =2.75*F90 -> 56925 | F90: 20700 | G90: =D90*E90 -> 0 | I90: =IF(G90=0,"-",1) -> -
A91: 10 | B91: 7500 | C91: pcs | E91: =2.75*F91 -> 73928.25 | F91: 26883 | G91: =D91*E91 -> 0 | I91: =IF(G91=0,"-",1) -> -
A92: 11 | B92: 10000 | C92: pcs | E92: =2.75*F92 -> 111003.75 | F92: 40365 | G92: =D92*E92 -> 0 | I92: =IF(G92=0,"-",1) -> -
A93: 1.2 Fiberglass Water Tanks | E93: =2.75*F93 -> 0 | F93: 0 | G93: =D93*E93 -> 0 | I93: =IF(SUM(G94:G101)=0,"-",1) -> -
A94: 1 | B94: 250 | C94: pcs | E94: =2.75*F94 -> 8376.5 | F94: 3046 | G94: =D94*E94 -> 0 | I94: =IF(G94=0,"-",1) -> -
A95: 2 | B95: 500 | C95: pcs | E95: =2.75*F95 -> 12611.5 | F95: 4586 | G95: =D95*E95 -> 0 | I95: =IF(G95=0,"-",1) -> -
A96: 3 | B96: 1000 | C96: pcs | E96: =2.75*F96 -> 14877.5 | F96: 5410 | G96: =D96*E96 -> 0 | I96: =IF(G96=0,"-",1) -> -
A97: 4 | B97: 1500 | C97: pcs | E97: =2.75*F97 -> 20608.5 | F97: 7494 | G97: =D97*E97 -> 0 | I97: =IF(G97=0,"-",1) -> -
A98: 5 | B98: 2000 | C98: pcs | E98: =2.75*F98 -> 25685 | F98: 9340 | G98: =D98*E98 -> 0 | I98: =IF(G98=0,"-",1) -> -
A99: 6 | B99: 3000 | C99: pcs | E99: =2.75*F99 -> 39864 | F99: 14496 | G99: =D99*E99 -> 0 | I99: =IF(G99=0,"-",1) -> -
A100: 7 | B100: 4000 | C100: pcs | E100: =2.75*F100 -> 45551 | F100: 16564 | G100: =D100*E100 -> 0 | I100: =IF(G100=0,"-",1) -> -
A101: 8 | B101: 5000 | C101: pcs | E101: =2.75*F101 -> 58487 | F101: 21268 | G101: =D101*E101 -> 0 | I101: =IF(G101=0,"-",1) -> -
...

Sheet Sheet2
A1: ዘምዘም ባንክ አ.ማ
A2: ZAMZAM BANK S.C
A3: PROPERTY ESTIMATIONFORM FOR GENERAL LOANS
I4: Branch
I5: Date | J5: 2/7/2026
A6: 1 | B6: Applicant's Name | F6: Fatuma Meketel
B7: Address: Town | E7: Answered | F7: _____________ | G7: Kebele | I7: House No. _____________
B8: P.O.Box ____________________ Tel. No. ___________________
A9: 2 | B9: Property of | D9: Kalsumo Mahamud | G9: Ownership C/No. | I9: 28926/18
B10: Location: Town | D10: Jijiga | E10: S/City | G10: Worda | J10: House No.
B11: Area of Compound | D11: 331.7 | F11: Sq. m. | G11: Paved in | H11: _____________ | K11: Asphalt
B12: Land Mark | K12: Gravel
B13: Distance from the main road______ | F13: Type of access road to site________ | K13: Cobble
A14: 3 | B14: Property owner address: Town ______________ Answered _________ Kebele _____________________
E15: House No. _______________ Tel. No. ___________________
A16: 4 | B16: ANALYSIS OF NEIGHBORHOOD
B17: a) General Use | F17: Industrial | I17: Residential | L17: Others
B18: b) Marketability | E18: Marketable
B19: c) Standard of Housing | G19: V.good
B20: d) Development State | G20: Developing
B21: e) Future Tendency | G21: Promising
B22: f) Transportation facilities | G22: Accessible
B23: g) Utilities | E23: Available
A24: 5 | B24: DESCRIPTION OF PROPERTY Construction permit No. | H24: Approved | J24: Date _______________
B25: Number of house on site (Servant's quarters and garage to be indicated separately)
A26: a) | B26: Main House | E26: Length | G26: Mts. X Breadth | J26: = | K26: =area!C2 -> 61.364
A27: b) | B27: Fence | E27: Length | G27: Mts. X Breadth | J27: = | K27: =area!C21 -> 0
A28: c) | B28: Compound | E28: Length | G28: Mts. X Breadth | J28: = | K28: =area!A23 -> 0
B29: WALLS | E29: HCB
B30: ROOF | E30: Metal Sheet
B31: FLOORS | E31: Tiles
B32: LIGHTING SYSTEM | E32: Electrical
B33: DOORS & WINDOWS | E33: Timber
B34: State of house (i.e. new, moderate, old etc.) | M34: =80.67*18928 -> 1526921.8
A35: 6 | B35: PRESENT USE OF BUILDING | G35: Villa MH residential
F36: Title deed no. | H36: =I9 -> 28926/18
A37: 7 | B37: PRESENT VALUE (Show separate value for each building)
A38: a) | B38: Total Bldg. Cost | I38: Birr | J38: =Location!F51 -> 1853192.8 | N38: =(410.69*18,928)
A39: b) | B39: ='[1]Location '!C125 -> Internal Structure | I39: Birr | J39: =Location!D76 -> 0
A40: c) | B40: ='[1]Location '!C126 -> External Elecrical & Sanitary Works | I40: Birr | J40: =Location!D77 -> 130801.3 | O40: =410.69*18928 -> 7773540.3
A41: d) | B41: ='[1]Location '!C127 -> Fence & compound = | I41: Birr | J41: =Location!D78 -> 0
A42: e) | B42: ='[1]Location '!C128 -> Consultancy Service | I42: Birr | J42: =Location!D79 -> 29015.914
A43: f) | B43: ='[1]Location '!C129 -> Location Value | I43: Birr | J43: =Location!D80 -> 812668 | M43: =J43/D11 -> 2450.009
H44: Total Birr | J44: =J38+J39+J40+J41+J42+J43 -> 2825678 | M44: =2739.2*394.5 -> 1080614.4
B45: Is there any thatched roof on site? | G45: NO | M45: =93.57*48900*1.2*0.9 -> 4941618.8
B46: is the property of the area as a whole reserved for any
B47: purpose or for the amelioration of the proposal new town plan project?
B48: Yes | E48: No | H48: No document
A51: 9 | B51: Remark | M51: =10.2-8.86 -> 1.34
B52: The service quarters has been excluded from the valuation as it does not meet the requirement.
A53: 10 | B53: ROUGH SKETCH LOCATION (N.B. Use prominent)
F54: coordinate- | G54: 9.342707,42.806341
B61: Enclosures
B62: Original | D62: Copy
B63: 26/6/2026 | E63: Elizabeth Mohammed
B64: Date of Inspection | E64: Appraiser's Name | G64: Appraiser's Signature | J64: Approved By

Sheet area
A1: MH
A2: =0.2+5.4+0.2 -> 5.8 | B2: =0.2+4.7+0.2+5.28+0.2 -> 10.58 | C2: =A2*B2 -> 61.364 | D2: 30200 | E2: =C2*D2 -> 1853192.8
A16: Fence
B17: 2.5 | C17: =A17*B17 -> 0
B18: 2.5 | C18: =A18*B18 -> 0
B19: 2.5 | C19: =A19*B19 -> 0
B20: 2.5 | C20: =A20*B20 -> 0
C21: =SUM(C17:C20) -> 0
A22: Compound

Sheet Sheet3
A1: WALLS | B1: ROOF | C1: FLOORS | D1: LIGHTING SYSTEM | E1: DOORS & WINDOWS
A2: Bricks | B2: Metal Sheet | C2: Tiles | D2: Electrical | E2: Timber
A3: Masonry | B3: R.C | C3: Timber | D3: Petrol | E3: Metal
A4: Metal Sheet | B4: Timber | C4: Cement | D4: Oil | E4: Aluminum
A5: HCB | B5: Thatch | C5: R.C
A6: Chika | B6: Tiles | C6: Uncovered

Sheet BOQ
A1: Zamzam Bank for under construction | E1: Date 4/06/2026
A2: Subject: Construction progress estimation
A3: Applicant name | C3: Anwar Umer
A4: Owner name | C4: Anwar Umer
A5: City | C5: Desse
A6: Woreda | C6: Furi
A7: Title deed no | C7: AM003031402024
A8: Coordinate | C8: 11.138768,39.644018
A9: Plot | C9: 252.04
A10: Project :G+3 Residential
G11: =F14*0.29 -> 575358.29 | O11: 1
A12: Summary | J12: 1 | K12: G | L12: 1 | M12: 1 | O12: 1
A13: Item no | B13: WORK DESCRIPTION | C13: PROJECT COST | D13: WORK EXCUTED | E13: WORK REMAINING | F13: =3146484.72/F14 -> 1.5859345 | J13: 1 | K13: FF | L13: 1 | M13: 1 | O13: 1
A14: 1 | B14: Sub Structure | C14: =$F$14*G14 -> 376958.88 | D14: =C14*1 -> 376958.88 | E14: =IF(C14=0,"-",C14-D14) -> 0 | F14: =Location!D75+Location!D77+Location!D78 -> 1983994.1 | G14: 0.19 | H14: Sub Structure | I14: 1 | J14: F | K14: 1
A15: 2 | B15: Super Structure | C15: =$F$14*G15 -> 575358.29 | D15: =C15*1 -> 575358.29 | E15: =IF(C15=0,"-",C15-D15) -> 0 | G15: 0.29 | H15: Super Structure | I15: 1 | J15: S | K15: 0
A16: 3 | B16: Block work- Internal | C16: =$F$14*G16 -> 39679.882 | D16: =C16*1 -> 39679.882 | E16: =IF(C16=0,"-",C16-D16) -> 0 | G16: 0.02 | H16: Block work- Internal | I16: 3 | K16: =#REF!+K14+K15 -> #REF!
A17: 4 | B17: Block work- External | C17: =$F$14*G17 -> 99199.705 | D17: =C17*1 -> 99199.705 | E17: =IF(C17=0,"-",C17-D17) -> 0 | G17: 0.05 | H17: Block work- External | J17: =K16/I16 -> #REF! | L17: =SUM(L10:L16) -> 2 | M17: =SUM(M10:M16) -> 2 | O17: =SUM(O10:O16) -> 3
A18: 5 | B18: Roofing | C18: =$F$14*G18 -> 59519.823 | D18: =C18*1 -> 59519.823 | E18: =IF(C18=0,"-",C18-D18) -> 0 | G18: 0.03 | H18: Roofing | M18: =M17/L17 -> 1 | O18: =O17/L17 -> 1.5
A19: 6 | B19: Joinery | C19: =$F$14*G19 -> 39679.882 | D19: =C19*0 -> 0 | E19: =IF(C19=0,"-",C19-D19) -> 39679.882 | G19: 0.02 | H19: Joinery
A20: 7 | B20: Metal Work | C20: =$F$14*G20 -> 138879.59 | D20: =C20*0 -> 0 | E20: =IF(C20=0,"-",C20-D20) -> 138879.59 | G20: 0.07 | H20: Metal Work
A21: 8 | B21: Floor finish | C21: =$F$14*G21 -> 138879.59 | D21: =C21*0 -> 0 | E21: =IF(C21=0,"-",C21-D21) -> 138879.59 | G21: 0.07 | H21: Floor finish
A22: 9 | B22: Wall finish- Internal | C22: =$F$14*G22 -> 198399.41 | D22: =C22*0.2 -> 39679.882 | E22: =IF(C22=0,"-",C22-D22) -> 158719.53 | G22: 0.1 | H22: Wall finish- Internal
A23: 10 | B23: Wall finish- External | C23: =$F$14*G23 -> 79359.764 | D23: =C23*0.2 -> 15871.953 | E23: =IF(C23=0,"-",C23-D23) -> 63487.811 | G23: 0.04 | H23: Wall finish- External
A24: 11 | B24: Ceiling works | C24: =$F$14*G24 -> 79359.764 | D24: =C24*0 -> 0 | E24: =IF(C24=0,"-",C24-D24) -> 79359.764 | G24: 0.04 | H24: Ceiling works
A25: 12 | B25: Hand rail and Balustrade | C25: =$F$14*G25 -> 19839.941 | D25: =C25*0 -> 0 | E25: =IF(C25=0,"-",C25-D25) -> 19839.941 | G25: 0.01 | H25: Hand rail and Balustrade
A26: 13 | B26: Sanitary Work | C26: =$F$14*G26 -> 59519.823 | D26: =C26*0.3 -> 17855.947 | E26: =IF(C26=0,"-",C26-D26) -> 41663.876 | G26: 0.03 | H26: Sanitary Work
A27: 14 | B27: Electrical Work | C27: =$F$14*G27 -> 79359.764 | D27: =C27*0.3 -> 23807.929 | E27: =IF(C27=0,"-",C27-D27) -> 55551.835 | G27: 0.04 | H27: Electrical Work
C28: =SUM(C14:C27) -> 1983994.1 | D28: =SUM(D14:D27) -> 1247932.3 | E28: =SUM(E14:E27) -> 736061.81 | G28: =SUM(G14:G27) -> 1
A29: 15 | B29: Electro Mechanical Works (Generator,lift, utillilty connection)
A30: 16 | B30: Mechanical Installation (extracting fans,ventilation ducts)
B31: Grand Total | C31: =C28 -> 1983994.1 | D31: =D28 -> 1247932.3 | E31: =E28 -> 736061.81 | G31: =SUM(G14:G27) -> 1 | I31: =C27/#REF! -> #REF!
B32: % of executed and remaining | C32: =C31/C31 -> 1 | D32: =D31/C31 -> 0.629 | E32: =IF(C31=0,"-",E31/C31) -> 0.371 | G32: =G31/#REF! -> #REF!
G33: =G32-0.05 -> #REF!
B34: Use of building | C34: G+3 residential | D34: Second and Third floor | E34: =area!#REF! -> #REF!
B35: Ground floor | C35: =area!C2 -> 61.364 | D35: Total Area | E35: =SUM(C35+C36+E34) -> #REF!
B36: First floor | C36: =area!C5 -> 0
B38: Remark
B39: BOQ has not been submitted therefore it should be submitted and checked by the engineer.
B41: Location Value | D41: =Location!B19 -> 812668 | F41: 0.10248352
B42: Consultancy service | D42: =Location!B73 -> 29015.914
B43: Total Executed+Location value+Consultancy service | D43: =D42+D41+D31 -> 2089616.2
A45: Prepared By: Elizabeth Mohammed | E45: Approved By : Sultan Jemal | F45: =5955013.68+5478204+52297.36+220292.1 -> 11705807
A46: Date of Inspection :25/05/2026
A47: Semi B+G+7
A48: Item no | B48: WORK DESCRIPTION | C48: PROJECT COST | D48: WORK EXCUTED | E48: WORK REMAINING
B49: A. SUB STRUCTURE | F49: 76897376
A50: 1 | B50: Excavation & Earth Work | C50: =G50*0.3*F49 -> 3691074 | D50: =C50*1 -> 3691074 | E50: =IF(C50=0,"-",C50-D50) -> 0 | F50: Sub Structure | G50: 0.16
A51: 2 | B51: Sundry | C51: =F49*0.1*G50 -> 1230358 | D51: =C51*1 -> 1230358 | E51: =IF(C51=0,"-",C51-D51) -> 0
A52: 3 | B52: Concrete work | C52: =F49*0.6*G50 -> 7382148.1 | D52: =C52*1 -> 7382148.1 | E52: =IF(C52=0,"-",C52-D52) -> 0
B53: Total A | C53: =SUM(C50:C52) -> 12303580 | D53: =SUM(D50:D52) -> 12303580 | E53: =SUM(E50:E52) -> 0
B54: B.SUPER STRUCTURE
A55: 4 | B55: Super Structure | C55: =$F$49*G55 -> 25376134 | D55: =C55*1 -> 25376134 | E55: =IF(C55=0,"-",C55-D55) -> 0 | F55: Super Structure | G55: 0.33
A56: 5 | B56: Block work- Internal | C56: =$F$49*G56 -> 1537947.5 | D56: =C56*1 -> 1537947.5 | E56: =IF(C56=0,"-",C56-D56) -> 0 | F56: Block work- Internal | G56: 0.02
A57: 6 | B57: Block work- External | C57: =$F$49*G57 -> 1537947.5 | D57: =C57*1 -> 1537947.5 | E57: =IF(C57=0,"-",C57-D57) -> 0 | F57: Block work- External | G57: 0.02
A58: 7 | B58: Roofing | C58: =$F$49*G58 -> 768973.76 | D58: =C58*1 -> 768973.76 | E58: =IF(C58=0,"-",C58-D58) -> 0 | F58: Roofing | G58: 0.01
A59: 8 | B59: Joinery | C59: =$F$49*G59 -> 2306921.3 | D59: =C59*0 -> 0 | E59: =IF(C59=0,"-",C59-D59) -> 2306921.3 | F59: Joinery | G59: 0.03
A60: 9 | B60: Metal Work | C60: =$F$49*G60 -> 5382816.3 | D60: =C60*1 -> 5382816.3 | E60: =IF(C60=0,"-",C60-D60) -> 0 | F60: Metal Work | G60: 0.07
A61: 10 | B61: Floor finish | C61: =$F$49*G61 -> 6151790.1 | D61: =C61*0 -> 0 | E61: =IF(C61=0,"-",C61-D61) -> 6151790.1 | F61: Floor finish | G61: 0.08
A62: 11 | B62: Wall finish- Internal | C62: =$F$49*G62 -> 8458711.3 | D62: =C62*0.7 -> 5921097.9 | E62: =IF(C62=0,"-",C62-D62) -> 2537613.4 | F62: Wall finish- Internal | G62: 0.11
A63: 12 | B63: Wall finish- External | C63: =$F$49*G63 -> 2306921.3 | D63: =C63*1 -> 2306921.3 | E63: =IF(C63=0,"-",C63-D63) -> 0 | F63: Wall finish- External | G63: 0.03
A64: 13 | B64: Ceiling works | C64: =$F$49*G64 -> 4613842.6 | D64: =C64*1 -> 4613842.6 | E64: =IF(C64=0,"-",C64-D64) -> 0 | F64: Ceiling works | G64: 0.06
A65: 14 | B65: Hand rail and Balustrade | C65: =$F$49*G65 -> 0 | D65: =C65*0 -> 0 | E65: =IF(C65=0,"-",C65-D65) -> - | F65: Hand rail and Balustrade | G65: 0
A66: 15 | B66: Sanitary Work | C66: =$F$49*G66 -> 1537947.5 | D66: =C66*0.6 -> 922768.51 | E66: =IF(C66=0,"-",C66-D66) -> 615179.01 | F66: Sanitary Work | G66: 0.02
A67: 16 | B67: Electrical Work | C67: =$F$49*G67 -> 4613842.6 | D67: =C67*0.6 -> 2768305.5 | E67: =IF(C67=0,"-",C67-D67) -> 1845537 | F67: Electrical Work | G67: 0.06
B68: Total B | C68: =SUM(C55:C67) -> 64593796 | D68: =SUM(D55:D67) -> 51136755 | E68: =SUM(E55:E67) -> 13457041
B69: Total ( A + B ) | C69: =C53+C68 -> 76897376 | D69: =D53+D68 -> 63440335 | E69: =IF(C69=0,"-",C69-D69) -> 13457041 | G69: =SUM(G50:G68) -> 1
B70: Consultancy Fee
B71: Total | C71: =C69 -> 76897376 | D71: =D69+D70 -> 63440335 | E71: =E69+E70 -> 13457041
B72: Percentage | C72: =C71/C71 -> 1 | D72: =D71/C71 -> 0.825 | E72: =IF(C71=0,"-",E71/C71) -> 0.175
A74: G+1 Service quarter
A75: Item no | B75: WORK DESCRIPTION | C75: PROJECT COST | D75: WORK EXCUTED | E75: WORK REMAINING
B76: A. SUB STRUCTURE | F76: 4447228.5
A77: 1 | B77: Excavation & Earth Work | C77: =F76*G77*0.3 -> 106733.48 | D77: =C77*1 -> 106733.48 | E77: =IF(C77=0,"-",C77-D77) -> 0 | F77: Sub Structure | G77: 0.08
A78: 2 | B78: Sundry | C78: =F76*0.1*G77 -> 35577.828 | D78: =C78*1 -> 35577.828 | E78: =IF(C78=0,"-",C78-D78) -> 0
A79: 3 | B79: Concrete work | C79: =F76*0.6*G77 -> 213466.97 | D79: =C79*1 -> 213466.97 | E79: =IF(C79=0,"-",C79-D79) -> 0
B80: Total A | C80: =SUM(C77:C79) -> 355778.28 | D80: =SUM(D77:D79) -> 355778.28 | E80: =SUM(E77:E79) -> 0
B81: B.SUPER STRUCTURE
A82: 4 | B82: Concrete Work | C82: =$F$76*G82 -> 400250.57 | D82: =C82*1 -> 400250.57 | E82: =IF(C82=0,"-",C82-D82) -> 0 | F82: Super Structure | G82: 0.09
A83: 5 | B83: Block work- Internal | C83: =$F$76*G83 -> 222361.43 | D83: =C83*1 -> 222361.43 | E83: =IF(C83=0,"-",C83-D83) -> 0 | F83: Block work- Internal | G83: 0.05
A84: 6 | B84: Block work- External | C84: =$F$76*G84 -> 578139.71 | D84: =C84*1 -> 578139.71 | E84: =IF(C84=0,"-",C84-D84) -> 0 | F84: Block work- External | G84: 0.13
A85: 7 | B85: Roofing | C85: =$F$76*G85 -> 355778.28 | D85: =C85*1 -> 355778.28 | E85: =IF(C85=0,"-",C85-D85) -> 0 | F85: Roofing | G85: 0.08
A86: 8 | B86: Joinery | C86: =$F$76*G86 -> 133416.86 | D86: =C86*1 -> 133416.86 | E86: =IF(C86=0,"-",C86-D86) -> 0 | F86: Joinery | G86: 0.03
A87: 9 | B87: Metal Work | C87: =$F$76*G87 -> 222361.43 | D87: =C87*1 -> 222361.43 | E87: =IF(C87=0,"-",C87-D87) -> 0 | F87: Metal Work | G87: 0.05
A88: 10 | B88: Floor finish | C88: =$F$76*G88 -> 266833.71 | D88: =C88*1 -> 266833.71 | E88: =IF(C88=0,"-",C88-D88) -> 0 | F88: Floor finish | G88: 0.06
A89: 11 | B89: Wall finish- Internal | C89: =$F$76*G89 -> 800501.14 | D89: =C89*1 -> 800501.14 | E89: =IF(C89=0,"-",C89-D89) -> 0 | F89: Wall finish- Internal | G89: 0.18
A90: 12 | B90: Wall finish- External | C90: =$F$76*G90 -> 444722.85 | D90: =C90*1 -> 444722.85 | E90: =IF(C90=0,"-",C90-D90) -> 0 | F90: Wall finish- External | G90: 0.1
A91: 13 | B91: Ceiling works | C91: =$F$76*G91 -> 355778.28 | D91: =C91*1 -> 355778.28 | E91: =IF(C91=0,"-",C91-D91) -> 0 | F91: Ceiling works | G91: 0.08
A92: 14 | B92: Hand rail and Balustrade | C92: =$F$76*G92 -> 133416.86 | D92: =C92*1 -> 133416.86 | E92: =IF(C92=0,"-",C92-D92) -> 0 | F92: Hand rail and Balustrade | G92: 0.03
A93: 15 | B93: Sanitary Work | C93: =$F$76*G93 -> 88944.571 | D93: =C93*1 -> 88944.571 | E93: =IF(C93=0,"-",C93-D93) -> 0 | F93: Sanitary Work | G93: 0.02
A94: 16 | B94: Electrical Work | C94: =$F$76*G94 -> 88944.571 | D94: =C94*1 -> 88944.571 | E94: =IF(C94=0,"-",C94-D94) -> 0 | F94: Electrical Work | G94: 0.02
B95: Total B | C95: =SUM(C82:C94) -> 4091450.3 | D95: =SUM(D82:D94) -> 4091450.3 | E95: =SUM(E82:E94) -> 0
B96: Total ( A + B ) | C96: =C80+C95 -> 4447228.5 | D96: =D80+D95 -> 4447228.5 | E96: =IF(C96=0,"-",C96-D96) -> 0
B97: Consultancy Fee
B98: Total | C98: =C96 -> 4447228.5 | D98: =D96+D97 -> 4447228.5 | E98: =E96+E97 -> 0
B99: Percentage | C99: =C98/C98 -> 1 | D99: =D98/C98 -> 1 | E99: =IF(C98=0,"-",E98/C98) -> 0

Sheet Building Component
E6: Building Components | F6: Single Storey | I6: G+1 & 2 | L6: G+3 & 4 | O6: G+5 & 6 | R6: >G+7 | U6: Multi Purpose Halls/Stores
F7: Poor | G7: Avg. | H7: Best | I7: Poor | J7: Avg. | K7: Best | L7: Poor | M7: Avg. | N7: Best | O7: Poor | P7: Avg. | Q7: Best | R7: Poor | S7: Avg. | T7: Best | U7: Poor | V7: Avg. | W7: Best
E8: Sub Structure | F8: 0.13 | G8: 0.12 | H8: 0.07 | I8: 0.29 | J8: 0.19 | K8: 0.08 | L8: 0.27 | M8: 0.19 | N8: 0.1 | O8: 0.34 | P8: 0.25 | Q8: 0.15 | R8: 0.23 | S8: 0.16 | T8: 0.1 | U8: 0.06 | V8: 0.25 | W8: 0.18 | Y8: =T8*1 -> 0.1 | Z8: =T8*1 -> 0.1
E9: Super Structure | F9: 0 | G9: 0.07 | H9: 0.07 | I9: 0.33 | J9: 0.22 | K9: 0.09 | L9: 0.41 | M9: 0.29 | N9: 0.16 | O9: 0.34 | P9: 0.26 | Q9: 0.16 | R9: 0.46 | S9: 0.33 | T9: 0.18 | U9: 0 | V9: 0.08 | W9: 0.09 | Y9: =T9*0.833 -> 0.14994 | Z9: =T9*1 -> 0.18
E10: Block work- Internal | F10: 0.04 | G10: 0.05 | H10: 0.04 | I10: 0.03 | J10: 0.03 | K10: 0.05 | L10: 0.03 | M10: 0.02 | N10: 0.03 | O10: 0.02 | P10: 0.02 | Q10: 0.01 | R10: 0.03 | S10: 0.02 | T10: 0.02 | U10: 0 | V10: 0 | W10: 0 | Y10: =T10*0.5 -> 0.01 | Z10: =T10*1 -> 0.02
E11: Block work- External | F11: 0.03 | G11: 0.05 | H11: 0.06 | I11: 0.07 | J11: 0.09 | K11: 0.13 | L11: 0.04 | M11: 0.05 | N11: 0.05 | O11: 0.02 | P11: 0.03 | Q11: 0.03 | R11: 0.03 | S11: 0.02 | T11: 0.02 | U11: 0.19 | V11: 0.13 | W11: 0.09 | Y11: =T11*0.5 -> 0.01 | Z11: =T11*1 -> 0.02
E12: Roofing | F12: 0.17 | G12: 0.1 | H12: 0.03 | I12: 0.04 | J12: 0.05 | K12: 0.08 | L12: 0.02 | M12: 0.03 | N12: 0.08 | O12: 0.01 | P12: 0.01 | Q12: 0.03 | R12: 0.01 | S12: 0.01 | T12: 0.02 | U12: 0.51 | V12: 0.22 | W12: 0.12 | Y12: =T12*0 -> 0 | Z12: =T12*1 -> 0.02
E13: Joinery | F13: 0.03 | G13: 0.06 | H13: 0.1 | I13: 0.01 | J13: 0.02 | K13: 0.03 | L13: 0.01 | M13: 0.02 | N13: 0.02 | O13: 0.02 | P13: 0.03 | Q13: 0.03 | R13: 0.02 | S13: 0.03 | T13: 0.03 | U13: 0.1 | V13: 0.02 | W13: 0 | Y13: =T13*0 -> 0 | Z13: =T13*1 -> 0.03
E14: Metal Work | F14: 0.2 | G14: 0.1 | H14: 0.08 | I14: 0.09 | J14: 0.07 | K14: 0.05 | L14: 0.09 | M14: 0.07 | N14: 0.06 | O14: 0.05 | P14: 0.04 | Q14: 0.04 | R14: 0.08 | S14: 0.07 | T14: 0.07 | U14: 0 | V14: 0.04 | W14: 0.08 | Y14: =T14*0 -> 0 | Z14: =T14*1 -> 0.07
E15: Floor finish | F15: 0.03 | G15: 0.1 | H15: 0.1 | I15: 0.02 | J15: 0.06 | K15: 0.06 | L15: 0.02 | M15: 0.07 | N15: 0.09 | O15: 0.02 | P15: 0.08 | Q15: 0.14 | R15: 0.02 | S15: 0.08 | T15: 0.13 | U15: 0 | V15: 0.1 | W15: 0.16 | Y15: =T15*0 -> 0 | Z15: =T15*1 -> 0.13
E16: Wall finish- Internal | F16: 0.14 | G16: 0.09 | H16: 0.1 | I16: 0.02 | J16: 0.1 | K16: 0.18 | L16: 0.02 | M16: 0.1 | N16: 0.21 | O16: 0.02 | P16: 0.09 | Q16: 0.16 | R16: 0.02 | S16: 0.11 | T16: 0.23 | U16: 0 | V16: 0.02 | W16: 0.06 | Y16: =T16*0 -> 0 | Z16: =T16*1 -> 0.23
E17: Wall finish- External | F17: 0.07 | G17: 0.08 | H17: 0.18 | I17: 0.01 | J17: 0.06 | K17: 0.1 | L17: 0 | M17: 0.04 | N17: 0.07 | O17: 0 | P17: 0.03 | Q17: 0.07 | R17: 0 | S17: 0.03 | T17: 0.06 | U17: 0 | V17: 0.02 | W17: 0.09 | Y17: =T17*0 -> 0 | Z17: =T17*1 -> 0.06
E18: Ceiling works | F18: 0.04 | G18: 0.06 | H18: 0.11 | I18: 0 | J18: 0.04 | K18: 0.08 | L18: 0 | M18: 0.04 | N18: 0.08 | O18: 0.02 | P18: 0.05 | Q18: 0.1 | R18: 0.02 | S18: 0.06 | T18: 0.08 | U18: 0 | V18: 0.05 | W18: 0.1 | Y18: =T18*0 -> 0 | Z18: =T18*1 -> 0.08
E19: Hand rail and Balustrade | F19: 0 | G19: 0 | H19: 0 | I19: 0.01 | J19: 0.01 | K19: 0.03 | L19: 0.01 | M19: 0.01 | N19: 0 | O19: 0.02 | P19: 0.01 | Q19: 0.01 | R19: 0 | S19: 0 | T19: 0 | U19: 0 | V19: 0 | W19: 0 | Y19: =T19*0 -> 0 | Z19: =T19*1 -> 0
E20: Sanitary Work | F20: 0.08 | G20: 0.06 | H20: 0.04 | I20: 0.04 | J20: 0.03 | K20: 0.02 | L20: 0.03 | M20: 0.03 | N20: 0.02 | O20: 0.03 | P20: 0.03 | Q20: 0.02 | R20: 0.02 | S20: 0.02 | T20: 0.01 | U20: 0.11 | V20: 0.04 | W20: 0.01 | Y20: =T20*0.2 -> 0.002 | Z20: =T20*1 -> 0.01
E21: Electrical Work | F21: 0.04 | G21: 0.06 | H21: 0.02 | I21: 0.04 | J21: 0.03 | K21: 0.02 | L21: 0.05 | M21: 0.04 | N21: 0.03 | O21: 0.09 | P21: 0.07 | Q21: 0.05 | R21: 0.06 | S21: 0.06 | T21: 0.05 | U21: 0.03 | V21: 0.03 | W21: 0.02 | Y21: =T21*0*0.2 -> 0 | Z21: =T21*1 -> 0.05
E22: Total | F22: 1 | G22: 1 | H22: 1 | I22: 1 | J22: 1 | K22: 1 | L22: 1 | M22: 1 | N22: 1 | O22: 1 | P22: 1 | Q22: 1 | R22: 1 | S22: 1 | T22: 1 | U22: 1 | V22: 1 | W22: 1 | Y22: =SUM(Y8:Y21) -> 0.27194 | Z22: =SUM(Z8:Z21) -> 1
Y23: =Y22*100 -> 27.194 | Z23: =Z22*100 -> 100
S26: =V8*0.5 -> 0.125

Sheet Sheet5
E5: =415000 -> 415000 | F5: 200 | G5: 1250 | H5: =F5*G5 -> 250000 | J5: 200 | K5: 1390 | L5: =J5*K5 -> 278000
F6: 150 | G6: 937 | H6: =F6*G6 -> 140550 | J6: 200 | K6: 890 | L6: =J6*K6 -> 178000
F7: =SUM(F5:F6) -> 350 | H7: =SUM(H5:H6) -> 390550 | J7: 20 | K7: 590 | L7: =J7*K7 -> 11800
J8: =SUM(J5:J7) -> 420 | L8: =SUM(L5:L7) -> 467800
F9: =E5/F7 -> 1185.7143
