Workbook
Name G_1___2: #REF!
Name G_1___2: #REF!
Name G_1___2: #REF!
Name G_7___above: #REF!
Name G_7___above: #REF!
Name G_7___above: #REF!
Name G_7__8: #REF!
Name G_7__8: #REF!
Name G_7__8: #REF!
Name GH: #REF!
Name GH: #REF!
Name GH: #REF!
Name MNJUB: #REF!
Name MNJUB: #REF!
Name MNJUB: #REF!

Sheet Sheet1
A1: Ranges of Replacement cost rates for properties located in Addis Ababa
A2: Building Types | B2: Range of replacement cost rate | D2: Range used only for management purpose | F2: The diffrence
B3: Max | C3: Min | D3: Max | E3: Min | F3: Max | G3: Min | H3: Remark
A4: G+1 and G+2 | B4: ='G+ Buildings'!D166 -> 18745.139 | C4: ='G+ Buildings'!E166 -> 11081.785 | D4: 15582 | E4: 7588 | F4: =B4-D4 -> 3163.1388 | G4: =C4-E4 -> 3493.7846 | H4: Birr/m²
A5: G+3 and G+4 | B5: ='G+ Buildings'!I166 -> 16537.649 | C5: ='G+ Buildings'!J166 -> 11107.469 | D5: 16618 | E5: 9170 | F5: =B5-D5 -> -80.3506 | G5: =C5-E5 -> 1937.4688 | H5: Birr/m²
A6: G+5 and G+6 | B6: ='G+ Buildings'!N166 -> 16167.256 | C6: ='G+ Buildings'!O166 -> 11070.97 | D6: 17122 | E6: 8680 | F6: =B6-D6 -> -954.7438 | G6: =C6-E6 -> 2390.9702 | H6: Birr/m²
A7: G+7 and G+8 | B7: ='G+ Buildings'!S166 -> 19888.762 | C7: ='G+ Buildings'!T166 -> 11065.563 | D7: 16660 | E7: 12292 | F7: =B7-D7 -> 3228.7616 | G7: =C7-E7 -> -1226.437 | H7: Birr/m²
A8: G+9 and G+10 | B8: ='G+ Buildings'!X166 -> 13517.728 | C8: ='G+ Buildings'!Y166 -> 10670.837 | F8: =B8-D8 -> 13517.728 | G8: =C8-E8 -> 10670.837 | H8: Birr/m²
A9: G+11 to G+16 | B9: ='G+ Buildings'!AC166 -> 16584.962 | C9: ='G+ Buildings'!AD166 -> 10918.217 | F9: =B9-D9 -> 16584.962 | G9: =C9-E9 -> 10918.217 | H9: Birr/m²
A10: G+17 to G+22 | B10: ='G+ Buildings'!AH166 -> 16455.19 | C10: ='G+ Buildings'!AI166 -> 11022.305 | F10: =B10-D10 -> 16455.19 | G10: =C10-E10 -> 11022.305 | H10: Birr/m²
A11: G+23 and above | B11: ='G+ Buildings'!AM166 -> 16725.55 | C11: ='G+ Buildings'!AN166 -> 10946.605 | F11: =B11-D11 -> 16725.55 | G11: =C11-E11 -> 10946.605 | H11: Birr/m²
A12: Villa Higher | B12: ='Villa Higher'!D178 -> 25555.453 | C12: ='Villa Higher'!E178 -> 7776.2408 | D12: 16245 | E12: 3976 | F12: =B12-D12 -> 9310.4528 | G12: =C12-E12 -> 3800.2408 | H12: Birr/m²
A13: Lower Villa | B13: ='Villa Lower'!E62 -> 8862.0375 | C13: ='Villa Lower'!G62 -> 1510.004 | D13: 4032 | E13: 1694 | F13: =B13-D13 -> 4830.0375 | G13: =C13-E13 -> -183.996 | H13: Birr/m²
A14: Multipurpose Halls H<= 4m | B14: ='Multi-Purposed halls'!D151 -> 59422.793 | C14: ='Multi-Purposed halls'!E151 -> 11724.093 | D14: 9604 | E14: 1694 | F14: =B14-D14 -> 49818.793 | G14: =C14-E14 -> 10030.093 | H14: Birr/m²
A15: H=4.5 | B15: ='Multi-Purposed halls'!H151 -> 17215.99 | C15: ='Multi-Purposed halls'!I151 -> 3344.6534 | D15: 4732 | E15: 378 | F15: =B15-D15 -> 12483.99 | G15: =C15-E15 -> 2966.6534 | H15: Birr/m²
A16: H=5.5 | B16: ='Multi-Purposed halls'!L151 -> 1785.288 | C16: ='Multi-Purposed halls'!M151 -> 486.212 | D16: 1705 | E16: 196 | F16: =B16-D16 -> 80.288 | G16: =C16-E16 -> 290.212 | H16: Birr/m³
A17: H=6.5 | B17: ='Multi-Purposed halls'!P151 -> 1578.3152 | C17: ='Multi-Purposed halls'!Q151 -> 425.5908 | F17: =B17-D17 -> 1578.3152 | G17: =C17-E17 -> 425.5908 | H17: Birr/m³
A18: H=7.5 | B18: ='Multi-Purposed halls'!T151 -> 1364.851 | C18: ='Multi-Purposed halls'!U151 -> 359.7115 | D18: 1324 | E18: 154 | F18: =B18-D18 -> 40.851 | G18: =C18-E18 -> 205.7115 | H18: Birr/m³
A19: H=8.5 | B19: ='Multi-Purposed halls'!X151 -> 1297.5762 | C19: ='Multi-Purposed halls'!Y151 -> 331.9023 | F19: =B19-D19 -> 1297.5762 | G19: =C19-E19 -> 331.9023 | H19: Birr/m³
A20: H=10.5 | B20: ='Multi-Purposed halls'!AB151 -> 1178.378 | C20: ='Multi-Purposed halls'!AC151 -> 310.957 | D20: 1113 | E20: 154 | F20: =B20-D20 -> 65.378 | G20: =C20-E20 -> 156.957 | H20: Birr/m³
A21: H=11.5 | B21: ='Multi-Purposed halls'!AF151 -> 1127.794 | C21: ='Multi-Purposed halls'!AG151 -> 293.261 | F21: =B21-D21 -> 1127.794 | G21: =C21-E21 -> 293.261 | H21: Birr/m³

Sheet Villa Lower
A2: ITEM NO. | B2: Building components
A3: 1 | B3: Foundation | C3: Factors | E3: Max | G3: Min
B4: 1.1 Earth Work But no cart away | C4: 1 | E4: =MAX(C4:C7) -> 47.16 | F4: =MAX(D4:D7) -> 0 | G4: =MIN(C4:C7) -> 1 | I4: =$C4*H4/100 -> 0
B5: 1.2 Earth Work Foundation & cart away | C5: 4 | H5: 100 | I5: =$C5*H5/100 -> 4
B6: 1.3 Earth Work Foundation, hardcore, mass concrete, stone masonry | C6: 20.49 | I6: =$C6*H6/100 -> 0
B7: 1.4 Earth Work Foundation, hardcore, mass concrete, stone masonry BGL & AGL | C7: 47.16 | I7: =$C7*H7/100 -> 0
A8: 2 | B8: Structure | I8: =$C8*H8/100 -> 0
A9: 3 | B9: Block Work (Internal) | I9: =$C9*H9/100 -> 0
B10: 3.1 Chicka | C10: 2.16 | E10: =MAX(C10:C13) -> 10.63 | F10: =MAX(D10:D13) -> 0 | G10: =MIN(C10:C14) -> 1 | I10: =$C10*H10/100 -> 0
B11: 3.2 Poor Chika | C11: 1 | I11: =$C11*H11/100 -> 0
B12: 3.3 HCB but no R.C structure and plastering | C12: 10.63 | H12: 100 | I12: =$C12*H12/100 -> 10.63
B13: 3.4 Stone masonry with cement-chicka mortar mix | C13: 8.4 | I13: =$C13*H13/100 -> 0
B14: 3.5 CIS Wall | C14: 1.89 | I14: =$C14*H14/100 -> 0
A15: 4 | B15: Block Work (External) | I15: =$C15*H15/100 -> 0
B16: 4.1 Chicka | C16: 2.16 | E16: =MAX(C16:C20) -> 10.63 | F16: =MAX(D16:D20) -> 0 | G16: =MIN(C16:C20) -> 1 | I16: =$C16*H16/100 -> 0
B17: 4.2 Poor Chika | C17: 1 | I17: =$C17*H17/100 -> 0
B18: 4.3 HCB but no R.C structure and plastering | C18: 10.63 | H18: 100 | I18: =$C18*H18/100 -> 10.63
B19: 4.4 Stone masonry with cement-chicka mortar mix | C19: 8.4 | I19: =$C19*H19/100 -> 0
B20: 4.5 CIS Wall | C20: 1.89 | I20: =$C20*H20/100 -> 0
A21: 5 | B21: Roofing | I21: =$C21*H21/100 -> 0
B22: 5.1 CIS G-35 on wood | C22: 1 | E22: =MAX(C22:C24) -> 1.62 | F22: =MAX(D22:D24) -> 0 | G22: =MIN(C22:C24) -> 1 | H22: 100 | I22: =$C22*H22/100 -> 1
B23: 5.2 CIS G-32 on wood | C23: 1.37 | I23: =$C23*H23/100 -> 0
B24: 5.3 CIS G-30 on wood | C24: 1.62 | I24: =$C24*H24/100 -> 0
A25: 6 | B25: Joinery | I25: =$C25*H25/100 -> 0
B26: 6.1 Internal wooden door made of Low quality wood | C26: 1.67 | E26: =MAX(C26:C27) -> 1.67 | F26: =MAX(D26:D27) -> 0 | G26: =MIN(C26:C27) -> 1 | I26: =$C26*H26/100 -> 0
B27: 6.2 As item No.1 above but made of Poor Quality wood | C27: 1 | I27: =$C27*H27/100 -> 0
A28: 7 | B28: Metal Works | I28: =$C28*H28/100 -> 0
B29: 7.1 LTZ or RHS | C29: 1 | E29: =MAX(C29) -> 1 | F29: =MAX(D29) -> 0 | G29: =MIN(C29:C30) -> 1 | H29: 100 | I29: =$C29*H29/100 -> 1
A30: 8 | B30: Floor Finish | I30: =$C30*H30/100 -> 0
B31: 8.1 Cement Screed | C31: 1 | E31: =MAX(C31:C34) -> 6.49 | F31: =MAX(D31:D34) -> 0 | G31: =MIN(C31:C34) -> 1 | H31: 100 | I31: =$C31*H31/100 -> 1
B32: 8.2 Cement Tile | C32: 2.72 | I32: =$C32*H32/100 -> 0
B33: 8.3 Terrazzo | C33: 3.06 | I33: =$C33*H33/100 -> 0
B34: 8.4 Poor quality wooden | C34: 6.49 | I34: =$C34*H34/100 -> 0
A35: 9 | B35: Wall Finish (Internal) | I35: =$C35*H35/100 -> 0
B36: 9.1 Pointed HCB | C36: 1 | E36: =MAX(C36:C39) -> 4.04 | F36: =MAX(D36:D39) -> 0 | G36: =MIN(C36:C39) -> 1 | H36: 100 | I36: =$C36*H36/100 -> 1
B37: 9.2 Painted | C37: 1.08 | I37: =$C37*H37/100 -> 0
B38: 9.3 Plastered | C38: 2.96 | I38: =$C38*H38/100 -> 0
B39: 9.4 Plastering & Painting | C39: 4.04 | I39: =$C39*H39/100 -> 0
A40: 10 | B40: Wall Finish (External) | I40: =$C40*H40/100 -> 0
B41: 10.1 Pointed HCB | C41: 1 | E41: =MAX(C41:C48) -> 13.32 | F41: =MAX(D41:D48) -> 0 | G41: =MIN(C41:C48) -> 1 | H41: 100 | I41: =$C41*H41/100 -> 1
B42: 10.2 Painted | C42: 1.08 | I42: =$C42*H42/100 -> 0
B43: 10.3 Plastered | C43: 2.96 | I43: =$C43*H43/100 -> 0
B44: 10.4 Rendered | C44: 2.96 | I44: =$C44*H44/100 -> 0
B45: 10.5 Rendered & Painted | C45: 4.04 | I45: =$C45*H45/100 -> 0
B46: 10.6 Ambo stone clad over ‘chicka’ wall | C46: 12.12 | I46: =$C46*H46/100 -> 0
B47: 10.7 Brick clad over ‘chicka’ wall | C47: 10.55 | I47: =$C47*H47/100 -> 0
B48: 10.8 Pointed Stone | C48: 13.32 | I48: =$C48*H48/100 -> 0
A49: 11 | B49: Ceiling Finish | I49: =$C49*H49/100 -> 0
B50: 11.1 Hardboard not painted | C50: 1.48 | E50: =MAX(C50:C54) -> 1.48 | F50: =MAX(D50:D54) -> 0 | G50: =MIN(C50:C54) -> 0.2 | I50: =$C50*H50/100 -> 0
B51: 11.2 Abujedi not Painted | C51: 1 | I51: =$C51*H51/100 -> 0
B52: 11.3 Painting | C52: 0.2 | I52: =$C52*H52/100 -> 0
B53: 11.4 Plywood not painted | C53: 1.19 | I53: =$C53*H53/100 -> 0
B54: 11.5 Chip wood not painted | C54: 1.24 | I54: =$C54*H54/100 -> 0
A55: 12 | B55: Electrical | I55: =$C55*H55/100 -> 0
B56: 12.1 Class A | C56: 4.21 | E56: =MAX(C56:C60) -> 4.21 | F56: =MAX(D56:D60) -> 0 | G56: =MIN(C56:C60) -> 1 | I56: =$C56*H56/100 -> 0
B57: 12.2 Class B | C57: 3.55 | I57: =$C57*H57/100 -> 0
B58: 12.3 Class C | C58: 2.31 | I58: =$C58*H58/100 -> 0
B59: 12.4 Class D | C59: 1.66 | I59: =$C59*H59/100 -> 0
B60: 12.5 Class E | C60: 1 | H60: 100 | I60: =$C60*H60/100 -> 1
B61: Factor sum | C61: =SUM(C4:C60) -> 216.69 | D61: =SUM(D4:D60) -> 0 | E61: =SUM(E4:E60) -> 102.25 | F61: =SUM(F4:F60) -> 0 | G61: =SUM(G4:G60) -> 10.2 | I61: =ROUND(SUM(I4:I60),2) -> 31.26
B62: Plinth Area/ Volumetric Rate (Ra=79.87flv+695.33) | D62: =IF(D61>0,(79.87*D61+695.33),0) -> 0 | E62: =IF(E61>0,(79.87*E61+695.33),0) -> 8862.0375 | F62: =IF(F61>0,(79.87*F61+695.33),0) -> 0 | G62: =IF(G61>0,(79.87*G61+695.33),0) -> 1510.004 | I62: =IF(I61>0,(79.87*I61+695.33),0) -> 3192.0662
B63: Depreciation %
B64: Plinth Area/ Volumetric Rate (Ra=79.87flv+695.33) | I64: =(1-H63%)*I62 -> 3192.0662
B65: Plinth Area/ Volumetric | I65: =Area!#REF!+Area!E15+Area!#REF! -> #REF!
B66: Total | I66: =I64*I65 -> #REF!

Sheet Villa Higher
A2: ITEM NO. | B2: Building components
A3: 1 | B3: Foundation | C3: Factors | D3: Max | E3: Min
B4: 1.1 Foundation Work in: Earthwortk,Hard-core,Mass concrete floor with C-15,Stone masnory AGL and BGL | C4: 1.31 | D4: =MAX(C4:C8) -> 8.3 | E4: =MIN(C4:C8) -> 1.31 | G4: =$C4*F4/100 -> 0
B5: 1.2 Foundation work as Item No.1 above but with mass concrete of higher class (c-20) | C5: 1.48 | G5: =$C5*F5/100 -> 0
B6: 1.3 Foundation work as Item No.2 above but with R.C. grade beam | C6: 2.85 | G6: =$C6*F6/100 -> 0
B7: 1.4 Foundation work as Item No.1 above but with R.C. floor slab and R.C grade beam | C7: 5.53 | G7: =$C7*F7/100 -> 0
B8: 1.4 Foundation work as Item No.4 above but with R.C. foundation column and R.C Footing | C8: 8.3 | G8: =$C8*F8/100 -> 0
A9: 2 | B9: Structure | G9: =$C9*F9/100 -> 0
B10: 2.1 Structure for mud and CIS-on- wooden walls | D10: =MAX(C10:C12) -> 9.19 | E10: =MIN(C10:C12) -> 4.2 | G10: =$C10*F10/100 -> 0
B11: 2.2 .R.C structure (Elevation colums and tie beam) | C11: 4.2 | G11: =$C11*F11/100 -> 0
B12: 2.3 As item no.2 above but for R.C roof slab | C12: 9.19 | G12: =$C12*F12/100 -> 0
A13: 3 | B13: Block Work | G13: =$C13*F13/100 -> 0
B14: 3.1 Internal | G14: =$C14*F14/100 -> 0
B15: 3.1.1 Chicka | C15: 0.48 | D15: =MAX(C15:C26) -> 6.92 | E15: =MIN(C15:C38) -> 0.48 | G15: =$C15*F15/100 -> 0
B16: 3.1.2 CIS G-32 | C16: 0.75 | G16: =$C16*F16/100 -> 0
B17: 3.1.3 CIS G-30 | C17: 0.71 | G17: =$C17*F17/100 -> 0
B18: 3.1.4 CIS G-28 | C18: 0.96 | G18: =$C18*F18/100 -> 0
B19: 3.1.5 HCB 15 cm thick | C19: 0.69 | G19: =$C19*F19/100 -> 0
B20: 3.1.6 Brick 12cm thick | C20: 2.2 | G20: =$C20*F20/100 -> 0
B21: 3.1.7 stone 40cm thick | C21: 1.21 | G21: =$C21*F21/100 -> 0
B22: 3.1.8 Chip wood-double | C22: 1.03 | G22: =$C22*F22/100 -> 0
B23: 3.1.9 Alumimium | C23: 6.92 | G23: =$C23*F23/100 -> 0
B24: 3.1.10 HCB 10 cm thick | C24: 0.55 | G24: =$C24*F24/100 -> 0
B25: 3.1.11 Hard board fixed to zigba frame (one face) | C25: 0.65 | G25: =$C25*F25/100 -> 0
B26: 3.1.12 Ditto as above but both side coverd | C26: 1.12 | G26: =$C26*F26/100 -> 0
B27: 3.2 External | G27: =$C27*F27/100 -> 0
B28: 3.2.1 Chicka | C28: 0.93 | D28: =MAX(C28:C38) -> 18.59 | E28: =MIN(C28:C38) -> 0.93 | G28: =$C28*F28/100 -> 0
B29: 3.2.2 CIS G-32 | C29: 1.44 | G29: =$C29*F29/100 -> 0
B30: 3.2.3 CIS G-30 | C30: 1.37 | G30: =$C30*F30/100 -> 0
B31: 3.2.4 CIS G-28 | C31: 1.86 | G31: =$C31*F31/100 -> 0
B32: 3.2.5 EGA on steel | C32: 2.33 | G32: =$C32*F32/100 -> 0
B33: 3.2.6 HCB 20 cm thick | C33: 1.35 | G33: =$C33*F33/100 -> 0
B34: 3.2.7 Brick 25cm thick | C34: 8.71 | G34: =$C34*F34/100 -> 0
B35: 3.2.8 stone 40cm thick | C35: 2.34 | G35: =$C35*F35/100 -> 0
B36: 3.2.9 stone 50cm thick | C36: 2.93 | G36: =$C36*F36/100 -> 0
B37: 3.2.10 Alumimium | C37: 13.8 | G37: =$C37*F37/100 -> 0
B38: 3.2.11 Curtin wall made with special frame & 4mm cored polycarbonate treated against UV rail | C38: 18.59 | G38: =$C38*F38/100 -> 0
A39: 4 | B39: Roofing | G39: =$C39*F39/100 -> 0
B40: 4.1 CIS G-32 on wood | C40: 1.6 | D40: =MAX(C40:C54) -> 4.98 | E40: =MIN(C40:C54) -> 1.6 | G40: =$C40*F40/100 -> 0
B41: 4.2 CIS G-30 on wood | C41: 1.61 | G41: =$C41*F41/100 -> 0
B42: 4.3 CIS G-28 on wood | C42: 1.97 | G42: =$C42*F42/100 -> 0
B43: 4.4 EGA on steel | C43: 3.24 | G43: =$C43*F43/100 -> 0
B44: 4.5 EGA on wood | C44: 2.16 | G44: =$C44*F44/100 -> 0
B45: 4.6 CIS G-28 on steel | C45: 2.95 | G45: =$C45*F45/100 -> 0
B46: 4.7 Cement roof tile | C46: 2.46 | G46: =$C46*F46/100 -> 0
B47: 4.8 R.C without water-proof material (Accessible) | C47: 3.73 | G47: =$C47*F47/100 -> 0
B48: 4.9 R.C without water-proof material (in Accessible) | C48: 2.99 | G48: =$C48*F48/100 -> 0
B49: 4.10 R.C with water-proof material (Accessible) | C49: 4.98 | G49: =$C49*F49/100 -> 0
B50: 4.11 R.C with water-proof material (in Accessible) | C50: 3.48 | G50: =$C50*F50/100 -> 0
B51: 4.11 Metal sheet roofing with sand coating on wood (Imported) | C51: 3.28 | G51: =$C51*F51/100 -> 0
B52: 4.12 Metal sheet roofing with sand coating on wood (local) | C52: 2.04 | G52: =$C52*F52/100 -> 0
... B54: 4.14 Metal sheet roofing with sand coating on steel (local) | C54: 3.06 | G54: =$C54*F54/100 -> 0
A55: 5 | B55: Joinery | G55: =$C55*F55/100 -> 0
B56: 5.1 Internal wooden door made of Low quality wood | C56: 1.07 | D56: =MAX(C56:C62) -> 4.58 | E56: =MIN(C56:C62) -> 1.07 | G56: =$C56*F56/100 -> 0
B57: 5.2 As item No.1 above but made of medium Quality wood | C57: 1.3 | G57: =$C57*F57/100 -> 0
B58: 5.3 As item No.2 above but with built-in cup board | C58: 2.35 | G58: =$C58*F58/100 -> 0
B59: 5.4 As item No.1 above but made of Quality wood | C59: 2.72 | G59: =$C59*F59/100 -> 0
B60: 5.5 As item No.4 above but with built-in cup board | C60: 2.86 | G60: =$C60*F60/100 -> 0
B61: 5.6 As item No.1 above but made of best Quality wood | C61: 4.35 | G61: =$C61*F61/100 -> 0
B62: 5.7 As item No.6 above but with built-in cup board | C62: 4.58 | G62: =$C62*F62/100 -> 0
A63: 6 | B63: Metal Works | G63: =$C63*F63/100 -> 0
B64: 6.1 LTZ or RHS profile for external openings with clear glass | C64: 2.55 | D64: =MAX(C64:C76) -> 4.13 | E64: =MIN(C64:C76) -> 1.92 | G64: =$C64*F64/100 -> 0
B65: 6.2 LTZ with 4mm- frosted glass | C65: 2.65 | F65: 100 | G65: =$C65*F65/100 -> 2.65
B66: 6.3 Ditto but with 4mm-tinted glass | C66: 2.64 | G66: =$C66*F66/100 -> 0
B67: 6.4 Ditto but with 6mm-tinted glass | C67: 3 | G67: =$C67*F67/100 -> 0
B68: 6.5 Secco profile for external openings with clear glass | C68: 1.92 | G68: =$C68*F68/100 -> 0
B69: 6.6 Secco with 4mm-frosted glass | C69: 1.98 | G69: =$C69*F69/100 -> 0
B70: 6.7 Ditto but with 4mm-tinted glass | C70: 2.01 | G70: =$C70*F70/100 -> 0
B71: 6.8 Ditto but with 6mm-tinted glass | C71: 2.36 | G71: =$C71*F71/100 -> 0
B72: 6.9 Imitation with clear glass | C72: 3.04 | G72: =$C72*F72/100 -> 0
B73: 6.10 Imitation with 4mm frosted glass | C73: 3.08 | G73: =$C73*F73/100 -> 0
B74: 6.11 Imitation with 4mm tinted glass | C74: 3.08 | G74: =$C74*F74/100 -> 0
B75: 6.12 Imitation with 6mm tinted glass | C75: 3.24 | G75: =$C75*F75/100 -> 0
B76: 6.13 Aluminium profile for external opening | C76: 4.13 | G76: =$C76*F76/100 -> 0
A77: 7 | B77: Floor Finish | G77: =$C77*F77/100 -> 0
B78: 7.1 Cement Screed | C78: 0.68 | D78: =MAX(C78:C95) -> 10.42 | E78: =MIN(C78:C95) -> 0.68 | F78: 100 | G78: =$C78*F78/100 -> 0.68
B79: 7.2 Cement Tile | C79: 1.43 | G79: =$C79*F79/100 -> 0
B80: 7.3 Terrazzo Tile | C80: 2.03 | G80: =$C80*F80/100 -> 0
B81: 7.4 PVC tile | C81: 2.38 | G81: =$C81*F81/100 -> 0
B82: 7.5 Ceramic medium quality Porcelain | C82: 3.37 | G82: =$C82*F82/100 -> 0
B83: 7.6 Ceramic best quality | C83: 4.21 | G83: =$C83*F83/100 -> 0
B84: 7.7 Porcelain | C84: 3.54 | G84: =$C84*F84/100 -> 0
B85: 7.8 Marble chip lower quality | C85: 4.44 | G85: =$C85*F85/100 -> 0
B86: 7.9 Marble chip best quality | C86: 5.33 | G86: =$C86*F86/100 -> 0
B87: 7.10 Harar marble | C87: 6.2 | G87: =$C87*F87/100 -> 0
B88: 7.11 Mankush marble | C88: 8.77 | G88: =$C88*F88/100 -> 0
B89: 7.12 Parquet lower quality on screed | C89: 4.52 | G89: =$C89*F89/100 -> 0
B90: 7.13 Parquet best quality on screed | C90: 10.42 | G90: =$C90*F90/100 -> 0
... B95: 7.18 Mosaic | C95: 5.12 | G95: =$C95*F95/100 -> 0
A96: 8 | B96: Wall Finish | G96: =$C96*F96/100 -> 0
B97: 8.1 Internal | G97: =$C97*F97/100 -> 0
B98: 8.1.1 plasterd | C98: 1.05 | D98: =MAX(C98:C115) -> 9.97 | E98: =MIN(C98:C115) -> 0.46 | G98: =$C98*F98/100 -> 0
B99: 8.1.2 Plasterd and painted | C99: 1.41 | F99: 100 | G99: =$C99*F99/100 -> 1.41
B100: 8.1.3 Pointed HCB | C100: 0.46 | G100: =$C100*F100/100 -> 0
B101: 8.1.4 Pointed dressed stone | C101: 0.6 | G101: =$C101*F101/100 -> 0
B102: 8.1.5 Pointed brick | C102: 0.75 | G102: =$C102*F102/100 -> 0
B103: 8.1.6 Plasterd and Addis I wall paper | C103: 3.62 | G103: =$C103*F103/100 -> 0
B104: 8.1.7 Mosaic | C104: 6.86 | G104: =$C104*F104/100 -> 0
B105: 8.1.8a Imported, high quality ceramic | C105: 5.63 | G105: =$C105*F105/100 -> 0
B106: 8.1.8b Imported, quality ceramic | C106: 3.55 | G106: =$C106*F106/100 -> 0
...

Sheet G+ Buildings
A2: ITEM NO. | B2: Building components
A3: 1 | B3: Foundation | C3: Factors | H3: Factors | M3: Factors | R3: Factors | W3: Factors | AB3: Factors | AG3: Factors | AL3: Factors
C4: G+1 & G+2 | H4: G+3 & G+4 | M4: G+5 & G+6 | R4: G+7 & G+8 | W4: G+9 & G+10 | AB4: G+11 to G+16 | AG4: G+17 to G+22 | AL4: G+23 & Above
D5: Max | E5: Min | I5: Max | J5: Min | N5: Max | O5: Min | S5: Max | T5: Min | X5: Max | Y5: Min | AC5: Max | AD5: Min | AH5: Max | AI5: Min | AM5: Max | AN5: Min
B6: 1.1 Foundation | C6: 4.99 | D6: =MAX(C6) -> 4.99 | E6: =MIN(C6) -> 4.99 | F6: 100 | G6: =$C6*F6/100 -> 4.99 | H6: 4.53 | I6: =MAX(H6) -> 4.53 | J6: =MIN(H6) -> 4.53 | L6: =$H6*K6/100 -> 0 | M6: 5.78 | N6: =MAX(M6) -> 5.78 | O6: =MIN(M6) -> 5.78 | Q6: =$M6*P6/100 -> 0 | R6: 3.29 | S6: =MAX(R6) -> 3.29 | T6: =MIN(R6) -> 3.29 | V6: =$R6*U6/100 -> 0 | W6: 4.61 | X6: =MAX(W6) -> 4.61 | Y6: =MIN(W6) -> 4.61 | AA6: =$W6*Z6/100 -> 0 | AB6: 3.72 | AC6: =MAX(AB6) -> 3.72 | AD6: =MIN(AB6) -> 3.72 | AF6: =$AB6*AE6/100 -> 0 | AG6: 4.9 | AH6: =MAX(AG6) -> 4.9 | AI6: =MIN(AG6) -> 4.9 | AK6: =$AG6*AJ6/100 -> 0 | AL6: 4.03 | AM6: =MAX(AL6) -> 4.03 | AN6: =MIN(AL6) -> 4.03 | AP6: =$AL6*AO6/100 -> 0
A7: 2 | B7: Structure | G7: =$C7*F7/100 -> 0 | L7: =$H7*K7/100 -> 0 | Q7: =$M7*P7/100 -> 0 | V7: =$R7*U7/100 -> 0 | AA7: =$W7*Z7/100 -> 0 | AF7: =$AB7*AE7/100 -> 0 | AK7: =$AG7*AJ7/100 -> 0 | AP7: =$AL7*AO7/100 -> 0
B8: 2.1 .R.C structure (Elevation colums and suspended beam) | C8: 4.94 | D8: =MAX(C8) -> 4.94 | E8: =MIN(C8) -> 4.94 | F8: 100 | G8: =$C8*F8/100 -> 4.94 | H8: 6.96 | I8: =MAX(H8) -> 6.96 | J8: =MIN(H8) -> 6.96 | L8: =$H8*K8/100 -> 0 | M8: 5.54 | N8: =MAX(M8) -> 5.54 | O8: =MIN(M8) -> 5.54 | Q8: =$M8*P8/100 -> 0 | R8: 5.75 | S8: =MAX(R8) -> 5.75 | T8: =MIN(R8) -> 5.75 | V8: =$R8*U8/100 -> 0 | W8: 4.01 | X8: =MAX(W8) -> 4.01 | Y8: =MIN(W8) -> 4.01 | AA8: =$W8*Z8/100 -> 0 | AB8: 6.85 | AC8: =MAX(AB8) -> 6.85 | AD8: =MIN(AB8) -> 6.85 | AF8: =$AB8*AE8/100 -> 0 | AG8: 7.16 | AH8: =MAX(AG8) -> 7.16 | AI8: =MIN(AG8) -> 7.16 | AK8: =$AG8*AJ8/100 -> 0 | AL8: 8.6 | AM8: =MAX(AL8) -> 8.6 | AN8: =MIN(AL8) -> 8.6 | AP8: =$AL8*AO8/100 -> 0
A9: 3 | B9: Block Work | G9: =$C9*F9/100 -> 0 | L9: =$H9*K9/100 -> 0 | Q9: =$M9*P9/100 -> 0 | V9: =$R9*U9/100 -> 0 | AA9: =$W9*Z9/100 -> 0 | AF9: =$AB9*AE9/100 -> 0 | AK9: =$AG9*AJ9/100 -> 0 | AP9: =$AL9*AO9/100 -> 0
B10: 3.1 Internal | G10: =$C10*F10/100 -> 0 | L10: =$H10*K10/100 -> 0 | Q10: =$M10*P10/100 -> 0 | V10: =$R10*U10/100 -> 0 | AA10: =$W10*Z10/100 -> 0 | AF10: =$AB10*AE10/100 -> 0 | AK10: =$AG10*AJ10/100 -> 0 | AP10: =$AL10*AO10/100 -> 0
B11: 3.1.1 HCB 15 cm thick | C11: 0.53 | D11: =MAX(C11:C17) -> 5.26 | E11: =MIN(C11:C17) -> 0.42 | F11: 100 | G11: =$C11*F11/100 -> 0.53 | H11: 0.43 | I11: =MAX(H11:H17) -> 4.31 | J11: =MIN(H11:H17) -> 0.34 | L11: =$H11*K11/100 -> 0 | M11: 0.29 | N11: =MAX(M11:M17) -> 2.95 | O11: =MIN(M11:M17) -> 0.23 | Q11: =$M11*P11/100 -> 0 | R11: 2.69 | S11: =MAX(R11:R17) -> 26.92 | T11: =MIN(R11:R17) -> 2.14 | V11: =$R11*U11/100 -> 0 | W11: 0.38 | X11: =MAX(W11:W17) -> 3.78 | Y11: =MIN(W11:W17) -> 0.3 | AA11: =$W11*Z11/100 -> 0 | AB11: 0.06 | AC11: =MAX(AB11:AB17) -> 0.61 | AD11: =MIN(AB11:AB17) -> 0.05 | AF11: =$AB11*AE11/100 -> 0 | AG11: 0.37 | AH11: =MAX(AG11:AG17) -> 3.72 | AI11: =MIN(AG11:AG17) -> 0.3 | AK11: =$AG11*AJ11/100 -> 0 | AL11: 0.24 | AM11: =MAX(AL11:AL17) -> 2.39 | AN11: =MIN(AL11:AL17) -> 0.19 | AP11: =$AL11*AO11/100 -> 0
B12: 3.1.2 Brick 12cm thick | C12: 1.68 | G12: =$C12*F12/100 -> 0 | H12: 1.37 | L12: =$H12*K12/100 -> 0 | M12: 0.94 | Q12: =$M12*P12/100 -> 0 | R12: 8.57 | V12: =$R12*U12/100 -> 0 | W12: 1.2 | AA12: =$W12*Z12/100 -> 0 | AB12: 0.2 | AF12: =$AB12*AE12/100 -> 0 | AG12: 1.19 | AK12: =$AG12*AJ12/100 -> 0 | AL12: 0.76 | AP12: =$AL12*AO12/100 -> 0
B13: 3.1.3 stone 40cm thick | C13: 0.92 | G13: =$C13*F13/100 -> 0 | H13: 0.75 | L13: =$H13*K13/100 -> 0 | M13: 0.52 | Q13: =$M13*P13/100 -> 0 | R13: 4.71 | V13: =$R13*U13/100 -> 0 | W13: 0.66 | AA13: =$W13*Z13/100 -> 0 | AB13: 0.11 | AF13: =$AB13*AE13/100 -> 0 | AG13: 0.65 | AK13: =$AG13*AJ13/100 -> 0 | AL13: 0.42 | AP13: =$AL13*AO13/100 -> 0
B14: 3.1.4 Chip wood-double | C14: 0.78 | G14: =$C14*F14/100 -> 0 | H14: 0.64 | L14: =$H14*K14/100 -> 0 | M14: 0.44 | Q14: =$M14*P14/100 -> 0 | R14: 4 | V14: =$R14*U14/100 -> 0 | W14: 0.56 | AA14: =$W14*Z14/100 -> 0 | AB14: 0.09 | AF14: =$AB14*AE14/100 -> 0 | AG14: 0.55 | AK14: =$AG14*AJ14/100 -> 0 | AL14: 0.36 | AP14: =$AL14*AO14/100 -> 0
B15: 3.1.5 Alumimium | C15: 5.26 | G15: =$C15*F15/100 -> 0 | H15: 4.31 | L15: =$H15*K15/100 -> 0 | M15: 2.95 | Q15: =$M15*P15/100 -> 0 | R15: 26.92 | V15: =$R15*U15/100 -> 0 | W15: 3.78 | AA15: =$W15*Z15/100 -> 0 | AB15: 0.61 | AF15: =$AB15*AE15/100 -> 0 | AG15: 3.72 | AK15: =$AG15*AJ15/100 -> 0 | AL15: 2.39 | AP15: =$AL15*AO15/100 -> 0
B16: 3.1.6 HCB 10 cm thick | C16: 0.42 | G16: =$C16*F16/100 -> 0 | H16: 0.34 | L16: =$H16*K16/100 -> 0 | M16: 0.23 | Q16: =$M16*P16/100 -> 0 | R16: 2.14 | V16: =$R16*U16/100 -> 0 | W16: 0.3 | AA16: =$W16*Z16/100 -> 0 | AB16: 0.05 | AF16: =$AB16*AE16/100 -> 0 | AG16: 0.3 | AK16: =$AG16*AJ16/100 -> 0 | AL16: 0.19 | AP16: =$AL16*AO16/100 -> 0
B17: 3.1.7 Magnesium/Gypsum Board | C17: 0.85 | G17: =$C17*F17/100 -> 0 | H17: 0.7 | L17: =$H17*K17/100 -> 0 | M17: 0.48 | Q17: =$M17*P17/100 -> 0 | R17: 4.36 | V17: =$R17*U17/100 -> 0 | W17: 0.61 | AA17: =$W17*Z17/100 -> 0 | AB17: 0.1 | AF17: =$AB17*AE17/100 -> 0 | AG17: 0.6 | AK17: =$AG17*AJ17/100 -> 0 | AL17: 0.39 | AP17: =$AL17*AO17/100 -> 0
B18: 3.2 External | G18: =$C18*F18/100 -> 0 | L18: =$H18*K18/100 -> 0 | Q18: =$M18*P18/100 -> 0 | V18: =$R18*U18/100 -> 0 | AA18: =$W18*Z18/100 -> 0 | AF18: =$AB18*AE18/100 -> 0 | AK18: =$AG18*AJ18/100 -> 0 | AP18: =$AL18*AO18/100 -> 0
B19: 3.2.1 HCB 20 cm thick | C19: 1.03 | D19: =MAX(C19:C25) -> 14.24 | E19: =MIN(C19:C25) -> 1.03 | F19: 100 | G19: =$C19*F19/100 -> 1.03 | H19: 0.58 | I19: =MAX(H19:H25) -> 8 | J19: =MIN(H19:H25) -> 0.58 | L19: =$H19*K19/100 -> 0 | M19: 0.29 | N19: =MAX(M19:M25) -> 4.05 | O19: =MIN(M19:M25) -> 0.29 | Q19: =$M19*P19/100 -> 0 | R19: 1.02 | S19: =MAX(R19:R25) -> 14.06 | T19: =MIN(R19:R25) -> 1.02 | V19: =$R19*U19/100 -> 0 | W19: 0.26 | X19: =MAX(W19:W25) -> 3.54 | Y19: =MIN(W19:W25) -> 0.26 | AA19: =$W19*Z19/100 -> 0 | AB19: 0.17 | AC19: =MAX(AB19:AB25) -> 2.34 | AD19: =MIN(AB19:AB25) -> 0.17 | AF19: =$AB19*AE19/100 -> 0 | AG19: 0.21 | AH19: =MAX(AG19:AG25) -> 2.82 | AI19: =MIN(AG19:AG25) -> 0.21 | AK19: =$AG19*AJ19/100 -> 0 | AL19: 0.91 | AM19: =MAX(AL19:AL25) -> 12.57 | AN19: =MIN(AL19:AL25) -> 0.91 | AP19: =$AL19*AO19/100 -> 0
B20: 3.2.2 Brick 25cm thick | C20: 6.67 | G20: =$C20*F20/100 -> 0 | H20: 3.75 | L20: =$H20*K20/100 -> 0 | M20: 1.9 | Q20: =$M20*P20/100 -> 0 | R20: 6.59 | V20: =$R20*U20/100 -> 0 | W20: 1.66 | AA20: =$W20*Z20/100 -> 0 | AB20: 1.1 | AF20: =$AB20*AE20/100 -> 0 | AG20: 1.32 | AK20: =$AG20*AJ20/100 -> 0 | AL20: 5.89 | AP20: =$AL20*AO20/100 -> 0
B21: 3.2.3 stone 40cm thick | C21: 1.8 | G21: =$C21*F21/100 -> 0 | H21: 1.01 | L21: =$H21*K21/100 -> 0 | M21: 0.51 | Q21: =$M21*P21/100 -> 0 | R21: 1.77 | V21: =$R21*U21/100 -> 0 | W21: 0.45 | AA21: =$W21*Z21/100 -> 0 | AB21: 0.3 | AF21: =$AB21*AE21/100 -> 0 | AG21: 0.36 | AK21: =$AG21*AJ21/100 -> 0 | AL21: 1.59 | AP21: =$AL21*AO21/100 -> 0
B22: 3.2.4 stone 50cm thick | C22: 2.24 | G22: =$C22*F22/100 -> 0 | H22: 1.26 | L22: =$H22*K22/100 -> 0 | M22: 0.64 | Q22: =$M22*P22/100 -> 0 | R22: 2.22 | V22: =$R22*U22/100 -> 0 | W22: 0.56 | AA22: =$W22*Z22/100 -> 0 | AB22: 0.37 | AF22: =$AB22*AE22/100 -> 0 | AG22: 0.45 | AK22: =$AG22*AJ22/100 -> 0 | AL22: 1.98 | AP22: =$AL22*AO22/100 -> 0
B23: 3.2.5 Alumimium | C23: 10.25 | G23: =$C23*F23/100 -> 0 | H23: 5.76 | L23: =$H23*K23/100 -> 0 | M23: 2.92 | Q23: =$M23*P23/100 -> 0 | R23: 10.13 | V23: =$R23*U23/100 -> 0 | W23: 2.55 | AA23: =$W23*Z23/100 -> 0 | AB23: 1.69 | AF23: =$AB23*AE23/100 -> 0 | AG23: 2.03 | AK23: =$AG23*AJ23/100 -> 0 | AL23: 9.05 | AP23: =$AL23*AO23/100 -> 0
B24: 3.2.6 Magnesium/Gypsum Board | C24: 1.66 | G24: =$C24*F24/100 -> 0 | H24: 0.93 | L24: =$H24*K24/100 -> 0 | M24: 0.47 | Q24: =$M24*P24/100 -> 0 | R24: 1.64 | V24: =$R24*U24/100 -> 0 | W24: 0.41 | AA24: =$W24*Z24/100 -> 0 | AB24: 0.27 | AF24: =$AB24*AE24/100 -> 0 | AG24: 0.33 | AK24: =$AG24*AJ24/100 -> 0 | AL24: 1.47 | AP24: =$AL24*AO24/100 -> 0
B25: 3.2.7 Curtin wall made with special frame & 4mm cored polycarbonate treated against UV rail | C25: 14.24 | G25: =$C25*F25/100 -> 0 | H25: 8 | L25: =$H25*K25/100 -> 0 | M25: 4.05 | Q25: =$M25*P25/100 -> 0 | R25: 14.06 | V25: =$R25*U25/100 -> 0 | W25: 3.54 | AA25: =$W25*Z25/100 -> 0 | AB25: 2.34 | AF25: =$AB25*AE25/100 -> 0 | AG25: 2.82 | AK25: =$AG25*AJ25/100 -> 0 | AL25: 12.57 | AP25: =$AL25*AO25/100 -> 0
A26: 4 | B26: Roofing | G26: =$C26*F26/100 -> 0 | L26: =$H26*K26/100 -> 0 | Q26: =$M26*P26/100 -> 0 | V26: =$R26*U26/100 -> 0 | AA26: =$W26*Z26/100 -> 0 | AF26: =$AB26*AE26/100 -> 0 | AK26: =$AG26*AJ26/100 -> 0 | AP26: =$AL26*AO26/100 -> 0
B27: 4.1 CIS G-32 on wood | C27: 1.8 | D27: =MAX(C27:C41) -> 6.5 | E27: =MIN(C27:C41) -> 1.32 | G27: =$C27*F27/100 -> 0 | H27: 0.7 | I27: =MAX(H27:H41) -> 4.13 | J27: =MIN(H27:H41) -> 0.56 | L27: =$H27*K27/100 -> 0 | M27: 0.4 | N27: =MAX(M27:M41) -> 4.59 | O27: =MIN(M27:M41) -> 0.3 | Q27: =$M27*P27/100 -> 0 | R27: 0.39 | S27: =MAX(R27:R41) -> 5.63 | T27: =MIN(R27:R41) -> 0.27 | V27: =$R27*U27/100 -> 0 | W27: 0.24 | X27: =MAX(W27:W41) -> 4.38 | Y27: =MIN(W27:W41) -> 0.17 | AA27: =$W27*Z27/100 -> 0 | AB27: 0.23 | AC27: =MAX(AB27:AB41) -> 24.05 | AD27: =MIN(AB27:AB41) -> 0.14 | AF27: =$AB27*AE27/100 -> 0 | AG27: 0.16 | AH27: =MAX(AG27:AG41) -> 9.57 | AI27: =MIN(AG27:AG41) -> 0.14 | AK27: =$AG27*AJ27/100 -> 0 | AL27: 0.08 | AM27: =MAX(AL27:AL41) -> 8.57 | AN27: =MIN(AL27:AL41) -> 0.06 | AP27: =$AL27*AO27/100 -> 0
B28: 4.2 CIS G-30 on wood | C28: 1.81 | G28: =$C28*F28/100 -> 0 | H28: 0.7 | L28: =$H28*K28/100 -> 0 | M28: 0.4 | Q28: =$M28*P28/100 -> 0 | R28: 0.39 | V28: =$R28*U28/100 -> 0 | W28: 0.24 | AA28: =$W28*Z28/100 -> 0 | AB28: 0.23 | AF28: =$AB28*AE28/100 -> 0 | AG28: 0.16 | AK28: =$AG28*AJ28/100 -> 0 | AL28: 0.08 | AP28: =$AL28*AO28/100 -> 0
B29: 4.3 CIS G-28 on wood | C29: 2.04 | G29: =$C29*F29/100 -> 0 | H29: 0.76 | L29: =$H29*K29/100 -> 0 | M29: 0.45 | Q29: =$M29*P29/100 -> 0 | R29: 0.45 | V29: =$R29*U29/100 -> 0 | W29: 0.27 | AA29: =$W29*Z29/100 -> 0 | AB29: 0.27 | AF29: =$AB29*AE29/100 -> 0 | AG29: 0.17 | AK29: =$AG29*AJ29/100 -> 0 | AL29: 0.1 | AP29: =$AL29*AO29/100 -> 0
B30: 4.4 EGA on steel | C30: 2.64 | G30: =$C30*F30/100 -> 0 | H30: 0.67 | L30: =$H30*K30/100 -> 0 | M30: 0.38 | Q30: =$M30*P30/100 -> 0 | R30: 0.37 | V30: =$R30*U30/100 -> 0 | W30: 0.23 | AA30: =$W30*Z30/100 -> 0 | AB30: 0.21 | AF30: =$AB30*AE30/100 -> 0 | AG30: 0.16 | AK30: =$AG30*AJ30/100 -> 0 | AL30: 0.08 | AP30: =$AL30*AO30/100 -> 0
B31: 4.5 EGA on wood | C31: 1.72 | G31: =$C31*F31/100 -> 0 | H31: 0.67 | L31: =$H31*K31/100 -> 0 | M31: 0.38 | Q31: =$M31*P31/100 -> 0 | R31: 0.37 | V31: =$R31*U31/100 -> 0 | W31: 0.23 | AA31: =$W31*Z31/100 -> 0 | AB31: 0.21 | AF31: =$AB31*AE31/100 -> 0 | AG31: 0.16 | AK31: =$AG31*AJ31/100 -> 0 | AL31: 0.08 | AP31: =$AL31*AO31/100 -> 0
B32: 4.6 CIS G-28 on steel | C32: 2.76 | G32: =$C32*F32/100 -> 0 | H32: 0.67 | L32: =$H32*K32/100 -> 0 | M32: 0.38 | Q32: =$M32*P32/100 -> 0 | R32: 0.37 | V32: =$R32*U32/100 -> 0 | W32: 0.23 | AA32: =$W32*Z32/100 -> 0 | AB32: 0.21 | AF32: =$AB32*AE32/100 -> 0 | AG32: 0.16 | AK32: =$AG32*AJ32/100 -> 0 | AL32: 0.08 | AP32: =$AL32*AO32/100 -> 0
B33: 4.7 Cement roof tile | C33: 1.32 | G33: =$C33*F33/100 -> 0 | H33: 0.56 | L33: =$H33*K33/100 -> 0 | M33: 0.3 | Q33: =$M33*P33/100 -> 0 | R33: 0.27 | V33: =$R33*U33/100 -> 0 | W33: 0.18 | AA33: =$W33*Z33/100 -> 0 | AB33: 0.14 | AF33: =$AB33*AE33/100 -> 0 | AG33: 0.14 | AK33: =$AG33*AJ33/100 -> 0 | AL33: 0.06 | AP33: =$AL33*AO33/100 -> 0
B34: 4.8 R.C without water-proof material (Accessible) | C34: 4.97 | G34: =$C34*F34/100 -> 0 | H34: 2.93 | L34: =$H34*K34/100 -> 0 | M34: 1.04 | Q34: =$M34*P34/100 -> 0 | R34: 0.94 | V34: =$R34*U34/100 -> 0 | W34: 0.77 | AA34: =$W34*Z34/100 -> 0 | AB34: 0.77 | AF34: =$AB34*AE34/100 -> 0 | AG34: 0.77 | AK34: =$AG34*AJ34/100 -> 0 | AL34: 0.77 | AP34: =$AL34*AO34/100 -> 0
B35: 4.9 R.C without water-proof material (in Accessible) | C35: 4.72 | G35: =$C35*F35/100 -> 0 | H35: 2.86 | L35: =$H35*K35/100 -> 0 | M35: 1.02 | Q35: =$M35*P35/100 -> 0 | R35: 0.92 | V35: =$R35*U35/100 -> 0 | W35: 0.75 | AA35: =$W35*Z35/100 -> 0 | AB35: 0.75 | AF35: =$AB35*AE35/100 -> 0 | AG35: 0.75 | AK35: =$AG35*AJ35/100 -> 0 | AL35: 0.75 | AP35: =$AL35*AO35/100 -> 0
B36: 4.10 R.C with water-proof material (Accessible) | C36: 6.5 | G36: =$C36*F36/100 -> 0 | H36: 2.39 | L36: =$H36*K36/100 -> 0 | M36: 2.72 | Q36: =$M36*P36/100 -> 0 | R36: 1.48 | V36: =$R36*U36/100 -> 0 | W36: 0.25 | AA36: =$W36*Z36/100 -> 0 | AB36: 0.43 | AF36: =$AB36*AE36/100 -> 0 | AG36: 0.65 | AK36: =$AG36*AJ36/100 -> 0 | AL36: 0.36 | AP36: =$AL36*AO36/100 -> 0
B37: 4.11 R.C with water-proof material (in Accessible) | C37: 5.52 | G37: =$C37*F37/100 -> 0 | H37: 2.27 | L37: =$H37*K37/100 -> 0 | M37: 2.21 | Q37: =$M37*P37/100 -> 0 | R37: 1.44 | V37: =$R37*U37/100 -> 0 | W37: 0.17 | AA37: =$W37*Z37/100 -> 0 | AB37: 0.27 | AF37: =$AB37*AE37/100 -> 0 | AG37: 0.34 | AK37: =$AG37*AJ37/100 -> 0 | AL37: 0.36 | AP37: =$AL37*AO37/100 -> 0
B38: 4.12 Metal sheet roofing with sand coating on wood (Imported) | C38: 3.55 | G38: =$C38*F38/100 -> 0 | H38: 4.13 | L38: =$H38*K38/100 -> 0 | M38: 4.59 | Q38: =$M38*P38/100 -> 0 | R38: 5.63 | V38: =$R38*U38/100 -> 0 | W38: 4.38 | AA38: =$W38*Z38/100 -> 0 | AB38: 24.05 | AF38: =$AB38*AE38/100 -> 0 | AG38: 9.57 | AK38: =$AG38*AJ38/100 -> 0 | AL38: 8.57 | AP38: =$AL38*AO38/100 -> 0
B39: 4.13 Metal sheet roofing with sand coating on wood (local) | C39: 2.21 | F39: 100 | G39: =$C39*F39/100 -> 2.21 | H39: 3.24 | L39: =$H39*K39/100 -> 0 | M39: 3.59 | Q39: =$M39*P39/100 -> 0 | R39: 4.4 | V39: =$R39*U39/100 -> 0 | W39: 3.43 | AA39: =$W39*Z39/100 -> 0 | AB39: 18.83 | AF39: =$AB39*AE39/100 -> 0 | AG39: 7.49 | AK39: =$AG39*AJ39/100 -> 0 | AL39: 6.71 | AP39: =$AL39*AO39/100 -> 0
B40: 4.14 Metal sheet roofing with sand coating on steel (Imported) | C40: 4.79 | G40: =$C40*F40/100 -> 0 | H40: 2.69 | L40: =$H40*K40/100 -> 0 | M40: 2.98 | Q40: =$M40*P40/100 -> 0 | R40: 3.66 | V40: =$R40*U40/100 -> 0 | W40: 2.85 | AA40: =$W40*Z40/100 -> 0 | AB40: 15.65 | AF40: =$AB40*AE40/100 -> 0 | AG40: 6.23 | AK40: =$AG40*AJ40/100 -> 0 | AL40: 5.57 | AP40: =$AL40*AO40/100 -> 0
B41: 4.15 Metal sheet roofing with sand coating on steel (local) | C41: 2.98 | G41: =$C41*F41/100 -> 0 | H41: 2.1 | L41: =$H41*K41/100 -> 0 | M41: 2.34 | Q41: =$M41*P41/100 -> 0 | R41: 2.86 | V41: =$R41*U41/100 -> 0 | W41: 2.23 | AA41: =$W41*Z41/100 -> 0 | AB41: 12.25 | AF41: =$AB41*AE41/100 -> 0 | AG41: 4.87 | AK41: =$AG41*AJ41/100 -> 0 | AL41: 4.36 | AP41: =$AL41*AO41/100 -> 0
A42: 5 | B42: Joinery | G42: =$C42*F42/100 -> 0 | L42: =$H42*K42/100 -> 0 | Q42: =$M42*P42/100 -> 0 | V42: =$R42*U42/100 -> 0 | AA42: =$W42*Z42/100 -> 0 | AF42: =$AB42*AE42/100 -> 0 | AK42: =$AG42*AJ42/100 -> 0 | AP42: =$AL42*AO42/100 -> 0
B43: 5.1 Internal wooden door made of Low quality wood | C43: 0.51 | D43: =MAX(C43:C49) -> 3.98 | E43: =MIN(C43:C49) -> 0.51 | G43: =$C43*F43/100 -> 0 | H43: 0.81 | I43: =MAX(H43:H49) -> 5.19 | J43: =MIN(H43:H49) -> 0.81 | L43: =$H43*K43/100 -> 0 | M43: 0.89 | N43: =MAX(M43:M49) -> 5.04 | O43: =MIN(M43:M49) -> 0.89 | Q43: =$M43*P43/100 -> 0 | R43: 0.74 | S43: =MAX(R43:R49) -> 3.29 | T43: =MIN(R43:R49) -> 0.74 | V43: =$R43*U43/100 -> 0 | W43: 0.07 | X43: =MAX(W43:W49) -> 0.44 | Y43: =MIN(W43:W49) -> 0.07 | AA43: =$W43*Z43/100 -> 0 | AB43: 0.61 | AC43: =MAX(AB43:AB49) -> 3.89 | AD43: =MIN(AB43:AB49) -> 0.61 | AF43: =$AB43*AE43/100 -> 0 | AG43: 1.47 | AH43: =MAX(AG43:AG49) -> 9.43 | AI43: =MIN(AG43:AG49) -> 1.47 | AK43: =$AG43*AJ43/100 -> 0 | AL43: 0.04 | AM43: =MAX(AL43:AL49) -> 0.23 | AN43: =MIN(AL43:AL49) -> 0.04 | AP43: =$AL43*AO43/100 -> 0
B44: 5.2 As item No.1 above but made of medium Quality wood | C44: 0.73 | G44: =$C44*F44/100 -> 0 | H44: 0.95 | L44: =$H44*K44/100 -> 0 | M44: 1.02 | Q44: =$M44*P44/100 -> 0 | R44: 0.82 | V44: =$R44*U44/100 -> 0 | W44: 0.08 | AA44: =$W44*Z44/100 -> 0 | AB44: 0.71 | AF44: =$AB44*AE44/100 -> 0 | AG44: 1.72 | AK44: =$AG44*AJ44/100 -> 0 | AL44: 0.04 | AP44: =$AL44*AO44/100 -> 0
B45: 5.3 As item No.2 above but with built-in cup board | C45: 2.2 | G45: =$C45*F45/100 -> 0 | H45: 1.04 | L45: =$H45*K45/100 -> 0 | M45: 1.1 | Q45: =$M45*P45/100 -> 0 | R45: 0.88 | V45: =$R45*U45/100 -> 0 | W45: 0.09 | AA45: =$W45*Z45/100 -> 0 | AB45: 0.78 | AF45: =$AB45*AE45/100 -> 0 | AG45: 1.88 | AK45: =$AG45*AJ45/100 -> 0 | AL45: 0.05 | AP45: =$AL45*AO45/100 -> 0
B46: 5.4 As item No.1 above but made of Quality wood | C46: 1.36 | G46: =$C46*F46/100 -> 0 | H46: 1.78 | L46: =$H46*K46/100 -> 0 | M46: 1.8 | Q46: =$M46*P46/100 -> 0 | R46: 1.31 | V46: =$R46*U46/100 -> 0 | W46: 0.15 | AA46: =$W46*Z46/100 -> 0 | AB46: 1.33 | AF46: =$AB46*AE46/100 -> 0 | AG46: 3.23 | AK46: =$AG46*AJ46/100 -> 0 | AL46: 0.08 | AP46: =$AL46*AO46/100 -> 0
B47: 5.5 As item No.4 above but with built-in cup board | C47: 3.08 | G47: =$C47*F47/100 -> 0 | H47: 4.02 | L47: =$H47*K47/100 -> 0 | M47: 3.93 | Q47: =$M47*P47/100 -> 0 | R47: 2.61 | V47: =$R47*U47/100 -> 0 | W47: 0.34 | AA47: =$W47*Z47/100 -> 0 | AB47: 3.01 | AF47: =$AB47*AE47/100 -> 0 | AG47: 7.31 | AK47: =$AG47*AJ47/100 -> 0 | AL47: 0.18 | AP47: =$AL47*AO47/100 -> 0
B48: 5.6 As item No.1 above but made of best Quality wood | C48: 2.26 | G48: =$C48*F48/100 -> 0 | H48: 2.94 | L48: =$H48*K48/100 -> 0 | M48: 2.91 | Q48: =$M48*P48/100 -> 0 | R48: 1.99 | V48: =$R48*U48/100 -> 0 | W48: 0.25 | AA48: =$W48*Z48/100 -> 0 | AB48: 2.21 | AF48: =$AB48*AE48/100 -> 0 | AG48: 5.35 | AK48: =$AG48*AJ48/100 -> 0 | AL48: 0.13 | AP48: =$AL48*AO48/100 -> 0
B49: 5.7 As item No.6 above but with built-in cup board | C49: 3.98 | G49: =$C49*F49/100 -> 0 | H49: 5.19 | L49: =$H49*K49/100 -> 0 | M49: 5.04 | Q49: =$M49*P49/100 -> 0 | R49: 3.29 | V49: =$R49*U49/100 -> 0 | W49: 0.44 | AA49: =$W49*Z49/100 -> 0 | AB49: 3.89 | AF49: =$AB49*AE49/100 -> 0 | AG49: 9.43 | AK49: =$AG49*AJ49/100 -> 0 | AL49: 0.23 | AP49: =$AL49*AO49/100 -> 0
A50: 6 | B50: Metal Works | G50: =$C50*F50/100 -> 0 | L50: =$H50*K50/100 -> 0 | Q50: =$M50*P50/100 -> 0 | V50: =$R50*U50/100 -> 0 | AA50: =$W50*Z50/100 -> 0 | AF50: =$AB50*AE50/100 -> 0 | AK50: =$AG50*AJ50/100 -> 0 | AP50: =$AL50*AO50/100 -> 0
B51: 6.1 LTZ or RHS profile for external openings with clear glass | C51: 2.02 | D51: =MAX(C51:C63) -> 2.9 | E51: =MIN(C51:C63) -> 1.66 | G51: =$C51*F51/100 -> 0 | H51: 1.62 | I51: =MAX(H51:H63) -> 2.29 | J51: =MIN(H51:H63) -> 1.35 | L51: =$H51*K51/100 -> 0 | M51: 1.2 | N51: =MAX(M51:M63) -> 1.63 | O51: =MIN(M51:M63) -> 1.03 | Q51: =$M51*P51/100 -> 0 | R51: 2.03 | S51: =MAX(R51:R63) -> 3.02 | T51: =MIN(R51:R63) -> 1.63 | V51: =$R51*U51/100 -> 0 | W51: 0.66 | X51: =MAX(W51:W63) -> 0.96 | Y51: =MIN(W51:W63) -> 0.54 | AA51: =$W51*Z51/100 -> 0 | AB51: 0.73 | AC51: =MAX(AB51:AB63) -> 1.18 | AD51: =MIN(AB51:AB63) -> 0.55 | AF51: =$AB51*AE51/100 -> 0 | AG51: 0.58 | AH51: =MAX(AG51:AG63) -> 0.88 | AI51: =MIN(AG51:AG63) -> 0.47 | AK51: =$AG51*AJ51/100 -> 0 | AL51: 0.61 | AM51: =MAX(AL51:AL63) -> 0.99 | AN51: =MIN(AL51:AL63) -> 0.46 | AP51: =$AL51*AO51/100 -> 0
B52: 6.2 LTZ with 4mm- frosted glass | C52: 2.07 | G52: =$C52*F52/100 -> 0 | H52: 1.66 | L52: =$H52*K52/100 -> 0 | M52: 1.23 | Q52: =$M52*P52/100 -> 0 | R52: 2.09 | V52: =$R52*U52/100 -> 0 | W52: 0.68 | AA52: =$W52*Z52/100 -> 0 | AB52: 0.76 | AF52: =$AB52*AE52/100 -> 0 | AG52: 0.6 | AK52: =$AG52*AJ52/100 -> 0 | AL52: 0.63 | AP52: =$AL52*AO52/100 -> 0
B53: 6.3 Ditto but with 4mm-tinted glass | C53: 2.07 | G53: =$C53*F53/100 -> 0 | H53: 1.66 | L53: =$H53*K53/100 -> 0 | M53: 1.22 | Q53: =$M53*P53/100 -> 0 | R53: 2.08 | V53: =$R53*U53/100 -> 0 | W53: 0.68 | AA53: =$W53*Z53/100 -> 0 | AB53: 0.76 | AF53: =$AB53*AE53/100 -> 0 | AG53: 0.6 | AK53: =$AG53*AJ53/100 -> 0 | AL53: 0.63 | AP53: =$AL53*AO53/100 -> 0
B54: 6.4 Ditto but with 6mm-tinted glass | C54: 2.27 | G54: =$C54*F54/100 -> 0 | H54: 1.81 | L54: =$H54*K54/100 -> 0 | M54: 1.32 | Q54: =$M54*P54/100 -> 0 | R54: 2.31 | V54: =$R54*U54/100 -> 0 | W54: 0.75 | AA54: =$W54*Z54/100 -> 0 | AB54: 0.86 | AF54: =$AB54*AE54/100 -> 0 | AG54: 0.67 | AK54: =$AG54*AJ54/100 -> 0 | AL54: 0.72 | AP54: =$AL54*AO54/100 -> 0
B55: 6.5 Secco profile for external openings with clear glass | C55: 1.66 | G55: =$C55*F55/100 -> 0 | H55: 1.35 | L55: =$H55*K55/100 -> 0 | M55: 1.03 | Q55: =$M55*P55/100 -> 0 | R55: 1.63 | V55: =$R55*U55/100 -> 0 | W55: 0.54 | AA55: =$W55*Z55/100 -> 0 | AB55: 0.55 | AF55: =$AB55*AE55/100 -> 0 | AG55: 0.47 | AK55: =$AG55*AJ55/100 -> 0 | AL55: 0.46 | AP55: =$AL55*AO55/100 -> 0
B56: 6.6 Secco with 4mm-frosted glass | C56: 1.7 | G56: =$C56*F56/100 -> 0 | H56: 1.37 | L56: =$H56*K56/100 -> 0 | M56: 1.04 | Q56: =$M56*P56/100 -> 0 | R56: 1.66 | V56: =$R56*U56/100 -> 0 | W56: 0.56 | AA56: =$W56*Z56/100 -> 0 | AB56: 0.57 | AF56: =$AB56*AE56/100 -> 0 | AG56: 0.48 | AK56: =$AG56*AJ56/100 -> 0 | AL56: 0.47 | AP56: =$AL56*AO56/100 -> 0
B57: 6.7 Ditto but with 4mm-tinted glass | C57: 1.71 | G57: =$C57*F57/100 -> 0 | H57: 1.38 | L57: =$H57*K57/100 -> 0 | M57: 1.05 | Q57: =$M57*P57/100 -> 0 | R57: 1.68 | V57: =$R57*U57/100 -> 0 | W57: 0.56 | AA57: =$W57*Z57/100 -> 0 | AB57: 0.58 | AF57: =$AB57*AE57/100 -> 0 | AG57: 0.48 | AK57: =$AG57*AJ57/100 -> 0 | AL57: 0.48 | AP57: =$AL57*AO57/100 -> 0
B58: 6.8 Ditto but with 6mm-tinted glass | C58: 1.91 | G58: =$C58*F58/100 -> 0 | H58: 1.54 | L58: =$H58*K58/100 -> 0 | M58: 1.15 | Q58: =$M58*P58/100 -> 0 | R58: 1.9 | V58: =$R58*U58/100 -> 0 | W58: 0.63 | AA58: =$W58*Z58/100 -> 0 | AB58: 0.68 | AF58: =$AB58*AE58/100 -> 0 | AG58: 0.55 | AK58: =$AG58*AJ58/100 -> 0 | AL58: 0.56 | AP58: =$AL58*AO58/100 -> 0
B59: 6.9 Imitation with clear glass | C59: 2.39 | G59: =$C59*F59/100 -> 0 | H59: 1.88 | L59: =$H59*K59/100 -> 0 | M59: 1.33 | Q59: =$M59*P59/100 -> 0 | R59: 2.33 | V59: =$R59*U59/100 -> 0 | W59: 0.76 | AA59: =$W59*Z59/100 -> 0 | AB59: 0.87 | AF59: =$AB59*AE59/100 -> 0 | AG59: 0.67 | AK59: =$AG59*AJ59/100 -> 0 | AL59: 0.72 | AP59: =$AL59*AO59/100 -> 0
B60: 6.10 Imitation with 4mm frosted glass | C60: 2.41 | G60: =$C60*F60/100 -> 0 | H60: 1.9 | L60: =$H60*K60/100 -> 0 | M60: 1.34 | Q60: =$M60*P60/100 -> 0 | R60: 2.36 | V60: =$R60*U60/100 -> 0 | W60: 0.76 | AA60: =$W60*Z60/100 -> 0 | AB60: 0.88 | AF60: =$AB60*AE60/100 -> 0 | AG60: 0.68 | AK60: =$AG60*AJ60/100 -> 0 | AL60: 0.74 | AP60: =$AL60*AO60/100 -> 0
B61: 6.11 Imitation with 4mm tinted glass | C61: 2.41 | G61: =$C61*F61/100 -> 0 | H61: 1.9 | L61: =$H61*K61/100 -> 0 | M61: 1.34 | Q61: =$M61*P61/100 -> 0 | R61: 2.36 | V61: =$R61*U61/100 -> 0 | W61: 0.76 | AA61: =$W61*Z61/100 -> 0 | AB61: 0.88 | AF61: =$AB61*AE61/100 -> 0 | AG61: 0.68 | AK61: =$AG61*AJ61/100 -> 0 | AL61: 0.73 | AP61: =$AL61*AO61/100 -> 0
B62: 6.12 Imitation with 6mm tinted glass | C62: 2.5 | G62: =$C62*F62/100 -> 0 | H62: 1.97 | L62: =$H62*K62/100 -> 0 | M62: 1.38 | Q62: =$M62*P62/100 -> 0 | R62: 2.46 | V62: =$R62*U62/100 -> 0 | W62: 0.79 | AA62: =$W62*Z62/100 -> 0 | AB62: 0.93 | AF62: =$AB62*AE62/100 -> 0 | AG62: 0.71 | AK62: =$AG62*AJ62/100 -> 0 | AL62: 0.77 | AP62: =$AL62*AO62/100 -> 0
B63: 6.13 Aluminium profile for external opening | C63: 2.9 | G63: =$C63*F63/100 -> 0 | H63: 2.29 | L63: =$H63*K63/100 -> 0 | M63: 1.63 | Q63: =$M63*P63/100 -> 0 | R63: 3.02 | V63: =$R63*U63/100 -> 0 | W63: 0.96 | AA63: =$W63*Z63/100 -> 0 | AB63: 1.18 | AF63: =$AB63*AE63/100 -> 0 | AG63: 0.88 | AK63: =$AG63*AJ63/100 -> 0 | AL63: 0.99 | AP63: =$AL63*AO63/100 -> 0
A64: 7 | B64: Floor Finish | G64: =$C64*F64/100 -> 0 | L64: =$H64*K64/100 -> 0 | Q64: =$M64*P64/100 -> 0 | V64: =$R64*U64/100 -> 0 | AA64: =$W64*Z64/100 -> 0 | AF64: =$AB64*AE64/100 -> 0 | AK64: =$AG64*AJ64/100 -> 0 | AP64: =$AL64*AO64/100 -> 0
B65: 7.1 Cement Screed | C65: 0.37 | D65: =MAX(C65:C82) -> 4.49 | E65: =MIN(C65:C82) -> 0.37 | G65: =$C65*F65/100 -> 0 | H65: 0.4 | I65: =MAX(H65:H82) -> 5.07 | J65: =MIN(H65:H82) -> 0.4 | L65: =$H65*K65/100 -> 0 | M65: 0.55 | N65: =MAX(M65:M82) -> 5.07 | O65: =MIN(M65:M82) -> 0.55 | Q65: =$M65*P65/100 -> 0 | R65: 0.34 | S65: =MAX(R65:R82) -> 5.19 | T65: =MIN(R65:R82) -> 0.34 | V65: =$R65*U65/100 -> 0 | W65: 0.18 | X65: =MAX(W65:W82) -> 1.53 | Y65: =MIN(W65:W82) -> 0.18 | AA65: =$W65*Z65/100 -> 0 | AB65: 0.43 | AC65: =MAX(AB65:AB82) -> 3.7 | AD65: =MIN(AB65:AB82) -> 0.43 | AF65: =$AB65*AE65/100 -> 0 | AG65: 0.39 | AH65: =MAX(AG65:AG82) -> 3.55 | AI65: =MIN(AG65:AG82) -> 0.39 | AK65: =$AG65*AJ65/100 -> 0 | AL65: 0.3 | AM65: =MAX(AL65:AL82) -> 3.63 | AN65: =MIN(AL65:AL82) -> 0.3 | AP65: =$AL65*AO65/100 -> 0
B66: 7.2 Cement Tile | C66: 0.68 | G66: =$C66*F66/100 -> 0 | H66: 0.76 | L66: =$H66*K66/100 -> 0 | M66: 0.89 | Q66: =$M66*P66/100 -> 0 | R66: 0.71 | V66: =$R66*U66/100 -> 0 | W66: 0.28 | AA66: =$W66*Z66/100 -> 0 | AB66: 0.68 | AF66: =$AB66*AE66/100 -> 0 | AG66: 0.64 | AK66: =$AG66*AJ66/100 -> 0 | AL66: 0.55 | AP66: =$AL66*AO66/100 -> 0
B67: 7.3 Terrazzo Tile | C67: 0.94 | G67: =$C67*F67/100 -> 0 | H67: 1.05 | L67: =$H67*K67/100 -> 0 | M67: 1.18 | Q67: =$M67*P67/100 -> 0 | R67: 1.01 | V67: =$R67*U67/100 -> 0 | W67: 0.36 | AA67: =$W67*Z67/100 -> 0 | AB67: 0.88 | AF67: =$AB67*AE67/100 -> 0 | AG67: 0.83 | AK67: =$AG67*AJ67/100 -> 0 | AL67: 0.76 | AP67: =$AL67*AO67/100 -> 0
B68: 7.4 PVC tile | C68: 1.09 | G68: =$C68*F68/100 -> 0 | H68: 1.22 | L68: =$H68*K68/100 -> 0 | M68: 1.34 | Q68: =$M68*P68/100 -> 0 | R68: 1.19 | V68: =$R68*U68/100 -> 0 | W68: 0.41 | AA68: =$W68*Z68/100 -> 0 | AB68: 1 | AF68: =$AB68*AE68/100 -> 0 | AG68: 0.94 | AK68: =$AG68*AJ68/100 -> 0 | AL68: 0.88 | AP68: =$AL68*AO68/100 -> 0
B69: 7.5 Ceramic medium quality Porcelain | C69: 1.22 | G69: =$C69*F69/100 -> 0 | H69: 1.37 | L69: =$H69*K69/100 -> 0 | M69: 1.48 | Q69: =$M69*P69/100 -> 0 | R69: 1.34 | V69: =$R69*U69/100 -> 0 | W69: 0.46 | AA69: =$W69*Z69/100 -> 0 | AB69: 1.11 | AF69: =$AB69*AE69/100 -> 0 | AG69: 1.05 | AK69: =$AG69*AJ69/100 -> 0 | AL69: 0.99 | AP69: =$AL69*AO69/100 -> 0
B70: 7.6 Ceramic best quality | C70: 1.86 | G70: =$C70*F70/100 -> 0 | H70: 2.09 | L70: =$H70*K70/100 -> 0 | M70: 2.18 | Q70: =$M70*P70/100 -> 0 | R70: 2.1 | V70: =$R70*U70/100 -> 0 | W70: 0.67 | AA70: =$W70*Z70/100 -> 0 | AB70: 1.61 | AF70: =$AB70*AE70/100 -> 0 | AG70: 1.54 | AK70: =$AG70*AJ70/100 -> 0 | AL70: 1.51 | AP70: =$AL70*AO70/100 -> 0
B71: 7.7 Porcelain | C71: 1.64 | G71: =$C71*F71/100 -> 0 | H71: 1.83 | L71: =$H71*K71/100 -> 0 | M71: 1.87 | Q71: =$M71*P71/100 -> 0 | R71: 1.76 | V71: =$R71*U71/100 -> 0 | W71: 0.57 | AA71: =$W71*Z71/100 -> 0 | AB71: 1.39 | AF71: =$AB71*AE71/100 -> 0 | AG71: 1.32 | AK71: =$AG71*AJ71/100 -> 0 | AL71: 1.27 | AP71: =$AL71*AO71/100 -> 0
B72: 7.8 Mosaic | C72: 2.25 | G72: =$C72*F72/100 -> 0 | H72: 2.53 | L72: =$H72*K72/100 -> 0 | M72: 2.61 | Q72: =$M72*P72/100 -> 0 | R72: 2.55 | V72: =$R72*U72/100 -> 0 | W72: 0.8 | AA72: =$W72*Z72/100 -> 0 | AB72: 1.92 | AF72: =$AB72*AE72/100 -> 0 | AG72: 1.83 | AK72: =$AG72*AJ72/100 -> 0 | AL72: 1.82 | AP72: =$AL72*AO72/100 -> 0
B73: 7.9 Marble chip lower quality | C73: 1.96 | G73: =$C73*F73/100 -> 0 | H73: 2.2 | L73: =$H73*K73/100 -> 0 | M73: 2.29 | Q73: =$M73*P73/100 -> 0 | R73: 2.21 | V73: =$R73*U73/100 -> 0 | W73: 0.7 | AA73: =$W73*Z73/100 -> 0 | AB73: 1.69 | AF73: =$AB73*AE73/100 -> 0 | AG73: 1.61 | AK73: =$AG73*AJ73/100 -> 0 | AL73: 1.58 | AP73: =$AL73*AO73/100 -> 0
B74: 7.10 Marble chip best quality | C74: 2.33 | G74: =$C74*F74/100 -> 0 | H74: 2.63 | L74: =$H74*K74/100 -> 0 | M74: 2.7 | Q74: =$M74*P74/100 -> 0 | R74: 2.65 | V74: =$R74*U74/100 -> 0 | W74: 0.82 | AA74: =$W74*Z74/100 -> 0 | AB74: 1.99 | AF74: =$AB74*AE74/100 -> 0 | AG74: 1.9 | AK74: =$AG74*AJ74/100 -> 0 | AL74: 1.89 | AP74: =$AL74*AO74/100 -> 0
B75: 7.11 Harar marble | C75: 2.7 | G75: =$C75*F75/100 -> 0 | H75: 3.05 | L75: =$H75*K75/100 -> 0 | M75: 3.11 | Q75: =$M75*P75/100 -> 0 | R75: 3.09 | V75: =$R75*U75/100 -> 0 | W75: 0.95 | AA75: =$W75*Z75/100 -> 0 | AB75: 2.28 | AF75: =$AB75*AE75/100 -> 0 | AG75: 2.18 | AK75: =$AG75*AJ75/100 -> 0 | AL75: 2.19 | AP75: =$AL75*AO75/100 -> 0
B76: 7.12 Mankush marble | C76: 3.79 | G76: =$C76*F76/100 -> 0 | H76: 4.28 | L76: =$H76*K76/100 -> 0 | M76: 4.3 | Q76: =$M76*P76/100 -> 0 | R76: 4.37 | V76: =$R76*U76/100 -> 0 | W76: 1.3 | AA76: =$W76*Z76/100 -> 0 | AB76: 3.14 | AF76: =$AB76*AE76/100 -> 0 | AG76: 3.01 | AK76: =$AG76*AJ76/100 -> 0 | AL76: 3.07 | AP76: =$AL76*AO76/100 -> 0
B77: 7.13 Parquet lower quality on screed | C77: 1.99 | G77: =$C77*F77/100 -> 0 | H77: 2.24 | L77: =$H77*K77/100 -> 0 | M77: 2.33 | Q77: =$M77*P77/100 -> 0 | R77: 2.25 | V77: =$R77*U77/100 -> 0 | W77: 0.71 | AA77: =$W77*Z77/100 -> 0 | AB77: 1.72 | AF77: =$AB77*AE77/100 -> 0 | AG77: 1.64 | AK77: =$AG77*AJ77/100 -> 0 | AL77: 1.61 | AP77: =$AL77*AO77/100 -> 0
... B82: 7.18 Granite | C82: 2.86 | G82: =$C82*F82/100 -> 0 | H82: 3.23 | L82: =$H82*K82/100 -> 0 | M82: 3.28 | Q82: =$M82*P82/100 -> 0 | R82: 3.28 | V82: =$R82*U82/100 -> 0 | W82: 1 | AA82: =$W82*Z82/100 -> 0 | AB82: 2.41 | AF82: =$AB82*AE82/100 -> 0 | AG82: 2.3 | AK82: =$AG82*AJ82/100 -> 0 | AL82: 2.32 | AP82: =$AL82*AO82/100 -> 0
A83: 8 | B83: Wall Finish | G83: =$C83*F83/100 -> 0 | L83: =$H83*K83/100 -> 0 | Q83: =$M83*P83/100 -> 0 | V83: =$R83*U83/100 -> 0 | AA83: =$W83*Z83/100 -> 0 | AF83: =$AB83*AE83/100 -> 0 | AK83: =$AG83*AJ83/100 -> 0 | AP83: =$AL83*AO83/100 -> 0
B84: 8.1 Internal | G84: =$C84*F84/100 -> 0 | L84: =$H84*K84/100 -> 0 | Q84: =$M84*P84/100 -> 0 | V84: =$R84*U84/100 -> 0 | AA84: =$W84*Z84/100 -> 0 | AF84: =$AB84*AE84/100 -> 0 | AK84: =$AG84*AJ84/100 -> 0 | AP84: =$AL84*AO84/100 -> 0
B85: 8.1.1 plasterd | C85: 1.18 | D85: =MAX(C85:C101) -> 11.23 | E85: =MIN(C85:C101) -> 0.52 | G85: =$C85*F85/100 -> 0 | H85: 0.9 | I85: =MAX(H85:H101) -> 8.56 | J85: =MIN(H85:H101) -> 0.4 | L85: =$H85*K85/100 -> 0 | M85: 0.98 | N85: =MAX(M85:M101) -> 9.31 | O85: =MIN(M85:M101) -> 0.43 | Q85: =$M85*P85/100 -> 0 | R85: 0.7 | S85: =MAX(R85:R101) -> 6.64 | T85: =MIN(R85:R101) -> 0.31 | V85: =$R85*U85/100 -> 0 | W85: 0.33 | X85: =MAX(W85:W101) -> 3.12 | Y85: =MIN(W85:W101) -> 0.15 | AA85: =$W85*Z85/100 -> 0 | AB85: 0.65 | AC85: =MAX(AB85:AB101) -> 3.1 | AD85: =MIN(AB85:AB101) -> 0.49 | AF85: =$AB85*AE85/100 -> 0 | AG85: 0.8 | AH85: =MAX(AG85:AG101) -> 7.64 | AI85: =MIN(AG85:AG101) -> 0.36 | AK85: =$AG85*AJ85/100 -> 0 | AL85: 1.25 | AM85: =MAX(AL85:AL101) -> 11.87 | AN85: =MIN(AL85:AL101) -> 0.55 | AP85: =$AL85*AO85/100 -> 0
B86: 8.1.2 Plasterd and painted | C86: 1.59 | G86: =$C86*F86/100 -> 0 | H86: 1.21 | L86: =$H86*K86/100 -> 0 | M86: 1.32 | Q86: =$M86*P86/100 -> 0 | R86: 0.94 | V86: =$R86*U86/100 -> 0 | W86: 0.44 | AA86: =$W86*Z86/100 -> 0 | AB86: 0.75 | AF86: =$AB86*AE86/100 -> 0 | AG86: 1.08 | AK86: =$AG86*AJ86/100 -> 0 | AL86: 1.68 | AP86: =$AL86*AO86/100 -> 0
B87: 8.1.3 Pointed HCB | C87: 0.52 | G87: =$C87*F87/100 -> 0 | H87: 0.4 | L87: =$H87*K87/100 -> 0 | M87: 0.43 | Q87: =$M87*P87/100 -> 0 | R87: 0.31 | V87: =$R87*U87/100 -> 0 | W87: 0.15 | AA87: =$W87*Z87/100 -> 0 | AB87: 0.49 | AF87: =$AB87*AE87/100 -> 0 | AG87: 0.36 | AK87: =$AG87*AJ87/100 -> 0 | AL87: 0.55 | AP87: =$AL87*AO87/100 -> 0
B88: 8.1.4 Pointed dressed stone | C88: 0.67 | G88: =$C88*F88/100 -> 0 | H88: 0.51 | L88: =$H88*K88/100 -> 0 | M88: 0.56 | Q88: =$M88*P88/100 -> 0 | R88: 0.4 | V88: =$R88*U88/100 -> 0 | W88: 0.19 | AA88: =$W88*Z88/100 -> 0 | AB88: 0.52 | AF88: =$AB88*AE88/100 -> 0 | AG88: 0.46 | AK88: =$AG88*AJ88/100 -> 0 | AL88: 0.71 | AP88: =$AL88*AO88/100 -> 0
B89: 8.1.5 Pointed brick | C89: 0.84 | G89: =$C89*F89/100 -> 0 | H89: 0.64 | L89: =$H89*K89/100 -> 0 | M89: 0.7 | Q89: =$M89*P89/100 -> 0 | R89: 0.5 | V89: =$R89*U89/100 -> 0 | W89: 0.23 | AA89: =$W89*Z89/100 -> 0 | AB89: 0.56 | AF89: =$AB89*AE89/100 -> 0 | AG89: 0.57 | AK89: =$AG89*AJ89/100 -> 0 | AL89: 0.89 | AP89: =$AL89*AO89/100 -> 0
B90: 8.1.6 Plasterd and Addis I wall paper | C90: 4.07 | G90: =$C90*F90/100 -> 0 | H90: 3.1 | L90: =$H90*K90/100 -> 0 | M90: 3.38 | Q90: =$M90*P90/100 -> 0 | R90: 2.41 | V90: =$R90*U90/100 -> 0 | W90: 1.13 | AA90: =$W90*Z90/100 -> 0 | AB90: 1.35 | AF90: =$AB90*AE90/100 -> 0 | AG90: 2.77 | AK90: =$AG90*AJ90/100 -> 0 | AL90: 4.31 | AP90: =$AL90*AO90/100 -> 0
B91: 8.1.7 Mosaic | C91: 7.73 | G91: =$C91*F91/100 -> 0 | H91: 5.89 | L91: =$H91*K91/100 -> 0 | M91: 6.41 | Q91: =$M91*P91/100 -> 0 | R91: 4.57 | V91: =$R91*U91/100 -> 0 | W91: 2.15 | AA91: =$W91*Z91/100 -> 0 | AB91: 2.24 | AF91: =$AB91*AE91/100 -> 0 | AG91: 5.26 | AK91: =$AG91*AJ91/100 -> 0 | AL91: 8.17 | AP91: =$AL91*AO91/100 -> 0
B92: 8.1.8a Imported, high quality ceramic | C92: 6.35 | G92: =$C92*F92/100 -> 0 | H92: 4.84 | L92: =$H92*K92/100 -> 0 | M92: 5.26 | Q92: =$M92*P92/100 -> 0 | R92: 3.75 | V92: =$R92*U92/100 -> 0 | W92: 1.77 | AA92: =$W92*Z92/100 -> 0 | AB92: 1.91 | AF92: =$AB92*AE92/100 -> 0 | AG92: 4.32 | AK92: =$AG92*AJ92/100 -> 0 | AL92: 6.71 | AP92: =$AL92*AO92/100 -> 0
B93: 8.1.8b Imported, quality ceramic | C93: 4 | G93: =$C93*F93/100 -> 0 | H93: 3.05 | L93: =$H93*K93/100 -> 0 | M93: 3.32 | Q93: =$M93*P93/100 -> 0 | R93: 2.37 | V93: =$R93*U93/100 -> 0 | W93: 1.11 | AA93: =$W93*Z93/100 -> 0 | AB93: 1.33 | AF93: =$AB93*AE93/100 -> 0 | AG93: 2.72 | AK93: =$AG93*AJ93/100 -> 0 | AL93: 4.23 | AP93: =$AL93*AO93/100 -> 0
B94: 8.1.8c Imported, medium quality ceramic | C94: 2.95 | G94: =$C94*F94/100 -> 0 | H94: 2.25 | L94: =$H94*K94/100 -> 0 | M94: 2.45 | Q94: =$M94*P94/100 -> 0 | R94: 1.75 | V94: =$R94*U94/100 -> 0 | W94: 0.82 | AA94: =$W94*Z94/100 -> 0 | AB94: 1.08 | AF94: =$AB94*AE94/100 -> 0 | AG94: 2.01 | AK94: =$AG94*AJ94/100 -> 0 | AL94: 3.12 | AP94: =$AL94*AO94/100 -> 0
B95: 8.1.8d Lower quality ceramic | C95: 2.91 | G95: =$C95*F95/100 -> 0 | H95: 2.22 | L95: =$H95*K95/100 -> 0 | M95: 2.41 | Q95: =$M95*P95/100 -> 0 | R95: 1.72 | V95: =$R95*U95/100 -> 0 | W95: 0.81 | AA95: =$W95*Z95/100 -> 0 | AB95: 1.07 | AF95: =$AB95*AE95/100 -> 0 | AG95: 1.98 | AK95: =$AG95*AJ95/100 -> 0 | AL95: 3.08 | AP95: =$AL95*AO95/100 -> 0
B96: 8.1.9 Pointed and painted HCB | C96: 0.94 | G96: =$C96*F96/100 -> 0 | H96: 0.71 | L96: =$H96*K96/100 -> 0 | M96: 0.78 | Q96: =$M96*P96/100 -> 0 | R96: 0.55 | V96: =$R96*U96/100 -> 0 | W96: 0.26 | AA96: =$W96*Z96/100 -> 0 | AB96: 0.59 | AF96: =$AB96*AE96/100 -> 0 | AG96: 0.64 | AK96: =$AG96*AJ96/100 -> 0 | AL96: 0.99 | AP96: =$AL96*AO96/100 -> 0
B97: 8.1.10 Pointed and painted Brick | C97: 1.25 | G97: =$C97*F97/100 -> 0 | H97: 0.96 | L97: =$H97*K97/100 -> 0 | M97: 1.04 | Q97: =$M97*P97/100 -> 0 | R97: 0.74 | V97: =$R97*U97/100 -> 0 | W97: 0.35 | AA97: =$W97*Z97/100 -> 0 | AB97: 0.66 | AF97: =$AB97*AE97/100 -> 0 | AG97: 0.85 | AK97: =$AG97*AJ97/100 -> 0 | AL97: 1.32 | AP97: =$AL97*AO97/100 -> 0
... B101: 8.1.15 Granite | C101: 10.51 | G101: =$C101*F101/100 -> 0 | H101: 8.01 | L101: =$H101*K101/100 -> 0 | M101: 8.71 | Q101: =$M101*P101/100 -> 0 | R101: 6.22 | V101: =$R101*U101/100 -> 0 | W101: 2.92 | AA101: =$W101*Z101/100 -> 0 | AB101: 2.92 | AF101: =$AB101*AE101/100 -> 0 | AG101: 7.15 | AK101: =$AG101*AJ101/100 -> 0 | AL101: 11.11 | AP101: =$AL101*AO101/100 -> 0
B102: 8.2 External | G102: =$C102*F102/100 -> 0 | L102: =$H102*K102/100 -> 0 | Q102: =$M102*P102/100 -> 0 | V102: =$R102*U102/100 -> 0 | AA102: =$W102*Z102/100 -> 0 | AF102: =$AB102*AE102/100 -> 0 | AK102: =$AG102*AJ102/100 -> 0 | AP102: =$AL102*AO102/100 -> 0
B103: 8.2.1 Plastering | C103: 0.55 | D103: =MAX(C103:C127) -> 5.2 | E103: =MIN(C103:C127) -> 0.24 | G103: =$C103*F103/100 -> 0 | H103: 0.23 | I103: =MAX(H103:H127) -> 2.24 | J103: =MIN(H103:H127) -> 0.1 | L103: =$H103*K103/100 -> 0 | M103: 0.24 | N103: =MAX(M103:M127) -> 2.25 | O103: =MIN(M103:M127) -> 0.11 | Q103: =$M103*P103/100 -> 0 | R103: 0.2 | S103: =MAX(R103:R127) -> 1.87 | T103: =MIN(R103:R127) -> 0.09 | V103: =$R103*U103/100 -> 0 | W103: 0.1 | X103: =MAX(W103:W127) -> 0.97 | Y103: =MIN(W103:W127) -> 0.05 | AA103: =$W103*Z103/100 -> 0 | AB103: 0.16 | AC103: =MAX(AB103:AB127) -> 1.14 | AD103: =MIN(AB103:AB127) -> 0.09 | AF103: =$AB103*AE103/100 -> 0 | AG103: 0.12 | AH103: =MAX(AG103:AG127) -> 0.87 | AI103: =MIN(AG103:AG127) -> 0.08 | AK103: =$AG103*AJ103/100 -> 0 | AL103: 0.11 | AM103: =MAX(AL103:AL127) -> 1.04 | AN103: =MIN(AL103:AL127) -> 0.05 | AP103: =$AL103*AO103/100 -> 0
B104: 8.2.2 Plastering and painting | C104: 0.74 | G104: =$C104*F104/100 -> 0 | H104: 0.32 | L104: =$H104*K104/100 -> 0 | M104: 0.32 | Q104: =$M104*P104/100 -> 0 | R104: 0.26 | V104: =$R104*U104/100 -> 0 | W104: 0.14 | AA104: =$W104*Z104/100 -> 0 | AB104: 0.2 | AF104: =$AB104*AE104/100 -> 0 | AG104: 0.15 | AK104: =$AG104*AJ104/100 -> 0 | AL104: 0.15 | AP104: =$AL104*AO104/100 -> 0
B105: 8.2.3 Pointed HCB | C105: 0.24 | G105: =$C105*F105/100 -> 0 | H105: 0.1 | L105: =$H105*K105/100 -> 0 | M105: 0.11 | Q105: =$M105*P105/100 -> 0 | R105: 0.09 | V105: =$R105*U105/100 -> 0 | W105: 0.05 | AA105: =$W105*Z105/100 -> 0 | AB105: 0.09 | AF105: =$AB105*AE105/100 -> 0 | AG105: 0.08 | AK105: =$AG105*AJ105/100 -> 0 | AL105: 0.05 | AP105: =$AL105*AO105/100 -> 0
B106: 8.2.4 Pointed stone | C106: 0.31 | G106: =$C106*F106/100 -> 0 | H106: 0.13 | L106: =$H106*K106/100 -> 0 | M106: 0.14 | Q106: =$M106*P106/100 -> 0 | R106: 0.11 | V106: =$R106*U106/100 -> 0 | W106: 0.06 | AA106: =$W106*Z106/100 -> 0 | AB106: 0.11 | AF106: =$AB106*AE106/100 -> 0 | AG106: 0.09 | AK106: =$AG106*AJ106/100 -> 0 | AL106: 0.06 | AP106: =$AL106*AO106/100 -> 0
B107: 8.2.5 Pointed ambo cladding | C107: 3.81 | G107: =$C107*F107/100 -> 0 | H107: 1.64 | L107: =$H107*K107/100 -> 0 | M107: 1.65 | Q107: =$M107*P107/100 -> 0 | R107: 1.37 | V107: =$R107*U107/100 -> 0 | W107: 0.71 | AA107: =$W107*Z107/100 -> 0 | AB107: 0.85 | AF107: =$AB107*AE107/100 -> 0 | AG107: 0.65 | AK107: =$AG107*AJ107/100 -> 0 | AL107: 0.76 | AP107: =$AL107*AO107/100 -> 0
B108: 8.2.6 Not pointed ambo cladding | C108: 3.5 | G108: =$C108*F108/100 -> 0 | H108: 1.5 | L108: =$H108*K108/100 -> 0 | M108: 1.51 | Q108: =$M108*P108/100 -> 0 | R108: 1.25 | V108: =$R108*U108/100 -> 0 | W108: 0.65 | AA108: =$W108*Z108/100 -> 0 | AB108: 0.78 | AF108: =$AB108*AE108/100 -> 0 | AG108: 0.6 | AK108: =$AG108*AJ108/100 -> 0 | AL108: 0.7 | AP108: =$AL108*AO108/100 -> 0
...

Sheet Multi-Purposed halls
A2: ITEM NO. | B2: Building components
C3: H | F3: <= | G3: 4 | H3: = | K3: 4.5 | L3: = | O3: 5.5 | P3: = | S3: 6.5 | V3: = | W3: 7.5 | Z3: = | AA3: 8.5 | AD3: = | AE3: 10.5 | AH3: = | AI3: 11.5
A4: 1 | B4: Foundation | C4: Factors | D4: Max | E4: Min | H4: Max | I4: Min | L4: Max | M4: Min | P4: Max | Q4: Min | T4: Max | U4: Min | X4: Max | Y4: Min | AB4: Max | AC4: Min | AF4: Max | AG4: Min
B5: 1.1 Foundation only earthwork | C5: 0.22 | D5: =MAX(C5:C16) -> 4.2 | E5: =MIN(C5:C16) -> 0.22 | G5: =$C5*F5/100 -> 0 | H5: =MAX(C5:C16) -> 4.2 | I5: =MIN(C5:C16) -> 0.22 | K5: =$C5*H5/100 -> 0.00924 | L5: 4.2 | M5: 0.22 | O5: =$C5*N5/100 -> 0 | P5: 4.2 | Q5: 0.22 | S5: =$C5*P5/100 -> 0.00924 | T5: 4.2 | U5: 0.22 | W5: =$C5*V5/100 -> 0 | X5: 4.2 | Y5: 0.22 | AA5: =$C5*Z5/100 -> 0 | AB5: 4.2 | AC5: 0.22 | AE5: =$C5*AD5/100 -> 0 | AF5: =MAX(C5:C16) -> 4.2 | AG5: =MIN(C5:C16) -> 0.22 | AI5: =$C5*AH5/100 -> 0
B6: 1.2 a. Earthwortk and masnory | C6: 0.69 | G6: =$C6*F6/100 -> 0 | K6: =$C6*H6/100 -> 0 | O6: =$C6*N6/100 -> 0 | S6: =$C6*P6/100 -> 0 | W6: =$C6*V6/100 -> 0 | AA6: =$C6*Z6/100 -> 0 | AE6: =$C6*AD6/100 -> 0 | AI6: =$C6*AH6/100 -> 0
B7: 1.2 b. AGL and BGL
B8: 1.3 Foundation work in | C8: 2 | G8: =$C8*F8/100 -> 0 | K8: =$C8*H8/100 -> 0 | O8: =$C8*N8/100 -> 0 | S8: =$C8*P8/100 -> 0 | W8: =$C8*V8/100 -> 0 | AA8: =$C8*Z8/100 -> 0 | AE8: =$C8*AD8/100 -> 0 | AI8: =$C8*AH8/100 -> 0
B9: 1.3a. Earthwork
B10: 1.3b. Hard rock
B11: 1.3c. Mass concrete floor slab
B12: 1.3d. R.C grade beam
B13: 1.3e. Masnory BGL and AGL
B14: 1.4 As item No.3 above but with R.C floor slab | C14: 2.87 | G14: =$C14*F14/100 -> 0 | K14: =$C14*H14/100 -> 0 | O14: =$C14*N14/100 -> 0 | S14: =$C14*P14/100 -> 0 | W14: =$C14*V14/100 -> 0 | AA14: =$C14*Z14/100 -> 0 | AE14: =$C14*AD14/100 -> 0 | AI14: =$C14*AH14/100 -> 0
B15: 1.5 As item no 4 above but with R.C footing and foundation column | C15: 3.43 | G15: =$C15*F15/100 -> 0 | K15: =$C15*H15/100 -> 0 | O15: =$C15*N15/100 -> 0 | S15: =$C15*P15/100 -> 0 | W15: =$C15*V15/100 -> 0 | AA15: =$C15*Z15/100 -> 0 | AE15: =$C15*AD15/100 -> 0 | AI15: =$C15*AH15/100 -> 0
B16: 1.6 As item no 5 above but for R.C roof slab | C16: 4.2 | O16: =$C16*N16/100 -> 0
A17: 2 | B17: Structure | G17: =$C17*F17/100 -> 0 | K17: =$C17*H17/100 -> 0 | O17: =$C17*N17/100 -> 0 | S17: =$C17*P17/100 -> 0 | W17: =$C17*V17/100 -> 0 | AA17: =$C17*Z17/100 -> 0 | AE17: =$C17*AD17/100 -> 0 | AI17: =$C17*AH17/100 -> 0
B18: 2.1 .R.C structure (Elevation colums and tie beam) | C18: 1.38 | D18: =MAX(C18:C20) -> 10.76 | E18: =MIN(C18:C20) -> 1.38 | G18: =$C18*F18/100 -> 0 | H18: =MAX(C18:C20) -> 10.76 | I18: =MIN(C18:C20) -> 1.38 | K18: =$C18*H18/100 -> 0.148488 | L18: 10.76 | M18: 1.38 | O18: =$C18*N18/100 -> 0 | P18: 10.76 | Q18: 1.38 | S18: =$C18*P18/100 -> 0.148488 | T18: 10.76 | U18: 1.38 | W18: =$C18*V18/100 -> 0 | X18: 10.76 | Y18: 1.38 | AA18: =$C18*Z18/100 -> 0 | AB18: 10.76 | AC18: 1.38 | AE18: =$C18*AD18/100 -> 0 | AF18: =MAX(C18:C20) -> 10.76 | AG18: =MIN(C18:C20) -> 1.38 | AI18: =$C18*AH18/100 -> 0
B19: 2.2 As item no.2 above but for R.C roof slab | C19: 2.37 | G19: =$C19*F19/100 -> 0 | K19: =$C19*H19/100 -> 0 | O19: =$C19*N19/100 -> 0 | S19: =$C19*P19/100 -> 0 | W19: =$C19*V19/100 -> 0 | AA19: =$C19*Z19/100 -> 0 | AE19: =$C19*AD19/100 -> 0 | AI19: =$C19*AH19/100 -> 0
B20: 2.3 Steel structure (R.H.S) | C20: 10.76 | G20: =$C20*F20/100 -> 0 | K20: =$C20*H20/100 -> 0 | O20: =$C20*N20/100 -> 0 | S20: =$C20*P20/100 -> 0 | W20: =$C20*V20/100 -> 0 | AA20: =$C20*Z20/100 -> 0 | AE20: =$C20*AD20/100 -> 0 | AI20: =$C20*AH20/100 -> 0
A21: 3 | B21: Block Work | G21: =$C21*F21/100 -> 0 | K21: =$C21*H21/100 -> 0 | O21: =$C21*N21/100 -> 0 | S21: =$C21*P21/100 -> 0 | W21: =$C21*V21/100 -> 0 | AA21: =$C21*Z21/100 -> 0 | AE21: =$C21*AD21/100 -> 0 | AI21: =$C21*AH21/100 -> 0
B22: 3.1 Internal | G22: =$C22*F22/100 -> 0 | K22: =$C22*H22/100 -> 0 | O22: =$C22*N22/100 -> 0 | S22: =$C22*P22/100 -> 0 | W22: =$C22*V22/100 -> 0 | AA22: =$C22*Z22/100 -> 0 | AE22: =$C22*AD22/100 -> 0 | AI22: =$C22*AH22/100 -> 0
B23: 3.1. see the methodology disscused on page 15 | G23: =$C23*F23/100 -> 0 | K23: =$C23*H23/100 -> 0 | O23: =$C23*N23/100 -> 0 | S23: =$C23*P23/100 -> 0 | W23: =$C23*V23/100 -> 0 | AA23: =$C23*Z23/100 -> 0 | AE23: =$C23*AD23/100 -> 0 | AI23: =$C23*AH23/100 -> 0
B24: 3.2 External | G24: =$C24*F24/100 -> 0 | K24: =$C24*H24/100 -> 0 | O24: =$C24*N24/100 -> 0 | S24: =$C24*P24/100 -> 0 | W24: =$C24*V24/100 -> 0 | AA24: =$C24*Z24/100 -> 0 | AE24: =$C24*AD24/100 -> 0 | AI24: =$C24*AH24/100 -> 0
B25: 3.2.1 Mud | C25: 0.26 | D25: =MAX(C25:C33) -> 2.42 | E25: =MIN(C25:C33) -> 0.26 | G25: =$C25*F25/100 -> 0 | H25: =MAX(C25:C33) -> 2.42 | I25: =MIN(C25:C33) -> 0.26 | K25: =$C25*H25/100 -> 0.006292 | L25: 2.42 | M25: 0.26 | O25: =$C25*N25/100 -> 0 | P25: 2.42 | Q25: 0.26 | S25: =$C25*P25/100 -> 0.006292 | T25: 2.42 | U25: 0.26 | W25: =$C25*V25/100 -> 0 | X25: 2.42 | Y25: 0.26 | AA25: =$C25*Z25/100 -> 0 | AB25: 2.42 | AC25: 0.26 | AE25: =$C25*AD25/100 -> 0 | AF25: =MAX(C25:C33) -> 2.42 | AG25: =MIN(C25:C33) -> 0.26 | AI25: =$C25*AH25/100 -> 0
B26: 3.2.2 CIS G-28 | C26: 0.52 | G26: =$C26*F26/100 -> 0 | K26: =$C26*H26/100 -> 0 | O26: =$C26*N26/100 -> 0 | S26: =$C26*P26/100 -> 0 | W26: =$C26*V26/100 -> 0 | AA26: =$C26*Z26/100 -> 0 | AE26: =$C26*AD26/100 -> 0 | AI26: =$C26*AH26/100 -> 0
B27: 3.2.3 CIS G-30 | C27: 0.38 | G27: =$C27*F27/100 -> 0 | K27: =$C27*H27/100 -> 0 | O27: =$C27*N27/100 -> 0 | S27: =$C27*P27/100 -> 0 | W27: =$C27*V27/100 -> 0 | AA27: =$C27*Z27/100 -> 0 | AE27: =$C27*AD27/100 -> 0 | AI27: =$C27*AH27/100 -> 0
B28: 3.2.4 CIS G-32 | C28: 0.4 | G28: =$C28*F28/100 -> 0 | K28: =$C28*H28/100 -> 0 | O28: =$C28*N28/100 -> 0 | S28: =$C28*P28/100 -> 0 | W28: =$C28*V28/100 -> 0 | AA28: =$C28*Z28/100 -> 0 | AE28: =$C28*AD28/100 -> 0 | AI28: =$C28*AH28/100 -> 0
B29: 3.2.5 EGA on steel | C29: 0.99 | G29: =$C29*F29/100 -> 0 | K29: =$C29*H29/100 -> 0 | O29: =$C29*N29/100 -> 0 | S29: =$C29*P29/100 -> 0 | W29: =$C29*V29/100 -> 0 | AA29: =$C29*Z29/100 -> 0 | AE29: =$C29*AD29/100 -> 0 | AI29: =$C29*AH29/100 -> 0
B30: 3.2.6 HCB 20 cm thick | C30: 0.38 | G30: =$C30*F30/100 -> 0 | K30: =$C30*H30/100 -> 0 | O30: =$C30*N30/100 -> 0 | S30: =$C30*P30/100 -> 0 | W30: =$C30*V30/100 -> 0 | AA30: =$C30*Z30/100 -> 0 | AE30: =$C30*AD30/100 -> 0 | AI30: =$C30*AH30/100 -> 0
B31: 3.2.7 Brick 25cm thick | C31: 2.42 | G31: =$C31*F31/100 -> 0 | K31: =$C31*H31/100 -> 0 | O31: =$C31*N31/100 -> 0 | S31: =$C31*P31/100 -> 0 | W31: =$C31*V31/100 -> 0 | AA31: =$C31*Z31/100 -> 0 | AE31: =$C31*AD31/100 -> 0 | AI31: =$C31*AH31/100 -> 0
B32: 3.2.8 stone 40cm thick | C32: 1.63 | G32: =$C32*F32/100 -> 0 | K32: =$C32*H32/100 -> 0 | O32: =$C32*N32/100 -> 0 | S32: =$C32*P32/100 -> 0 | W32: =$C32*V32/100 -> 0 | AA32: =$C32*Z32/100 -> 0 | AE32: =$C32*AD32/100 -> 0 | AI32: =$C32*AH32/100 -> 0
B33: 3.2.9 stone 50cm thick | C33: 2.19 | G33: =$C33*F33/100 -> 0 | K33: =$C33*H33/100 -> 0 | O33: =$C33*N33/100 -> 0 | S33: =$C33*P33/100 -> 0 | W33: =$C33*V33/100 -> 0 | AA33: =$C33*Z33/100 -> 0 | AE33: =$C33*AD33/100 -> 0 | AI33: =$C33*AH33/100 -> 0
B34: 3.2.10 Alumimium | C34: 0 | G34: =$C34*F34/100 -> 0 | K34: =$C34*H34/100 -> 0 | O34: =$C34*N34/100 -> 0 | S34: =$C34*P34/100 -> 0 | W34: =$C34*V34/100 -> 0 | AA34: =$C34*Z34/100 -> 0 | AE34: =$C34*AD34/100 -> 0 | AI34: =$C34*AH34/100 -> 0
A35: 4 | B35: Roofing | G35: =$C35*F35/100 -> 0 | K35: =$C35*H35/100 -> 0 | O35: =$C35*N35/100 -> 0 | S35: =$C35*P35/100 -> 0 | W35: =$C35*V35/100 -> 0 | AA35: =$C35*Z35/100 -> 0 | AE35: =$C35*AD35/100 -> 0 | AI35: =$C35*AH35/100 -> 0
B36: 4.1 CIS G-32 on wood | C36: 4.29 | D36: =MAX(C36:C44) -> 16.22 | E36: =MIN(C36:C44) -> 4.14 | G36: =$C36*F36/100 -> 0 | H36: =MAX(C36:C44) -> 16.22 | I36: =MIN(C36:C44) -> 4.14 | K36: =$C36*H36/100 -> 0.695838 | L36: 16.22 | M36: 4.14 | O36: =$C36*N36/100 -> 0 | P36: 16.22 | Q36: 4.14 | S36: =$C36*P36/100 -> 0.695838 | T36: 16.22 | U36: 4.14 | W36: =$C36*V36/100 -> 0 | X36: 16.22 | Y36: 4.14 | AA36: =$C36*Z36/100 -> 0 | AB36: 16.22 | AC36: 4.14 | AE36: =$C36*AD36/100 -> 0 | AF36: =MAX(C36:C44) -> 16.22 | AG36: =MIN(C36:C44) -> 4.14 | AI36: =$C36*AH36/100 -> 0
B37: 4.2 CIS G-30 on wood | C37: 4.41 | G37: =$C37*F37/100 -> 0 | K37: =$C37*H37/100 -> 0 | O37: =$C37*N37/100 -> 0 | S37: =$C37*P37/100 -> 0 | W37: =$C37*V37/100 -> 0 | AA37: =$C37*Z37/100 -> 0 | AE37: =$C37*AD37/100 -> 0 | AI37: =$C37*AH37/100 -> 0
B38: 4.3 CIS G-28 on wood | C38: 4.71 | G38: =$C38*F38/100 -> 0 | K38: =$C38*H38/100 -> 0 | O38: =$C38*N38/100 -> 0 | S38: =$C38*P38/100 -> 0 | W38: =$C38*V38/100 -> 0 | AA38: =$C38*Z38/100 -> 0 | AE38: =$C38*AD38/100 -> 0 | AI38: =$C38*AH38/100 -> 0
B39: 4.4 EGA on steel | C39: 15.25 | G39: =$C39*F39/100 -> 0 | K39: =$C39*H39/100 -> 0 | O39: =$C39*N39/100 -> 0 | S39: =$C39*P39/100 -> 0 | W39: =$C39*V39/100 -> 0 | AA39: =$C39*Z39/100 -> 0 | AE39: =$C39*AD39/100 -> 0 | AI39: =$C39*AH39/100 -> 0
B40: 4.5 EGA on wood | C40: 9.98 | G40: =$C40*F40/100 -> 0 | K40: =$C40*H40/100 -> 0 | O40: =$C40*N40/100 -> 0 | S40: =$C40*P40/100 -> 0 | W40: =$C40*V40/100 -> 0 | AA40: =$C40*Z40/100 -> 0 | AE40: =$C40*AD40/100 -> 0 | AI40: =$C40*AH40/100 -> 0
B41: 4.6 CIS G-28 on steel | C41: 16.22 | G41: =$C41*F41/100 -> 0 | K41: =$C41*H41/100 -> 0 | O41: =$C41*N41/100 -> 0 | S41: =$C41*P41/100 -> 0 | W41: =$C41*V41/100 -> 0 | AA41: =$C41*Z41/100 -> 0 | AE41: =$C41*AD41/100 -> 0 | AI41: =$C41*AH41/100 -> 0
B42: 4.7 Cement roof tile | C42: 4.14 | G42: =$C42*F42/100 -> 0 | K42: =$C42*H42/100 -> 0 | O42: =$C42*N42/100 -> 0 | S42: =$C42*P42/100 -> 0 | W42: =$C42*V42/100 -> 0 | AA42: =$C42*Z42/100 -> 0 | AE42: =$C42*AD42/100 -> 0 | AI42: =$C42*AH42/100 -> 0
B43: 4.8 R.C without water-proof material | C43: 6.91 | G43: =$C43*F43/100 -> 0 | K43: =$C43*H43/100 -> 0 | O43: =$C43*N43/100 -> 0 | S43: =$C43*P43/100 -> 0 | W43: =$C43*V43/100 -> 0 | AA43: =$C43*Z43/100 -> 0 | AE43: =$C43*AD43/100 -> 0 | AI43: =$C43*AH43/100 -> 0
B44: 4.9 R.C with water-proof material | C44: 8.02 | G44: =$C44*F44/100 -> 0 | K44: =$C44*H44/100 -> 0 | O44: =$C44*N44/100 -> 0 | S44: =$C44*P44/100 -> 0 | W44: =$C44*V44/100 -> 0 | AA44: =$C44*Z44/100 -> 0 | AE44: =$C44*AD44/100 -> 0 | AI44: =$C44*AH44/100 -> 0
A45: 5 | B45: Joinery | G45: =$C45*F45/100 -> 0 | K45: =$C45*H45/100 -> 0 | O45: =$C45*N45/100 -> 0 | S45: =$C45*P45/100 -> 0 | W45: =$C45*V45/100 -> 0 | AA45: =$C45*Z45/100 -> 0 | AE45: =$C45*AD45/100 -> 0 | AI45: =$C45*AH45/100 -> 0
B46: 5.1 Low quality wood External | C46: 0.8 | D46: =MAX(C46:C49) -> 1.32 | E46: =MIN(C46:C49) -> 0.3 | G46: =$C46*F46/100 -> 0 | H46: =MAX(C46:C49) -> 1.32 | I46: =MIN(C46:C49) -> 0.3 | K46: =$C46*H46/100 -> 0.01056 | L46: 1.32 | M46: 0.3 | O46: =$C46*N46/100 -> 0 | P46: 1.32 | Q46: 0.3 | S46: =$C46*P46/100 -> 0.01056 | T46: 1.32 | U46: 0.3 | W46: =$C46*V46/100 -> 0 | X46: 1.32 | Y46: 0.3 | AA46: =$C46*Z46/100 -> 0 | AB46: 1.32 | AC46: 0.3 | AE46: =$C46*AD46/100 -> 0 | AF46: =MAX(C46:C49) -> 1.32 | AG46: =MIN(C46:C49) -> 0.3 | AI46: =$C46*AH46/100 -> 0
B47: 5.2 medium Quality wood ,External | C47: 0.3 | G47: =$C47*F47/100 -> 0 | K47: =$C47*H47/100 -> 0 | O47: =$C47*N47/100 -> 0 | S47: =$C47*P47/100 -> 0 | W47: =$C47*V47/100 -> 0 | AA47: =$C47*Z47/100 -> 0 | AE47: =$C47*AD47/100 -> 0 | AI47: =$C47*AH47/100 -> 0
B48: 5.3 Quality external | C48: 0.76 | G48: =$C48*F48/100 -> 0 | K48: =$C48*H48/100 -> 0 | O48: =$C48*N48/100 -> 0 | S48: =$C48*P48/100 -> 0 | W48: =$C48*V48/100 -> 0 | AA48: =$C48*Z48/100 -> 0 | AE48: =$C48*AD48/100 -> 0 | AI48: =$C48*AH48/100 -> 0
B49: 5.4 Best quality wood external | C49: 1.32 | G49: =$C49*F49/100 -> 0 | K49: =$C49*H49/100 -> 0 | O49: =$C49*N49/100 -> 0 | S49: =$C49*P49/100 -> 0 | W49: =$C49*V49/100 -> 0 | AA49: =$C49*Z49/100 -> 0 | AE49: =$C49*AD49/100 -> 0 | AI49: =$C49*AH49/100 -> 0
A50: 6 | B50: Metal Works | G50: =$C50*F50/100 -> 0 | K50: =$C50*H50/100 -> 0 | O50: =$C50*N50/100 -> 0 | S50: =$C50*P50/100 -> 0 | W50: =$C50*V50/100 -> 0 | AA50: =$C50*Z50/100 -> 0 | AE50: =$C50*AD50/100 -> 0 | AI50: =$C50*AH50/100 -> 0
B51: 6.1 LTZ or RHS profile for external openings with clear glass | C51: 0.67 | D51: =MAX(C51:C59) -> 1.08 | E51: =MIN(C51:C59) -> 0.5 | G51: =$C51*F51/100 -> 0 | H51: =MAX(C51:C59) -> 1.08 | I51: =MIN(C51:C59) -> 0.5 | K51: =$C51*H51/100 -> 0.007236 | L51: 1.08 | M51: 0.5 | O51: =$C51*N51/100 -> 0 | P51: 1.08 | Q51: 0.5 | S51: =$C51*P51/100 -> 0.007236 | T51: 1.08 | U51: 0.5 | W51: =$C51*V51/100 -> 0 | X51: 1.08 | Y51: 0.5 | AA51: =$C51*Z51/100 -> 0 | AB51: 1.08 | AC51: 0.5 | AE51: =$C51*AD51/100 -> 0 | AF51: =MAX(C51:C59) -> 1.08 | AG51: =MIN(C51:C59) -> 0.5 | AI51: =$C51*AH51/100 -> 0
B52: 6.2 Ditto above but with 4mm- frosted glass | C52: 0.69 | G52: =$C52*F52/100 -> 0 | K52: =$C52*H52/100 -> 0 | O52: =$C52*N52/100 -> 0 | S52: =$C52*P52/100 -> 0 | W52: =$C52*V52/100 -> 0 | AA52: =$C52*Z52/100 -> 0 | AE52: =$C52*AD52/100 -> 0 | AI52: =$C52*AH52/100 -> 0
B53: 6.3 Ditto but with 4mm-tinted glass | C53: 0.69 | G53: =$C53*F53/100 -> 0 | K53: =$C53*H53/100 -> 0 | O53: =$C53*N53/100 -> 0 | S53: =$C53*P53/100 -> 0 | W53: =$C53*V53/100 -> 0 | AA53: =$C53*Z53/100 -> 0 | AE53: =$C53*AD53/100 -> 0 | AI53: =$C53*AH53/100 -> 0
B54: 6.4 Ditto but with 6mm-tinted glass | C54: 0.78 | G54: =$C54*F54/100 -> 0 | K54: =$C54*H54/100 -> 0 | O54: =$C54*N54/100 -> 0 | S54: =$C54*P54/100 -> 0 | W54: =$C54*V54/100 -> 0 | AA54: =$C54*Z54/100 -> 0 | AE54: =$C54*AD54/100 -> 0 | AI54: =$C54*AH54/100 -> 0
B55: 6.3 Ditto but with 4mm-clear glass | C55: 0.5 | O55: =$C55*N55/100 -> 0
B56: 6.5 Secco with 4mm-frosted glass | C56: 0.52 | G56: =$C56*F56/100 -> 0 | K56: =$C56*H56/100 -> 0 | O56: =$C56*N56/100 -> 0 | S56: =$C56*P56/100 -> 0 | W56: =$C56*V56/100 -> 0 | AA56: =$C56*Z56/100 -> 0 | AE56: =$C56*AD56/100 -> 0 | AI56: =$C56*AH56/100 -> 0
B57: 6.6 Ditto but with 4mm-tinted glass | C57: 0.52 | G57: =$C57*F57/100 -> 0 | K57: =$C57*H57/100 -> 0 | O57: =$C57*N57/100 -> 0 | S57: =$C57*P57/100 -> 0 | W57: =$C57*V57/100 -> 0 | AA57: =$C57*Z57/100 -> 0 | AE57: =$C57*AD57/100 -> 0 | AI57: =$C57*AH57/100 -> 0
B58: 6.7 Ditto but with 6mm-tinted glass | C58: 0.62 | G58: =$C58*F58/100 -> 0 | K58: =$C58*H58/100 -> 0 | O58: =$C58*N58/100 -> 0 | S58: =$C58*P58/100 -> 0 | W58: =$C58*V58/100 -> 0 | AA58: =$C58*Z58/100 -> 0 | AE58: =$C58*AD58/100 -> 0 | AI58: =$C58*AH58/100 -> 0
B59: 6.8 Ditto as above but aluminium | C59: 1.08 | G59: =$C59*F59/100 -> 0 | K59: =$C59*H59/100 -> 0 | O59: =$C59*N59/100 -> 0 | S59: =$C59*P59/100 -> 0 | W59: =$C59*V59/100 -> 0 | AA59: =$C59*Z59/100 -> 0 | AE59: =$C59*AD59/100 -> 0 | AI59: =$C59*AH59/100 -> 0
A60: 7 | B60: Floor Finish | G60: =$C60*F60/100 -> 0 | K60: =$C60*H60/100 -> 0 | O60: =$C60*N60/100 -> 0 | S60: =$C60*P60/100 -> 0 | W60: =$C60*V60/100 -> 0 | AA60: =$C60*Z60/100 -> 0 | AE60: =$C60*AD60/100 -> 0 | AI60: =$C60*AH60/100 -> 0
B61: 7.1 Cement Screed | C61: 0.27 | D61: =MAX(C61:C75) -> 4.18 | E61: =MIN(C61:C75) -> 0.27 | G61: =$C61*F61/100 -> 0 | H61: =MAX(C61:C75) -> 4.18 | I61: =MIN(C61:C75) -> 0.27 | K61: =$C61*H61/100 -> 0.011286 | L61: 4.18 | M61: 0.27 | O61: =$C61*N61/100 -> 0 | P61: 4.18 | Q61: 0.27 | S61: =$C61*P61/100 -> 0.011286 | T61: 4.18 | U61: 0.27 | W61: =$C61*V61/100 -> 0 | X61: 4.18 | Y61: 0.27 | AA61: =$C61*Z61/100 -> 0 | AB61: 4.18 | AC61: 0.27 | AE61: =$C61*AD61/100 -> 0 | AF61: =MAX(C61:C75) -> 4.18 | AG61: =MIN(C61:C75) -> 0.27 | AI61: =$C61*AH61/100 -> 0
B62: 7.2 Cement Tile | C62: 0.57 | G62: =$C62*F62/100 -> 0 | K62: =$C62*H62/100 -> 0 | O62: =$C62*N62/100 -> 0 | S62: =$C62*P62/100 -> 0 | W62: =$C62*V62/100 -> 0 | AA62: =$C62*Z62/100 -> 0 | AE62: =$C62*AD62/100 -> 0 | AI62: =$C62*AH62/100 -> 0
B63: 7.3 Terrazzo Tile | C63: 0.81 | G63: =$C63*F63/100 -> 0 | K63: =$C63*H63/100 -> 0 | O63: =$C63*N63/100 -> 0 | S63: =$C63*P63/100 -> 0 | W63: =$C63*V63/100 -> 0 | AA63: =$C63*Z63/100 -> 0 | AE63: =$C63*AD63/100 -> 0 | AI63: =$C63*AH63/100 -> 0
B64: 7.4 PVC tile | C64: 0.95 | G64: =$C64*F64/100 -> 0 | K64: =$C64*H64/100 -> 0 | O64: =$C64*N64/100 -> 0 | S64: =$C64*P64/100 -> 0 | W64: =$C64*V64/100 -> 0 | AA64: =$C64*Z64/100 -> 0 | AE64: =$C64*AD64/100 -> 0 | AI64: =$C64*AH64/100 -> 0
B65: 7.5 Ceramic medium quality Porcelain | C65: 1.08 | G65: =$C65*F65/100 -> 0 | K65: =$C65*H65/100 -> 0 | O65: =$C65*N65/100 -> 0 | S65: =$C65*P65/100 -> 0 | W65: =$C65*V65/100 -> 0 | AA65: =$C65*Z65/100 -> 0 | AE65: =$C65*AD65/100 -> 0 | AI65: =$C65*AH65/100 -> 0
B66: 7.6 Ceramic best quality | C66: 1.69 | G66: =$C66*F66/100 -> 0 | K66: =$C66*H66/100 -> 0 | O66: =$C66*N66/100 -> 0 | S66: =$C66*P66/100 -> 0 | W66: =$C66*V66/100 -> 0 | AA66: =$C66*Z66/100 -> 0 | AE66: =$C66*AD66/100 -> 0 | AI66: =$C66*AH66/100 -> 0
B67: 7.7 Marble chip lower quality | C67: 1.78 | G67: =$C67*F67/100 -> 0 | K67: =$C67*H67/100 -> 0 | O67: =$C67*N67/100 -> 0 | S67: =$C67*P67/100 -> 0 | W67: =$C67*V67/100 -> 0 | AA67: =$C67*Z67/100 -> 0 | AE67: =$C67*AD67/100 -> 0 | AI67: =$C67*AH67/100 -> 0
B68: 7.8 Marble chip best quality | C68: 2.14 | G68: =$C68*F68/100 -> 0 | K68: =$C68*H68/100 -> 0 | O68: =$C68*N68/100 -> 0 | S68: =$C68*P68/100 -> 0 | W68: =$C68*V68/100 -> 0 | AA68: =$C68*Z68/100 -> 0 | AE68: =$C68*AD68/100 -> 0 | AI68: =$C68*AH68/100 -> 0
B69: 7.9 Harar marble | C69: 2.49 | G69: =$C69*F69/100 -> 0 | K69: =$C69*H69/100 -> 0 | O69: =$C69*N69/100 -> 0 | S69: =$C69*P69/100 -> 0 | W69: =$C69*V69/100 -> 0 | AA69: =$C69*Z69/100 -> 0 | AE69: =$C69*AD69/100 -> 0 | AI69: =$C69*AH69/100 -> 0
B70: 7.10 Mankush marble | C70: 3.52 | G70: =$C70*F70/100 -> 0 | K70: =$C70*H70/100 -> 0 | O70: =$C70*N70/100 -> 0 | S70: =$C70*P70/100 -> 0 | W70: =$C70*V70/100 -> 0 | AA70: =$C70*Z70/100 -> 0 | AE70: =$C70*AD70/100 -> 0 | AI70: =$C70*AH70/100 -> 0
B71: 7.11 Parquet best quality on screed | C71: 4.18 | G71: =$C71*F71/100 -> 0 | K71: =$C71*H71/100 -> 0 | O71: =$C71*N71/100 -> 0 | S71: =$C71*P71/100 -> 0 | W71: =$C71*V71/100 -> 0 | AA71: =$C71*Z71/100 -> 0 | AE71: =$C71*AD71/100 -> 0 | AI71: =$C71*AH71/100 -> 0
B72: 7.12 Parquet quality on screed | C72: 2.84 | G72: =$C72*F72/100 -> 0 | K72: =$C72*H72/100 -> 0 | O72: =$C72*N72/100 -> 0 | S72: =$C72*P72/100 -> 0 | W72: =$C72*V72/100 -> 0 | AA72: =$C72*Z72/100 -> 0 | AE72: =$C72*AD72/100 -> 0 | AI72: =$C72*AH72/100 -> 0
B73: 7.13 Parquet medium quality on screed | C73: 2.84 | G73: =$C73*F73/100 -> 0 | K73: =$C73*H73/100 -> 0 | O73: =$C73*N73/100 -> 0 | S73: =$C73*P73/100 -> 0 | W73: =$C73*V73/100 -> 0 | AA73: =$C73*Z73/100 -> 0 | AE73: =$C73*AD73/100 -> 0 | AI73: =$C73*AH73/100 -> 0
... B75: 7.15 Granite | C75: 2.64 | G75: =$C75*F75/100 -> 0 | K75: =$C75*H75/100 -> 0 | O75: =$C75*N75/100 -> 0 | S75: =$C75*P75/100 -> 0 | W75: =$C75*V75/100 -> 0 | AA75: =$C75*Z75/100 -> 0 | AE75: =$C75*AD75/100 -> 0 | AI75: =$C75*AH75/100 -> 0
A76: 8 | B76: Wall Finish | G76: =$C76*F76/100 -> 0 | K76: =$C76*H76/100 -> 0 | O76: =$C76*N76/100 -> 0 | S76: =$C76*P76/100 -> 0 | W76: =$C76*V76/100 -> 0 | AA76: =$C76*Z76/100 -> 0 | AE76: =$C76*AD76/100 -> 0 | AI76: =$C76*AH76/100 -> 0
B77: 8.1 Internal | G77: =$C77*F77/100 -> 0 | K77: =$C77*H77/100 -> 0 | O77: =$C77*N77/100 -> 0 | S77: =$C77*P77/100 -> 0 | W77: =$C77*V77/100 -> 0 | AA77: =$C77*Z77/100 -> 0 | AE77: =$C77*AD77/100 -> 0 | AI77: =$C77*AH77/100 -> 0
B78: 8.1.1 plasterd | C78: 0.21 | D78: =MAX(C78:C95) -> 2 | E78: =MIN(C78:C119) -> 0.09 | G78: =$C78*F78/100 -> 0 | H78: =MAX(C78:C95) -> 2 | I78: =MIN(C78:C119) -> 0.09 | K78: =$C78*H78/100 -> 0.0042 | L78: 2 | M78: 0.09 | O78: =$C78*N78/100 -> 0 | P78: 2 | Q78: 0.09 | S78: =$C78*P78/100 -> 0.0042 | T78: 2 | U78: 0.09 | W78: =$C78*V78/100 -> 0 | X78: 2 | Y78: 0.09 | AA78: =$C78*Z78/100 -> 0 | AB78: 2 | AC78: 0.09 | AE78: =$C78*AD78/100 -> 0 | AF78: =MAX(C78:C95) -> 2 | AG78: =MIN(C78:C119) -> 0.09 | AI78: =$C78*AH78/100 -> 0
B79: 8.1.2 Plasterd and painted | C79: 0.28 | G79: =$C79*F79/100 -> 0 | K79: =$C79*H79/100 -> 0 | O79: =$C79*N79/100 -> 0 | S79: =$C79*P79/100 -> 0 | W79: =$C79*V79/100 -> 0 | AA79: =$C79*Z79/100 -> 0 | AE79: =$C79*AD79/100 -> 0 | AI79: =$C79*AH79/100 -> 0
B80: 8.1.3 Pointed HCB | C80: 0.09 | G80: =$C80*F80/100 -> 0 | K80: =$C80*H80/100 -> 0 | O80: =$C80*N80/100 -> 0 | S80: =$C80*P80/100 -> 0 | W80: =$C80*V80/100 -> 0 | AA80: =$C80*Z80/100 -> 0 | AE80: =$C80*AD80/100 -> 0 | AI80: =$C80*AH80/100 -> 0
B81: 8.1.4 Pointed dressed stone | C81: 0.12 | G81: =$C81*F81/100 -> 0 | K81: =$C81*H81/100 -> 0 | O81: =$C81*N81/100 -> 0 | S81: =$C81*P81/100 -> 0 | W81: =$C81*V81/100 -> 0 | AA81: =$C81*Z81/100 -> 0 | AE81: =$C81*AD81/100 -> 0 | AI81: =$C81*AH81/100 -> 0
B82: 8.1.5 Pointed brick | C82: 0.15 | G82: =$C82*F82/100 -> 0 | K82: =$C82*H82/100 -> 0 | O82: =$C82*N82/100 -> 0 | S82: =$C82*P82/100 -> 0 | W82: =$C82*V82/100 -> 0 | AA82: =$C82*Z82/100 -> 0 | AE82: =$C82*AD82/100 -> 0 | AI82: =$C82*AH82/100 -> 0
B83: 8.1.6 Plasterd and Addis I wall paper | C83: 0.73 | G83: =$C83*F83/100 -> 0 | K83: =$C83*H83/100 -> 0 | O83: =$C83*N83/100 -> 0 | S83: =$C83*P83/100 -> 0 | W83: =$C83*V83/100 -> 0 | AA83: =$C83*Z83/100 -> 0 | AE83: =$C83*AD83/100 -> 0 | AI83: =$C83*AH83/100 -> 0
B84: 8.1.7 Mosaic | C84: 1.38 | G84: =$C84*F84/100 -> 0 | K84: =$C84*H84/100 -> 0 | O84: =$C84*N84/100 -> 0 | S84: =$C84*P84/100 -> 0 | W84: =$C84*V84/100 -> 0 | AA84: =$C84*Z84/100 -> 0 | AE84: =$C84*AD84/100 -> 0 | AI84: =$C84*AH84/100 -> 0
B85: 8.1.8a Imported, high quality ceramic | C85: 1.13 | G85: =$C85*F85/100 -> 0 | K85: =$C85*H85/100 -> 0 | O85: =$C85*N85/100 -> 0 | S85: =$C85*P85/100 -> 0 | W85: =$C85*V85/100 -> 0 | AA85: =$C85*Z85/100 -> 0 | AE85: =$C85*AD85/100 -> 0 | AI85: =$C85*AH85/100 -> 0
B86: 8.1.8b Imported, quality ceramic | C86: 0.71 | G86: =$C86*F86/100 -> 0 | K86: =$C86*H86/100 -> 0 | O86: =$C86*N86/100 -> 0 | S86: =$C86*P86/100 -> 0 | W86: =$C86*V86/100 -> 0 | AA86: =$C86*Z86/100 -> 0 | AE86: =$C86*AD86/100 -> 0 | AI86: =$C86*AH86/100 -> 0
B87: 8.1.8c Imported, medium quality ceramic | C87: 0.53 | G87: =$C87*F87/100 -> 0 | K87: =$C87*H87/100 -> 0 | O87: =$C87*N87/100 -> 0 | S87: =$C87*P87/100 -> 0 | W87: =$C87*V87/100 -> 0 | AA87: =$C87*Z87/100 -> 0 | AE87: =$C87*AD87/100 -> 0 | AI87: =$C87*AH87/100 -> 0
B88: 8.1.8d Lower quality ceramic | C88: 0.52 | G88: =$C88*F88/100 -> 0 | K88: =$C88*H88/100 -> 0 | O88: =$C88*N88/100 -> 0 | S88: =$C88*P88/100 -> 0 | W88: =$C88*V88/100 -> 0 | AA88: =$C88*Z88/100 -> 0 | AE88: =$C88*AD88/100 -> 0 | AI88: =$C88*AH88/100 -> 0
B89: 8.1.9 Pointed and painted HCB | C89: 0.17 | G89: =$C89*F89/100 -> 0 | K89: =$C89*H89/100 -> 0 | O89: =$C89*N89/100 -> 0 | S89: =$C89*P89/100 -> 0 | W89: =$C89*V89/100 -> 0 | AA89: =$C89*Z89/100 -> 0 | AE89: =$C89*AD89/100 -> 0 | AI89: =$C89*AH89/100 -> 0
B90: 8.1.10 Pointed and painted Brick | C90: 0.22 | G90: =$C90*F90/100 -> 0 | K90: =$C90*H90/100 -> 0 | O90: =$C90*N90/100 -> 0 | S90: =$C90*P90/100 -> 0 | W90: =$C90*V90/100 -> 0 | AA90: =$C90*Z90/100 -> 0 | AE90: =$C90*AD90/100 -> 0 | AI90: =$C90*AH90/100 -> 0
... B95: 8.1.15 Boka marble | C95: 1.87 | G95: =$C95*F95/100 -> 0 | K95: =$C95*H95/100 -> 0 | O95: =$C95*N95/100 -> 0 | S95: =$C95*P95/100 -> 0 | W95: =$C95*V95/100 -> 0 | AA95: =$C95*Z95/100 -> 0 | AE95: =$C95*AD95/100 -> 0 | AI95: =$C95*AH95/100 -> 0
B96: 8.2 External | G96: =$C96*F96/100 -> 0 | K96: =$C96*H96/100 -> 0 | O96: =$C96*N96/100 -> 0 | S96: =$C96*P96/100 -> 0 | W96: =$C96*V96/100 -> 0 | AA96: =$C96*Z96/100 -> 0 | AE96: =$C96*AD96/100 -> 0 | AI96: =$C96*AH96/100 -> 0
B97: 8.2.1 Plastering | C97: 0.26 | D97: =MAX(C97:C119) -> 2.49 | E97: =MIN(C97:C119) -> 0.12 | G97: =$C97*F97/100 -> 0 | H97: =MAX(C97:C119) -> 2.49 | I97: =MIN(C97:C119) -> 0.12 | K97: =$C97*H97/100 -> 0.006474 | L97: 2.49 | M97: 0.12 | O97: =$C97*N97/100 -> 0 | P97: 2.49 | Q97: 0.12 | S97: =$C97*P97/100 -> 0.006474 | T97: 2.49 | U97: 0.12 | W97: =$C97*V97/100 -> 0 | X97: 2.49 | Y97: 0.12 | AA97: =$C97*Z97/100 -> 0 | AB97: 2.49 | AC97: 0.12 | AE97: =$C97*AD97/100 -> 0 | AF97: =MAX(C97:C119) -> 2.49 | AG97: =MIN(C97:C119) -> 0.12 | AI97: =$C97*AH97/100 -> 0
B98: 8.2.2 Plastering and painting | C98: 0.35 | G98: =$C98*F98/100 -> 0 | K98: =$C98*H98/100 -> 0 | O98: =$C98*N98/100 -> 0 | S98: =$C98*P98/100 -> 0 | W98: =$C98*V98/100 -> 0 | AA98: =$C98*Z98/100 -> 0 | AE98: =$C98*AD98/100 -> 0 | AI98: =$C98*AH98/100 -> 0
B99: 8.2.3 Pointed HCB | C99: 0.12 | G99: =$C99*F99/100 -> 0 | K99: =$C99*H99/100 -> 0 | O99: =$C99*N99/100 -> 0 | S99: =$C99*P99/100 -> 0 | W99: =$C99*V99/100 -> 0 | AA99: =$C99*Z99/100 -> 0 | AE99: =$C99*AD99/100 -> 0 | AI99: =$C99*AH99/100 -> 0
B100: 8.2.4 Pointed stone | C100: 0.15 | G100: =$C100*F100/100 -> 0 | K100: =$C100*H100/100 -> 0 | O100: =$C100*N100/100 -> 0 | S100: =$C100*P100/100 -> 0 | W100: =$C100*V100/100 -> 0 | AA100: =$C100*Z100/100 -> 0 | AE100: =$C100*AD100/100 -> 0 | AI100: =$C100*AH100/100 -> 0
B101: 8.2.5 pointed ambo cladding | C101: 1.82 | G101: =$C101*F101/100 -> 0 | K101: =$C101*H101/100 -> 0 | O101: =$C101*N101/100 -> 0 | S101: =$C101*P101/100 -> 0 | W101: =$C101*V101/100 -> 0 | AA101: =$C101*Z101/100 -> 0 | AE101: =$C101*AD101/100 -> 0 | AI101: =$C101*AH101/100 -> 0
B102: 8.2.6 Not pointed ambo cladding | C102: 1.67 | G102: =$C102*F102/100 -> 0 | K102: =$C102*H102/100 -> 0 | O102: =$C102*N102/100 -> 0 | S102: =$C102*P102/100 -> 0 | W102: =$C102*V102/100 -> 0 | AA102: =$C102*Z102/100 -> 0 | AE102: =$C102*AD102/100 -> 0 | AI102: =$C102*AH102/100 -> 0
B103: 8.2.7 Dressed stone cladding | C103: 1.67 | G103: =$C103*F103/100 -> 0 | K103: =$C103*H103/100 -> 0 | O103: =$C103*N103/100 -> 0 | S103: =$C103*P103/100 -> 0 | W103: =$C103*V103/100 -> 0 | AA103: =$C103*Z103/100 -> 0 | AE103: =$C103*AD103/100 -> 0 | AI103: =$C103*AH103/100 -> 0
B104: 8.2.8 pointing brick | C104: 0.19 | G104: =$C104*F104/100 -> 0 | K104: =$C104*H104/100 -> 0 | O104: =$C104*N104/100 -> 0 | S104: =$C104*P104/100 -> 0 | W104: =$C104*V104/100 -> 0 | AA104: =$C104*Z104/100 -> 0 | AE104: =$C104*AD104/100 -> 0 | AI104: =$C104*AH104/100 -> 0
B105: 8.2.9 Rendred | C105: 0.26 | G105: =$C105*F105/100 -> 0 | K105: =$C105*H105/100 -> 0 | O105: =$C105*N105/100 -> 0 | S105: =$C105*P105/100 -> 0 | W105: =$C105*V105/100 -> 0 | AA105: =$C105*Z105/100 -> 0 | AE105: =$C105*AD105/100 -> 0 | AI105: =$C105*AH105/100 -> 0
B106: 8.2.10 Rendred and painted | C106: 0.35 | G106: =$C106*F106/100 -> 0 | K106: =$C106*H106/100 -> 0 | O106: =$C106*N106/100 -> 0 | S106: =$C106*P106/100 -> 0 | W106: =$C106*V106/100 -> 0 | AA106: =$C106*Z106/100 -> 0 | AE106: =$C106*AD106/100 -> 0 | AI106: =$C106*AH106/100 -> 0
...

Sheet Plot grade
B1: No | D1: Plot grade
B2: 1 | D2: 1-1b
B3: 2 | D3: 1-1a
B4: 3 | D4: 1-1
B5: 4 | D5: 1-2
B6: 5 | D6: 2-1
B7: 6 | D7: 1-3
B8: 7 | D8: 2-2
B9: 8 | D9: 3-1
B10: 9 | D10: 2-3
B11: 10 | D11: 3-2
B12: 11 | D12: 4-1
B13: 12 | D13: 3-3
... B16: 15 | D16: 4-4
B18: Lot Area | D18: 1-1b | F18: 1-1a | H18: 1-1 | J18: 1-2 | L18: 2-1 | N18: 1-3 | P18: 2-2 | R18: 3-1 | T18: 2-3 | V18: 3-2 | X18: 4-1 | Z18: 3-3 | AB18: 4-2 | AD18: 4-3 | AF18: 4-4
D19: 1 | F19: 2 | H19: 3 | J19: 4 | L19: 5 | N19: 6 | P19: 7 | R19: 8 | T19: 9 | V19: 10 | X19: 11 | Z19: 12 | AB19: 13 | AD19: 14 | AF19: 15
B20: 0-100 | C20: 100 | D20: 67844 | E20: =$C$20*D20 -> 6784400 | F20: 44355 | G20: =$C$20*F20 -> 4435500 | H20: 35523 | I20: =$C$20*H20 -> 3552300 | J20: 30912 | K20: =$C$20*J20 -> 3091200 | L20: 26368 | M20: =$C$20*L20 -> 2636800 | N20: 23599 | O20: =$C$20*N20 -> 2359900 | P20: 21576 | Q20: =$C$20*P20 -> 2157600 | R20: 20351 | S20: =$C$20*R20 -> 2035100 | T20: 17283 | U20: =$C$20*T20 -> 1728300 | V20: 16267 | W20: =$C$20*V20 -> 1626700 | X20: 15202 | Y20: =$C$20*X20 -> 1520200 | Z20: 14559 | AA20: =$C$20*Z20 -> 1455900 | AB20: 14168 | AC20: =$C$20*AB20 -> 1416800 | AD20: 13275 | AE20: =$C$20*AD20 -> 1327500 | AF20: 126888
B21: 101-200 | C21: 200 | D21: 62975 | E21: =E20+((C21-C20)*D21) -> 13081900 | F21: 43454 | G21: =G20+((C21-C20)*F21) -> 8780900 | H21: 345992 | I21: =I20+((C21-C20)*H21) -> 38151500 | J21: 30521 | K21: =K20+((C21-C20)*J21) -> 6143300 | L21: 26031 | M21: =M20+((C21-C20)*L21) -> 5239900 | N21: 23069 | O21: =O20+((C21-C20)*N21) -> 4666800 | P21: 20104 | Q21: =Q20+((C21-C20)*P21) -> 4168000 | R21: 18420 | S21: =S20+((C21-C20)*R21) -> 3877100 | T21: 17082 | U21: =U20+((C21-C20)*T21) -> 3436500 | V21: 15588 | W21: =W20+((C21-C20)*V21) -> 3185500 | X21: 14625 | Y21: =Y20+((C21-C20)*X21) -> 2982700 | Z21: 14104 | AA21: =AA20+((C21-C20)*Z21) -> 2866300 | AB21: 13800 | AC21: =AC20+((C21-C20)*AB21) -> 2796800 | AD21: 12537 | AE21: =AE20+((C21-C20)*AD21) -> 2581200 | AF21: 11933
B22: 201-300 | C22: 300 | D22: 58106 | E22: =E21+((C22-C21)*D22) -> 18892500 | F22: 42553 | G22: =G21+((C22-C21)*F22) -> 13036200 | H22: 34261 | I22: =I21+((C22-C21)*H22) -> 41577600 | J22: 30130 | K22: =K21+((C22-C21)*J22) -> 9156300 | L22: 25694 | M22: =M21+((C22-C21)*L22) -> 7809300 | N22: 22539 | O22: =O21+((C22-C21)*N22) -> 6920700 | P22: 19022 | Q22: =Q21+((C22-C21)*P22) -> 6070200 | R22: 17315 | S22: =S21+((C22-C21)*R22) -> 5608600 | T22: 16898 | U22: =U21+((C22-C21)*T22) -> 5126300 | V22: 14991 | W22: =W21+((C22-C21)*V22) -> 4684600 | X22: 14128 | Y22: =Y21+((C22-C21)*X22) -> 4395500 | Z22: 13518 | AA22: =AA21+((C22-C21)*Z22) -> 4218100 | AB22: 13622 | AC22: =AC21+((C22-C21)*AB22) -> 4159000 | AD22: 11799 | AE22: =AE21+((C22-C21)*AD22) -> 3761100 | AF22: 11318
B23: 301-400 | C23: 400 | D23: 54919 | E23: =E22+((C23-C22)*D23) -> 24384400 | F23: 41705 | G23: =G22+((C23-C22)*F23) -> 17206700 | H23: 33805 | I23: =I22+((C23-C22)*H23) -> 44958100 | J23: 29745 | K23: =K22+((C23-C22)*J23) -> 12130800 | L23: 25445 | M23: =M22+((C23-C22)*L23) -> 10353800 | N23: 22284 | O23: =O22+((C23-C22)*N23) -> 9149100 | P23: 18829 | Q23: =Q22+((C23-C22)*P23) -> 7953100 | R23: 17146 | S23: =S22+((C23-C22)*R23) -> 7323200 | T23: 16726 | U23: =U22+((C23-C22)*T23) -> 6798900 | V23: 14541 | W23: =W22+((C23-C22)*V23) -> 6138700 | X23: 13986 | Y23: =Y22+((C23-C22)*X23) -> 5794100 | Z23: 13385 | AA23: =AA22+((C23-C22)*Z23) -> 5556600 | AB23: 13487 | AC23: =AC22+((C23-C22)*AB23) -> 5507700 | AD23: 11644 | AE23: =AE22+((C23-C22)*AD23) -> 4925500 | AF23: 11197
B24: 401-500 | C24: 500 | D24: 54358 | E24: =E23+((C24-C23)*D24) -> 29820200 | F24: 41283 | G24: =G23+((C24-C23)*F24) -> 21335000 | H24: 33463 | I24: =I23+((C24-C23)*H24) -> 48304400 | J24: 29444 | K24: =K23+((C24-C23)*J24) -> 15075200 | L24: 25195 | M24: =M23+((C24-C23)*L24) -> 12873300 | N24: 22048 | O24: =O23+((C24-C23)*N24) -> 11353900 | P24: 18636 | Q24: =Q23+((C24-C23)*P24) -> 9816700 | R24: 16977 | S24: =S23+((C24-C23)*R24) -> 9020900 | T24: 16554 | U24: =U23+((C24-C23)*T24) -> 8454300 | V24: 14691 | W24: =W23+((C24-C23)*V24) -> 7607800 | X24: 13844 | Y24: =Y23+((C24-C23)*X24) -> 7178500 | Z24: 13252 | AA24: =AA23+((C24-C23)*Z24) -> 6881800 | AB24: 13352 | AC24: =AC23+((C24-C23)*AB24) -> 6842900 | AD24: 11513 | AE24: =AE23+((C24-C23)*AD24) -> 6076800 | AF24: 11076
B25: 501-600 | C25: 600 | D25: 20732 | E25: =E24+((C25-C24)*D25) -> 31893400 | F25: 18639 | G25: =G24+((C25-C24)*F25) -> 23198900 | H25: 17813 | I25: =I24+((C25-C24)*H25) -> 50085700 | J25: 18643 | K25: =K24+((C25-C24)*J25) -> 16939500 | L25: 16694 | M25: =M24+((C25-C24)*L25) -> 14542700 | N25: 14505 | O25: =O24+((C25-C24)*N25) -> 12804400 | P25: 14141 | Q25: =Q24+((C25-C24)*P25) -> 11230800 | R25: 12909 | S25: =S24+((C25-C24)*R25) -> 10311800 | T25: 11677 | U25: =U24+((C25-C24)*T25) -> 9622000 | V25: 11071 | W25: =W24+((C25-C24)*V25) -> 8714900 | X25: 10703 | Y25: =Y24+((C25-C24)*X25) -> 8248800 | Z25: 9812 | AA25: =AA24+((C25-C24)*Z25) -> 7863000 | AB25: 7311 | AC25: =AC24+((C25-C24)*AB25) -> 7574000 | AD25: 7239 | AE25: =AE24+((C25-C24)*AD25) -> 6800700 | AF25: 6212
B26: 601-700 | C26: 700 | D26: 20477 | E26: =E25+((C26-C25)*D26) -> 33941100 | F26: 18351 | G26: =G25+((C26-C25)*F26) -> 25034000 | H26: 17591 | I26: =I25+((C26-C25)*H26) -> 51844800 | J26: 16832 | K26: =K25+((C26-C25)*J26) -> 18622700 | L26: 16408 | M26: =M25+((C26-C25)*L26) -> 16183500 | N26: 14318 | O26: =O25+((C26-C25)*N26) -> 14236200 | P26: 13946 | Q26: =Q25+((C26-C25)*P26) -> 12625400 | R26: 12612 | S26: =S25+((C26-C25)*R26) -> 11573000 | T26: 11545 | U26: =U25+((C26-C25)*T26) -> 10776500 | V26: 11006 | W26: =W25+((C26-C25)*V26) -> 9815500 | X26: 10551 | Y26: =Y25+((C26-C25)*X26) -> 9303900 | Z26: 9731 | AA26: =AA25+((C26-C25)*Z26) -> 8836100 | AB26: 7221 | AC26: =AC25+((C26-C25)*AB26) -> 8296100 | AD26: 7215 | AE26: =AE25+((C26-C25)*AD26) -> 7522200 | AF26: 6167
B27: 701-800 | C27: 800 | D27: 20213 | E27: =E26+((C27-C26)*D27) -> 35962400 | F27: 18501 | G27: =G26+((C27-C26)*F27) -> 26884100 | H27: 18739 | I27: =I26+((C27-C26)*H27) -> 53718700 | J27: 18220 | K27: =K26+((C27-C26)*J27) -> 20444700 | L27: 16394 | M27: =M26+((C27-C26)*L27) -> 17822900 | N27: 14154 | O27: =O26+((C27-C26)*N27) -> 15651600 | P27: 13967 | Q27: =Q26+((C27-C26)*P27) -> 14022100 | R27: 13388 | S27: =S26+((C27-C26)*R27) -> 12911800 | T27: 12804 | U27: =U26+((C27-C26)*T27) -> 12056900 | V27: 12348 | W27: =W26+((C27-C26)*V27) -> 11050300 | X27: 11897 | Y27: =Y26+((C27-C26)*X27) -> 10493600 | Z27: 10044 | AA27: =AA26+((C27-C26)*Z27) -> 9840500 | AB27: 8936 | AC27: =AC26+((C27-C26)*AB27) -> 9189700 | AD27: 7184 | AE27: =AE26+((C27-C26)*AD27) -> 8240600 | AF27: 6118
B28: 801-900 | C28: 900 | D28: 25258 | E28: =E27+((C28-C27)*D28) -> 38488200 | F28: 23415 | G28: =G27+((C28-C27)*F28) -> 29225600 | H28: 23415 | I28: =I27+((C28-C27)*H28) -> 56060200 | J28: 22656 | K28: =K27+((C28-C27)*J28) -> 22710300 | L28: 21508 | M28: =M27+((C28-C27)*L28) -> 19973700 | N28: 20158 | O28: =O27+((C28-C27)*N28) -> 17667400 | P28: 20107 | Q28: =Q27+((C28-C27)*P28) -> 16032800 | R28: 19988 | S28: =S27+((C28-C27)*R28) -> 14910600 | T28: 19861 | U28: =U27+((C28-C27)*T28) -> 14043000 | V28: 19614 | W28: =W27+((C28-C27)*V28) -> 13011700 | X28: 19382 | Y28: =Y27+((C28-C27)*X28) -> 12431800 | Z28: 16111 | AA28: =AA27+((C28-C27)*Z28) -> 11451600 | AB28: 14026 | AC28: =AC27+((C28-C27)*AB28) -> 10592300 | AD28: 7158 | AE28: =AE27+((C28-C27)*AD28) -> 8956400 | AF28: 6062
B29: 901-1000 | C29: 1000 | D29: 25001 | E29: =E28+((C29-C28)*D29) -> 40988300 | F29: 23190 | G29: =G28+((C29-C28)*F29) -> 31544600 | H29: 23190 | I29: =I28+((C29-C28)*H29) -> 58379200 | J29: 23332 | K29: =K28+((C29-C28)*J29) -> 25043500 | L29: 21968 | M29: =M28+((C29-C28)*L29) -> 22170500 | N29: 21622 | O29: =O28+((C29-C28)*N29) -> 19829600 | P29: 20783 | Q29: =Q28+((C29-C28)*P29) -> 18111100 | R29: 20366 | S29: =S28+((C29-C28)*R29) -> 16947200 | T29: 19943 | U29: =U28+((C29-C28)*T29) -> 16037300 | V29: 19871 | W29: =W28+((C29-C28)*V29) -> 14998800 | X29: 19249 | Y29: =Y28+((C29-C28)*X29) -> 14356700 | Z29: 18181 | AA29: =AA28+((C29-C28)*Z29) -> 13269700 | AB29: 16066 | AC29: =AC28+((C29-C28)*AB29) -> 12198900 | AD29: 7130 | AE29: =AE28+((C29-C28)*AD29) -> 9669400 | AF29: 6011
B30: 1001-1100 | C30: 1100 | D30: 24751 | E30: =E29+((C30-C29)*D30) -> 43463400 | F30: 22575 | G30: =G29+((C30-C29)*F30) -> 33802100 | H30: 21758 | I30: =I29+((C30-C29)*H30) -> 60555000 | J30: 21064 | K30: =K29+((C30-C29)*J30) -> 27149900 | L30: 20168 | M30: =M29+((C30-C29)*L30) -> 24187300 | N30: 19825 | O30: =O29+((C30-C29)*N30) -> 21812100 | P30: 18009 | Q30: =Q29+((C30-C29)*P30) -> 19912000 | R30: 17165 | S30: =S29+((C30-C29)*R30) -> 18663700 | T30: 16316 | U30: =U29+((C30-C29)*T30) -> 17668900 | V30: 7699 | W30: =W29+((C30-C29)*V30) -> 15768700 | X30: 7486 | Y30: =Y29+((C30-C29)*X30) -> 15105300 | Z30: 7412 | AA30: =AA29+((C30-C29)*Z30) -> 14010900 | AB30: 7340 | AC30: =AC29+((C30-C29)*AB30) -> 12932900 | AD30: 6600 | AE30: =AE29+((C30-C29)*AD30) -> 10329400 | AF30: 5966
B31: 1101-1200 | C31: 1200 | D31: 26991 | E31: =E30+((C31-C30)*D31) -> 46162500 | F31: 25943 | G31: =G30+((C31-C30)*F31) -> 36396400 | H31: 21050 | I31: =I30+((C31-C30)*H31) -> 62660000 | J31: 20390 | K31: =K30+((C31-C30)*J31) -> 29188900 | L31: 19852 | M31: =M30+((C31-C30)*L31) -> 26172500 | N31: 19488 | O31: =O30+((C31-C30)*N31) -> 23760900 | P31: 17803 | Q31: =Q30+((C31-C30)*P31) -> 21692300 | R31: 16905 | S31: =S30+((C31-C30)*R31) -> 20354200 | T31: 15843 | U31: =U30+((C31-C30)*T31) -> 19253200 | V31: 7623 | W31: =W30+((C31-C30)*V31) -> 16531000 | X31: 7335 | Y31: =Y30+((C31-C30)*X31) -> 15838800 | Z31: 7276 | AA31: =AA30+((C31-C30)*Z31) -> 14738500 | AB31: 7249 | AC31: =AC30+((C31-C30)*AB31) -> 13657800 | AD31: 6545 | AE31: =AE30+((C31-C30)*AD31) -> 10983900 | AF31: 5916
B32: 1201-1300 | C32: 1300 | D32: 26638 | E32: =E31+((C32-C31)*D32) -> 48826300 | F32: 25605 | G32: =G31+((C32-C31)*F32) -> 38956900 | H32: 17908 | I32: =I31+((C32-C31)*H32) -> 64450800 | J32: 17269 | K32: =K31+((C32-C31)*J32) -> 30915800 | L32: 16881 | M32: =M31+((C32-C31)*L32) -> 27860600 | N32: 16517 | O32: =O31+((C32-C31)*N32) -> 25412600 | P32: 15951 | Q32: =Q31+((C32-C31)*P32) -> 23287400 | R32: 16558 | S32: =S31+((C32-C31)*R32) -> 22010000 | T32: 15382 | U32: =U31+((C32-C31)*T32) -> 20791400 | V32: 7699 | W32: =W31+((C32-C31)*V32) -> 17300900 | X32: 7184 | Y32: =Y31+((C32-C31)*X32) -> 16557200 | Z32: 7148 | AA32: =AA31+((C32-C31)*Z32) -> 15453300 | AB32: 7099 | AC32: =AC31+((C32-C31)*AB32) -> 14367700 | AD32: 5361 | AE32: =AE31+((C32-C31)*AD32) -> 11520000 | AF32: 5875
... B44: 40001-70000 | C44: 70000 | D44: 4540 | E44: =E43+((C44-C43)*D44) -> 574677400 | F44: 4134 | G44: =G43+((C44-C43)*F44) -> 511702900 | H44: 4034 | I44: =I43+((C44-C43)*H44) -> 453592000 | J44: 3673 | K44: =K43+((C44-C43)*J44) -> 397844300 | L44: 3166 | M44: =M43+((C44-C43)*L44) -> 990523500 | N44: 2597 | O44: =O43+((C44-C43)*N44) -> 307058300 | P44: 2477 | Q44: =Q43+((C44-C43)*P44) -> 281272400 | R44: 2237 | S44: =S43+((C44-C43)*R44) -> 230181800 | T44: 1936 | U44: =U43+((C44-C43)*T44) -> 210368600 | V44: 1640 | W44: =W43+((C44-C43)*V44) -> 190544300 | X44: 1328 | Y44: =Y43+((C44-C43)*X44) -> 173690500 | Z44: 850 | AA44: =AA43+((C44-C43)*Z44) -> 151894500 | AB44: 715 | AC44: =AC43+((C44-C43)*AB44) -> 141740600 | AD44: 520 | AE44: =AE43+((C44-C43)*AD44) -> 87844900 | AF44: 547
B45: >70000 | D45: 2012 | E45: =E44+((C45-C44)*D45) -> 433837400 | F45: 1874 | G45: =G44+((C45-C44)*F45) -> 380522900 | H45: 1848 | I45: =I44+((C45-C44)*H45) -> 324232000 | J45: 1738 | K45: =K44+((C45-C44)*J45) -> 276184300 | L45: 1488 | M45: =M44+((C45-C44)*L45) -> 886363500 | N45: 1218 | O45: =O44+((C45-C44)*N45) -> 221798300 | P45: 1079 | Q45: =Q44+((C45-C44)*P45) -> 205742400 | R45: 1089 | S45: =S44+((C45-C44)*R45) -> 153951800 | T45: 707 | U45: =U44+((C45-C44)*T45) -> 160878600 | V45: 677 | W45: =W44+((C45-C44)*V45) -> 143154300 | X45: 641 | Y45: =Y44+((C45-C44)*X45) -> 128820500 | Z45: 401 | AA45: =AA44+((C45-C44)*Z45) -> 123824500 | AB45: 364 | AC45: =AC44+((C45-C44)*AB45) -> 116260600 | AD45: 361 | AE45: =AE44+((C45-C44)*AD45) -> 62574900 | AF45: 295
B48: Architectural
B49: Structural
B50: Electrical
B51: Sanitary
B52: Specification and Bill of quantity
B54: Water Supply & Drain Line
B55: Septic tank
B56: Intake line & man holes
B57: Compound lighting

Sheet Fence and Compund
B2: Fence Work
A3: Item | B3: Description | C3: Unit | D3: Quantity | E3: New Rate | F3: Amount | H3: =IF(SUM(F4:F55)=0,"-",1) -> 1
A4: 1 | B4: Stone masonry fence, semi-dressed | H4: =IF(SUM(F5:F12)=0,"-",1) -> -
A5: 1.1 | B5: Left for finishing | C5: m3 | E5: 1605.37 | F5: =E5*D5 -> 0 | H5: =IF(F5=0,"-",1) -> -
A6: 1.2 | B6: One side pointed | C6: m3 | E6: 1678.86 | F6: =E6*D6 -> 0 | H6: =IF(F6=0,"-",1) -> -
A7: 1.3 | B7: Two sides pointed | C7: m3 | E7: 1752.37 | F7: =E7*D7 -> 0 | H7: =IF(F7=0,"-",1) -> -
A8: 1.4 | B8: One sides plastered | C8: m3 | E8: 1812.39 | F8: =E8*D8 -> 0 | H8: =IF(F8=0,"-",1) -> -
A9: 1.5 | B9: Two side plastered | C9: m3 | E9: 1756.01 | F9: =E9*D9 -> 0 | H9: =IF(F9=0,"-",1) -> -
A10: 1.6 | B10: One side rendered | C10: m3 | E10: 1575.99 | F10: =E10*D10 -> 0 | H10: =IF(F10=0,"-",1) -> -
A11: 1.7 | B11: Two sides rendered | C11: m3 | E11: 1756.01 | F11: =E11*D11 -> 0 | H11: =IF(F11=0,"-",1) -> -
A12: 1.8 | B12: Painting (add to the above fence work if there is any) | C12: m2 | E12: 62.84 | F12: =E12*D12 -> 0 | H12: =IF(F12=0,"-",1) -> -
A13: 2 | B13: Stone masonry fence well dressed | E13: 0 | H13: =IF(SUM(F14:F17)=0,"-",1) -> -
A14: 2.1 | B14: Left for finishing | C14: m3 | E14: 1679.81 | F14: =E14*D14 -> 0 | H14: =IF(F14=0,"-",1) -> -
A15: 2.2 | B15: One side pointed | C15: m3 | E15: 1743.72 | F15: =E15*D15 -> 0 | H15: =IF(F15=0,"-",1) -> -
A16: 2.4 | B16: Two sides pointed | C16: m3 | E16: 1807.64 | F16: =E16*D16 -> 0 | H16: =IF(F16=0,"-",1) -> -
A17: 2.5 | B17: Foundation (Add on the above fence work) | C17: ml | E17: 989.95 | F17: =E17*D17 -> 0 | H17: =IF(F17=0,"-",1) -> -
A18: 3 | B18: HCB fence | F18: =E18*D18 -> 0 | H18: =IF(SUM(F19:F26)=0,"-",1) -> 1
A19: 3.1 | B19: Left for finishing | C19: m2 | E19: 444.21 | F19: =E19*D19 -> 0 | H19: =IF(F19=0,"-",1) -> -
A20: 3.2 | B20: One side pointed | C20: m2 | E20: 532.4 | F20: =E20*D20 -> 0 | H20: =IF(F20=0,"-",1) -> -
A21: 3.3 | B21: Two sides pointed | C21: m2 | E21: 620.61 | F21: =E21*D21 -> 0 | H21: =IF(F21=0,"-",1) -> -
A22: 3.4 | B22: One side plastered | C22: m2 | E22: 692.63 | F22: =E22*D22 -> 0 | H22: =IF(F22=0,"-",1) -> -
A23: 3.5 | B23: Two side plastered | C23: m2 | E23: 750.12 | F23: =E23*D23 -> 0 | H23: =IF(F23=0,"-",1) -> -
A24: 3.6 | B24: One side rendered | C24: m2 | E24: 692.63 | F24: =E24*D24 -> 0 | H24: =IF(F24=0,"-",1) -> -
A25: 3.7 | B25: Two sides rendered | C25: m2 | D25: =+(8+11.83-3)*2.5 -> 42.075 | E25: 750.12 | F25: =E25*D25 -> 31561.299 | H25: =IF(F25=0,"-",1) -> 1
A26: 3.8 | B26: Painting (Add the unit price on the above finishing if there are any) | C26: m2 | E26: 62.84 | F26: =E26*D26 -> 0 | H26: =IF(F26=0,"-",1) -> -
A27: 4 | B27: Brick fence (25cm thick) | H27: =IF(SUM(F28:F35)=0,"-",1) -> -
A28: 4.1 | B28: Left for finishing | C28: m2 | E28: 1659.38 | F28: =E28*D28 -> 0 | H28: =IF(F28=0,"-",1) -> -
A29: 4.2 | B29: One side pointed | C29: m2 | E29: 1710.51 | F29: =E29*D29 -> 0 | H29: =IF(F29=0,"-",1) -> -
A30: 4.3 | B30: Two sides pointed | C30: m2 | E30: 1761.65 | F30: =E30*D30 -> 0 | H30: =IF(F30=0,"-",1) -> -
A31: 4.4 | B31: One side plastered | C31: m2 | E31: 1803.4 | F31: =E31*D31 -> 0 | H31: =IF(F31=0,"-",1) -> -
A32: 4.5 | B32: Two sides plastered | C32: m2 | E32: 1947.42 | F32: =E32*D32 -> 0 | H32: =IF(F32=0,"-",1) -> -
A33: 4.6 | B33: One side rendered | C33: m2 | E33: 1659.38 | F33: =E33*D33 -> 0 | H33: =IF(F33=0,"-",1) -> -
A34: 4.7 | B34: Two sides rendered | C34: m2 | E34: 1803.4 | F34: =E34*D34 -> 0 | H34: =IF(F34=0,"-",1) -> -
A35: 4.8 | B35: Painting (Add the unit price on the above finishing if there are any) | C35: m2 | E35: 62.84 | F35: =E35*D35 -> 0 | H35: =IF(F35=0,"-",1) -> -
A36: 5 | B36: Brick fence (12cm) | H36: =IF(SUM(F37:F44)=0,"-",1) -> -
A37: 5.1 | B37: Left for finishing | C37: m2 | E37: 1015.44 | F37: =E37*D37 -> 0 | H37: =IF(F37=0,"-",1) -> -
A38: 5.2 | B38: One side pointed | C38: m2 | E38: 1144.07 | F38: =E38*D38 -> 0 | H38: =IF(F38=0,"-",1) -> -
A39: 5.3 | B39: Two sides pointed | C39: m2 | E39: 1272.7 | F39: =E39*D39 -> 0 | H39: =IF(F39=0,"-",1) -> -
A40: 5.4 | B40: One side plastered | C40: m2 | E40: 1195.46 | F40: =E40*D40 -> 0 | H40: =IF(F40=0,"-",1) -> -
A41: 5.5 | B41: Two sides plastered | C41: m2 | E41: 1375.48 | F41: =E41*D41 -> 0 | H41: =IF(F41=0,"-",1) -> -
A42: 5.6 | B42: One side rendered | C42: m2 | E42: 1195.46 | F42: =E42*D42 -> 0 | H42: =IF(F42=0,"-",1) -> -
A43: 5.7 | B43: Two sides rendered | C43: m2 | E43: 1375.48 | F43: =E43*D43 -> 0 | H43: =IF(F43=0,"-",1) -> -
A44: 5.8 | B44: Painting (add to the above fence work) | C44: m2 | E44: 62.84 | F44: =E44*D44 -> 0 | H44: =IF(F44=0,"-",1) -> -
A45: 6 | B45: Hydra foam Fence (12cm) | H45: =IF(SUM(F46:F53)=0,"-",1) -> 1
A46: 6.1 | B46: Left for finishing | C46: m2 | E46: 322.85 | F46: =E46*D46 -> 0 | H46: =IF(F46=0,"-",1) -> -
A47: 7 | B47: Hydra foam Fence (14cm) | H47: =IF(SUM(F48:F55)=0,"-",1) -> 1
A48: 7.1 | B48: Left for finishing | C48: m2 | E48: 437.78 | F48: =E48*D48 -> 0 | H48: =IF(F48=0,"-",1) -> -
A49: 8 | B49: Metal grill | C49: m2 | E49: 2120 | F49: =E49*D49 -> 0 | H49: =IF(F49=0,"-",1) -> -
A50: 9 | B50: RHS metal grill fence | C50: ml | E50: 848.4 | F50: =E50*D50 -> 0 | H50: =IF(F50=0,"-",1) -> -
A51: 10 | B51: Main gate with metal sheet | C51: m2 | E51: 1950 | F51: =E51*D51 -> 0 | H51: =IF(F51=0,"-",1) -> -
A52: 11 | B52: Main gate with RHS grill structure | C52: m2 | D52: 12 | E52: 2800 | F52: =E52*D52 -> 33600 | H52: =IF(F52=0,"-",1) -> 1
A53: 12 | B53: Decorated gates with RHS grill structure and metal sheet | C53: m2 | E53: 4550 | F53: =E53*D53 -> 0 | H53: =IF(F53=0,"-",1) -> -
A54: 13 | B54: Securty Wire | C54: ml | D54: =8+11 -> 19 | E54: 441.2 | F54: =E54*D54 -> 8382.8 | H54: =IF(F54=0,"-",1) -> 1
B55: Total Fence Work | E55: 0 | F55: =SUM(F6:F54) -> 73544.099 | H55: =IF(F55=0,"-",1) -> 1
E56: 0 | H56: =IF(D56=0,"-",1) -> -
B57: Compound Work | E57: 0 | H57: =IF(SUM(F58:F65)=0,"-",1) -> -
A58: Item | B58: Description | C58: Unit | D58: Quantity | E58: Rate | F58: Amount | H58: =IF(SUM(F59:F66)=0,"-",1) -> 1
A59: 1 | B59: 7cm-thick red ash pavement | C59: m2 | E59: 91.23 | F59: =D59*E59 -> 0 | H59: =IF(F59=0,"-",1) -> -
A60: 2 | B60: 5cm-thick gravel pavement | C60: m2 | E60: 165 | F60: =D60*E60 -> 0 | H60: =IF(F60=0,"-",1) -> -
A61: 3 | B61: Roughly dressed stone pavement | C61: m2 | E61: 496.95 | F61: =D61*E61 -> 0 | H61: =IF(F61=0,"-",1) -> -
A62: 4 | B62: Asphalt | C62: m2 | E62: 1142.86 | F62: =D62*E62 -> 0 | H62: =IF(F62=0,"-",1) -> -
A63: 5 | B63: 10cm thick C-15 concrete pavement | C63: m2 | E63: 699.23 | F63: =D63*E63 -> 0 | H63: =IF(F63=0,"-",1) -> -
A64: 6 | B64: Ditto but RC pavement | C64: m2 | E64: 898.24 | F64: =D64*E64 -> 0 | H64: =IF(F64=0,"-",1) -> -
A65: 7 | B65: Checkered tile with 15cm thick RC slab | C65: m2 | E65: 1227.04 | F65: =D65*E65 -> 0 | H65: =IF(F65=0,"-",1) -> -
A66: 8 | B66: Checkered tile with mass concrete | C66: m2 | D66: =94-Area!D4 -> 20.174 | E66: 849.82 | F66: =D66*E66 -> 17144.269 | H66: =IF(F66=0,"-",1) -> 1
A67: 9 | B67: Best Quality marble chips with RC concrete | C67: m2 | E67: 1128.5 | F67: =D67*E67 -> 0 | H67: =IF(F67=0,"-",1) -> -
A68: 10 | B68: Harar marble chips with RC concrete | C68: m2 | E68: 1512.28 | F68: =D68*E68 -> 0 | H68: =IF(F68=0,"-",1) -> -
A69: 11 | B69: Terrazzo tile with RC concrete | C69: m2 | E69: 1366.44 | F69: =D69*E69 -> 0 | H69: =IF(F69=0,"-",1) -> -
A70: 12 | B70: Ditto but with mass concrete | C70: m2 | E70: 989.22 | F70: =D70*E70 -> 0 | H70: =IF(F70=0,"-",1) -> -
A71: 13 | B71: Ceramic tile with RC concrete | C71: m2 | E71: 1885.15 | F71: =D71*E71 -> 0 | H71: =IF(F71=0,"-",1) -> -
A72: 14 | B72: Ditto but with mass concrete. | C72: m2 | E72: 1507.94 | F72: =D72*E72 -> 0 | H72: =IF(F72=0,"-",1) -> -
A73: 15 | B73: Cement tile with RC concrete | C73: m2 | E73: 1227.04 | F73: =D73*E73 -> 0 | H73: =IF(F73=0,"-",1) -> -
A74: 16 | B74: Ditto but with mass concrete. | C74: m2 | E74: 840.73 | F74: =D74*E74 -> 0 | H74: =IF(F74=0,"-",1) -> -
A75: 17 | B75: Concrete Curb Stone | C75: ml | E75: 400.22 | F75: =D75*E75 -> 0 | H75: =IF(F75=0,"-",1) -> -
B76: Total Compound Work | F76: =SUM(F59:F75) -> 17144.269 | H76: =IF(F76=0,"-",1) -> 1
H77: =IF(F77=0,"-",1) -> -
B78: Total Fence & Compound Work | F78: =(F76+F55)*2.75 -> 249393.01 | H78: =IF(F78=0,"-",1) -> 1
A79: WATER TANKS AND SUPPORTS | H79: =IF(SUM(F80:F87)=0,"-",1) -> -
A80: 1.0 Water tanks | H80: =IF(SUM(F81:F88)=0,"-",1) -> -
A81: 1.1 Plastic Water Tanks | E81: 0 | H81: =IF(SUM(F82:F89)=0,"-",1) -> -
A82: Item No. | B82: Capacity ( litters) | C82: unit | D82: Quantity | E82: Rate | F82: Amount | H82: =IF(SUM(F83:F90)=0,"-",1) -> -
A83: 1 | B83: 250 | C83: pcs | E83: 1620 | F83: =E83*D83 -> 0 | H83: =IF(F83=0,"-",1) -> -
A84: 2 | B84: 500 | C84: pcs | E84: 2775 | F84: =E84*D84 -> 0 | H84: =IF(F84=0,"-",1) -> -
A85: 3 | B85: 1000 | C85: pcs | E85: 5025 | F85: =E85*D85 -> 0 | H85: =IF(F85=0,"-",1) -> -
A86: 4 | B86: 1500 | C86: pcs | E86: 5700 | F86: =E86*D86 -> 0 | H86: =IF(F86=0,"-",1) -> -
A87: 5 | B87: 2000 | C87: pcs | E87: 7950 | F87: =E87*D87 -> 0 | H87: =IF(F87=0,"-",1) -> -
A88: 7 | B88: 3000 | C88: pcs | E88: 12300 | F88: =E88*D88 -> 0 | H88: =IF(F88=0,"-",1) -> -
A89: 8 | B89: 4000 | C89: pcs | E89: 16950 | F89: =E89*D89 -> 0 | H89: =IF(F89=0,"-",1) -> -
A90: 9 | B90: 5000 | C90: pcs | E90: 20700 | F90: =E90*D90 -> 0 | H90: =IF(F90=0,"-",1) -> -
A91: 10 | B91: 7500 | C91: pcs | E91: 26883 | F91: =E91*D91 -> 0 | H91: =IF(F91=0,"-",1) -> -
A92: 11 | B92: 10000 | C92: pcs | E92: 40365 | F92: =E92*D92 -> 0 | H92: =IF(F92=0,"-",1) -> -
A93: 1.2 Fiberglass Water Tanks | E93: 0 | H93: =IF(SUM(F94:F101)=0,"-",1) -> 1
A94: 1 | B94: 250 | C94: pcs | E94: 3046 | F94: =E94*D94 -> 0 | H94: =IF(F94=0,"-",1) -> -
A95: 2 | B95: 500 | C95: pcs | E95: 4586 | F95: =E95*D95 -> 0 | H95: =IF(F95=0,"-",1) -> -
A96: 3 | B96: 1000 | C96: pcs | E96: 5410 | F96: =E96*D96 -> 0 | H96: =IF(F96=0,"-",1) -> -
A97: 4 | B97: 1500 | C97: pcs | E97: 7494 | F97: =E97*D97 -> 0 | H97: =IF(F97=0,"-",1) -> -
A98: 5 | B98: 2000 | C98: pcs | E98: 9340 | F98: =E98*D98 -> 0 | H98: =IF(F98=0,"-",1) -> -
A99: 6 | B99: 3000 | C99: pcs | D99: 1 | E99: 14496 | F99: =E99*D99 -> 14496 | H99: =IF(F99=0,"-",1) -> 1
A100: 7 | B100: 4000 | C100: pcs | E100: 16564 | F100: =E100*D100 -> 0 | H100: =IF(F100=0,"-",1) -> -
A101: 8 | B101: 5000 | C101: pcs | E101: 21268 | F101: =E101*D101 -> 0 | H101: =IF(F101=0,"-",1) -> -
...

Sheet Location
A6: Location value
A7: Property location
A8: City | B8: Addis Ababa
A9: Sub city | B9: Addis Ketma
A10: Worda/Kebele | B10: W-01
A11: Plot Area | B11: =Sheet2!D11 -> 94
A12: Plot Grade | B12: 2-1
A13: Location Value | B13: =IF(B12="1-1b",D48,IF(B12="1-1a",F48,IF(B12="1-1",H48,IF(B12="1-2",J48,IF(B12="2-1",L48,IF(B12="1-3",N48,IF(B12="2-2",P48,IF(B12="3-1",R48,IF(B12="2-3",T48,IF(B12="3-2",V48,IF(B12="4-1",X48,IF(B12="3-3",Z48,IF(B12="4-2",AB48,IF(B12="4-3",AD48,IF(B12="4-4",AF48))))))))))))))) -> 2478592
A14: Total lease amount
A15: Paid up Lease amount | B15: 0
A16: Remaining lease amount
A17: Location Value | B17: =B13 -> 2478592 | D17: =B17/B11 -> 26368
A18: Location value in previous Estimation | Q18: =B13-Q19 -> -1432964.9
A19: Location value Considered | B19: =MAX(B17,B18)-B16 -> 2478592 | Q19: =(100*Q22)+(100*Q23)+(1.99*Q24) -> 3911556.9 | AE19: =100*AE22+100*AE23 -> 2462100
C20: 1-1b | E20: 1-1a | G20: 1-1 | I20: 1-2 | K20: 2-1 | M20: 1-3 | O20: 2-2 | Q20: 3-1 | S20: 2-3 | U20: 3-2 | W20: 4-1 | Y20: 3-3 | AA20: 4-2 | AC20: 4-3 | AE20: 4-4
C21: 1 | E21: 2 | G21: 3 | I21: 4 | K21: 5 | M21: 6 | O21: 7 | Q21: 8 | S21: 9 | U21: 10 | W21: 11 | Y21: 12 | AA21: 13 | AC21: 14 | AE21: 15
A22: 0-100 | B22: 100 | C22: 67844 | D22: =$B$22*C22 -> 6784400 | E22: 44355 | F22: =$B$22*E22 -> 4435500 | G22: 35523 | H22: =$B$22*G22 -> 3552300 | I22: 30912 | J22: =$B$22*I22 -> 3091200 | K22: 26368 | L22: =$B$22*K22 -> 2636800 | M22: 23599 | N22: =$B$22*M22 -> 2359900 | O22: 21576 | P22: =$B$22*O22 -> 2157600 | Q22: 20351 | R22: =$B$22*Q22 -> 2035100 | S22: 17283 | T22: =$B$22*S22 -> 1728300 | U22: 16267 | V22: =$B$22*U22 -> 1626700 | W22: 15202 | X22: =$B$22*W22 -> 1520200 | Y22: 14559 | Z22: =$B$22*Y22 -> 1455900 | AA22: 14168 | AB22: =$B$22*AA22 -> 1416800 | AC22: 13275 | AD22: =$B$22*AC22 -> 1327500 | AE22: 12688 | AF22: =$B$22*AE22 -> 1268800
A23: 101-200 | B23: 200 | C23: 62975 | D23: =D22+((B23-B22)*C23) -> 13081900 | E23: 43454 | F23: =F22+((B23-B22)*E23) -> 8780900 | G23: 34892 | H23: =H22+((B23-B22)*G23) -> 7041500 | I23: 30521 | J23: =J22+((B23-B22)*I23) -> 6143300 | K23: 26031 | L23: =L22+((B23-B22)*K23) -> 5239900 | M23: 23069 | N23: =N22+((B23-B22)*M23) -> 4666800 | O23: 20104 | P23: =P22+((B23-B22)*O23) -> 4168000 | Q23: 18420 | R23: =R22+((B23-B22)*Q23) -> 3877100 | S23: 17082 | T23: =T22+((B23-B22)*S23) -> 3436500 | U23: 15588 | V23: =V22+((B23-B22)*U23) -> 3185500 | W23: 14625 | X23: =X22+((B23-B22)*W23) -> 2982700 | Y23: 14104 | Z23: =Z22+((B23-B22)*Y23) -> 2866300 | AA23: 13800 | AB23: =AB22+((B23-B22)*AA23) -> 2796800 | AC23: 12537 | AD23: =AD22+((B23-B22)*AC23) -> 2581200 | AE23: 11933 | AF23: =AF22+((B23-B22)*AE23) -> 2462100
A24: 201-300 | B24: 300 | C24: 58106 | D24: =D23+((B24-B23)*C24) -> 18892500 | E24: 42553 | F24: =F23+((B24-B23)*E24) -> 13036200 | G24: 34261 | H24: =H23+((B24-B23)*G24) -> 10467600 | I24: 30130 | J24: =J23+((B24-B23)*I24) -> 9156300 | K24: 25694 | L24: =L23+((B24-B23)*K24) -> 7809300 | M24: 22539 | N24: =N23+((B24-B23)*M24) -> 6920700 | O24: 19022 | P24: =P23+((B24-B23)*O24) -> 6070200 | Q24: 17315 | R24: =R23+((B24-B23)*Q24) -> 5608600 | S24: 16898 | T24: =T23+((B24-B23)*S24) -> 5126300 | U24: 14991 | V24: =V23+((B24-B23)*U24) -> 4684600 | W24: 14128 | X24: =X23+((B24-B23)*W24) -> 4395500 | Y24: 13518 | Z24: =Z23+((B24-B23)*Y24) -> 4218100 | AA24: 13622 | AB24: =AB23+((B24-B23)*AA24) -> 4159000 | AC24: 11799 | AD24: =AD23+((B24-B23)*AC24) -> 3761100 | AE24: 11318 | AF24: =AF23+((B24-B23)*AE24) -> 3593900
A25: 301-400 | B25: 400 | C25: 54919 | D25: =D24+((B25-B24)*C25) -> 24384400 | E25: 41705 | F25: =F24+((B25-B24)*E25) -> 17206700 | G25: 33805 | H25: =H24+((B25-B24)*G25) -> 13848100 | I25: 29745 | J25: =J24+((B25-B24)*I25) -> 12130800 | K25: 25445 | L25: =L24+((B25-B24)*K25) -> 10353800 | M25: 22284 | N25: =N24+((B25-B24)*M25) -> 9149100 | O25: 18829 | P25: =P24+((B25-B24)*O25) -> 7953100 | Q25: 17146 | R25: =R24+((B25-B24)*Q25) -> 7323200 | S25: 16726 | T25: =T24+((B25-B24)*S25) -> 6798900 | U25: 14541 | V25: =V24+((B25-B24)*U25) -> 6138700 | W25: 13986 | X25: =X24+((B25-B24)*W25) -> 5794100 | Y25: 13385 | Z25: =Z24+((B25-B24)*Y25) -> 5556600 | AA25: 13487 | AB25: =AB24+((B25-B24)*AA25) -> 5507700 | AC25: 11644 | AD25: =AD24+((B25-B24)*AC25) -> 4925500 | AE25: 11197 | AF25: =AF24+((B25-B24)*AE25) -> 4713600
A26: 401-500 | B26: 500 | C26: 54358 | D26: =D25+((B26-B25)*C26) -> 29820200 | E26: 41283 | F26: =F25+((B26-B25)*E26) -> 21335000 | G26: 33463 | H26: =H25+((B26-B25)*G26) -> 17194400 | I26: 29444 | J26: =J25+((B26-B25)*I26) -> 15075200 | K26: 25195 | L26: =L25+((B26-B25)*K26) -> 12873300 | M26: 22048 | N26: =N25+((B26-B25)*M26) -> 11353900 | O26: 18636 | P26: =P25+((B26-B25)*O26) -> 9816700 | Q26: 16977 | R26: =R25+((B26-B25)*Q26) -> 9020900 | S26: 16554 | T26: =T25+((B26-B25)*S26) -> 8454300 | U26: 14691 | V26: =V25+((B26-B25)*U26) -> 7607800 | W26: 13844 | X26: =X25+((B26-B25)*W26) -> 7178500 | Y26: 13252 | Z26: =Z25+((B26-B25)*Y26) -> 6881800 | AA26: 13352 | AB26: =AB25+((B26-B25)*AA26) -> 6842900 | AC26: 11513 | AD26: =AD25+((B26-B25)*AC26) -> 6076800 | AE26: 11076 | AF26: =AF25+((B26-B25)*AE26) -> 5821200
A27: 501-600 | B27: 600 | C27: 20732 | D27: =D26+((B27-B26)*C27) -> 31893400 | E27: 18639 | F27: =F26+((B27-B26)*E27) -> 23198900 | G27: 17813 | H27: =H26+((B27-B26)*G27) -> 18975700 | I27: 18643 | J27: =J26+((B27-B26)*I27) -> 16939500 | K27: 16694 | L27: =L26+((B27-B26)*K27) -> 14542700 | M27: 14505 | N27: =N26+((B27-B26)*M27) -> 12804400 | O27: 14141 | P27: =P26+((B27-B26)*O27) -> 11230800 | Q27: 12909 | R27: =R26+((B27-B26)*Q27) -> 10311800 | S27: 11677 | T27: =T26+((B27-B26)*S27) -> 9622000 | U27: 11071 | V27: =V26+((B27-B26)*U27) -> 8714900 | W27: 10703 | X27: =X26+((B27-B26)*W27) -> 8248800 | Y27: 9812 | Z27: =Z26+((B27-B26)*Y27) -> 7863000 | AA27: 7311 | AB27: =AB26+((B27-B26)*AA27) -> 7574000 | AC27: 7239 | AD27: =AD26+((B27-B26)*AC27) -> 6800700 | AE27: 6212 | AF27: =AF26+((B27-B26)*AE27) -> 6442400
A28: 601-700 | B28: 700 | C28: 20477 | D28: =D27+((B28-B27)*C28) -> 33941100 | E28: 18351 | F28: =F27+((B28-B27)*E28) -> 25034000 | G28: 17591 | H28: =H27+((B28-B27)*G28) -> 20734800 | I28: 16832 | J28: =J27+((B28-B27)*I28) -> 18622700 | K28: 16408 | L28: =L27+((B28-B27)*K28) -> 16183500 | M28: 14318 | N28: =N27+((B28-B27)*M28) -> 14236200 | O28: 13946 | P28: =P27+((B28-B27)*O28) -> 12625400 | Q28: 12612 | R28: =R27+((B28-B27)*Q28) -> 11573000 | S28: 11545 | T28: =T27+((B28-B27)*S28) -> 10776500 | U28: 11006 | V28: =V27+((B28-B27)*U28) -> 9815500 | W28: 10551 | X28: =X27+((B28-B27)*W28) -> 9303900 | Y28: 9731 | Z28: =Z27+((B28-B27)*Y28) -> 8836100 | AA28: 7221 | AB28: =AB27+((B28-B27)*AA28) -> 8296100 | AC28: 7215 | AD28: =AD27+((B28-B27)*AC28) -> 7522200 | AE28: 6167 | AF28: =AF27+((B28-B27)*AE28) -> 7059100
A29: 701-800 | B29: 800 | C29: 20213 | D29: =D28+((B29-B28)*C29) -> 35962400 | E29: 18501 | F29: =F28+((B29-B28)*E29) -> 26884100 | G29: 18739 | H29: =H28+((B29-B28)*G29) -> 22608700 | I29: 18220 | J29: =J28+((B29-B28)*I29) -> 20444700 | K29: 16394 | L29: =L28+((B29-B28)*K29) -> 17822900 | M29: 14154 | N29: =N28+((B29-B28)*M29) -> 15651600 | O29: 13967 | P29: =P28+((B29-B28)*O29) -> 14022100 | Q29: 13388 | R29: =R28+((B29-B28)*Q29) -> 12911800 | S29: 12804 | T29: =T28+((B29-B28)*S29) -> 12056900 | U29: 12348 | V29: =V28+((B29-B28)*U29) -> 11050300 | W29: 11897 | X29: =X28+((B29-B28)*W29) -> 10493600 | Y29: 10044 | Z29: =Z28+((B29-B28)*Y29) -> 9840500 | AA29: 8936 | AB29: =AB28+((B29-B28)*AA29) -> 9189700 | AC29: 7184 | AD29: =AD28+((B29-B28)*AC29) -> 8240600 | AE29: 6118 | AF29: =AF28+((B29-B28)*AE29) -> 7670900
A30: 801-900 | B30: 900 | C30: 25258 | D30: =D29+((B30-B29)*C30) -> 38488200 | E30: 23415 | F30: =F29+((B30-B29)*E30) -> 29225600 | G30: 23415 | H30: =H29+((B30-B29)*G30) -> 24950200 | I30: 22656 | J30: =J29+((B30-B29)*I30) -> 22710300 | K30: 21508 | L30: =L29+((B30-B29)*K30) -> 19973700 | M30: 20158 | N30: =N29+((B30-B29)*M30) -> 17667400 | O30: 20107 | P30: =P29+((B30-B29)*O30) -> 16032800 | Q30: 19988 | R30: =R29+((B30-B29)*Q30) -> 14910600 | S30: 19861 | T30: =T29+((B30-B29)*S30) -> 14043000 | U30: 19614 | V30: =V29+((B30-B29)*U30) -> 13011700 | W30: 19382 | X30: =X29+((B30-B29)*W30) -> 12431800 | Y30: 16111 | Z30: =Z29+((B30-B29)*Y30) -> 11451600 | AA30: 14026 | AB30: =AB29+((B30-B29)*AA30) -> 10592300 | AC30: 7158 | AD30: =AD29+((B30-B29)*AC30) -> 8956400 | AE30: 6062 | AF30: =AF29+((B30-B29)*AE30) -> 8277100
A31: 901-1000 | B31: 1000 | C31: 25001 | D31: =D30+((B31-B30)*C31) -> 40988300 | E31: 23190 | F31: =F30+((B31-B30)*E31) -> 31544600 | G31: 23190 | H31: =H30+((B31-B30)*G31) -> 27269200 | I31: 23332 | J31: =J30+((B31-B30)*I31) -> 25043500 | K31: 21968 | L31: =L30+((B31-B30)*K31) -> 22170500 | M31: 21622 | N31: =N30+((B31-B30)*M31) -> 19829600 | O31: 20783 | P31: =P30+((B31-B30)*O31) -> 18111100 | Q31: 20366 | R31: =R30+((B31-B30)*Q31) -> 16947200 | S31: 19943 | T31: =T30+((B31-B30)*S31) -> 16037300 | U31: 19871 | V31: =V30+((B31-B30)*U31) -> 14998800 | W31: 19249 | X31: =X30+((B31-B30)*W31) -> 14356700 | Y31: 18181 | Z31: =Z30+((B31-B30)*Y31) -> 13269700 | AA31: 16066 | AB31: =AB30+((B31-B30)*AA31) -> 12198900 | AC31: 7130 | AD31: =AD30+((B31-B30)*AC31) -> 9669400 | AE31: 6011 | AF31: =AF30+((B31-B30)*AE31) -> 8878200
A32: 1001-1100 | B32: 1100 | C32: 24751 | D32: =D31+((B32-B31)*C32) -> 43463400 | E32: 22575 | F32: =F31+((B32-B31)*E32) -> 33802100 | G32: 21758 | H32: =H31+((B32-B31)*G32) -> 29445000 | I32: 21064 | J32: =J31+((B32-B31)*I32) -> 27149900 | K32: 20168 | L32: =L31+((B32-B31)*K32) -> 24187300 | M32: 19825 | N32: =N31+((B32-B31)*M32) -> 21812100 | O32: 18009 | P32: =P31+((B32-B31)*O32) -> 19912000 | Q32: 17165 | R32: =R31+((B32-B31)*Q32) -> 18663700 | S32: 16316 | T32: =T31+((B32-B31)*S32) -> 17668900 | U32: 7699 | V32: =V31+((B32-B31)*U32) -> 15768700 | W32: 7486 | X32: =X31+((B32-B31)*W32) -> 15105300 | Y32: 7412 | Z32: =Z31+((B32-B31)*Y32) -> 14010900 | AA32: 7340 | AB32: =AB31+((B32-B31)*AA32) -> 12932900 | AC32: 6600 | AD32: =AD31+((B32-B31)*AC32) -> 10329400 | AE32: 5966 | AF32: =AF31+((B32-B31)*AE32) -> 9474800
A33: 1101-1200 | B33: 1200 | C33: 26991 | D33: =D32+((B33-B32)*C33) -> 46162500 | E33: 25943 | F33: =F32+((B33-B32)*E33) -> 36396400 | G33: 21050 | H33: =H32+((B33-B32)*G33) -> 31550000 | I33: 20390 | J33: =J32+((B33-B32)*I33) -> 29188900 | K33: 19852 | L33: =L32+((B33-B32)*K33) -> 26172500 | M33: 19488 | N33: =N32+((B33-B32)*M33) -> 23760900 | O33: 17803 | P33: =P32+((B33-B32)*O33) -> 21692300 | Q33: 16905 | R33: =R32+((B33-B32)*Q33) -> 20354200 | S33: 15843 | T33: =T32+((B33-B32)*S33) -> 19253200 | U33: 7623 | V33: =V32+((B33-B32)*U33) -> 16531000 | W33: 7335 | X33: =X32+((B33-B32)*W33) -> 15838800 | Y33: 7276 | Z33: =Z32+((B33-B32)*Y33) -> 14738500 | AA33: 7249 | AB33: =AB32+((B33-B32)*AA33) -> 13657800 | AC33: 6545 | AD33: =AD32+((B33-B32)*AC33) -> 10983900 | AE33: 5916 | AF33: =AF32+((B33-B32)*AE33) -> 10066400
A34: 1201-1300 | B34: 1300 | C34: 26638 | D34: =D33+((B34-B33)*C34) -> 48826300 | E34: 25605 | F34: =F33+((B34-B33)*E34) -> 38956900 | G34: 17908 | H34: =H33+((B34-B33)*G34) -> 33340800 | I34: 17269 | J34: =J33+((B34-B33)*I34) -> 30915800 | K34: 16881 | L34: =L33+((B34-B33)*K34) -> 27860600 | M34: 16517 | N34: =N33+((B34-B33)*M34) -> 25412600 | O34: 15951 | P34: =P33+((B34-B33)*O34) -> 23287400 | Q34: 16558 | R34: =R33+((B34-B33)*Q34) -> 22010000 | S34: 15382 | T34: =T33+((B34-B33)*S34) -> 20791400 | U34: 7699 | V34: =V33+((B34-B33)*U34) -> 17300900 | W34: 7184 | X34: =X33+((B34-B33)*W34) -> 16557200 | Y34: 7148 | Z34: =Z33+((B34-B33)*Y34) -> 15453300 | AA34: 7099 | AB34: =AB33+((B34-B33)*AA34) -> 14367700 | AC34: 5361 | AD34: =AD33+((B34-B33)*AC34) -> 11520000 | AE34: 5875 | AF34: =AF33+((B34-B33)*AE34) -> 10653900
... A46: 40001-70000 | B46: 70000 | C46: 4540 | D46: =D45+((B46-B45)*C46) -> 574677400 | E46: 4134 | F46: =F45+((B46-B45)*E46) -> 511702900 | G46: 4034 | H46: =H45+((B46-B45)*G46) -> 422482000 | I46: 3673 | J46: =J45+((B46-B45)*I46) -> 397844300 | K46: 3166 | L46: =L45+((B46-B45)*K46) -> 990523500 | M46: 2597 | N46: =N45+((B46-B45)*M46) -> 307058300 | O46: 2477 | P46: =P45+((B46-B45)*O46) -> 281272400 | Q46: 2237 | R46: =R45+((B46-B45)*Q46) -> 230181800 | S46: 1936 | T46: =T45+((B46-B45)*S46) -> 210368600 | U46: 1640 | V46: =V45+((B46-B45)*U46) -> 190544300 | W46: 1328 | X46: =X45+((B46-B45)*W46) -> 173690500 | Y46: 850 | Z46: =Z45+((B46-B45)*Y46) -> 151894500 | AA46: 715 | AB46: =AB45+((B46-B45)*AA46) -> 141740600 | AC46: 520 | AD46: =AD45+((B46-B45)*AC46) -> 87844900 | AE46: 547 | AF46: =AF45+((B46-B45)*AE46) -> 80552100
A47: >70000 | C47: 2012 | D47: =D46+((B47-B46)*C47) -> 433837400 | E47: 1874 | F47: =F46+((B47-B46)*E47) -> 380522900 | G47: 1848 | H47: =H46+((B47-B46)*G47) -> 293122000 | I47: 1738 | J47: =J46+((B47-B46)*I47) -> 276184300 | K47: 1488 | L47: =L46+((B47-B46)*K47) -> 886363500 | M47: 1218 | N47: =N46+((B47-B46)*M47) -> 221798300 | O47: 1079 | P47: =P46+((B47-B46)*O47) -> 205742400 | Q47: 1089 | R47: =R46+((B47-B46)*Q47) -> 153951800 | S47: 707 | T47: =T46+((B47-B46)*S47) -> 160878600 | U47: 677 | V47: =V46+((B47-B46)*U47) -> 143154300 | W47: 641 | X47: =X46+((B47-B46)*W47) -> 128820500 | Y47: 401 | Z47: =Z46+((B47-B46)*Y47) -> 123824500 | AA47: 364 | AB47: =AB46+((B47-B46)*AA47) -> 116260600 | AC47: 361 | AD47: =AD46+((B47-B46)*AC47) -> 62574900 | AE47: 295 | AF47: =AF46+((B47-B46)*AE47) -> 59902100
D48: =IF(B11<100,B11*C22,(IF($B$11<=2500,(LOOKUP($B$11,$B$22:$B$47,D$22:D$47))+(($B$11-LOOKUP($B$11,$B$22:$B$47))*LOOKUP(($B$11+100),$B$22:$B$47,C$22:C$47)),IF((2500<$B$11)*AND($B$11<=10000),(LOOKUP($B$11,$B$22:$B$47,D$22:D$47))+(($B$11-LOOKUP($B$11,$B$22:$B$47))*LOOKUP(($B$11+7500),$B$22:$B$47,C$22:C$47)),IF((10000<$B$11)*AND($B$11<=20000),(LOOKUP($B$11,$B$22:$B$47,D$22:D$47))+(($B$11-LOOKUP($B$11,$B$22:$B$47))*LOOKUP(($B$11+10000),$B$22:$B$47,C$22:C$47)),IF((20000<$B$11)*AND($B$11<=40000),(LOOKUP($B$11,$B$22:$B$47,D$22:D$47))+(($B$11-LOOKUP($B$11,$B$22:$B$47))*LOOKUP(($B$11+20000),$B$22:$B$47,C$22:C$47)),IF((40000<$B$11)*AND($B$11<=70000),(LOOKUP($B$11,$B$22:$B$47,D$22:D$47))+(($B$11-LOOKUP($B$11,$B$22:$B$47))*LOOKUP(($B$11+30000),$B$22:$B$47,C$22:C$47)),(LOOKUP($B$11,$B$22:$B$47,D$22:D$47))+(($B$11-LOOKUP($B$11,$B$22:$B$47))*C$47)))))))) -> 6377336 | F48: =IF(B11<100,B11*E22,(IF($B$11<=2500,(LOOKUP($B$11,$B$22:$B$47,F$22:F$47))+(($B$11-LOOKUP($B$11,$B$22:$B$47))*LOOKUP(($B$11+100),$B$22:$B$47,E$22:E$47)),IF((2500<$B$11)*AND($B$11<=10000),(LOOKUP($B$11,$B$22:$B$47,F$22:F$47))+(($B$11-LOOKUP($B$11,$B$22:$B$47))*LOOKUP(($B$11+7500),$B$22:$B$47,E$22:E$47)),IF((10000<$B$11)*AND($B$11<=20000),(LOOKUP($B$11,$B$22:$B$47,F$22:F$47))+(($B$11-LOOKUP($B$11,$B$22:$B$47))*LOOKUP(($B$11+10000),$B$22:$B$47,E$22:E$47)),IF((20000<$B$11)*AND($B$11<=40000),(LOOKUP($B$11,$B$22:$B$47,F$22:F$47))+(($B$11-LOOKUP($B$11,$B$22:$B$47))*LOOKUP(($B$11+20000),$B$22:$B$47,E$22:E$47)),IF((40000<$B$11)*AND($B$11<=70000),(LOOKUP($B$11,$B$22:$B$47,F$22:F$47))+(($B$11-LOOKUP($B$11,$B$22:$B$47))*LOOKUP(($B$11+30000),$B$22:$B$47,E$22:E$47)),(LOOKUP($B$11,$B$22:$B$47,F$22:F$47))+(($B$11-LOOKUP($B$11,$B$22:$B$47))*E$47)))))))) -> 4169370 | H48: =IF(B11<100,B11*G22,(IF($B$11<=2500,(LOOKUP($B$11,$B$22:$B$47,H$22:H$47))+(($B$11-LOOKUP($B$11,$B$22:$B$47))*LOOKUP(($B$11+100),$B$22:$B$47,G$22:G$47)),IF((2500<$B$11)*AND($B$11<=10000),(LOOKUP($B$11,$B$22:$B$47,H$22:H$47))+(($B$11-LOOKUP($B$11,$B$22:$B$47))*LOOKUP(($B$11+7500),$B$22:$B$47,G$22:G$47)),IF((10000<$B$11)*AND($B$11<=20000),(LOOKUP($B$11,$B$22:$B$47,H$22:H$47))+(($B$11-LOOKUP($B$11,$B$22:$B$47))*LOOKUP(($B$11+10000),$B$22:$B$47,G$22:G$47)),IF((20000<$B$11)*AND($B$11<=40000),(LOOKUP($B$11,$B$22:$B$47,H$22:H$47))+(($B$11-LOOKUP($B$11,$B$22:$B$47))*LOOKUP(($B$11+20000),$B$22:$B$47,G$22:G$47)),IF((40000<$B$11)*AND($B$11<=70000),(LOOKUP($B$11,$B$22:$B$47,H$22:H$47))+(($B$11-LOOKUP($B$11,$B$22:$B$47))*LOOKUP(($B$11+30000),$B$22:$B$47,G$22:G$47)),(LOOKUP($B$11,$B$22:$B$47,H$22:H$47))+(($B$11-LOOKUP($B$11,$B$22:$B$47))*G$47)))))))) -> 3339162 | J48: =IF(B11<100,B11*I22,(IF($B$11<=2500,(LOOKUP($B$11,$B$22:$B$47,J$22:J$47))+(($B$11-LOOKUP($B$11,$B$22:$B$47))*LOOKUP(($B$11+100),$B$22:$B$47,I$22:I$47)),IF((2500<$B$11)*AND($B$11<=10000),(LOOKUP($B$11,$B$22:$B$47,J$22:J$47))+(($B$11-LOOKUP($B$11,$B$22:$B$47))*LOOKUP(($B$11+7500),$B$22:$B$47,I$22:I$47)),IF((10000<$B$11)*AND($B$11<=20000),(LOOKUP($B$11,$B$22:$B$47,J$22:J$47))+(($B$11-LOOKUP($B$11,$B$22:$B$47))*LOOKUP(($B$11+10000),$B$22:$B$47,I$22:I$47)),IF((20000<$B$11)*AND($B$11<=40000),(LOOKUP($B$11,$B$22:$B$47,J$22:J$47))+(($B$11-LOOKUP($B$11,$B$22:$B$47))*LOOKUP(($B$11+20000),$B$22:$B$47,I$22:I$47)),IF((40000<$B$11)*AND($B$11<=70000),(LOOKUP($B$11,$B$22:$B$47,J$22:J$47))+(($B$11-LOOKUP($B$11,$B$22:$B$47))*LOOKUP(($B$11+30000),$B$22:$B$47,I$22:I$47)),(LOOKUP($B$11,$B$22:$B$47,J$22:J$47))+(($B$11-LOOKUP($B$11,$B$22:$B$47))*I$47)))))))) -> 2905728 | L48: =IF(B11<100,B11*K22,(IF($B$11<=2500,(LOOKUP($B$11,$B$22:$B$47,L$22:L$47))+(($B$11-LOOKUP($B$11,$B$22:$B$47))*LOOKUP(($B$11+100),$B$22:$B$47,K$22:K$47)),IF((2500<$B$11)*AND($B$11<=10000),(LOOKUP($B$11,$B$22:$B$47,L$22:L$47))+(($B$11-LOOKUP($B$11,$B$22:$B$47))*LOOKUP(($B$11+7500),$B$22:$B$47,K$22:K$47)),IF((10000<$B$11)*AND($B$11<=20000),(LOOKUP($B$11,$B$22:$B$47,L$22:L$47))+(($B$11-LOOKUP($B$11,$B$22:$B$47))*LOOKUP(($B$11+10000),$B$22:$B$47,K$22:K$47)),IF((20000<$B$11)*AND($B$11<=40000),(LOOKUP($B$11,$B$22:$B$47,L$22:L$47))+(($B$11-LOOKUP($B$11,$B$22:$B$47))*LOOKUP(($B$11+20000),$B$22:$B$47,K$22:K$47)),IF((40000<$B$11)*AND($B$11<=70000),(LOOKUP($B$11,$B$22:$B$47,L$22:L$47))+(($B$11-LOOKUP($B$11,$B$22:$B$47))*LOOKUP(($B$11+30000),$B$22:$B$47,K$22:K$47)),(LOOKUP($B$11,$B$22:$B$47,L$22:L$47))+(($B$11-LOOKUP($B$11,$B$22:$B$47))*K$47)))))))) -> 2478592 | N48: =IF(B11<100,B11*M22,(IF($B$11<=2500,(LOOKUP($B$11,$B$22:$B$47,N$22:N$47))+(($B$11-LOOKUP($B$11,$B$22:$B$47))*LOOKUP(($B$11+100),$B$22:$B$47,M$22:M$47)),IF((2500<$B$11)*AND($B$11<=10000),(LOOKUP($B$11,$B$22:$B$47,N$22:N$47))+(($B$11-LOOKUP($B$11,$B$22:$B$47))*LOOKUP(($B$11+7500),$B$22:$B$47,M$22:M$47)),IF((10000<$B$11)*AND($B$11<=20000),(LOOKUP($B$11,$B$22:$B$47,N$22:N$47))+(($B$11-LOOKUP($B$11,$B$22:$B$47))*LOOKUP(($B$11+10000),$B$22:$B$47,M$22:M$47)),IF((20000<$B$11)*AND($B$11<=40000),(LOOKUP($B$11,$B$22:$B$47,N$22:N$47))+(($B$11-LOOKUP($B$11,$B$22:$B$47))*LOOKUP(($B$11+20000),$B$22:$B$47,M$22:M$47)),IF((40000<$B$11)*AND($B$11<=70000),(LOOKUP($B$11,$B$22:$B$47,N$22:N$47))+(($B$11-LOOKUP($B$11,$B$22:$B$47))*LOOKUP(($B$11+30000),$B$22:$B$47,M$22:M$47)),(LOOKUP($B$11,$B$22:$B$47,N$22:N$47))+(($B$11-LOOKUP($B$11,$B$22:$B$47))*M$47)))))))) -> 2218306 | P48: =IF(B11<100,B11*O22,(IF($B$11<=2500,(LOOKUP($B$11,$B$22:$B$47,P$22:P$47))+(($B$11-LOOKUP($B$11,$B$22:$B$47))*LOOKUP(($B$11+100),$B$22:$B$47,O$22:O$47)),IF((2500<$B$11)*AND($B$11<=10000),(LOOKUP($B$11,$B$22:$B$47,P$22:P$47))+(($B$11-LOOKUP($B$11,$B$22:$B$47))*LOOKUP(($B$11+7500),$B$22:$B$47,O$22:O$47)),IF((10000<$B$11)*AND($B$11<=20000),(LOOKUP($B$11,$B$22:$B$47,P$22:P$47))+(($B$11-LOOKUP($B$11,$B$22:$B$47))*LOOKUP(($B$11+10000),$B$22:$B$47,O$22:O$47)),IF((20000<$B$11)*AND($B$11<=40000),(LOOKUP($B$11,$B$22:$B$47,P$22:P$47))+(($B$11-LOOKUP($B$11,$B$22:$B$47))*LOOKUP(($B$11+20000),$B$22:$B$47,O$22:O$47)),IF((40000<$B$11)*AND($B$11<=70000),(LOOKUP($B$11,$B$22:$B$47,P$22:P$47))+(($B$11-LOOKUP($B$11,$B$22:$B$47))*LOOKUP(($B$11+30000),$B$22:$B$47,O$22:O$47)),(LOOKUP($B$11,$B$22:$B$47,P$22:P$47))+(($B$11-LOOKUP($B$11,$B$22:$B$47))*O$47)))))))) -> 2028144 | R48: =IF(B11<100,B11*Q22,(IF($B$11<=2500,(LOOKUP($B$11,$B$22:$B$47,R$22:R$47))+(($B$11-LOOKUP($B$11,$B$22:$B$47))*LOOKUP(($B$11+100),$B$22:$B$47,Q$22:Q$47)),IF((2500<$B$11)*AND($B$11<=10000),(LOOKUP($B$11,$B$22:$B$47,R$22:R$47))+(($B$11-LOOKUP($B$11,$B$22:$B$47))*LOOKUP(($B$11+7500),$B$22:$B$47,Q$22:Q$47)),IF((10000<$B$11)*AND($B$11<=20000),(LOOKUP($B$11,$B$22:$B$47,R$22:R$47))+(($B$11-LOOKUP($B$11,$B$22:$B$47))*LOOKUP(($B$11+10000),$B$22:$B$47,Q$22:Q$47)),IF((20000<$B$11)*AND($B$11<=40000),(LOOKUP($B$11,$B$22:$B$47,R$22:R$47))+(($B$11-LOOKUP($B$11,$B$22:$B$47))*LOOKUP(($B$11+20000),$B$22:$B$47,Q$22:Q$47)),IF((40000<$B$11)*AND($B$11<=70000),(LOOKUP($B$11,$B$22:$B$47,R$22:R$47))+(($B$11-LOOKUP($B$11,$B$22:$B$47))*LOOKUP(($B$11+30000),$B$22:$B$47,Q$22:Q$47)),(LOOKUP($B$11,$B$22:$B$47,R$22:R$47))+(($B$11-LOOKUP($B$11,$B$22:$B$47))*Q$47)))))))) -> 1912994 | T48: =IF(B11<100,B11*S22,(IF($B$11<=2500,(LOOKUP($B$11,$B$22:$B$47,T$22:T$47))+(($B$11-LOOKUP($B$11,$B$22:$B$47))*LOOKUP(($B$11+100),$B$22:$B$47,S$22:S$47)),IF((2500<$B$11)*AND($B$11<=10000),(LOOKUP($B$11,$B$22:$B$47,T$22:T$47))+(($B$11-LOOKUP($B$11,$B$22:$B$47))*LOOKUP(($B$11+7500),$B$22:$B$47,S$22:S$47)),IF((10000<$B$11)*AND($B$11<=20000),(LOOKUP($B$11,$B$22:$B$47,T$22:T$47))+(($B$11-LOOKUP($B$11,$B$22:$B$47))*LOOKUP(($B$11+10000),$B$22:$B$47,S$22:S$47)),IF((20000<$B$11)*AND($B$11<=40000),(LOOKUP($B$11,$B$22:$B$47,T$22:T$47))+(($B$11-LOOKUP($B$11,$B$22:$B$47))*LOOKUP(($B$11+20000),$B$22:$B$47,S$22:S$47)),IF((40000<$B$11)*AND($B$11<=70000),(LOOKUP($B$11,$B$22:$B$47,T$22:T$47))+(($B$11-LOOKUP($B$11,$B$22:$B$47))*LOOKUP(($B$11+30000),$B$22:$B$47,S$22:S$47)),(LOOKUP($B$11,$B$22:$B$47,T$22:T$47))+(($B$11-LOOKUP($B$11,$B$22:$B$47))*S$47)))))))) -> 1624602 | V48: =IF(B11<100,B11*U22,(IF($B$11<=2500,(LOOKUP($B$11,$B$22:$B$47,V$22:V$47))+(($B$11-LOOKUP($B$11,$B$22:$B$47))*LOOKUP(($B$11+100),$B$22:$B$47,U$22:U$47)),IF((2500<$B$11)*AND($B$11<=10000),(LOOKUP($B$11,$B$22:$B$47,V$22:V$47))+(($B$11-LOOKUP($B$11,$B$22:$B$47))*LOOKUP(($B$11+7500),$B$22:$B$47,U$22:U$47)),IF((10000<$B$11)*AND($B$11<=20000),(LOOKUP($B$11,$B$22:$B$47,V$22:V$47))+(($B$11-LOOKUP($B$11,$B$22:$B$47))*LOOKUP(($B$11+10000),$B$22:$B$47,U$22:U$47)),IF((20000<$B$11)*AND($B$11<=40000),(LOOKUP($B$11,$B$22:$B$47,V$22:V$47))+(($B$11-LOOKUP($B$11,$B$22:$B$47))*LOOKUP(($B$11+20000),$B$22:$B$47,U$22:U$47)),IF((40000<$B$11)*AND($B$11<=70000),(LOOKUP($B$11,$B$22:$B$47,V$22:V$47))+(($B$11-LOOKUP($B$11,$B$22:$B$47))*LOOKUP(($B$11+30000),$B$22:$B$47,U$22:U$47)),(LOOKUP($B$11,$B$22:$B$47,V$22:V$47))+(($B$11-LOOKUP($B$11,$B$22:$B$47))*U$47)))))))) -> 1529098 | X48: =IF(B11<100,B11*W22,(IF($B$11<=2500,(LOOKUP($B$11,$B$22:$B$47,X$22:X$47))+(($B$11-LOOKUP($B$11,$B$22:$B$47))*LOOKUP(($B$11+100),$B$22:$B$47,W$22:W$47)),IF((2500<$B$11)*AND($B$11<=10000),(LOOKUP($B$11,$B$22:$B$47,X$22:X$47))+(($B$11-LOOKUP($B$11,$B$22:$B$47))*LOOKUP(($B$11+7500),$B$22:$B$47,W$22:W$47)),IF((10000<$B$11)*AND($B$11<=20000),(LOOKUP($B$11,$B$22:$B$47,X$22:X$47))+(($B$11-LOOKUP($B$11,$B$22:$B$47))*LOOKUP(($B$11+10000),$B$22:$B$47,W$22:W$47)),IF((20000<$B$11)*AND($B$11<=40000),(LOOKUP($B$11,$B$22:$B$47,X$22:X$47))+(($B$11-LOOKUP($B$11,$B$22:$B$47))*LOOKUP(($B$11+20000),$B$22:$B$47,W$22:W$47)),IF((40000<$B$11)*AND($B$11<=70000),(LOOKUP($B$11,$B$22:$B$47,X$22:X$47))+(($B$11-LOOKUP($B$11,$B$22:$B$47))*LOOKUP(($B$11+30000),$B$22:$B$47,W$22:W$47)),(LOOKUP($B$11,$B$22:$B$47,X$22:X$47))+(($B$11-LOOKUP($B$11,$B$22:$B$47))*W$47)))))))) -> 1428988 | Z48: =IF(B11<100,B11*Y22,(IF($B$11<=2500,(LOOKUP($B$11,$B$22:$B$47,Z$22:Z$47))+(($B$11-LOOKUP($B$11,$B$22:$B$47))*LOOKUP(($B$11+100),$B$22:$B$47,Y$22:Y$47)),IF((2500<$B$11)*AND($B$11<=10000),(LOOKUP($B$11,$B$22:$B$47,Z$22:Z$47))+(($B$11-LOOKUP($B$11,$B$22:$B$47))*LOOKUP(($B$11+7500),$B$22:$B$47,Y$22:Y$47)),IF((10000<$B$11)*AND($B$11<=20000),(LOOKUP($B$11,$B$22:$B$47,Z$22:Z$47))+(($B$11-LOOKUP($B$11,$B$22:$B$47))*LOOKUP(($B$11+10000),$B$22:$B$47,Y$22:Y$47)),IF((20000<$B$11)*AND($B$11<=40000),(LOOKUP($B$11,$B$22:$B$47,Z$22:Z$47))+(($B$11-LOOKUP($B$11,$B$22:$B$47))*LOOKUP(($B$11+20000),$B$22:$B$47,Y$22:Y$47)),IF((40000<$B$11)*AND($B$11<=70000),(LOOKUP($B$11,$B$22:$B$47,Z$22:Z$47))+(($B$11-LOOKUP($B$11,$B$22:$B$47))*LOOKUP(($B$11+30000),$B$22:$B$47,Y$22:Y$47)),(LOOKUP($B$11,$B$22:$B$47,Z$22:Z$47))+(($B$11-LOOKUP($B$11,$B$22:$B$47))*Y$47)))))))) -> 1368546 | AB48: =IF(B11<100,B11*AA22,(IF($B$11<=2500,(LOOKUP($B$11,$B$22:$B$47,AB$22:AB$47))+(($B$11-LOOKUP($B$11,$B$22:$B$47))*LOOKUP(($B$11+100),$B$22:$B$47,AA$22:AA$47)),IF((2500<$B$11)*AND($B$11<=10000),(LOOKUP($B$11,$B$22:$B$47,AB$22:AB$47))+(($B$11-LOOKUP($B$11,$B$22:$B$47))*LOOKUP(($B$11+7500),$B$22:$B$47,AA$22:AA$47)),IF((10000<$B$11)*AND($B$11<=20000),(LOOKUP($B$11,$B$22:$B$47,AB$22:AB$47))+(($B$11-LOOKUP($B$11,$B$22:$B$47))*LOOKUP(($B$11+10000),$B$22:$B$47,AA$22:AA$47)),IF((20000<$B$11)*AND($B$11<=40000),(LOOKUP($B$11,$B$22:$B$47,AB$22:AB$47))+(($B$11-LOOKUP($B$11,$B$22:$B$47))*LOOKUP(($B$11+20000),$B$22:$B$47,AA$22:AA$47)),IF((40000<$B$11)*AND($B$11<=70000),(LOOKUP($B$11,$B$22:$B$47,AB$22:AB$47))+(($B$11-LOOKUP($B$11,$B$22:$B$47))*LOOKUP(($B$11+30000),$B$22:$B$47,AA$22:AA$47)),(LOOKUP($B$11,$B$22:$B$47,AB$22:AB$47))+(($B$11-LOOKUP($B$11,$B$22:$B$47))*AA$47)))))))) -> 1331792 | AD48: =IF(B11<100,B11*AC22,(IF($B$11<=2500,(LOOKUP($B$11,$B$22:$B$47,AD$22:AD$47))+(($B$11-LOOKUP($B$11,$B$22:$B$47))*LOOKUP(($B$11+100),$B$22:$B$47,AC$22:AC$47)),IF((2500<$B$11)*AND($B$11<=10000),(LOOKUP($B$11,$B$22:$B$47,AD$22:AD$47))+(($B$11-LOOKUP($B$11,$B$22:$B$47))*LOOKUP(($B$11+7500),$B$22:$B$47,AC$22:AC$47)),IF((10000<$B$11)*AND($B$11<=20000),(LOOKUP($B$11,$B$22:$B$47,AD$22:AD$47))+(($B$11-LOOKUP($B$11,$B$22:$B$47))*LOOKUP(($B$11+10000),$B$22:$B$47,AC$22:AC$47)),IF((20000<$B$11)*AND($B$11<=40000),(LOOKUP($B$11,$B$22:$B$47,AD$22:AD$47))+(($B$11-LOOKUP($B$11,$B$22:$B$47))*LOOKUP(($B$11+20000),$B$22:$B$47,AC$22:AC$47)),IF((40000<$B$11)*AND($B$11<=70000),(LOOKUP($B$11,$B$22:$B$47,AD$22:AD$47))+(($B$11-LOOKUP($B$11,$B$22:$B$47))*LOOKUP(($B$11+30000),$B$22:$B$47,AC$22:AC$47)),(LOOKUP($B$11,$B$22:$B$47,AD$22:AD$47))+(($B$11-LOOKUP($B$11,$B$22:$B$47))*AC$47)))))))) -> 1247850 | AF48: =IF(B11<100,B11*AE22,(IF($B$11<=2500,(LOOKUP($B$11,$B$22:$B$47,AF$22:AF$47))+(($B$11-LOOKUP($B$11,$B$22:$B$47))*LOOKUP(($B$11+100),$B$22:$B$47,AE$22:AE$47)),IF((2500<$B$11)*AND($B$11<=10000),(LOOKUP($B$11,$B$22:$B$47,AF$22:AF$47))+(($B$11-LOOKUP($B$11,$B$22:$B$47))*LOOKUP(($B$11+7500),$B$22:$B$47,AE$22:AE$47)),IF((10000<$B$11)*AND($B$11<=20000),(LOOKUP($B$11,$B$22:$B$47,AF$22:AF$47))+(($B$11-LOOKUP($B$11,$B$22:$B$47))*LOOKUP(($B$11+10000),$B$22:$B$47,AE$22:AE$47)),IF((20000<$B$11)*AND($B$11<=40000),(LOOKUP($B$11,$B$22:$B$47,AF$22:AF$47))+(($B$11-LOOKUP($B$11,$B$22:$B$47))*LOOKUP(($B$11+20000),$B$22:$B$47,AE$22:AE$47)),IF((40000<$B$11)*AND($B$11<=70000),(LOOKUP($B$11,$B$22:$B$47,AF$22:AF$47))+(($B$11-LOOKUP($B$11,$B$22:$B$47))*LOOKUP(($B$11+30000),$B$22:$B$47,AE$22:AE$47)),(LOOKUP($B$11,$B$22:$B$47,AF$22:AF$47))+(($B$11-LOOKUP($B$11,$B$22:$B$47))*AC$47)))))))) -> 1192672
A49: Internal structure | B49: ='Fence and Compund'!F207 -> 200000
A50: External sanitary work | B50: For A = | D50: =Area!D15 -> 224.3772
A51: Water Supply & Drain Line | D51: =IF(D50=0,0,IF(D50<=200,4.37-D50*0.014,IF(D50<=2000,2.34-D50/1103,IF(D50<=2800,1.2-D50/3025,IF(2800<D50,0.2))))) -> 2.1365755 | E51: % X | F51: =Area!F15 -> 9446280.1 | G51: Birr
A52: Septic tank | D52: =IF(A51="Water Supply & Drain Line", D51*(F51+B49)/100,0) -> 206100.06 | E52: Birr
A53: Septic tank | B53: 1 | C53: Capacity = | D53: =IF(AND(A53="Septic tank",F51<>0),IF(D50<=200,10,IF(D50<1000,ROUND(((D50-200)/80+10),2),IF(D50=1000,20,IF(D50<2000,ROUND(((D50-1000)/100+20),2),IF(D50=2000,30,IF(D50<3000,ROUND(((D50-2000)*0.03+30),2),IF(D50>=3000,60))))))),0) -> 10.3 | E53: m3 | F53: =ROUND((B53*D53),2) -> 10.3
B54: y=3064X+23793 => | D54: =IF(D53=0,0,3064*F53+23793) -> 55352.2 | E54: Birr
A55: Capacity Factor =
A56: Total External sanitary work | D56: =D54+D52 -> 261452.26
A57: External Electric work
B58: Floor area (M2) | C58: Intake line & man holes | E58: Compound lighting
B59: =D50 -> 224.3772 | C59: =IF(C58="Intake line & man holes",(IF(B59<=200,0.35,IF(B59<=1000,0.35+(0.59-0.35)/(1000-200)*(B59-200),IF(B59<=2000,(0.89-0.59)*(B59-1000)/(2000-1000)+0.59,IF(B59<3000,(1.01-0.89)/(3000-200)*(B59-2000)+0.89,IF(B59>=3000,1.01)))))),0) -> 0.35731316 | E59: =IF(E58="Compound lighting",(IF(B59<=200,0.26,IF(B59<=1000,0.26+(0.45-0.26)/(1000-200)*(B59-200),IF(B59<=2000,(0.69-0.45)/(2000-1000)*(B59-1000)+0.45,IF(B59<3000,(0.36-0.69)/(3000-2000)*(B59-2000)+0.69,IF(B59>=3000,0.36)))))),0) -> 0.26578958
B60: Total Percentage | C60: =C59+E59 -> 0.62310274
C62: =C60 -> 0.62310274 | D62: =F51 -> 9446280.1 | F62: Birr
C63: =IF(OR(C60=0,F51=0),0,MAX(C62*D62/100,7500)) -> 58860.031 | E63: Birr
A64: Water Tank & stand | B64: = | C64: ='Fence and Compund'!F145 -> 108710.25 | E64: Birr
A65: External Electric and sanitary work | B65: = | C65: =C64+C63+D56 -> 429022.54 | E65: Birr | H65: =2130*60 -> 127800
A66: Consultancy fee | B66: Project Cost | C66: =D75+D76+D77+D78 -> 10324696
A67: Including Design & Supervision
A68: Architectural | B68: =IF(A68="Architectural",(IF(C66<=500000,45%*4.25%*C66*(C68/100),IF(C66<=1000000,45%*3.75%*C66*(C68/100),IF(C66<=2500000,45%*3.25%*C66*(C68/100),IF(C66<=5000000,45%*2.75%*C66*(C68/100),IF(C66<=10000000,45%*2.25%*C66*(C68/100),IF(C66>10000000,45%*1.75%*C66*(C68/100)))))))),0) -> 81306.978 | C68: 100
A69: Structural | B69: =IF(A69="Structural",(IF(C66<=500000,30%*4.25%*C66*(C69/100),IF(C66<=1000000,30%*3.75%*C66*(C69/100),IF(C66<=2500000,30%*3.25%*C66*(C69/100),IF(C66<=5000000,30%*2.75%*C66*(C69/100),IF(C66<=10000000,30%*2.25%*C66*(C69/100),IF(C66>10000000,30%*1.75%*C66*(C69/100)))))))),0) -> 0
A70: Electrical | B70: =IF(A70="Electrical",(IF(C66<=500000,10%*4.25%*C66*(C70/100),IF(C66<=1000000,10%*3.75%*C66*(C70/100),IF(C66<=2500000,10%*3.25%*C66*(C70/100),IF(C66<=5000000,10%*2.75%*C66*(C70/100),IF(C66<=10000000,10%*2.25%*C66*(C70/100),IF(C66>10000000,10%*1.75%*C66*(C70/100)))))))),0) -> 0
A71: Sanitary | B71: =IF(A71="Sanitary",(IF(C66<=500000,2.75%*4.25%*C66*(C71/100),IF(C66<=1000000,2.75%*3.75%*C66*(C71/100),IF(C66<=2500000,2.75%*3.25%*C66*(C71/100),IF(C66<=5000000,2.75%*2.75%*C66*(C71/100),IF(C66<=10000000,2.75%*2.25%*C66*(C71/100),IF(C66>10000000,2.75%*1.75%*C66*(C71/100)))))))),0) -> 0
A72: Specification and Bill of quantity | B72: =IF(A72="Specification and bill of quantity",(IF(C66<=500000,2.25%*4.25%*C66*(C72/100),IF(C66<=1000000,2.25%*3.75%*C66*(C72/100),IF(C66<=2500000,2.25%*3.25%*C66*(C72/100),IF(C66<=5000000,2.25%*2.75%*C66*(C72/100),IF(C66<=10000000,2.25%*2.25%*C66*(C72/100),IF(C66>10000000,2.25%*1.75%*C66*(C72/100)))))))),0) -> 0
A73: Total Consultancy Fee | B73: =SUM(B68:B72) -> 81306.978
B75: Building Cost | D75: =F51 -> 9446280.1
B76: Internal Structure | D76: =B49 -> 200000
B77: External Elecrical & Sanitary Works | D77: =C65 -> 429022.54
B78: Fence & compound = | D78: ='Fence and Compund'!F78 -> 249393.01
B79: Consultancy Service | D79: =B73 -> 81306.978
B80: Location Value | D80: =B19 -> 2478592
B81: Total Estimate = | D81: =SUM(D75:D80) -> 12884595

Sheet Sheet2
A1: ዘምዘም ባንክ አ.ማ
A2: ZAMZAM BANK S.C
A3: PROPERTY ESTIMATIONFORM FOR GENERAL LOANS
I4: Branch | J4: Head Office
I5: Date
A6: 1 | B6: Applicant's Name | E6: XY
B7: Address: Town | E7: Wereda | F7: _____________ | G7: Kebele | I7: House No. _____________
B8: P.O.Box ____________________ Tel. No. ___________________
A9: 2 | B9: Property of | D9: XY | G9: Ownership C/No. | I9: XY
B10: Location: Town | D10: AA | E10: S/City | F10: Nifas Silk-Lafto | G10: Woreda | H10: 2 | J10: House No.
B11: Area of Compound | D11: 94 | F11: Sq. m. | G11: Paved in | H11: _____________ | K11: Asphalt
B12: Land Mark | K12: Gravel
B13: Distance from the main road______ | F13: Type of access road to site________ | K13: Cobble
A14: 3 | B14: Property owner adress: Town ______________ Wereda _________ Kebele _____________________
E15: House No. _______________ Tel. No. ___________________
A16: 4 | B16: ANALYSIS OF NEIGHBORHOOD
B17: a) General Use | F17: Industrial | H17: Residential | K17: Others
B18: b) Marketability | E18: Marketable
B19: c) Standard of Housing | G19: Excellent
B20: d) Development State | G20: Developing
B21: e) Future Tendency | G21: Promising
B22: f) Transportation facilities | G22: Accessable
B23: g) Utilities | E23: Available
A24: 5 | B24: DESCRIPTION OF PROPERTY Construction permit No. | J24: Date:-
B25: Number of house on site (Service's quarters and garage to be indicated separately)
A26: a) | B26: GF | E26: Length | G26: Mts. X Breadth | H26: 8.2*9.53-4*1.08 | J26: = | K26: =Area!D4 -> 73.826
A27: b) | B27: FF | E27: Length | G27: Mts. X Breadth | H27: 8.2*9.53-4*1.08+0.5*2+0.6*2.36 | J27: = | K27: =Area!D10 -> 75.2756
A28: c) | B28: 2F | E28: Length | G28: Mts. X Breadth | H28: 8.2*9.53-4*1.08+0.5*2+0.6*2.36 | J28: = | K28: =+K27 -> 75.2756
A29: f) | B29: Terrace | E29: Length | G29: Mts. X Breadth | J29: =
A30: g) | B30: Total | E30: Length | G30: Mts. X Breadth | J30: = | K30: =SUM(K26:K29) -> 224.3772
F31: G+2 Residence Building
D32: Wall | F32: HCB
F33: HCB
F34: Brick
F35: Chicka
F36: Metal Sheet
F37: Masonry
D38: Roof | F38: Tiles
F39: Metal Sheet
F40: Tiles
F41: R.C
F42: Timber
F43: Thatch
D44: Floors | F44: Tiles
F45: Tiles
F46: Timber
F47: Cement
F48: R.C
F49: Uncovered
D50: Lighting System | F50: Electrical
F51: Electrical
F52: Petrol
F53: Oil
D54: Doors & Windows | F54: Aluminium
F55: Timber
F56: Metal
F57: Aluminium
B58: State of house (i.e new, moderate, old etc)
A59: 6 | B59: PRESENT USE OF BUILDING | F59: =F31 -> G+2 Residence Building
F60: Title deed no. | H60: =I9 -> XY
A61: 7 | B61: PRESENT VALUE (Show separate value for each building)
A62: a) | B62: Building | I62: Birr | J62: =Location!D75 -> 9446280.1
A63: b) | B63: ='[1]Location '!C125 -> Internal Structure | I63: Birr | J63: =Location!D76 -> 200000
A64: c) | B64: ='[1]Location '!C126 -> External Elecrical & Sanitary Works | I64: Birr | J64: =Location!D77 -> 429022.54
A65: d) | B65: ='[1]Location '!C127 -> Fence & compound = | I65: Birr | J65: =Location!D78 -> 249393.01
A66: e) | B66: ='[1]Location '!C128 -> Consultancy Service | I66: Birr | J66: =Location!D79 -> 81306.978
A67: f | B67: ='[1]Location '!C129 -> Location Value | I67: Birr | J67: =Location!D80 -> 2478592
H68: Total Birr | J68: =SUM(J62:L67) -> 12884595
A69: 8 | B69: Property Sales Value Range from Birr | F69: =0.9*J68 -> 11596135 | I69: to Birr | J69: =1.1*J68 -> 14173054
B70: In case of forclosure, what would be the forced value? | I70: =F69 -> 11596135
B71: Is there any thatched roof on site? | G71: NO
B72: is the property of the area as a whole reserved for any
B73: purpose or for the amelioration of the proposal new town plan project?
B74: Yes | E74: No | H74: No document
A77: 9 | B77: Remark:- | D77: • This valuation is done based on the actual measurement, thus the approved plan has to be submitted and checked by the engineer.
A80: 10 | B80: ROUGH SKETCH LOCATION (N.B. Use prominent | H80: 8.959403, 38.
B95: 12/08/2023 | E95: Adnan Esmael
B96: Date of Inspection | E96: Appraiser's Name | G96: Appraiser's Signature | J96: Approved By

Sheet Area
B1: Ground floor
B2: 8.2 | C2: 9.53 | D2: =+B2*C2 -> 78.146
B3: -4 | C3: 1.08 | D3: =+B3*C3 -> -4.32
D4: =SUM(D2:D3) -> 73.826
B5: First Floor
B6: 8.2 | C6: 9.53 | D6: =+B6*C6 -> 78.146
B7: -4 | C7: 1.08 | D7: =+B7*C7 -> -4.32
B8: 0.5 | C8: 2 | D8: =+B8*C8*0.6 -> 0.6
B9: 0.6 | C9: 2.36 | D9: =+B9*C9*0.6 -> 0.8496
D10: =SUM(D6:D9) -> 75.2756
B12: SecondFloor
D13: =+D10 -> 75.2756
C15: Total | D15: =+D4+D10+D13 -> 224.3772 | E15: 42100 | F15: =+D15*E15 -> 9446280.1
